Workbook
Name ___INDEX_SHEET___ASAP_Utilities: #REF!
Name ___INDEX_SHEET___ASAP_Utilities: #REF!

Sheet 香港市场目标
A1: 分类 | B1: KOL | C1: 备注 | D1: 2月例子数 | E1: 2月日均例子数 | F1: 截至5.20例子数 | G1: 截至5.20日均例子数 | H1: 6月-实际日均 | I1: 6月实际-合计 | J1: 46174 | K1: 46175 | L1: 46176 | M1: 46177 | N1: 46178 | O1: 46179 | P1: 46180 | Q1: 46181 | R1: 46182 | S1: 46183 | T1: 46184 | U1: 46185 | V1: 46186 | W1: 46187 | X1: 46188 | Y1: 46189 | Z1: 46190 | AA1: 46191 | AB1: 46192 | AC1: 46193 | AD1: 46194 | AE1: 46195 | AF1: 46196 | AG1: 46197 | AH1: 46198 | AI1: 46199 | AJ1: 46200 | AK1: 46201 | AL1: 46202 | AM1: 46203 | AN1: MTD例子目标 | AO1: 实际例子达成 | AP1: 例子gap | AQ1: MTD约课例子目标 | AR1: 实际约课达成 | AS1: 约课例子gap | AT1: 约课成本
A2: KOL | B2: 钟嘉欣图片 | F2: 202 | G2: =F2/20 | H2: =I2/30 | I2: =SUM(J2:AM2) | J2: 9 | K2: 9 | L2: 10 | M2: 10 | N2: 10 | O2: 11 | P2: 11 | Q2: 9 | R2: 9 | S2: 10 | T2: 10 | U2: 10 | V2: 11 | W2: 11 | X2: 9 | Y2: 9 | Z2: 10 | AA2: 10 | AB2: 10 | AC2: 11 | AD2: 11 | AE2: 9 | AF2: 9 | AG2: 10 | AH2: 10 | AI2: 10 | AJ2: 11 | AK2: 11 | AL2: 10 | AM2: 10 | AN2: =J2+K2+L2+M2+N2+O2+P2 | AO2: 88 | AP2: 74 | AQ2: =AN2*55% | AR2: =VLOOKUP(B2,[4]Sheet3!$B:$M,12,0) | AS2: 45 | AT2: =VLOOKUP(B2,[4]Sheet3!$B:$O,14,0) | AU2: 1040.1138
B3: 钟嘉欣视频1 | C3: 模型目标225（通过测试新素材提升至目标） | F3: 96 | G3: =F3/20 | H3: =I3/30 | I3: =SUM(J3:AM3) | J3: 4 | K3: 5 | L3: 5 | M3: 5 | N3: 5 | O3: 5 | P3: 5 | Q3: 4 | R3: 5 | S3: 5 | T3: 5 | U3: 5 | V3: 5 | W3: 5 | X3: 4 | Y3: 5 | Z3: 5 | AA3: 5 | AB3: 5 | AC3: 5 | AD3: 5 | AE3: 4 | AF3: 5 | AG3: 5 | AH3: 5 | AI3: 5 | AJ3: 5 | AK3: 5 | AL3: 4 | AM3: 5 | AN3: =J3+K3+L3+M3+N3+O3+P3 | AO3: 43 | AP3: 62 | AQ3: =AN3*55% | AR3: =VLOOKUP(B3,[4]Sheet3!$B:$M,12,0) | AS3: 18 | AT3: =VLOOKUP(B3,[4]Sheet3!$B:$O,14,0) | AU3: 1787.2923
B4: 钟嘉欣视频 | C4: 预估每天4条 | H4: =I4/30 | I4: =SUM(J4:AM4) | J4: 4 | K4: 4 | L4: 4 | M4: 4 | N4: 4 | O4: 4 | P4: 4 | Q4: 4 | R4: 4 | S4: 4 | T4: 4 | U4: 4 | V4: 4 | W4: 4 | X4: 4 | Y4: 4 | Z4: 4 | AA4: 4 | AB4: 4 | AC4: 4 | AD4: 4 | AE4: 4 | AF4: 4 | AG4: 4 | AH4: 4 | AI4: 4 | AJ4: 4 | AK4: 4 | AL4: 4 | AM4: 4 | AN4: =J4+K4+L4+M4+N4+O4+P4 | AO4: 36 | AP4: 55 | AQ4: =AN4*55% | AR4: =VLOOKUP(B4,[4]Sheet3!$B:$M,12,0) | AS4: 20 | AT4: =VLOOKUP(B4,[4]Sheet3!$B:$O,14,0) | AU4: 1074.0415
B5: 其他汇总 | F5: 27 | G5: =F5/20 | H5: =I5/30 | I5: =SUM(J5:AM5) | J5: 1 | K5: 1 | L5: 1 | M5: 1 | N5: 1 | O5: 1 | P5: 1 | Q5: 1 | R5: 1 | S5: 1 | T5: 1 | U5: 1 | V5: 1 | W5: 1 | X5: 1 | Y5: 1 | Z5: 1 | AA5: 1 | AB5: 1 | AC5: 1 | AD5: 1 | AE5: 1 | AF5: 1 | AG5: 1 | AH5: 1 | AI5: 1 | AJ5: 1 | AK5: 1 | AL5: 1 | AM5: 1 | AN5: =J5+K5+L5+M5+N5+O5+P5 | AO5: 9 | AP5: 9 | AQ5: =AN5*55% | AR5: 4 | AS5: 5 | AU5: 1079.9642
B6: KOL-汇总 | F6: =SUM(F2:F5) | G6: =F6/20 | H6: =I6/30 | I6: =SUM(J6:AM6) | J6: =SUM(J2:J5) | K6: =SUM(K2:K5) | L6: =SUM(L2:L5) | M6: =SUM(M2:M5) | N6: =SUM(N2:N5) | O6: =SUM(O2:O5) | P6: =SUM(P2:P5) | Q6: =SUM(Q2:Q5) | ... AO6: =SUM(AO2:AO5) | AP6: 200 | AQ6: =AN6*0.55 | AR6: =SUM(AR2:AR5) | AS6: 88 | AT6: 1236.9605 | AU6: 1202.9208
A7: 独立站HK | B7: 出席礼品测试 | C7: 参考51talk，预估一个月30条 | H7: =I7/30 | I7: =SUM(J7:AM7) | P7: 1 | Q7: 1 | R7: 1 | S7: 1 | T7: 2 | U7: 2 | V7: 1 | W7: 1 | X7: 1 | Y7: 1 | Z7: 1 | AA7: 2 | AB7: 2 | AC7: 1 | AD7: 1 | AE7: 1 | AF7: 1 | AG7: 1 | AH7: 2 | AI7: 2 | AJ7: 1 | AK7: 1 | AL7: 1 | AM7: 1 | AN7: =J7+K7+L7+M7+N7+O7+P7 | AO7: 3 | AP7: 4 | AQ7: =AN7*0.6 | AR7: 2 | AS7: 2 | AU7: 432.97561
B8: edm | C8: 正在走流程，预估月底上线 | I8: =SUM(J8:AM8) | AD8: 1 | AE8: 1 | AF8: 1 | AG8: 1 | AH8: 1 | AI8: 1 | AJ8: 1 | AK8: 1 | AL8: 1 | AM8: 1 | AN8: =J8+K8+L8+M8+N8+O8+P8 | AO8: 0 | AP8: 0 | AQ8: =AN8*0.6 | AS8: 0
A9: 商超&社群 | B9: 代理商场 | C9: 代理商场（预计8+1，合计9） | I9: =SUM(J9:AM9) | N9: 10 | O9: 50 | P9: 50 | U9: 20 | V9: 40 | W9: 40 | X9: 20 | AA9: 20 | AB9: 40 | AC9: 40 | AD9: 20 | AE9: 20 | AH9: 20 | AI9: 20 | AJ9: 40 | AK9: 20 | AN9: =J9+K9+L9+M9+N9+O9+P9 | AO9: 110 | AP9: 103 | AQ9: =AN9*0.78 | AR9: 64 | AS9: 73 | AU9: 304.28219
B10: 澳門展会 | I10: =SUM(J10:AM10) | U10: 20 | V10: 40 | W10: 40 | AN10: =J10+K10+L10+M10+N10+O10+P10 | AO10: 0 | AP10: 0 | AQ10: =AN10*0.78 | AS10: 0
B11: 代理人汇总 | F11: 20 | G11: =F11/20 | H11: =I11/31 | I11: =SUM(J11:AM11) | J11: 1 | K11: 1 | L11: 1 | M11: 1 | N11: 1 | O11: 1 | P11: 1 | Q11: 1 | R11: 1 | S11: 1 | T11: 1 | U11: 1 | V11: 1 | W11: 1 | X11: 1 | Y11: 1 | Z11: 1 | AA11: 1 | AB11: 1 | AC11: 1 | AD11: 1 | AE11: 1 | AF11: 1 | AG11: 1 | AH11: 1 | AI11: 1 | AJ11: 1 | AK11: 1 | AL11: 1 | AM11: 1 | AN11: =J11+K11+L11+M11+N11+O11+P11 | AO11: 9 | AP11: 3 | AQ11: =AN11*0.6 | AR11: 1 | AS11: 1 | AU11: 0
B12: 合计 | I12: =SUM(I9:I11) | J12: =SUM(J9:J11) | K12: =SUM(K9:K11) | L12: =SUM(L9:L11) | M12: =SUM(M9:M11) | N12: =SUM(N9:N11) | O12: =SUM(O9:O11) | P12: =SUM(P9:P11) | ... AM12: =SUM(AM9:AM11) | AN12: =SUM(AN7:AN11) | AO12: =SUM(AO7:AO11) | AP12: 106 | AQ12: =SUM(AQ7:AQ11) | AR12: =SUM(AR7:AR11) | AS12: 74 | AU12: 300.17027
B13: 合计 | I13: =I12+I6+I7+I8 | J13: =J12+J6 | K13: =K12+K6 | L13: =L12+L6 | M13: =M12+M6 | N13: =N12+N6 | O13: =O12+O6 | P13: =P12+P6 | Q13: =Q12+Q6 | ... AO13: =AO12+AO6 | AP13: 310 | AQ13: =AQ12+AQ6 | AR13: =AR12+AR6 | AS13: 164 | AU13: 786.19258
AQ15: =AO13/AN13
B16: KOL历史 | C16: 3月 | D16: 4月 | E16: 5月 | F16: 6月 | G16: 7月 | H16: 8月 | I16: 9月 | J16: 10月 | K16: 11月 | L16: 12月 | M16: 1月 | N16: 2月 | O16: 3月 | P16: 4月 | Q16: 46162
B17: 累计例子 | C17: 727 | D17: 565 | E17: 1080 | F17: 1123 | G17: 665 | H17: 973 | I17: 1530 | J17: 1847 | K17: 1112 | L17: 796 | M17: 787 | N17: 360 | O17: 677 | P17: 468 | Q17: 325 | AV17: =AO6/AN6 | AW17: =AR6/AQ6
B18: 平均成本 | C18: 431 | D18: 571 | E18: 673 | F18: 763 | G18: 969 | H18: 644 | I18: =I19/I17 | J18: =J19/J17 | K18: =K19/K17 | L18: =L19/L17 | M18: =M19/M17 | N18: =N19/N17 | O18: =O19/O17 | P18: =P19/P17 | Q18: =Q19/Q17 | AQ18: =AO9/AN9 | AV18: =AO9/AN9
I19: 807722 | J19: 895008 | K19: 1134508 | L19: 935636 | M19: 615368.77 | N19: 306862 | O19: 465727 | P19: 342428 | Q19: 201491 | AV19: =AO13/AN13
B20: 日均例子 | C20: =C17/31 | D20: =D17/30 | E20: =E17/31 | F20: =F17/30 | G20: =G17/31 | H20: =H17/31 | I20: =I17/30 | J20: =J17/31 | K20: =K17/30 | L20: =L17/31 | M20: =M17/31 | N20: =N17/28 | O20: =O17/31 | P20: =P17/31 | Q20: =Q17/20 | AO20: =#REF!/#REF!
AW21: =AR13/AQ13
B23: 6月目标预计 | C23: 例子数 | D23: 成本 | E23: 消耗 | AT23: 陈琪
A24: KOLHK | B24: KOL | C24: =I6 | D24: 650 | E24: =C24*D24 | M24: . | AT24: Bob林盛斌
A25: 线下HK | B25: 展会 | C25: =I10 | D25: =P37 | E25: =D25*C25 | P25: 420840 | AT25: 钟嘉欣图片
A26: 社群HK | B26: 代理人 | C26: =I11 | D26: 300 | E26: =C26*D26 | P26: 420 | AQ26: =#REF!/#REF!
A27: 线下HK | B27: 商超 | C27: =I9 | D27: 250 | E27: =C27*D27 | P27: 1030 | AT27: 钟嘉欣视频1
B28: 其他汇总 | C28: =I7+I8 | D28: 200 | E28: =C28*D28
B29: 合计 | C29: =C24+C25+C27+C26+C28 | D29: =E29/C29 | E29: =E24+E25+E27+E26+E28 | P29: =P25/P27*P26 | AT29: 蔡雪莹
AT30: 陈琪直播
AO31: 15填 | AT31: 陳展鵬
AT32: 專家鄧明儀
B33: 展会 | C33: 2月BB展 | D33: 5月课外活动展 | E33: 5月儿童展 | F33: 7月书展 | G33: 8月展会 | H33: 9月展会 | I33: 10月创意文化展 | J33: 10月兒童書展 | K33: 12月儿童书展 | L33: 12月澳门展 | M33: 2月BB展 | N33: 5月课外活动展 | O33: 5月儿童书展 | P33: 6月澳门展 | AT33: 陳凱琳
B34: 累计例子 | C34: 235 | D34: 303 | E34: 301 | F34: 587 | G34: 270 | H34: 150 | I34: 200 | J34: 400 | K34: =展会数据测算!U24 | L34: =展会数据测算!W24 | M34: =展会数据测算!Y24 | N34: =展会数据测算!AC24 | O34: =展会数据测算!AE24 | P34: 100 | AT34: 麥雅緻直播
B35: 平均成本 | C35: =C36/C34 | D35: 177 | E35: 228 | F35: 236 | G35: 140 | H35: 145 | I35: 146 | J35: 121 | K35: =展会数据测算!U26 | L35: =展会数据测算!W26 | M35: =展会数据测算!Y26 | AT35: 呂慧儀直播
B36: 总消耗 | C36: 41427 | D36: 53609 | E36: 68721 | F36: 138753 | G36: 52080 | I36: 34009.26 | J36: 57839.73 | K36: =K34*K35 | L36: =L34*L35 | M36: =展会数据测算!Y22 | N36: =展会数据测算!AC22 | O36: =展会数据测算!AE22 | P36: =展会数据测算!AG30 | AT36: 嘉欣购物团
B37: 平均成本（含差旅CPS） | C37: 232 | D37: 236 | E37: 288 | F37: 301 | G37: 234 | H37: 171 | I37: 205 | J37: 176 | K37: =K36/K34 | L37: =L36/L34 | M37: =M36/M34 | N37: =展会数据测算!AC27 | O37: =展会数据测算!AE27 | P37: =展会数据测算!AG31 | AT37: 其他汇总
N38: 2TMK+4CC | O38: 2TMK+2CC | P38: 2CC+2TMK
B40: 线下HK历史达成数据 | C40: 总目标 | D40: 实际总达成 | E40: 书展目标 | F40: 书展达成 | G40: 商超目标 | H40: 商超达成 | I40: 总目标达成率 | J40: 书展达成率 | K40: 商超达成率
B41: 45931 | C41: =E41+G41 | D41: =F41+H41 | E41: 650 | F41: 375 | G41: 210 | H41: 222 | I41: =D41/C41 | J41: =F41/E41 | K41: =H41/G41
B42: 45962 | C42: =E42+G42 | D42: =F42+H42 | G42: 400 | H42: 319 | I42: =D42/C42 | K42: =H42/G42
B43: 45992 | C43: =E43+G43 | D43: =F43+H43 | E43: 600 | F43: 634 | G43: 500 | H43: 422 | I43: =D43/C43 | J43: =F43/E43 | K43: =H43/G43
B44: 46023 | C44: =E44+G44 | D44: =F44+H44 | G44: 520 | H44: 339 | I44: =D44/C44 | K44: =H44/G44
B45: 46054 | C45: =E45+G45 | D45: =F45+H45 | E45: 282 | F45: 270 | G45: 300 | H45: 99 | I45: =D45/C45 | J45: =F45/E45 | K45: =H45/G45
B46: 46082 | C46: =E46+G46 | D46: =F46+H46 | E46: 410 | F46: 368 | G46: 560 | H46: 359 | I46: =D46/C46 | J46: =F46/E46 | K46: =H46/G46
B47: 46113 | C47: =E47+G47 | D47: =F47+H47 | E47: 110 | F47: 77 | G47: 480 | H47: 277 | I47: =D47/C47 | J47: =F47/E47 | K47: =H47/G47

Sheet 嘉欣购物团（暂定）
A1: 麦雅致 | B1: 例子占比 | C1: 总例子数 | D1: 成本 | E1: 加权 | F1: 实际投放时间 | G1: 投放时间1个半月
A2: 汇总 | B2: 1 | C2: 100 | D2: 700 | E2: =SUMPRODUCT(C3:C4,D3:D4)/C2 | F2: 30 | I2: 以项目或周期为单位 | J2: 前端投放参数-预估 | K2: 益智 | L2: 美术
A3: 11月 | B3: =C3/$C$2 | C3: 30 | D3: 700 | F3: 10 | I3: 主投 | J3: 注册例子数 | K3: 100 | N3: 其他参数（海外调整） | O3: 益智 | P3: 美术
A4: 12月 | B4: =C4/$C$2 | C4: 70 | D4: 700 | F4: 20 | I4: 主投 | J4: 分发例子数 | N4: 销售人均承接例子数 | O4: 93.8 | P4: 103
I5: 主投 | J5: 单例子成本（CPA） | K5: 700 | N5: 销售人均固定人工成本 | O5: 10622 | P5: 11145.017
I6: 主投 | J6: 单到课例子成本（CPA） | N6: 销售提成比例 | O6: 0.079 | P6: 0.077
I7: 主投 | J7: 渠道佣金（CPS） | K7: 0.25 | N7: 礼品及其他费用比例 | O7: 0.017 | P7: 0.022
I8: 主投 | J8: 投放费用（CPT) | K8: 4000 | N8: 出席试听课费用 | O8: 86.4 | P8: 82
I9: 辅投 | J9: 注册例子数 | N9: 单例子渠道运营人工成本及其他 | O9: 33.49 | P9: 75
I10: 辅投 | J10: 分发例子数 | N10: 是否过TMK | O10: 是 | P10: 是
I11: 辅投 | J11: 单例子成本（CPA） | N11: TMK人均承担例子量 | O11: 1055 | P11: 1233
I12: 辅投 | J12: 单到课例子成本（CPA） | N12: TMK人均成本 | O12: 11181 | P12: 11486.424
I13: 辅投 | J13: 渠道佣金（CPS） | N13: 备注：绿色填充部分可调整，没有对应的参数可留空
I14: 辅投 | J14: 投放费用（CPT) | O14: =O5/O4 | P14: =P5/P4
O15: =O12/O11
J16: 过程指标-预估
J17: 注册分发率 | K17: 0.5
I18: 主投 | J18: 滚动注册出席率 | K18: 0.38
I19: 主投 | J19: 滚动出席转化率 | K19: 0.35
I20: 主投 | J20: 滚动注册转化率 | K20: 0.18
I21: 主投 | J21: 正价课ASP | K21: 5000
I22: 辅投 | J22: 注册分发率
I23: 辅投 | J23: 滚动注册出席率
I24: 辅投 | J24: 滚动出席转化率
I25: 辅投 | J25: 滚动注册转化率
I26: 辅投 | J26: 正价课ASP
J28: ROI 1相关指标-自动计算
I29: 主投 | J29: 到课学员数量 | K29: =K18*K3 | L29: =L18*L3 | N29: 例子数*注册出席率
I30: 主投 | J30: 正价课学员数量 | K30: =K3*K20 | L30: =L3*L20 | N30: 例子数*注册转化率
I31: 主投 | J31: 正价课GMV | K31: =K30*K21 | L31: =L30*L21 | N31: ASP*学员人数
I32: 主投 | J32: 前端投放总成本 | K32: =K5*K3+K7*K31+K8+K29*K6+K3*O9 | L32: =L5*L3+L7*L31+L8+L29*L6+L3*P9 | N32: 例子数*单例子成本+GMV*CPS佣金比例+投放费用+单到课例子成本*出席人数+例子数*单例子运营人工成本
I33: 辅投 | J33: 到课学员数量 | K33: =K23*K9 | L33: =L23*L9
I34: 辅投 | J34: 正价课学员数量 | K34: =K9*K25 | L34: =L9*L25
I35: 辅投 | J35: 正价课GMV | K35: =K26*K34 | L35: =L26*L34
I36: 辅投 | J36: 前端投放总成本 | K36: =K9*K11+K13*K35+K14+K12*K33+K9*P9 | L36: =L9*L11+L13*L35+L14+L12*L33+L9*O9 | N36: 例子数*单例子成本+GMV*CPS佣金比例+投放费用+单到课例子成本*出席人数+例子数*单例子运营人工成本
I37: 主投+辅投 | J37: 每单获客成本1 | K37: =(K32+K36)/(K30+K34) | L37: =(L32+L36)/(L30+L34) | N37: 前端投放总成本/学员人数
J38: ROI 1 | K38: =(K31+K35)/(K32+K36) | L38: =(L31+L35)/(L32+L36) | N38: GMV/前端投放总成本
J40: ROI 2相关指标-自动计算
I41: 主投 | J41: 试听课费用 | K41: =K29*O8 | L41: =L29*P8 | N41: 单课时试听课费用*出席人数
I42: 主投 | J42: TMK费用 | K42: =IF(O10="是",K3/O11*O12,0) | L42: =IF(P10="是",L3/P11*P12,0) | N42: 例子数/TMK人均承担例子量*TMK人均成本=TMK人数*TMK人均成本
I43: 主投 | J43: 销售成本 | K43: =K4/O4*O5+K31*(O6+O7) | L43: =L4/P4*P5+L31*(P6+P7) | N43: 分发例子数/销售人均承接例子数*销售人均固定人工成本+GMV*（销售提成比例+礼品及其他费用比例）
I44: 辅投 | J44: 试听课费用 | K44: =K33*P8 | L44: =L33*O8
I45: 辅投 | J45: TMK费用 | K45: =IF(P10="是",K9/P11*P12,0) | L45: =IF(O10="是",L9/O11*O12,0)
I46: 辅投 | J46: 销售成本 | K46: =K10/P4*P5+K35*(P6+P7) | L46: =L10/O4*O5+L35*(O6+O7) | N46: 分发例子数/销售人均承接例子数*销售人均固定人工成本+GMV*（销售提成比例+礼品及其他费用比例）
I47: 主投+辅投 | J47: 每单获客成本2 | K47: =K37+SUM(K41:K46)/(K30+K34) | L47: =L37+SUM(L41:L46)/(L30+L34) | N47: 市场费用+试听课费用+TMK费用+销售费用
J48: ROI 2 | K48: =(K31+K35)/(K32+K36+SUM(K41:K46)) | L48: =(L31+L35)/(L32+L36+SUM(L41:L46))

Sheet 钟嘉欣新视频
A1: 钟嘉欣新视频 | B1: 例子占比 | C1: 总例子数 | D1: 成本 | E1: 加权 | F1: 实际投放时间 | G1: 投放时间4个半月
A2: 汇总 | B2: 1 | C2: 900 | D2: 650 | E2: {=SUMPRODUCT(C3:C7,D3:D7)/C2} | F2: =SUM(F3:F7) | I2: 以项目或周期为单位 | J2: 前端投放参数-预估 | K2: 益智 | L2: 美术
A3: 3月（13天，预计3.19投放） | B3: 0.15 | C3: =B3*C2 | D3: 550 | F3: 13 | I3: 主投 | J3: 注册例子数 | K3: 900 | N3: 其他参数（海外调整） | O3: 益智 | P3: 美术
A4: 4月 | B4: 0.3 | C4: =B4*C2 | D4: 600 | F4: 30 | I4: 主投 | J4: 分发例子数 | N4: 销售人均承接例子数 | O4: 93.8 | P4: 103
A5: 5月 | B5: 0.25 | C5: =B5*C2 | D5: 650 | F5: 31 | I5: 主投 | J5: 单例子成本（CPA） | K5: 650 | N5: 销售人均固定人工成本 | O5: 10622 | P5: 11145.017
A6: 6月 | B6: 0.15 | C6: =B6*C2 | D6: 700 | F6: 30 | I6: 主投 | J6: 单到课例子成本（CPA） | N6: 销售提成比例 | O6: 0.079 | P6: 0.077
A7: 7月 | B7: 0.15 | C7: =B7*C2 | D7: 700 | F7: 31 | I7: 主投 | J7: 渠道佣金（CPS） | N7: 礼品及其他费用比例 | O7: 0.017 | P7: 0.022
I8: 主投 | J8: 投放费用（CPT) | K8: =160000*0.91 | N8: 出席试听课费用 | O8: 86.4 | P8: 82
I9: 辅投 | J9: 注册例子数 | N9: 单例子渠道运营人工成本及其他 | O9: 33.49 | P9: 75
I10: 辅投 | J10: 分发例子数 | N10: 是否过TMK | O10: 是 | P10: 是
I11: 辅投 | J11: 单例子成本（CPA） | N11: TMK人均承担例子量 | O11: 1055 | P11: 1233
I12: 辅投 | J12: 单到课例子成本（CPA） | N12: TMK人均成本 | O12: 11181 | P12: 11486.424
I13: 辅投 | J13: 渠道佣金（CPS） | N13: 备注：绿色填充部分可调整，没有对应的参数可留空
I14: 辅投 | J14: 投放费用（CPT) | O14: =O5/O4 | P14: =P5/P4
O15: =O12/O11
J16: 过程指标-预估
J17: 注册分发率 | K17: 0.5
I18: 主投 | J18: 滚动注册出席率 | K18: 0.38
I19: 主投 | J19: 滚动出席转化率 | K19: 0.35
I20: 主投 | J20: 滚动注册转化率 | K20: 0.165
I21: 主投 | J21: 正价课ASP | K21: 5000
I22: 辅投 | J22: 注册分发率
I23: 辅投 | J23: 滚动注册出席率
I24: 辅投 | J24: 滚动出席转化率
I25: 辅投 | J25: 滚动注册转化率
I26: 辅投 | J26: 正价课ASP
J28: ROI 1相关指标-自动计算
I29: 主投 | J29: 到课学员数量 | K29: =K18*K3 | L29: =L18*L3 | N29: 例子数*注册出席率
I30: 主投 | J30: 正价课学员数量 | K30: =K3*K20 | L30: =L3*L20 | N30: 例子数*注册转化率
I31: 主投 | J31: 正价课GMV | K31: =K30*K21 | L31: =L30*L21 | N31: ASP*学员人数
I32: 主投 | J32: 前端投放总成本 | K32: =K5*K3+K7*K31+K8+K29*K6+K3*O9 | L32: =L5*L3+L7*L31+L8+L29*L6+L3*P9 | N32: 例子数*单例子成本+GMV*CPS佣金比例+投放费用+单到课例子成本*出席人数+例子数*单例子运营人工成本
I33: 辅投 | J33: 到课学员数量 | K33: =K23*K9 | L33: =L23*L9
I34: 辅投 | J34: 正价课学员数量 | K34: =K9*K25 | L34: =L9*L25
I35: 辅投 | J35: 正价课GMV | K35: =K26*K34 | L35: =L26*L34
I36: 辅投 | J36: 前端投放总成本 | K36: =K9*K11+K13*K35+K14+K12*K33+K9*P9 | L36: =L9*L11+L13*L35+L14+L12*L33+L9*O9 | N36: 例子数*单例子成本+GMV*CPS佣金比例+投放费用+单到课例子成本*出席人数+例子数*单例子运营人工成本
I37: 主投+辅投 | J37: 每单获客成本1 | K37: =(K32+K36)/(K30+K34) | L37: =(L32+L36)/(L30+L34) | N37: 前端投放总成本/学员人数
J38: ROI 1 | K38: =(K31+K35)/(K32+K36) | L38: =(L31+L35)/(L32+L36) | N38: GMV/前端投放总成本
J40: ROI 2相关指标-自动计算
I41: 主投 | J41: 试听课费用 | K41: =K29*O8 | L41: =L29*P8 | N41: 单课时试听课费用*出席人数
I42: 主投 | J42: TMK费用 | K42: =IF(O10="是",K3/O11*O12,0) | L42: =IF(P10="是",L3/P11*P12,0) | N42: 例子数/TMK人均承担例子量*TMK人均成本=TMK人数*TMK人均成本
I43: 主投 | J43: 销售成本 | K43: =K4/O4*O5+K31*(O6+O7) | L43: =L4/P4*P5+L31*(P6+P7) | N43: 分发例子数/销售人均承接例子数*销售人均固定人工成本+GMV*（销售提成比例+礼品及其他费用比例）
I44: 辅投 | J44: 试听课费用 | K44: =K33*P8 | L44: =L33*O8
I45: 辅投 | J45: TMK费用 | K45: =IF(P10="是",K9/P11*P12,0) | L45: =IF(O10="是",L9/O11*O12,0)
I46: 辅投 | J46: 销售成本 | K46: =K10/P4*P5+K35*(P6+P7) | L46: =L10/O4*O5+L35*(O6+O7) | N46: 分发例子数/销售人均承接例子数*销售人均固定人工成本+GMV*（销售提成比例+礼品及其他费用比例）
I47: 主投+辅投 | J47: 每单获客成本2 | K47: =K37+SUM(K41:K46)/(K30+K34) | L47: =L37+SUM(L41:L46)/(L30+L34) | N47: 市场费用+试听课费用+TMK费用+销售费用
J48: ROI 2 | K48: =(K31+K35)/(K32+K36+SUM(K41:K46)) | L48: =(L31+L35)/(L32+L36+SUM(L41:L46))

Sheet 周家蔚
A1: 吕慧仪 | B1: 例子占比 | C1: 总例子数 | D1: 成本 | E1: 加权 | F1: 实际投放天数 | G1: 预计上线时间11.15
A2: 汇总 | B2: 1 | C2: 420 | D2: 700 | E2: {=SUMPRODUCT(C3:C6,D3:D6)/C2} | I2: 以项目或周期为单位 | J2: 前端投放参数-预估 | K2: 益智 | L2: 美术
A3: 2月 | B3: 0.1 | C3: =C$2*B3 | D3: 600 | F3: 15 | I3: 主投 | J3: 注册例子数 | K3: 420 | N3: 其他参数（海外调整） | O3: 益智 | P3: 美术
A4: 3月 | B4: 0.4 | C4: =C$2*B4 | D4: 650 | F4: 31 | I4: 主投 | J4: 分发例子数 | N4: 销售人均承接例子数 | O4: 93.8 | P4: 103
A5: 4月 | B5: 0.3 | C5: =C$2*B5 | D5: 735 | F5: 31 | I5: 主投 | J5: 单例子成本（CPA） | K5: 700 | N5: 销售人均固定人工成本 | O5: 10622 | P5: 11145.017
A6: 5月 | B6: 0.2 | C6: =C$2*B6 | D6: 795 | F6: 13 | I6: 主投 | J6: 单到课例子成本（CPA） | N6: 销售提成比例 | O6: 0.079 | P6: 0.077
I7: 主投 | J7: 渠道佣金（CPS） | N7: 礼品及其他费用比例 | O7: 0.017 | P7: 0.022
I8: 主投 | J8: 投放费用（CPT) | K8: 84500 | N8: 出席试听课费用 | O8: 86.4 | P8: 82
I9: 辅投 | J9: 注册例子数 | N9: 单例子渠道运营人工成本及其他 | O9: 33.49 | P9: 75
I10: 辅投 | J10: 分发例子数 | N10: 是否过TMK | O10: 是 | P10: 是
I11: 辅投 | J11: 单例子成本（CPA） | N11: TMK人均承担例子量 | O11: 1055 | P11: 1233
I12: 辅投 | J12: 单到课例子成本（CPA） | N12: TMK人均成本 | O12: 11181 | P12: 11486.424
I13: 辅投 | J13: 渠道佣金（CPS） | N13: 备注：绿色填充部分可调整，没有对应的参数可留空
I14: 辅投 | J14: 投放费用（CPT) | O14: =O5/O4 | P14: =P5/P4
O15: =O12/O11
J16: 过程指标-预估
J17: 注册分发率 | K17: 0.5
I18: 主投 | J18: 滚动注册出席率 | K18: 0.38
I19: 主投 | J19: 滚动出席转化率 | K19: 0.35
I20: 主投 | J20: 滚动注册转化率 | K20: 0.18
I21: 主投 | J21: 正价课ASP | K21: 5000
I22: 辅投 | J22: 注册分发率
I23: 辅投 | J23: 滚动注册出席率
I24: 辅投 | J24: 滚动出席转化率
I25: 辅投 | J25: 滚动注册转化率
I26: 辅投 | J26: 正价课ASP
J28: ROI 1相关指标-自动计算
I29: 主投 | J29: 到课学员数量 | K29: =K18*K3 | L29: =L18*L3 | N29: 例子数*注册出席率
I30: 主投 | J30: 正价课学员数量 | K30: =K3*K20 | L30: =L3*L20 | N30: 例子数*注册转化率
I31: 主投 | J31: 正价课GMV | K31: =K30*K21 | L31: =L30*L21 | N31: ASP*学员人数
I32: 主投 | J32: 前端投放总成本 | K32: =K5*K3+K7*K31+K8+K29*K6+K3*O9 | L32: =L5*L3+L7*L31+L8+L29*L6+L3*P9 | N32: 例子数*单例子成本+GMV*CPS佣金比例+投放费用+单到课例子成本*出席人数+例子数*单例子运营人工成本
I33: 辅投 | J33: 到课学员数量 | K33: =K23*K9 | L33: =L23*L9
I34: 辅投 | J34: 正价课学员数量 | K34: =K9*K25 | L34: =L9*L25
I35: 辅投 | J35: 正价课GMV | K35: =K26*K34 | L35: =L26*L34
I36: 辅投 | J36: 前端投放总成本 | K36: =K9*K11+K13*K35+K14+K12*K33+K9*P9 | L36: =L9*L11+L13*L35+L14+L12*L33+L9*O9 | N36: 例子数*单例子成本+GMV*CPS佣金比例+投放费用+单到课例子成本*出席人数+例子数*单例子运营人工成本
I37: 主投+辅投 | J37: 每单获客成本1 | K37: =(K32+K36)/(K30+K34) | L37: =(L32+L36)/(L30+L34) | N37: 前端投放总成本/学员人数
J38: ROI 1 | K38: =(K31+K35)/(K32+K36) | L38: =(L31+L35)/(L32+L36) | N38: GMV/前端投放总成本
J40: ROI 2相关指标-自动计算
I41: 主投 | J41: 试听课费用 | K41: =K29*O8 | L41: =L29*P8 | N41: 单课时试听课费用*出席人数
I42: 主投 | J42: TMK费用 | K42: =IF(O10="是",K3/O11*O12,0) | L42: =IF(P10="是",L3/P11*P12,0) | N42: 例子数/TMK人均承担例子量*TMK人均成本=TMK人数*TMK人均成本
I43: 主投 | J43: 销售成本 | K43: =K4/O4*O5+K31*(O6+O7) | L43: =L4/P4*P5+L31*(P6+P7) | N43: 分发例子数/销售人均承接例子数*销售人均固定人工成本+GMV*（销售提成比例+礼品及其他费用比例）
I44: 辅投 | J44: 试听课费用 | K44: =K33*P8 | L44: =L33*O8
I45: 辅投 | J45: TMK费用 | K45: =IF(P10="是",K9/P11*P12,0) | L45: =IF(O10="是",L9/O11*O12,0)
I46: 辅投 | J46: 销售成本 | K46: =K10/P4*P5+K35*(P6+P7) | L46: =L10/O4*O5+L35*(O6+O7) | N46: 分发例子数/销售人均承接例子数*销售人均固定人工成本+GMV*（销售提成比例+礼品及其他费用比例）
I47: 主投+辅投 | J47: 每单获客成本2 | K47: =K37+SUM(K41:K46)/(K30+K34) | L47: =L37+SUM(L41:L46)/(L30+L34) | N47: 市场费用+试听课费用+TMK费用+销售费用
J48: ROI 2 | K48: =(K31+K35)/(K32+K36+SUM(K41:K46)) | L48: =(L31+L35)/(L32+L36+SUM(L41:L46))

Sheet 邓明仪直播
A1: 邓明仪直播 | B1: 例子占比 | C1: 总例子数 | D1: 成本 | E1: 加权 | F1: 实际投放时间 | G1: 投放时间1个半月
A2: 汇总 | B2: 1 | C2: 180 | D2: 680 | E2: {=SUMPRODUCT(C3:C6,D3:D6)/C2} | F2: 90 | I2: 以项目或周期为单位 | J2: 前端投放参数-预估 | K2: 益智 | L2: 美术
A3: 12月 | B3: 0.5 | C3: =B3*C2 | D3: 600 | F3: 23 | I3: 主投 | J3: 注册例子数 | K3: 180 | N3: 其他参数（海外调整） | O3: 益智 | P3: 美术
A4: 1月 | B4: 0.25 | C4: =B4*C2 | D4: 700 | F4: 31 | I4: 主投 | J4: 分发例子数 | N4: 销售人均承接例子数 | O4: 93.8 | P4: 103
A5: 2月 | B5: 0.2 | C5: =B5*C2 | D5: 750 | F5: 28 | I5: 主投 | J5: 单例子成本（CPA） | K5: 700 | N5: 销售人均固定人工成本 | O5: 10622 | P5: 11145.017
A6: 3月 | B6: 0.05 | C6: =B6*C2 | D6: 800 | F6: 8 | I6: 主投 | J6: 单到课例子成本（CPA） | N6: 销售提成比例 | O6: 0.079 | P6: 0.077
I7: 主投 | J7: 渠道佣金（CPS） | N7: 礼品及其他费用比例 | O7: 0.017 | P7: 0.022
I8: 主投 | J8: 投放费用（CPT) | K8: 30000 | N8: 出席试听课费用 | O8: 86.4 | P8: 82
I9: 辅投 | J9: 注册例子数 | N9: 单例子渠道运营人工成本及其他 | O9: 33.49 | P9: 75
I10: 辅投 | J10: 分发例子数 | N10: 是否过TMK | O10: 是 | P10: 是
I11: 辅投 | J11: 单例子成本（CPA） | N11: TMK人均承担例子量 | O11: 1055 | P11: 1233
I12: 辅投 | J12: 单到课例子成本（CPA） | N12: TMK人均成本 | O12: 11181 | P12: 11486.424
I13: 辅投 | J13: 渠道佣金（CPS） | N13: 备注：绿色填充部分可调整，没有对应的参数可留空
I14: 辅投 | J14: 投放费用（CPT) | O14: =O5/O4 | P14: =P5/P4
O15: =O12/O11
J16: 过程指标-预估
J17: 注册分发率 | K17: 0.5
I18: 主投 | J18: 滚动注册出席率 | K18: 0.38
I19: 主投 | J19: 滚动出席转化率 | K19: 0.35
I20: 主投 | J20: 滚动注册转化率 | K20: 0.165
I21: 主投 | J21: 正价课ASP | K21: 5000
I22: 辅投 | J22: 注册分发率
I23: 辅投 | J23: 滚动注册出席率
I24: 辅投 | J24: 滚动出席转化率
I25: 辅投 | J25: 滚动注册转化率
I26: 辅投 | J26: 正价课ASP
J28: ROI 1相关指标-自动计算
I29: 主投 | J29: 到课学员数量 | K29: =K18*K3 | L29: =L18*L3 | N29: 例子数*注册出席率
I30: 主投 | J30: 正价课学员数量 | K30: =K3*K20 | L30: =L3*L20 | N30: 例子数*注册转化率
I31: 主投 | J31: 正价课GMV | K31: =K30*K21 | L31: =L30*L21 | N31: ASP*学员人数
I32: 主投 | J32: 前端投放总成本 | K32: =K5*K3+K7*K31+K8+K29*K6+K3*O9 | L32: =L5*L3+L7*L31+L8+L29*L6+L3*P9 | N32: 例子数*单例子成本+GMV*CPS佣金比例+投放费用+单到课例子成本*出席人数+例子数*单例子运营人工成本
I33: 辅投 | J33: 到课学员数量 | K33: =K23*K9 | L33: =L23*L9
I34: 辅投 | J34: 正价课学员数量 | K34: =K9*K25 | L34: =L9*L25
I35: 辅投 | J35: 正价课GMV | K35: =K26*K34 | L35: =L26*L34
I36: 辅投 | J36: 前端投放总成本 | K36: =K9*K11+K13*K35+K14+K12*K33+K9*P9 | L36: =L9*L11+L13*L35+L14+L12*L33+L9*O9 | N36: 例子数*单例子成本+GMV*CPS佣金比例+投放费用+单到课例子成本*出席人数+例子数*单例子运营人工成本
I37: 主投+辅投 | J37: 每单获客成本1 | K37: =(K32+K36)/(K30+K34) | L37: =(L32+L36)/(L30+L34) | N37: 前端投放总成本/学员人数
J38: ROI 1 | K38: =(K31+K35)/(K32+K36) | L38: =(L31+L35)/(L32+L36) | N38: GMV/前端投放总成本
J40: ROI 2相关指标-自动计算
I41: 主投 | J41: 试听课费用 | K41: =K29*O8 | L41: =L29*P8 | N41: 单课时试听课费用*出席人数
I42: 主投 | J42: TMK费用 | K42: =IF(O10="是",K3/O11*O12,0) | L42: =IF(P10="是",L3/P11*P12,0) | N42: 例子数/TMK人均承担例子量*TMK人均成本=TMK人数*TMK人均成本
I43: 主投 | J43: 销售成本 | K43: =K4/O4*O5+K31*(O6+O7) | L43: =L4/P4*P5+L31*(P6+P7) | N43: 分发例子数/销售人均承接例子数*销售人均固定人工成本+GMV*（销售提成比例+礼品及其他费用比例）
I44: 辅投 | J44: 试听课费用 | K44: =K33*P8 | L44: =L33*O8
I45: 辅投 | J45: TMK费用 | K45: =IF(P10="是",K9/P11*P12,0) | L45: =IF(O10="是",L9/O11*O12,0)
I46: 辅投 | J46: 销售成本 | K46: =K10/P4*P5+K35*(P6+P7) | L46: =L10/O4*O5+L35*(O6+O7) | N46: 分发例子数/销售人均承接例子数*销售人均固定人工成本+GMV*（销售提成比例+礼品及其他费用比例）
I47: 主投+辅投 | J47: 每单获客成本2 | K47: =K37+SUM(K41:K46)/(K30+K34) | L47: =L37+SUM(L41:L46)/(L30+L34) | N47: 市场费用+试听课费用+TMK费用+销售费用
J48: ROI 2 | K48: =(K31+K35)/(K32+K36+SUM(K41:K46)) | L48: =(L31+L35)/(L32+L36+SUM(L41:L46))

Sheet 麦雅致
A1: 麦雅致 | B1: 例子占比 | C1: 总例子数 | D1: 成本 | E1: 加权 | F1: 实际投放时间 | G1: 投放时间1个半月
A2: 汇总 | B2: 1 | C2: 280 | D2: 700 | E2: =SUMPRODUCT(C3:C4,D3:D4)/C2 | F2: 45 | J2: 以项目或周期为单位 | K2: 前端投放参数-预估 | L2: 益智 | M2: 美术
A3: 11月 | B3: =C3/$C$2 | C3: 180 | D3: 700 | F3: 25 | J3: 主投 | K3: 注册例子数 | L3: 280 | O3: 其他参数（海外调整） | P3: 益智 | Q3: 美术
A4: 12月 | B4: =C4/$C$2 | C4: 100 | D4: 800 | F4: 20 | J4: 主投 | K4: 分发例子数 | O4: 销售人均承接例子数 | P4: 93.8 | Q4: 103
J5: 主投 | K5: 单例子成本（CPA） | L5: 700 | O5: 销售人均固定人工成本 | P5: 10622 | Q5: 11145.017
J6: 主投 | K6: 单到课例子成本（CPA） | O6: 销售提成比例 | P6: 0.079 | Q6: 0.077
J7: 主投 | K7: 渠道佣金（CPS） | O7: 礼品及其他费用比例 | P7: 0.017 | Q7: 0.022
J8: 主投 | K8: 投放费用（CPT) | L8: 75000 | O8: 出席试听课费用 | P8: 86.4 | Q8: 82
J9: 辅投 | K9: 注册例子数 | O9: 单例子渠道运营人工成本及其他 | P9: 33.49 | Q9: 75
J10: 辅投 | K10: 分发例子数 | O10: 是否过TMK | P10: 是 | Q10: 是
J11: 辅投 | K11: 单例子成本（CPA） | O11: TMK人均承担例子量 | P11: 1055 | Q11: 1233
J12: 辅投 | K12: 单到课例子成本（CPA） | O12: TMK人均成本 | P12: 11181 | Q12: 11486.424
J13: 辅投 | K13: 渠道佣金（CPS） | O13: 备注：绿色填充部分可调整，没有对应的参数可留空
J14: 辅投 | K14: 投放费用（CPT) | P14: =P5/P4 | Q14: =Q5/Q4
P15: =P12/P11
K16: 过程指标-预估
K17: 注册分发率 | L17: 0.5
J18: 主投 | K18: 滚动注册出席率 | L18: 0.38
J19: 主投 | K19: 滚动出席转化率 | L19: 0.35
J20: 主投 | K20: 滚动注册转化率 | L20: 0.18
J21: 主投 | K21: 正价课ASP | L21: 5000
J22: 辅投 | K22: 注册分发率
J23: 辅投 | K23: 滚动注册出席率
J24: 辅投 | K24: 滚动出席转化率
J25: 辅投 | K25: 滚动注册转化率
J26: 辅投 | K26: 正价课ASP
K28: ROI 1相关指标-自动计算
J29: 主投 | K29: 到课学员数量 | L29: =L18*L3 | M29: =M18*M3 | O29: 例子数*注册出席率
J30: 主投 | K30: 正价课学员数量 | L30: =L3*L20 | M30: =M3*M20 | O30: 例子数*注册转化率
J31: 主投 | K31: 正价课GMV | L31: =L30*L21 | M31: =M30*M21 | O31: ASP*学员人数
J32: 主投 | K32: 前端投放总成本 | L32: =L5*L3+L7*L31+L8+L29*L6+L3*P9 | M32: =M5*M3+M7*M31+M8+M29*M6+M3*Q9 | O32: 例子数*单例子成本+GMV*CPS佣金比例+投放费用+单到课例子成本*出席人数+例子数*单例子运营人工成本
J33: 辅投 | K33: 到课学员数量 | L33: =L23*L9 | M33: =M23*M9
J34: 辅投 | K34: 正价课学员数量 | L34: =L9*L25 | M34: =M9*M25
J35: 辅投 | K35: 正价课GMV | L35: =L26*L34 | M35: =M26*M34
J36: 辅投 | K36: 前端投放总成本 | L36: =L9*L11+L13*L35+L14+L12*L33+L9*Q9 | M36: =M9*M11+M13*M35+M14+M12*M33+M9*P9 | O36: 例子数*单例子成本+GMV*CPS佣金比例+投放费用+单到课例子成本*出席人数+例子数*单例子运营人工成本
J37: 主投+辅投 | K37: 每单获客成本1 | L37: =(L32+L36)/(L30+L34) | M37: =(M32+M36)/(M30+M34) | O37: 前端投放总成本/学员人数
K38: ROI 1 | L38: =(L31+L35)/(L32+L36) | M38: =(M31+M35)/(M32+M36) | O38: GMV/前端投放总成本
K40: ROI 2相关指标-自动计算
J41: 主投 | K41: 试听课费用 | L41: =L29*P8 | M41: =M29*Q8 | O41: 单课时试听课费用*出席人数
J42: 主投 | K42: TMK费用 | L42: =IF(P10="是",L3/P11*P12,0) | M42: =IF(Q10="是",M3/Q11*Q12,0) | O42: 例子数/TMK人均承担例子量*TMK人均成本=TMK人数*TMK人均成本
J43: 主投 | K43: 销售成本 | L43: =L4/P4*P5+L31*(P6+P7) | M43: =M4/Q4*Q5+M31*(Q6+Q7) | O43: 分发例子数/销售人均承接例子数*销售人均固定人工成本+GMV*（销售提成比例+礼品及其他费用比例）
J44: 辅投 | K44: 试听课费用 | L44: =L33*Q8 | M44: =M33*P8
J45: 辅投 | K45: TMK费用 | L45: =IF(Q10="是",L9/Q11*Q12,0) | M45: =IF(P10="是",M9/P11*P12,0)
J46: 辅投 | K46: 销售成本 | L46: =L10/Q4*Q5+L35*(Q6+Q7) | M46: =M10/P4*P5+M35*(P6+P7) | O46: 分发例子数/销售人均承接例子数*销售人均固定人工成本+GMV*（销售提成比例+礼品及其他费用比例）
J47: 主投+辅投 | K47: 每单获客成本2 | L47: =L37+SUM(L41:L46)/(L30+L34) | M47: =M37+SUM(M41:M46)/(M30+M34) | O47: 市场费用+试听课费用+TMK费用+销售费用
K48: ROI 2 | L48: =(L31+L35)/(L32+L36+SUM(L41:L46)) | M48: =(M31+M35)/(M32+M36+SUM(M41:M46))

Sheet 吕慧仪
A1: 吕慧仪 | B1: 例子占比 | C1: 总例子数 | D1: 成本 | E1: 加权 | F1: 实际投放天数 | G1: 预计上线时间11.15
A2: 汇总 | B2: 1 | C2: 230 | D2: 700 | E2: {=SUMPRODUCT(C3:C6,D3:D6)/C2} | I2: 以项目或周期为单位 | J2: 前端投放参数-预估 | K2: 益智 | L2: 美术
A3: 11月 | B3: =C3/$C$2 | C3: 100 | D3: 600 | F3: 15 | I3: 主投 | J3: 注册例子数 | K3: 230 | N3: 其他参数（海外调整） | O3: 益智 | P3: 美术
A4: 12月 | B4: =C4/$C$2 | C4: 70 | D4: 650 | F4: 31 | I4: 主投 | J4: 分发例子数 | N4: 销售人均承接例子数 | O4: 93.8 | P4: 103
A5: 1月 | B5: =C5/$C$2 | C5: 40 | D5: 800 | F5: 31 | I5: 主投 | J5: 单例子成本（CPA） | K5: 700 | N5: 销售人均固定人工成本 | O5: 10622 | P5: 11145.017
A6: 2月 | B6: =C6/$C$2 | C6: 20 | D6: 900 | F6: 13 | I6: 主投 | J6: 单到课例子成本（CPA） | N6: 销售提成比例 | O6: 0.079 | P6: 0.077
I7: 主投 | J7: 渠道佣金（CPS） | N7: 礼品及其他费用比例 | O7: 0.017 | P7: 0.022
I8: 主投 | J8: 投放费用（CPT) | K8: 60000 | N8: 出席试听课费用 | O8: 86.4 | P8: 82
I9: 辅投 | J9: 注册例子数 | N9: 单例子渠道运营人工成本及其他 | O9: 33.49 | P9: 75
I10: 辅投 | J10: 分发例子数 | N10: 是否过TMK | O10: 是 | P10: 是
I11: 辅投 | J11: 单例子成本（CPA） | N11: TMK人均承担例子量 | O11: 1055 | P11: 1233
I12: 辅投 | J12: 单到课例子成本（CPA） | N12: TMK人均成本 | O12: 11181 | P12: 11486.424
I13: 辅投 | J13: 渠道佣金（CPS） | N13: 备注：绿色填充部分可调整，没有对应的参数可留空
I14: 辅投 | J14: 投放费用（CPT) | O14: =O5/O4 | P14: =P5/P4
O15: =O12/O11
J16: 过程指标-预估
J17: 注册分发率 | K17: 0.5
I18: 主投 | J18: 滚动注册出席率 | K18: 0.38
I19: 主投 | J19: 滚动出席转化率 | K19: 0.35
I20: 主投 | J20: 滚动注册转化率 | K20: 0.18
I21: 主投 | J21: 正价课ASP | K21: 5000
I22: 辅投 | J22: 注册分发率
I23: 辅投 | J23: 滚动注册出席率
I24: 辅投 | J24: 滚动出席转化率
I25: 辅投 | J25: 滚动注册转化率
I26: 辅投 | J26: 正价课ASP
J28: ROI 1相关指标-自动计算
I29: 主投 | J29: 到课学员数量 | K29: =K18*K3 | L29: =L18*L3 | N29: 例子数*注册出席率
I30: 主投 | J30: 正价课学员数量 | K30: =K3*K20 | L30: =L3*L20 | N30: 例子数*注册转化率
I31: 主投 | J31: 正价课GMV | K31: =K30*K21 | L31: =L30*L21 | N31: ASP*学员人数
I32: 主投 | J32: 前端投放总成本 | K32: =K5*K3+K7*K31+K8+K29*K6+K3*O9 | L32: =L5*L3+L7*L31+L8+L29*L6+L3*P9 | N32: 例子数*单例子成本+GMV*CPS佣金比例+投放费用+单到课例子成本*出席人数+例子数*单例子运营人工成本
I33: 辅投 | J33: 到课学员数量 | K33: =K23*K9 | L33: =L23*L9
I34: 辅投 | J34: 正价课学员数量 | K34: =K9*K25 | L34: =L9*L25
I35: 辅投 | J35: 正价课GMV | K35: =K26*K34 | L35: =L26*L34
I36: 辅投 | J36: 前端投放总成本 | K36: =K9*K11+K13*K35+K14+K12*K33+K9*P9 | L36: =L9*L11+L13*L35+L14+L12*L33+L9*O9 | N36: 例子数*单例子成本+GMV*CPS佣金比例+投放费用+单到课例子成本*出席人数+例子数*单例子运营人工成本
I37: 主投+辅投 | J37: 每单获客成本1 | K37: =(K32+K36)/(K30+K34) | L37: =(L32+L36)/(L30+L34) | N37: 前端投放总成本/学员人数
J38: ROI 1 | K38: =(K31+K35)/(K32+K36) | L38: =(L31+L35)/(L32+L36) | N38: GMV/前端投放总成本
J40: ROI 2相关指标-自动计算
I41: 主投 | J41: 试听课费用 | K41: =K29*O8 | L41: =L29*P8 | N41: 单课时试听课费用*出席人数
I42: 主投 | J42: TMK费用 | K42: =IF(O10="是",K3/O11*O12,0) | L42: =IF(P10="是",L3/P11*P12,0) | N42: 例子数/TMK人均承担例子量*TMK人均成本=TMK人数*TMK人均成本
I43: 主投 | J43: 销售成本 | K43: =K4/O4*O5+K31*(O6+O7) | L43: =L4/P4*P5+L31*(P6+P7) | N43: 分发例子数/销售人均承接例子数*销售人均固定人工成本+GMV*（销售提成比例+礼品及其他费用比例）
I44: 辅投 | J44: 试听课费用 | K44: =K33*P8 | L44: =L33*O8
I45: 辅投 | J45: TMK费用 | K45: =IF(P10="是",K9/P11*P12,0) | L45: =IF(O10="是",L9/O11*O12,0)
I46: 辅投 | J46: 销售成本 | K46: =K10/P4*P5+K35*(P6+P7) | L46: =L10/O4*O5+L35*(O6+O7) | N46: 分发例子数/销售人均承接例子数*销售人均固定人工成本+GMV*（销售提成比例+礼品及其他费用比例）
I47: 主投+辅投 | J47: 每单获客成本2 | K47: =K37+SUM(K41:K46)/(K30+K34) | L47: =L37+SUM(L41:L46)/(L30+L34) | N47: 市场费用+试听课费用+TMK费用+销售费用
J48: ROI 2 | K48: =(K31+K35)/(K32+K36+SUM(K41:K46)) | L48: =(L31+L35)/(L32+L36+SUM(L41:L46))

Sheet 專家鄧明儀
A1: 專家鄧明儀 | B1: 例子占比 | C1: 总例子数 | D1: 成本 | E1: 加权
A2: 汇总 | B2: 1 | C2: 65 | D2: 720 | E2: =SUMPRODUCT(C3:C5,D3:D5)/C2 | H2: 以项目或周期为单位 | I2: 前端投放参数-预估 | J2: 益智 | K2: 美术
A3: 10月 | B3: =C3/$C$2 | C3: 40 | D3: 600 | H3: 主投 | I3: 注册例子数 | J3: 65 | M3: 其他参数（海外调整） | N3: 益智 | O3: 美术
A4: 11月 | B4: =C4/$C$2 | C4: 20 | D4: 750 | H4: 主投 | I4: 分发例子数 | M4: 销售人均承接例子数 | N4: 93.8 | O4: 103
A5: 12月 | B5: =C5/$C$2 | C5: 5 | D5: 900 | H5: 主投 | I5: 单例子成本（CPA） | J5: 700 | M5: 销售人均固定人工成本 | N5: 10622 | O5: 11145.017
H6: 主投 | I6: 单到课例子成本（CPA） | M6: 销售提成比例 | N6: 0.079 | O6: 0.077
H7: 主投 | I7: 渠道佣金（CPS） | M7: 礼品及其他费用比例 | N7: 0.017 | O7: 0.022
H8: 主投 | I8: 投放费用（CPT) | J8: 16740 | M8: 出席试听课费用 | N8: 86.4 | O8: 82
H9: 辅投 | I9: 注册例子数 | M9: 单例子渠道运营人工成本及其他 | N9: 33.49 | O9: 75
H10: 辅投 | I10: 分发例子数 | M10: 是否过TMK | N10: 是 | O10: 是
H11: 辅投 | I11: 单例子成本（CPA） | M11: TMK人均承担例子量 | N11: 1055 | O11: 1233
H12: 辅投 | I12: 单到课例子成本（CPA） | M12: TMK人均成本 | N12: 11181 | O12: 11486.424
H13: 辅投 | I13: 渠道佣金（CPS） | M13: 备注：绿色填充部分可调整，没有对应的参数可留空
H14: 辅投 | I14: 投放费用（CPT) | N14: =N5/N4 | O14: =O5/O4
N15: =N12/N11
I16: 过程指标-预估
I17: 注册分发率 | J17: 0.5
H18: 主投 | I18: 滚动注册出席率 | J18: 0.38
H19: 主投 | I19: 滚动出席转化率 | J19: 0.35
H20: 主投 | I20: 滚动注册转化率 | J20: 0.18
H21: 主投 | I21: 正价课ASP | J21: 5000
H22: 辅投 | I22: 注册分发率
H23: 辅投 | I23: 滚动注册出席率
H24: 辅投 | I24: 滚动出席转化率
H25: 辅投 | I25: 滚动注册转化率
H26: 辅投 | I26: 正价课ASP
I28: ROI 1相关指标-自动计算
H29: 主投 | I29: 到课学员数量 | J29: =J18*J3 | K29: =K18*K3 | M29: 例子数*注册出席率
H30: 主投 | I30: 正价课学员数量 | J30: =J3*J20 | K30: =K3*K20 | M30: 例子数*注册转化率
H31: 主投 | I31: 正价课GMV | J31: =J30*J21 | K31: =K30*K21 | M31: ASP*学员人数
H32: 主投 | I32: 前端投放总成本 | J32: =J5*J3+J7*J31+J8+J29*J6+J3*N9 | K32: =K5*K3+K7*K31+K8+K29*K6+K3*O9 | M32: 例子数*单例子成本+GMV*CPS佣金比例+投放费用+单到课例子成本*出席人数+例子数*单例子运营人工成本
H33: 辅投 | I33: 到课学员数量 | J33: =J23*J9 | K33: =K23*K9
H34: 辅投 | I34: 正价课学员数量 | J34: =J9*J25 | K34: =K9*K25
H35: 辅投 | I35: 正价课GMV | J35: =J26*J34 | K35: =K26*K34
H36: 辅投 | I36: 前端投放总成本 | J36: =J9*J11+J13*J35+J14+J12*J33+J9*O9 | K36: =K9*K11+K13*K35+K14+K12*K33+K9*N9 | M36: 例子数*单例子成本+GMV*CPS佣金比例+投放费用+单到课例子成本*出席人数+例子数*单例子运营人工成本
H37: 主投+辅投 | I37: 每单获客成本1 | J37: =(J32+J36)/(J30+J34) | K37: =(K32+K36)/(K30+K34) | M37: 前端投放总成本/学员人数
I38: ROI 1 | J38: =(J31+J35)/(J32+J36) | K38: =(K31+K35)/(K32+K36) | M38: GMV/前端投放总成本
I40: ROI 2相关指标-自动计算
H41: 主投 | I41: 试听课费用 | J41: =J29*N8 | K41: =K29*O8 | M41: 单课时试听课费用*出席人数
H42: 主投 | I42: TMK费用 | J42: =IF(N10="是",J3/N11*N12,0) | K42: =IF(O10="是",K3/O11*O12,0) | M42: 例子数/TMK人均承担例子量*TMK人均成本=TMK人数*TMK人均成本
H43: 主投 | I43: 销售成本 | J43: =J4/N4*N5+J31*(N6+N7) | K43: =K4/O4*O5+K31*(O6+O7) | M43: 分发例子数/销售人均承接例子数*销售人均固定人工成本+GMV*（销售提成比例+礼品及其他费用比例）
H44: 辅投 | I44: 试听课费用 | J44: =J33*O8 | K44: =K33*N8
H45: 辅投 | I45: TMK费用 | J45: =IF(O10="是",J9/O11*O12,0) | K45: =IF(N10="是",K9/N11*N12,0)
H46: 辅投 | I46: 销售成本 | J46: =J10/O4*O5+J35*(O6+O7) | K46: =K10/N4*N5+K35*(N6+N7) | M46: 分发例子数/销售人均承接例子数*销售人均固定人工成本+GMV*（销售提成比例+礼品及其他费用比例）
H47: 主投+辅投 | I47: 每单获客成本2 | J47: =J37+SUM(J41:J46)/(J30+J34) | K47: =K37+SUM(K41:K46)/(K30+K34) | M47: 市场费用+试听课费用+TMK费用+销售费用
I48: ROI 2 | J48: =(J31+J35)/(J32+J36+SUM(J41:J46)) | K48: =(K31+K35)/(K32+K36+SUM(K41:K46))

Sheet 陳凱琳
A1: 陳凱琳 | B1: 例子占比 | C1: 总例子数 | D1: 成本 | E1: 加权
A2: 汇总 | B2: 1 | C2: 700 | D2: 720 | E2: {=SUMPRODUCT(C3:C6,D3:D6)/C2}
A3: 10月 | B3: =C3/$C$2 | C3: 140 | D3: 550
A4: 11月 | B4: =C4/$C$2 | C4: 300 | D4: 640 | G4: =230/30*20+170/30*10
A5: 12月 | B5: =C5/$C$2 | C5: 190 | D5: 750
A6: 1月 | B6: =C6/$C$2 | C6: 70 | D6: 900

Sheet 陈展鹏
A1: 陈展鹏 | B1: 例子占比 | C1: 总例子数 | D1: 成本 | E1: 加权
A2: 汇总 | B2: 1 | C2: 380 | D2: 720 | E2: =SUMPRODUCT(C3:C6,D3:D6)/C2
A3: 9月 | B3: =C3/$C$2 | C3: 170 | D3: 550
A4: 10月 | B4: =C4/$C$2 | C4: 120 | D4: 800
A5: 11月 | B5: =C5/$C$2 | C5: 70 | D5: 900
A6: 12月 | B6: =C6/$C$2 | C6: 20 | D6: 1000

Sheet 陈琪
A1: 陈展鹏 | B1: 例子占比 | C1: 总例子数 | D1: 成本 | E1: 加权
A2: 汇总 | B2: 1 | C2: 320 | D2: 720 | E2: =SUMPRODUCT(C3:C8,D3:D8)/450
A3: 9月 | B3: =C3/$C$2 | C3: 200 | D3: 550
A4: 10月 | B4: =C4/$C$2 | C4: 100 | D4: 800
A5: 11月 | B5: =C5/$C$2 | C5: 60 | D5: 900
A6: 12月 | B6: =C6/$C$2 | C6: 40 | D6: 1000
A7: 1月 | B7: =C7/$C$2 | C7: 30 | D7: 1000
A8: 2月 | B8: =C8/$C$2 | C8: 20 | D8: 1000

Sheet 展会数据测算
A1: 汇率 | B1: 0.93 | D1: 0.93 | F1: 0.93 | I1: 0.92 | K1: 0.93 | M1: 0.93 | O1: 0.91 | Q1: 0.93 | AB1: 0.93 | AD1: 0.93
A2: 展会 | B2: 2025年2月BB展 | D2: 2025年5月课外活动展 | F2: 2025年5月儿童书展 | H2: 2025年7月大湾区 | I2: 2025年7月儿童书展 | K2: 8月bb展 | M2: 9月澳门展 | O2: 10月创意文化展（预估） | Q2: 10月兒童書展（预估） | S2: 12月兒童書展（预估） | U2: 8個展位(以此为准） | V2: 12月澳门展 | X2: 2026年BB展開支 | Z2: 26年4月月澳门展 | AB2: 2025年5月课外活动展 | AD2: 2025年5月儿童书展 | AF2: 6月澳门展
A3: 项目 | B3: 费用-HKD | C3: 费用-RMB | D3: 费用-HKD | E3: 费用-RMB | F3: 费用-HKD | G3: 费用-RMB | H3: 费用-RMB | I3: 费用-HKD | J3: 费用-RMB | K3: 费用-HKD | L3: 费用-RMB | M3: 费用-HKD | N3: 费用-RMB | O3: 费用-HKD | P3: 费用-RMB | Q3: 费用-HKD | R3: 费用-RMB | S3: 费用-HKD | T3: 费用-RMB | U3: 费用-RMB | V3: 费用-HKD | W3: 费用-RMB | X3: 费用-HKD | Y3: 费用-RMB | Z3: 费用-HKD | AA3: 费用-RMB | AB3: 费用-HKD | AC3: 费用-RMB | AD3: 费用-HKD | AE3: 费用-RMB | AF3: 费用-HKD | AG3: 费用-RMB
A4: 展位费 | B4: 30000 | C4: =B4*$B$1 | D4: 42960 | E4: =D4*$D$1 | F4: 50000 | G4: =F4*$F$1 | H4: 0 | I4: 112392 | J4: =I4*$I$1 | K4: 29000 | L4: =K4*$K$1 | M4: 13000 | N4: =M4*$K$1 | O4: 21924 | P4: =O4*$O$1 | Q4: 29800 | R4: =Q4*$K$1 | S4: 29800 | T4: 27714 | U4: 49885.2 | V4: 15000 | W4: =V4*$Q$1 | X4: 18000 | Y4: 16380 | Z4: 13000 | AA4: =Z4*$K$1 | AB4: 28000 | AC4: =AB4*$D$1 | AD4: 29800 | AE4: =AD4*$F$1 | AF4: 12000 | AG4: =AF4*$K$1
A5: 搭建费 | B5: 3700 | C5: =B5*$B$1 | D5: 5066 | E5: =D5*$D$1 | F5: 9486 | G5: =F5*$F$1 | H5: 0 | I5: 7324 | J5: =I5*$I$1 | K5: 2841 | L5: =K5*$K$1 | M5: 3750 | N5: =M5*$K$1 | O5: 2103 | P5: =O5*$O$1 | Q5: 9486 | R5: =Q5*$K$1 | S5: 9486 | T5: 8822 | U5: 12408.9 | V5: 3915 | W5: =V5*$Q$1 | X5: 2400 | Y5: 2184 | Z5: 3750 | AA5: =Z5*$K$1 | AB5: 5066 | AC5: =AB5*$D$1 | AD5: =9486/2 | AE5: =AD5*$F$1 | AF5: 3000 | AG5: =AF5*$K$1
A6: 礼品-馬克筆 | B6: 3526.88 | C6: =B6*$B$1 | D6: 5454 | E6: =D6*$D$1 | F6: 7741.94 | G6: =F6*$F$1 | H6: 0 | I6: 14464.29 | J6: =I6*$I$1 | K6: 2948.03 | L6: =K6*$K$1 | M6: 2000 | N6: =M6*$K$1 | O6: 5030 | P6: =O6*$O$1 | Q6: 6290.32 | R6: =Q6*$K$1 | S6: 6290.32 | T6: 5850 | U6: 8775 | V6: =12.5*98/0.93 | W6: =V6*$Q$1 | X6: 5413.4615 | Y6: 4926.25 | Z6: 2000 | AA6: =Z6*$K$1 | AB6: =12.5*280 | AC6: =AB6*$D$1 | AD6: =12.5*370 | AE6: =AD6*$F$1 | AF6: =12.5*120 | AG6: =AF6*$K$1
A7: 禮品物流費
A8: POP制作/打印等 | B8: 1140 | C8: =B8*$B$1 | I8: 540 | J8: =I8*$I$1
A9: WIFI 蛋租赁 | B9: 580 | C9: =B9*$B$1 | D9: 580 | E9: =D9*$D$1 | F9: 515 | G9: =F9*$F$1 | H9: 0 | I9: 990 | J9: =I9*$I$1 | K9: 580 | L9: =K9*$K$1 | M9: 580 | N9: =M9*$K$1 | O9: 499 | P9: =O9*$O$1 | Q9: 515 | R9: =Q9*$K$1 | S9: 515 | T9: 479 | U9: 445.4 | V9: 500 | W9: =V9*$Q$1 | Z9: 580 | AA9: =Z9*$K$1 | AB9: 580 | AC9: =AB9*$D$1 | AD9: 515 | AE9: =AD9*$F$1
A10: 文具 | B10: 77 | C10: =B10*$B$1
A11: 电费 | K11: 1420 | L11: =K11*$K$1
A12: 礼品-氣球 | E12: 3174 | G12: =F12*$F$1 | I12: 1219.78 | J12: =I12*$I$1
A13: pad充電線*8 | E13: 160
A14: 香港物流費 | B14: 1580 | C14: =B14*$B$1 | D14: 1600 | E14: ¥1,488.0 | F14: 1600 | G14: =F14*$F$1 | H14: 0 | I14: 2350 | J14: =I14*$I$1 | K14: 1600 | L14: =K14*$K$1 | M14: 2000 | N14: =M14*$K$1 | O14: 830 | P14: =O14*$O$1 | Q14: 1600 | R14: =Q14*$K$1 | S14: 1600 | T14: 2976 | U14: 2767.7 | V14: 1500 | W14: =V14*$Q$1 | X14: 1900 | Y14: 1729 | Z14: 2000 | AA14: =Z14*$K$1 | AB14: 1600 | AC14: ¥1,488.0 | AD14: 1600 | AE14: =AD14*$F$1 | AF14: 2000 | AG14: =AF14*$K$1
A15: 餐費 | B15: 3942.2 | C15: =B15*$B$1 | D15: 3387.1 | E15: ¥3,150.0 | F15: 4351.4 | G15: =F15*$F$1 | H15: 0 | I15: 11538.46 | J15: =I15*$I$1 | K15: 2628.13 | L15: =K15*$K$1 | M15: 2000 | N15: =M15*$K$1 | O15: 1800 | P15: =O15*$O$1 | Q15: 4351.4 | R15: =Q15*$K$1 | S15: 4351.4 | T15: 4046.8 | U15: 4046.8 | V15: 2250 | W15: =V15*$Q$1 | Z15: 2000 | AA15: =Z15*$K$1 | AB15: 3387.1 | AC15: ¥3,150.0 | AD15: 4351.4 | AE15: =AD15*$F$1 | AF15: 2000 | AG15: =AF15*$K$1
A16: 工衣洗衣 | F16: 200 | G16: =F16*$F$1
A17: 代理CPS费（预估） | H17: =60000*35% | J17: =122*9%*4500*35% | L17: =(270-140)*9%*4500*30% | P17: =50*9%*4500*35% | R17: =90*9%*4500*35% | X17: =Y17/0.91 | Y17: =85692.541*0.35
A18: 差旅（住宿）（预估） | C18: =800*4*3 | E18: =1200*4*3 | G18: =1200*4*3 | H18: 0 | J18: =1100*4*7 | L18: =1000*3+2000*2 | N18: =700*4 | P18: =750*4 | R18: =750*8 | U18: =750*8 | W18: =750*4 | AC18: =1200*6*3 | AE18: =1200*4*3 | AG18: =700*4
A19: 差率（车票）（预估） | C19: =8*430 | E19: =8*430 | G19: =8*430 | H19: 0 | J19: =16*430 | L19: =5*430 | N19: =200*6 | P19: =430*4 | R19: =430*8 | U19: =430*8 | W19: =430*4 | AC19: =12*430 | AE19: =8*430 | AG19: =200*6
A21: 總開支 | B21: =SUM(B4:B16) | C21: =SUM(C4:C16) | D21: =SUM(D4:D16) | E21: =SUM(E4:E16) | F21: =SUM(F4:F16) | G21: =SUM(G4:G16) | I21: =SUM(I4:I16) | J21: =SUM(J4:J16) | K21: =SUM(K4:K16) | L21: =SUM(L4:L16) | M21: =SUM(M4:M16) | N21: =SUM(N4:N16) | O21: =SUM(O4:O16) | P21: =SUM(P4:P16) | ... R21: =SUM(R4:R16) | U21: =SUM(U4:U16) | W21: =SUM(W4:W16) | Y21: =SUM(Y4:Y17) | Z21: =SUM(Z4:Z16) | AA21: =SUM(AA4:AA16) | AB21: =SUM(AB4:AB16) | AC21: =SUM(AC4:AC16) | AD21: =SUM(AD4:AD16) | AE21: =SUM(AE4:AE16) | AF21: =SUM(AF4:AF16) | AG21: =SUM(AG4:AG16)
A22: 总开支（含差旅） | C22: =C21+C18+C19 | E22: =E21+E18+E19 | G22: =G21+G18+G19 | H22: =H21+H18+H19+H17 | J22: =J21+J18+J19+J17 | L22: =L21+L18+L19+L17 | N22: =N21+N18+N19+N17 | P22: =P21+P18+P19+P17 | R22: =R21+R18+R19+R17 | U22: =U21+U18+U19+U17 | W22: =W21+W18+W19+W17 | Y22: =Y21 | AA22: =AA21+AA18+AA19+AA17 | AC22: =AC21+AC18+AC19 | AE22: =AE21+AE18+AE19 | AG22: =AG21+AG18+AG19+AG17
A24: 总例子数 | C24: 235 | E24: 303 | G24: 301 | H24: 155 | J24: 587 | L24: 270 | N24: 150 | P24: 200 | R24: 400 | U24: 450 | W24: 150 | Y24: 282 | AA24: 110 | AC24: 260 | AE24: 350 | AG24: 100
A26: 平均例子成本（总，不含差旅合CPS） | C26: =C21/C24 | E26: =E21/E24 | G26: =G21/G24 | J26: =J21/J24 | L26: =(L21)/L24 | N26: =(N21)/N24 | P26: =(P21)/P24 | R26: =(R21)/R24 | U26: =(U21)/U24 | W26: =(W21)/W24 | Y26: =(Y21)/Y24 | AA26: =(AA21)/AA24 | AC26: =AC21/AC24 | AE26: =AE21/AE24 | AG26: =(AG21)/AG24
A27: 平均例子成本（总，含差旅CPS） | C27: =C22/C24 | E27: =E22/E24 | G27: =G22/G24 | H27: =H22/H24 | J27: =J22/J24 | L27: =L22/L24 | N27: =N22/N24 | P27: =P22/P24 | R27: =R22/R24 | U27: =U22/U24 | W27: =W22/W24 | Y27: =Y22/Y24 | AA27: =AA22/AA24 | AC27: =AC22/AC24 | AE27: =AE22/AE24 | AG27: =AG22/AG24
A30: 成本（展位搭建礼品物流餐费） | C30: =C4+C5+C6+C14+C15 | D30: =D4+D5+D6+D14+D15 | E30: 53374.3 | G30: =G4+G5+G6+G14+G15 | J30: =J4+J5+J6+J14+J15 | L30: =L4+L5+L6+L14+L15 | N30: =N4+N5+N6+N14+N15 | P30: =P4+P5+P6+P14+P15 | R30: =R4+R5+R6+R14+R15 | U30: =U4+U5+U6+U14+U15 | AA30: =AA4+AA5+AA6+AA14+AA15 | AG30: =AG4+AG5+AG6+AG14+AG15
A31: 平均例子成本（展位搭建礼品物流餐费） | C31: =C30/C24 | E31: =E30/E24 | G31: =G30/G24 | J31: =J30/J24 | L31: =L30/L24 | N31: =N30/N24 | P31: =P30/P24 | R31: =R30/R24 | U31: =U30/U24 | AA31: =AA30/AA24 | AG31: =AG30/AG24
K34: 代理CPS费用 | L34: =(270-140)*9%*4500*30%

Sheet BB展ROI测算数据
F2: 主投思维 | I2: 2025/2/14-16日 | K2: 2025年5月3-5日 | L2: 2025年5月23-25日 | M2: 45689 | N2: 45870 | O2: 2026年2月6-8日 | P2: 2026年2月6-8日
B3: 参数：8月初 | C3: 益智 | D3: 美术 | H3: 9月兒童書展 | I3: 12月兒童書展 | J3: 2月BB展 | K3: 課外活動展 | L3: 5月兒童展 | M3: 2月BB展 | N3: 8月BB展 | O3: 3月BB展 | P3: 3月BB展
B4: 单例子销售固定人工成本 | C4: 89.09 | D4: 83.45 | F4: 链路合计 | G4: ROI 2 | H4: =H5/H6 | I4: =I5/I6 | J4: =J5/J6 | K4: =K5/K6 | L4: =L5/L6 | M4: =M5/M6 | N4: =N5/N6 | O4: =O5/O6 | P4: =P5/P6
B5: 单例子TMK人工成本 | C5: 8.99 | D5: 8.99 | F5: 链路合计 | G5: GMV | H5: =H17+H35 | I5: =I17+I35 | J5: =J17+J35 | K5: =K17+K35 | L5: =L17+L35 | M5: =M17+M35 | N5: =N17+N35 | O5: =O17+O35 | P5: =P17+P35
B6: 销售提成比例 | C6: 0.0894 | D6: 0.0839 | F6: 链路合计 | G6: ROI 2成本项 | H6: =H36+H18 | I6: =I36+I18 | J6: =J36+J18 | K6: =K36+K18 | L6: =L36+L18 | M6: =M36+M18 | N6: =N36+N18 | O6: =O36+O18 | P6: =P36+P18
B7: 礼品及其他费用比例 | C7: 0.0132 | D7: 0.0155 | F7: 链路合计 | G7: 渠道预算 | H7: 97616 | I7: 145759.8 | J7: 41427.9 | K7: 51452.7 | L7: 60000 | M7: =[1]開支總表!C15 | N7: =M7 | O7: =[1]開支總表!E15 | P7: =[1]開支總表!F15
B8: 试听课单课时成本 | C8: 83.03 | D8: 74.31 | F8: 入場人數 | H8: 300000 | I8: 380000 | J8: 150000 | K8: 150000 | L8: 300000 | M8: 50000 | N8: 50000 | O8: 50000 | P8: 50000
B9: 单例子市场运营人工及日常成本 | C9: 100 | D9: 100 | F9: 主投 | G9: 例子数 | H9: 420 | I9: 360 | J9: 235 | K9: 303 | L9: 301 | M9: 235 | N9: 328 | O9: =(M9+N9)/2 | P9: =O9
F10: 主投 | G10: 例子分发率 | H10: =H14/H9 | I10: =H10 | J10: =H10 | K10: =I10 | L10: =K10 | M10: =K10 | N10: =L10 | O10: =M10 | P10: =N10
F11: 主投 | G11: 例子到课率 | H11: =H15/H9 | I11: 0.517 | J11: 0.51 | K11: =82.8%*86.9% | L11: =77.7%*77.8% | M11: 0.535 | N11: 0.52 | O11: =(M11+N11)/2 | P11: =O11
F12: 主投 | G12: 滚动转化率 | H12: =H16/H9 | I12: 0.094 | J12: 0.085 | K12: 0.139 | L12: 0.09 | M12: 0.085 | N12: 0.052 | O12: =(M12+N12)/2 | P12: =O12
F13: 主投 | G13: ASP | H13: =H17/H16 | I13: 3943 | J13: 4444 | K13: 4220 | L13: 4898 | M13: 4444 | N13: 4329 | O13: 4444 | P13: 4444
F14: 主投 | G14: 分发数 | H14: 416 | I14: =I$9*I10 | J14: =J$9*J10 | K14: =K$9*K10 | L14: =L$9*L10 | M14: =M$9*M10 | N14: =N$9*N10 | O14: =O$9*O10 | P14: =P$9*P10
F15: 主投 | G15: 到课数 | H15: 281 | I15: =I$9*I11 | J15: =J$9*J11 | K15: =K$9*K11 | L15: =L$9*L11 | M15: =M$9*M11 | N15: =N$9*N11 | O15: =O$9*O11 | P15: =P$9*P11
F16: 主投 | G16: 转化数 | H16: 43 | I16: =I$9*I12 | J16: =J$9*J12 | K16: =K$9*K12 | L16: =L$9*L12 | M16: =M$9*M12 | N16: =N$9*N12 | O16: =O$9*O12 | P16: =P$9*P12
F17: 主投 | G17: GMV | H17: 181744 | I17: =I13*I16 | J17: =J13*J16 | K17: =K13*K16 | L17: =L13*L16 | M17: =M13*M16 | N17: =N13*N16 | O17: =O13*O16 | P17: =P13*P16
F18: 主投 | G18: ROI 2成本项 | H18: =SUM(H19:H23)+H7 | I18: =SUM(I19:I23)+I7 | J18: =SUM(J19:J23)+J7 | K18: =SUM(K19:K23)+K7 | L18: =SUM(L19:L23)+L7 | M18: =SUM(M19:M23)+M7 | N18: =SUM(N19:N23)+N7 | O18: =SUM(O19:O23)+O7 | P18: =SUM(P19:P23)+P7
F19: 主投 | G19: 销售固定成本 | H19: =H14*$C$4 | I19: =I14*$C$4 | J19: =J14*$C$4 | K19: =K14*$C$4 | L19: =L14*$C$4 | M19: =M14*$C$4 | N19: =N14*$C$4 | O19: =O14*$C$4 | P19: =P14*$C$4
F20: 主投 | G20: 销售变动成本 | H20: =H17*($C$6+$C$7) | I20: =I17*($C$6+$C$7) | J20: =J17*($C$6+$C$7) | K20: =K17*($C$6+$C$7) | L20: =L17*($C$6+$C$7) | M20: =M17*($C$6+$C$7) | N20: =N17*($C$6+$C$7) | O20: =O17*($C$6+$C$7) | P20: =P17*($C$6+$C$7)
F21: 主投 | G21: TMK费用 | H21: =H9*$C$5 | I21: =I9*$C$5 | J21: =J9*$C$5 | K21: =K9*$C$5 | L21: =L9*$C$5 | M21: =M9*$C$5 | N21: =N9*$C$5 | O21: =O9*$C$5 | P21: =P9*$C$5
F22: 主投 | G22: DEMO费用 | H22: =H14*$C$8 | I22: =I15*$C$8 | J22: =J15*$C$8 | K22: =K15*$C$8 | L22: =L15*$C$8 | M22: =M15*$C$8 | N22: =N15*$C$8 | O22: =O15*$C$8 | P22: =P15*$C$8
F23: 主投 | G23: 运营人工成本 | H23: =H9*$C$9/2 | I23: =I9*$C$9/2 | J23: =J9*$C$9/2 | K23: =K9*$C$9/2 | L23: =L9*$C$9/2 | M23: =M9*$C$9/2 | N23: =N9*$C$9/2 | O23: =O9*$C$9/2 | P23: =P9*$C$9/2
F24: 主投 | G24: ROI 2 | H24: =H17/H18 | I24: =I17/I18 | J24: =J17/J18 | K24: =K17/K18 | L24: =L17/L18 | M24: =M17/M18 | N24: =N17/N18 | O24: =O17/O18 | P24: =P17/P18
F26: 辅投 | G26: 联投率 | H26: =H27/H9 | I26: 0.85 | J26: 0.85 | K26: 0.85 | L26: 0.85
F27: 辅投 | G27: 例子数 | H27: 419 | I27: =I9*I26 | J27: =J9*J26 | K27: =K9*K26 | L27: =L9*L26
F28: 辅投 | G28: 例子分发率 | H28: =H32/H27 | I28: 0.39 | J28: 0.5 | K28: 0.5 | L28: 0.47
F29: 辅投 | G29: 例子到课率 | H29: =H33/H27 | I29: 0.28 | J29: 0.29 | K29: 0.44 | L29: 0.34
F30: 辅投 | G30: 滚动转化率 | H30: =H34/H27 | I30: =H30 | J30: 0.043 | K30: 0.032 | L30: 0.016
F31: 辅投 | G31: ASP | H31: =H35/H34 | I31: 3045 | J31: 2837 | K31: 3588 | L31: 4568
F32: 辅投 | G32: 分发数 | H32: 418 | I32: =I$27*I28 | J32: =J$27*J28 | K32: =K$27*K28 | L32: =L$27*L28 | M32: =M$27*M28 | N32: =N$27*N28 | O32: =O$27*O28 | P32: =P$27*P28
F33: 辅投 | G33: 到课数 | H33: 161 | I33: =I$27*I29 | J33: =J$27*J29 | K33: =K$27*K29 | L33: =L$27*L29 | M33: =M$27*M29 | N33: =N$27*N29 | O33: =O$27*O29 | P33: =P$27*P29
F34: 辅投 | G34: 转化数 | H34: 12 | I34: =I$27*I30 | J34: =J$27*J30 | K34: =K$27*K30 | L34: =L$27*L30 | M34: =M$27*M30 | N34: =N$27*N30 | O34: =O$27*O30 | P34: =P$27*P30
F35: 辅投 | G35: GMV | H35: 37457 | I35: =I31*I34 | J35: =J31*J34 | K35: =K31*K34 | L35: =L31*L34 | M35: =M31*M34 | N35: =N31*N34 | O35: =O31*O34 | P35: =P31*P34
F36: 辅投 | G36: ROI 2成本项 | H36: =SUM(H37:H41) | I36: =SUM(I37:I41) | J36: =SUM(J37:J41) | K36: =SUM(K37:K41) | L36: =SUM(L37:L41) | M36: =SUM(M37:M41) | N36: =SUM(N37:N41) | O36: =SUM(O37:O41) | P36: =SUM(P37:P41)
F37: 辅投 | G37: 销售固定成本 | H37: =H32*$D$4 | I37: =I32*$D$4 | J37: =J32*$D$4 | K37: =K32*$D$4 | L37: =L32*$D$4 | M37: =M32*$D$4 | N37: =N32*$D$4 | O37: =O32*$D$4 | P37: =P32*$D$4
F38: 辅投 | G38: 销售变动成本 | H38: =H35*($D$6+$D$7) | I38: =I35*($D$6+$D$7) | J38: =J35*($D$6+$D$7) | K38: =K35*($D$6+$D$7) | L38: =L35*($D$6+$D$7) | M38: =M35*($D$6+$D$7) | N38: =N35*($D$6+$D$7) | O38: =O35*($D$6+$D$7) | P38: =P35*($D$6+$D$7)
F39: 辅投 | G39: TMK费用 | H39: =H27*$D$5 | I39: =I27*$D$5 | J39: =J27*$D$5 | K39: =K27*$D$5 | L39: =L27*$D$5 | M39: =M27*$D$5 | N39: =N27*$D$5 | O39: =O27*$D$5 | P39: =P27*$D$5
F40: 辅投 | G40: DEMO费用 | H40: =H32*$D$8 | I40: =I33*$D$8 | J40: =J33*$D$8 | K40: =K33*$D$8 | L40: =L33*$D$8 | M40: =M33*$D$8 | N40: =N33*$D$8 | O40: =O33*$D$8 | P40: =P33*$D$8
F41: 辅投 | G41: 运营人工成本 | H41: =H27*$D$9/2 | I41: =I27*$D$9/2 | J41: =J27*$D$9/2 | K41: =K27*$D$9/2 | L41: =L27*$D$9/2 | M41: =M27*$D$9/2 | N41: =N27*$D$9/2 | O41: =O27*$D$9/2 | P41: =P27*$D$9/2
F42: 辅投 | G42: ROI 2 | H42: =H35/H36 | I42: =I35/I36 | J42: =J35/J36 | K42: =K35/K36 | L42: =L35/L36 | M42: =M35/M36 | N42: =N35/N36 | O42: =O35/O36 | P42: =P35/P36

Sheet BB展ROI测算数据 (2)
F2: 主投思维
B3: 参数：8月初 | C3: 益智 | D3: 美术 | H3: 4月澳門展
B4: 单例子销售固定人工成本 | C4: 89.09 | D4: 83.45 | F4: 链路合计 | G4: ROI 2 | H4: =H5/H6
B5: 单例子TMK人工成本 | C5: 8.99 | D5: 8.99 | F5: 链路合计 | G5: GMV | H5: =H19+H37
B6: 销售提成比例 | C6: 0.0894 | D6: 0.0839 | F6: 链路合计 | G6: ROI 2成本项 | H6: =H38+H20
B7: 礼品及其他费用比例 | C7: 0.0132 | D7: 0.0155 | F7: 链路合计 | G7: 渠道预算 | H7: 21696.9
B8: 试听课单课时成本 | C8: 83.03 | D8: 74.31 | F8: 入場人數 | H8: 300000
B9: 单例子市场运营人工及日常成本 | C9: 100 | D9: 100 | F9: 主投 | G9: 例子数 | H9: 110
F10: 主投 | G10: 例子分发率 | H10: =H15/H9
F11: 主投 | G11: 例子约课率 | H11: 0.75
F12: 主投 | G12: 例子到课率 | H12: =H17/H9
F13: 主投 | G13: 滚动转化率 | H13: =H18/H9
F14: 主投 | G14: ASP | H14: =H19/H18
F15: 主投 | G15: 分发数 | H15: 110
F16: 主投 | G16: 约课数 | H16: =H9*H11
F17: 主投 | G17: 到课数 | H17: =H16*0.8
F18: 主投 | G18: 转化数 | H18: =H9*10%
F19: 主投 | G19: GMV | H19: =H18*4500
F20: 主投 | G20: ROI 2成本项 | H20: =SUM(H21:H25)+H7
F21: 主投 | G21: 销售固定成本 | H21: =H15*$C$4
F22: 主投 | G22: 销售变动成本 | H22: =H19*($C$6+$C$7)
F23: 主投 | G23: TMK费用 | H23: =H9*$C$5
F24: 主投 | G24: DEMO费用 | H24: =H15*$C$8
F25: 主投 | G25: 运营人工成本 | H25: =H9*$C$9/2
F26: 主投 | G26: ROI 2 | H26: =H19/H20

Sheet 回本预测
A1: 当前消耗月份数 | B1: KOL | C1: 目前总cpt+投放消耗 | D1: 剩余cpt | E1: 全额CPT+投放消耗 | F1: 投放消耗 | G1: 其他截至目前成本 | H1: 全额CPT+投放消耗总成本 | I1: 投放消耗+其他成本 | J1: 总GMV | K1: ROI2 | L1: ROI2 | M1: ROI1 | N1: 成本Gap | O1: CPT成本/天 | P1: 历史单例子成本 | Q1: 单例子成本/个 | R1: 历史约课率 | S1: 约课率预设 | T1: 历史出席率 | U1: 出席率预设 | V1: 历史滚转 | W1: 滚转预设 | X1: 历史ASP | Y1: ASP预设 | Z1: 单例子链路成本 | AA1: 历史ROI2 | AB1: 目标ROI2 | AC1: 最低ROI2 | AD1: 单例子利润 | AE1: 例子缺口
K2: （全额CPT+投放消耗+其他成本） | L2: （投放消耗+其他成本） | M2: （仅投放消耗）
A3: 92天 | B3: 陈琪-汇总 | C3: 821009 | D3: 8184 | E3: 829193 | F3: 761853 | G3: 463124 | H3: 1292317 | I3: 1224977 | J3: 1447546 | K3: 1.12 | L3: 1.18 | M3: 1.9
A4: 90天 | B4: 孙慧雪-汇总 | C4: 430793 | D4: 0 | E4: 430793 | F4: 365693 | G4: 168630 | H4: 599423 | I4: 534323 | J4: 550196 | K4: 0.92 | L4: 1.03 | M4: 1.5
B5: 陈倩扬-汇总 | C5: 215431 | D5: 0 | E5: 215431 | F5: 170791 | G5: 90137 | H5: 305568 | I5: 260928 | J5: 292684 | K5: 0.96 | L5: 1.12 | M5: 1.71
A6: 90天 | B6: Bob-汇总 | C6: 363482 | D6: 0 | E6: 363482 | F6: 293732 | G6: 140020 | H6: 503503 | I6: 433753 | J6: 442780 | K6: 0.88 | L6: 1.02 | M6: 1.51
A7: 110天 | B7: 陈山聪-汇总 | C7: 372628 | D7: 4883 | E7: 377510 | F7: 318920 | G7: 128442 | H7: 505952 | I7: 447362 | J7: 417480 | K7: 0.83 | L7: 0.93 | M7: 1.31
A8: 90天 | B8: 陈敏之-汇总 | C8: 385930 | D8: 0 | E8: 385930 | F8: 318040 | G8: 138038 | H8: 523968 | I8: 456078 | J8: 449736 | K8: 0.86 | L8: 0.99 | M8: 1.41
A9: 90天 | B9: 林子善-汇总 | C9: 228248 | D9: 0 | E9: 228248 | F9: 186398 | G9: 70148 | H9: 298396 | I9: 256546 | J9: 197777 | K9: 0.66 | L9: 0.77 | M9: 1.06 | N9: =(J9-H9)*AC9 | O9: =(E9-F9)/90 | P9: 741 | Q9: 700 | R9: 0.474 | S9: 0.5 | T9: 0.367 | U9: 0.38 | V9: 0.1364 | W9: 0.18 | X9: 4709 | Y9: 5000 | Z9: 535 | AA9: 0.65 | AB9: 1.04 | AC9: 0.8 | AD9: =W9*Y9*(AB9-AC9) | AE9: =N9/AD9
A10: 80天 | B10: mamidaily-汇总 | C10: 117328 | D10: 6148 | E10: 123476 | F10: 68141 | G10: 22947 | H10: 146422 | I10: 91087 | J10: 79620 | K10: 0.54 | L10: 0.87 | M10: 1.17 | N10: =(J10-H10)*AC10 | O10: =(E10-F10)/90 | P10: 1333 | Q10: 700 | R10: 0.568 | S10: 0.55 | T10: 0.488 | U10: 0.45 | V10: 0.1705 | W10: 0.2 | X10: 5308 | Y10: 5000 | Z10: 632 | AA10: 0.56 | AB10: 1.06 | AC10: 0.8 | AD10: =W10*Y10*(AB10-AC10) | AE10: =N10/AD10
A11: 62天 | B11: 吴若希-汇总 | C11: 107349 | D11: 19675 | E11: 127023 | F11: 63783 | G11: 16145 | H11: 143168 | I11: 79928 | J11: 30116 | K11: 0.21 | L11: 0.38 | M11: 0.47 | N11: =(J11-H11)*AC11 | O11: =(E11-F11)/90 | P11: 1278 | Q11: 700 | R11: 0.4643 | S11: 0.5 | T11: 0.369 | U11: 0.38 | V11: 0.0833 | W11: 0.15 | X11: 4302 | Y11: 4500 | Z11: 535 | AA11: 0.24 | AB11: 0.65 | AC11: 0.8 | AD11: =W11*Y11*(AB11-AC11) | AE11: 无限，回不了
A12: 40天 | B12: 张美妮-汇总 | C12: 35855 | D12: 13950 | E12: 49805 | F12: 24695 | G12: 5368 | H12: 55173 | I12: 30063 | J12: 3588 | K12: 0.07 | L12: 0.12 | M12: 0.15 | N12: =(J12-H12)*AC12 | O12: =(E12-F12)/90 | P12: 1019 | Q12: 700 | R12: 0.3143 | S12: 0.45 | T12: 0.379 | U12: 0.38 | V12: 0.0286 | W12: 0.15 | X12: 3588 | Y12: 4500 | Z12: 632 | AA12: 0.22 | AB12: 0.76 | AC12: 0.8 | AD12: =W12*Y12*(AB12-AC12) | AE12: 无限，回不了
A13: 31天 | B13: 钟嘉欣-汇总 | C13: 193227 | D13: 341000 | E13: 534227 | F13: 162227 | G13: 79003 | H13: 613230 | I13: 241230 | J13: 168804 | K13: 0.28 | L13: 0.70 | M13: 1.04
A14: 10天 | B14: 蔡雪莹-汇总 | C14: 12336 | D14: 23147 | E14: 35482 | F14: 9442 | G14: 5909 | H14: 41391 | I14: 15351 | J14: 0 | K14: 0 | L14: 0.00 | M14: 0
B15: 汇总 | C15: 3413150 | D15: 416986 | E15: 3830136 | F15: 2822101 | G15: 1353477 | H15: 5183613 | I15: 4175578 | J15: 4136648 | K15: 0.8 | L15: 0.99 | M15: 1.47
P16: 本月分摊 | AF16: 定标
A17: 180天 | B17: 陈琪（直播） | D17: =70000*0.93 | N17: =0-D17 | P17: =N17*0.5 | Q17: 600 | S17: 0.5 | U17: 0.38 | W17: 0.18 | Y17: 5000 | AB17: 0.97 | AC17: 0.8 | AD17: =W17*Y17*(AB17-AC17) | AE17: =P17/AD17 | AF17: 240
A18: 90天 | B18: 陈展鹏 | D18: =100000*0.93 | N18: =0-D18 | P18: =N18*0.5*0.5 | Q18: 600 | S18: 0.5 | U18: 0.38 | W18: 0.18 | Y18: 5000 | AB18: 0.98 | AC18: 0.8 | AD18: =W18*Y18*(AB18-AC18) | AE18: =P18/AD18 | AF18: 170
A19: 90天 | B19: 鄧明儀 | D19: =18000*0.93 | N19: =0-D19 | P19: =N19*0.5*0.5 | Q19: 600 | S19: 0.5 | U19: 0.38 | W19: 0.18 | Y19: 5000 | AB19: 0.98 | AC19: 0.8 | AD19: =W19*Y19*(AB19-AC19) | AE19: =P19/AD19 | AF19: 35
A20: 90天 | B20: 陳凱琳 | D20: =200000*0.93 | N20: =0-D20 | P20: =N20*0.5*0.5 | Q20: 600 | S20: 0.5 | U20: 0.38 | W20: 0.18 | Y20: 5000 | AB20: 0.98 | AC20: 0.8 | AD20: =W20*Y20*(AB20-AC20) | AE20: =P20/AD20 | AF20: 300

Sheet 历史KOL数据
J1: 主投 | AP1: 辅投 | BR1: 汇总
B2: 渠道组 | C2: 供应商 | D2: 渠道名称 | E2: 主投 | F2: 辅投 | G2: 结算方式 | H2: 当月CPT金额 | I2: 滚动消耗 | J2: 滚动消耗(不含赠课成本) | K2: 单例子成本 | L2: 例子数 | M2: 分发数 | N2: 剔除毛例子 分发数 | O2: 约课数 | P2: 到课数 | Q2: 滚动到课数 | R2: 当月成交数 | S2: 滚动成交数 | T2: 当月GMV | U2: 滚动GMV | V2: 海外GMV占比 | W2: 滚动ASP | X2: 例子分发率 | Y2: 分发约课率 | Z2: 例子约课率 | AA2: 约课到课率 | AB2: 滚动应到课率 | AC2: 到课转化率 | AD2: 注册转化率 | AE2: 滚动转化率 | AF2: 滚动ROI2总成本 | AG2: 滚动ROI2 | AH2: 滚动应到课人数 | AI2: 滚动到课人数 | AJ2: 滚动到课人次 | AK2: 运营成本 | AL2: 销售固定成本 | AM2: 销售变动成本 | AN2: TMK费用 | AO2: DEMO费用 | AP2: 例子数 | AQ2: 分发数 | AR2: 剔除毛例子分发数 | AS2: 约课数 | AT2: 到课数 | AU2: 滚动到课数 | AV2: 当月成交 | AW2: 滚动成交数 | AX2: 当月GMV | AY2: 滚动GMV | AZ2: 海外GMV占比 | BA2: 滚动ASP | BB2: 例子分发率 | BC2: 分发约课率 | BD2: 例子约课率 | BE2: 约课到课率 | BF2: 滚动应到课率 | BG2: 到课转化率 | BH2: 注册转化率 | BI2: 滚动转化率 | BJ2: 滚动应到课人数 | BK2: 滚动到课人数 | BL2: 滚动到课人次 | BM2: 运营成本 | BN2: 销售固定成本 | BO2: 销售变动成本 | BP2: TMK费用 | BQ2: DEMO费用 | BR2: 当月GMV | BS2: 滚动GMV | BT2: 海外GMV占比 | BU2: 滚动其他成本 | BV2: 同源其他成本 | BW2: 运营成本 | BX2: 滚动消耗 | BY2: 同源消耗 | BZ2: 当月ROI2总成本 | CA2: 当月ROI2 | CB2: 滚动赠课成本 | CC2: 滚动ROI2总成本 | CD2: 滚动ROI2 | CE2: O-ROI总成本 | CF2: O-ROI
A3: 2024年-12月陈琪 | C3: 陈琪 | D3: KOLHK-香港-陈琪-Shukei-思维&美术 | E3: 思维 | F3: 美术 | G3: CPT | I3: 33739 | J3: 33739 | K3: 177 | L3: 191 | M3: 138 | N3: 139 | O3: 91 | P3: 63 | Q3: 63 | R3: 15 | S3: 15 | T3: 59520 | U3: 59520 | V3: 1 | W3: 3968 | X3: 0.723 | Y3: 0.659 | Z3: 0.476 | AA3: 0.692 | AB3: 0.955 | AC3: 0.238 | AD3: 0.079 | AE3: 0.079 | AF3: 50678 | AG3: 1.17 | AH3: 66 | AI3: 63 | AJ3: 69 | AK3: 11247 | AL3: 16717 | AM3: 6655 | AN3: 1781 | AO3: 5844 | AP3: 190 | AQ3: 26 | AR3: 26 | AS3: 31 | AT3: 23 | AU3: 23 | AV3: 3 | AW3: 3 | AX3: 12498 | AY3: 12498 | AZ3: 1 | BA3: 4166 | BB3: 0.137 | BC3: 1.192 | BD3: 0.163 | BE3: 0.742 | BF3: 0.767 | BG3: 0.13 | BH3: 0.016 | BI3: 0.016 | BJ3: 30 | BK3: 23 | BL3: 23 | BM3: 8938 | BN3: 4012 | BO3: 1313 | BP3: 1853 | BQ3: 1980 | BR3: 72018 | BS3: 72018 | BT3: 1 | BU3: 40155 | BV3: 40035 | BW3: 20185 | BX3: 33739 | BY3: 33739 | BZ3: 93959 | CA3: 0.77 | CC3: 94080 | CD3: 0.77 | CE3: 77472 | CF3: 0.93
A4: 2025年-1月陈琪 | C4: 陈琪 | D4: KOLHK-香港-陈琪-Shukei-思维&美术 | E4: 思维 | F4: 美术 | G4: CPT | I4: 40592 | J4: 40592 | K4: 344 | L4: 118 | M4: 45 | N4: 48 | O4: 48 | P4: 40 | Q4: 51 | R4: 14 | S4: 15 | T4: 69532 | U4: 73220 | V4: 1 | W4: 4881 | X4: 0.381 | Y4: 1.067 | Z4: 0.407 | AA4: 0.833 | AB4: 0.962 | AC4: 0.35 | AD4: 0.119 | AE4: 0.127 | AF4: 73894 | AG4: 0.99 | AH4: 53 | AI4: 51 | AJ4: 57 | AK4: 14458 | AL4: 6862 | AM4: 6046 | AN4: 1311 | AO4: 4627 | AP4: 118 | AQ4: 30 | AR4: 36 | AS4: 29 | AT4: 17 | AU4: 19 | AV4: 2 | AW4: 2 | AX4: 6529 | AY4: 6529 | AZ4: 1 | BA4: 3265 | BB4: 0.254 | BC4: 0.967 | BD4: 0.246 | BE4: 0.586 | BF4: 0.559 | BG4: 0.118 | BH4: 0.017 | BI4: 0.017 | BJ4: 34 | BK4: 19 | BL4: 20 | BM4: 13720 | BN4: 3869 | BO4: 610 | BP4: 1311 | BQ4: 1631 | BR4: 76061 | BS4: 79749 | BT4: 1 | BU4: 26266 | BV4: 23751 | BW4: 28178 | BX4: 40592 | BY4: 40592 | BZ4: 92520 | CA4: 0.82 | CC4: 95035 | CD4: 0.84 | CE4: 84558 | CF4: 0.94
A5: 2025年-2月陈琪 | C5: 陈琪 | D5: KOLHK-香港-陈琪-Shukei-思维&美术 | E5: 思维 | F5: 美术 | G5: CPT | I5: 48635 | J5: 48635 | K5: 269 | L5: 181 | M5: 85 | N5: 86 | O5: 90 | P5: 64 | Q5: 72 | R5: 23 | S5: 27 | T5: 118186 | U5: 138838 | V5: 1 | W5: 5142 | X5: 0.47 | Y5: 1.059 | Z5: 0.497 | AA5: 0.711 | AB5: 0.947 | AC5: 0.359 | AD5: 0.127 | AE5: 0.149 | AF5: 93017 | AG5: 1.49 | AH5: 76 | AI5: 72 | AJ5: 78 | AK5: 12472 | AL5: 11124 | AM5: 12886 | AN5: 1250 | AO5: 6649 | AP5: 164 | AQ5: 46 | AR5: 49 | AS5: 52 | AT5: 21 | AU5: 24 | AV5: 2 | AW5: 2 | AX5: 7176 | AY5: 7176 | AZ5: 1 | BA5: 3588 | BB5: 0.28 | BC5: 1.13 | BD5: 0.317 | BE5: 0.404 | BF5: 0.453 | BG5: 0.095 | BH5: 0.012 | BI5: 0.012 | BJ5: 53 | BK5: 24 | BL5: 25 | BM5: 10654 | BN5: 4401 | BO5: 691 | BP5: 1198 | BQ5: 1847 | BR5: 125362 | BS5: 146014 | BT5: 1 | BU5: 40047 | BV5: 36743 | BW5: 23126 | BX5: 48635 | BY5: 48635 | BZ5: 108503 | CA5: 1.16 | CC5: 111808 | CD5: 1.31 | CE5: 114557 | CF5: 1.27
A6: 2025年-3月陈琪 | C6: 陈琪 | D6: KOLHK-香港-陈琪-Shukei-思维&美术 | E6: 思维 | F6: 美术 | G6: CPT | I6: 113250 | J6: 113250 | K6: 380 | L6: 298 | M6: 142 | N6: 146 | O6: 152 | P6: 117 | Q6: 132 | R6: 47 | S6: 55 | T6: 243836 | U6: 275640 | V6: 1 | W6: 5012 | X6: 0.477 | Y6: 1.07 | Z6: 0.51 | AA6: 0.77 | AB6: 0.95 | AC6: 0.402 | AD6: 0.158 | AE6: 0.185 | AF6: 193915 | AG6: 1.42 | AH6: 139 | AI6: 132 | AJ6: 138 | AK6: 26636 | AL6: 14433 | AM6: 26387 | AN6: 2005 | AO6: 11202 | AP6: 18 | AQ6: 17 | AR6: 25 | AS6: 17 | AT6: 10 | AU6: 13 | AV6: 2 | AW6: 2 | AX6: 7735 | AY6: 7735 | AZ6: 1 | BA6: 3868 | BB6: 0.944 | BC6: 1 | BD6: 0.944 | BE6: 0.588 | BF6: 0.542 | BG6: 0.2 | BH6: 0.111 | BI6: 0.111 | BJ6: 24 | BK6: 13 | BL6: 14 | BM6: 1471 | BN6: 2100 | BO6: 760 | BP6: 121 | BQ6: 1142 | BR6: 251571 | BS6: 283375 | BT6: 1 | BU6: 58151 | BV6: 52577 | BW6: 28107 | BX6: 113250 | BY6: 113250 | BZ6: 193935 | CA6: 1.3 | CC6: 199509 | CD6: 1.42 | CE6: 195102 | CF6: 1.45
A7: 2025年-4月陈琪 | C7: 陈琪 | D7: KOLHK-香港-陈琪-Shukei-思维&美术 | E7: 思维 | F7: 美术 | G7: CPT | I7: 131732 | J7: 131732 | K7: 540 | L7: 244 | M7: 122 | N7: 128 | O7: 127 | P7: 100 | Q7: 124 | R7: 41 | S7: 48 | T7: 180708 | U7: 211424 | V7: 1 | W7: 4405 | X7: 0.5 | Y7: 1.041 | Z7: 0.52 | AA7: 0.787 | AB7: 0.984 | AC7: 0.41 | AD7: 0.168 | AE7: 0.197 | AF7: 210353 | AG7: 1.01 | AH7: 126 | AI7: 124 | AJ7: 134 | AK7: 27025 | AL7: 18959 | AM7: 18955 | AN7: 2412 | AO7: 11270 | AP7: 20 | AQ7: 18 | AR7: 20 | AS7: 18 | AT7: 11 | AU7: 13 | AV7: 0 | AW7: 0 | AX7: 0 | AY7: 0 | BB7: 0.9 | BC7: 1 | BD7: 0.9 | BE7: 0.611 | BF7: 0.65 | BG7: 0 | BH7: 0 | BI7: 0 | BJ7: 20 | BK7: 13 | BL7: 14 | BM7: 2093 | BN7: 2050 | BO7: 0 | BP7: 198 | BQ7: 1114 | BR7: 180708 | BS7: 211424 | BT7: 1 | BU7: 54958 | BV7: 48849 | BW7: 29118 | BX7: 131732 | BY7: 131732 | BZ7: 209699 | CA7: 0.86 | CC7: 215808 | CD7: 0.98 | CE7: 206490 | CF7: 1.02
A8: 2025年-5月陈琪 | I8: 163228 | J8: 163228 | K8: 633 | L8: 258 | M8: 119 | N8: 124 | O8: 116 | P8: 84 | Q8: 106 | R8: 34 | S8: 45 | T8: 171724 | U8: 222292 | V8: 1 | W8: 4940 | X8: 0.461 | Y8: 0.975 | Z8: 0.45 | AA8: 0.724 | AB8: 0.955 | AC8: 0.405 | AD8: 0.132 | AE8: 0.174 | AF8: 226867 | AG8: 0.98 | AH8: 111 | AI8: 106 | AJ8: 116 | AK8: 14628 | AL8: 15218 | AM8: 21318 | AN8: 2399 | AO8: 10076 | AP8: 6 | AQ8: 5 | AR8: 6 | AS8: 5 | AT8: 3 | AU8: 6 | AV8: 0 | AW8: 0 | AX8: 0 | AY8: 0 | BB8: 0.833 | BC8: 1 | BD8: 0.833 | BE8: 0.6 | BF8: 0.75 | BG8: 0 | BH8: 0 | BI8: 0 | BJ8: 8 | BK8: 6 | BL8: 6 | BM8: 281 | BN8: 656 | BO8: 0 | BP8: 56 | BQ8: 466 | BR8: 171724 | BS8: 222292 | BT8: 1 | BU8: 50189 | BV8: 42212 | BW8: 14909 | BX8: 163228 | BY8: 163228 | BZ8: 220349 | CA8: 0.78 | CC8: 228326 | CD8: 0.97 | CE8: 233217 | CF8: 0.95
A9: 2025年-6月陈琪 | I9: 154847 | J9: 145314 | K9: 759 | L9: 204 | M9: 114 | N9: 124 | O9: 116 | P9: 96 | Q9: 130 | R9: 43 | S9: 53 | T9: 209284 | U9: 255664 | V9: 1 | W9: 4824 | X9: 0.559 | Y9: 1.018 | Z9: 0.569 | AA9: 0.828 | AB9: 0.929 | AC9: 0.448 | AD9: 0.211 | AE9: 0.26 | AF9: 220689 | AG9: 1.16 | AH9: 140 | AI9: 130 | AJ9: 150 | AK9: 12724 | AL9: 13936 | AM9: 24680 | AN9: 1647 | AO9: 12953 | AP9: 99 | AQ9: 30 | AR9: 30 | AS9: 29 | AT9: 17 | AU9: 20 | AV9: 1 | AW9: 1 | AX9: 3588 | AY9: 3588 | AZ9: 1 | BA9: 3588 | BB9: 0.303 | BC9: 0.967 | BD9: 0.293 | BE9: 0.586 | BF9: 0.625 | BG9: 0.059 | BH9: 0.01 | BI9: 0.01 | BJ9: 32 | BK9: 20 | BL9: 20 | BM9: 5542 | BN9: 2699 | BO9: 373 | BP9: 800 | BQ9: 1579 | BR9: 212872 | BS9: 259252 | BT9: 1 | BU9: 58844 | BV9: 48947 | BW9: 18322 | BX9: 154847 | BY9: 153067 | BZ9: 220336 | CA9: 0.97 | CB9: 9533 | CC9: 232013 | CD9: 1.12 | CE9: 236491 | CF9: 1.1
A10: 2025年-7月陈琪 | I10: 120482 | J10: 114209 | K10: 813 | L10: 148 | M10: 62 | N10: 69 | O10: 64 | P10: 52 | Q10: 77 | R10: 24 | S10: 35 | T10: 121912 | U10: 163880 | V10: 1 | W10: 4682 | X10: 0.419 | Y10: 1.032 | Z10: 0.432 | AA10: 0.813 | AB10: 0.963 | AC10: 0.462 | AD10: 0.162 | AE10: 0.236 | AF10: 160110 | AG10: 1.02 | AH10: 80 | AI10: 77 | AJ10: 87 | AK10: 6513 | AL10: 7240 | AM10: 16781 | AN10: 1523 | AO10: 7668 | AP10: 4 | AQ10: 3 | AR10: 4 | AS10: 4 | AT10: 2 | AU10: 2 | AV10: 0 | AW10: 1 | AX10: 0 | AY10: 1880 | AZ10: 1 | BA10: 1880 | BB10: 0.75 | BC10: 1.333 | BD10: 1 | BE10: 0.5 | BF10: 0.5 | BG10: 0 | BH10: 0 | BI10: 0.25 | BJ10: 4 | BK10: 2 | BL10: 2 | BM10: 0 | BN10: 379 | BO10: 197 | BP10: 41 | BQ10: 164 | BR10: 121912 | BS10: 165760 | BT10: 1 | BU10: 33996 | BV10: 26115 | BW10: 6513 | BX10: 120482 | BY10: 118443 | BZ10: 151071 | CA10: 0.81 | CB10: 6273 | CC10: 160991 | CD10: 1.03 | CE10: 165878 | CF10: 1
A11: 2025年-8月陈琪 | I11: 38341 | J11: 35866 | K11: 834 | L11: 46 | M11: 21 | N11: 25 | O11: 21 | P11: 16 | Q11: 36 | R11: 6 | S11: 14 | T11: 24028 | U11: 57832 | V11: 1 | W11: 4131 | X11: 0.457 | Y11: 1 | Z11: 0.457 | AA11: 0.762 | AB11: 1 | AC11: 0.375 | AD11: 0.13 | AE11: 0.304 | AF11: 55313 | AG11: 1.05 | AH11: 36 | AI11: 36 | AJ11: 38 | AK11: 4153 | AL11: 3088 | AM11: 5922 | AN11: 460 | AO11: 3349 | AP11: 0 | AQ11: 0 | AR11: 0 | AS11: 0 | AT11: 0 | AU11: 0 | AV11: 0 | AW11: 0 | AX11: 0 | AY11: 0 | BJ11: 0 | BK11: 0 | BL11: 0 | BM11: 0 | BN11: 0 | BO11: 0 | BP11: 0 | BQ11: 0 | BR11: 24028 | BS11: 57832 | BT11: 1 | BU11: 12819 | BV11: 7101 | BW11: 4153 | BX11: 38341 | BY11: 36927 | BZ11: 48180 | CA11: 0.5 | CB11: 2475 | CC11: 55313 | CD11: 1.05 | CE11: 54610 | CF11: 1.06
A12: 2025年-9月陈琪 | H12: 651 | I12: 23292 | J12: 22220 | K12: 597 | L12: 39 | M12: 18 | N12: 20 | O12: 19 | P12: 11 | Q12: 21 | R12: 3 | S12: 6 | T12: 11564 | U12: 22328 | V12: 1 | W12: 3721 | X12: 0.462 | Y12: 1.056 | Z12: 0.487 | AA12: 0.579 | AB12: 1 | AC12: 0.273 | AD12: 0.077 | AE12: 0.154 | AF12: 33904 | AG12: 0.66 | AH12: 21 | AI12: 21 | AJ12: 22 | AK12: 2955 | AL12: 2892 | AM12: 2507 | AN12: 390 | AO12: 1868 | AP12: 0 | AQ12: 0 | AR12: 1 | AS12: 0 | AT12: 0 | AU12: 0 | AV12: 0 | AW12: 0 | AX12: 0 | AY12: 0 | BJ12: 0 | BK12: 0 | BL12: 0 | BM12: 0 | BN12: 95 | BO12: 0 | BP12: 0 | BQ12: 0 | BR12: 11564 | BS12: 22328 | BT12: 1 | BU12: 7752 | BV12: 5225 | BW12: 2955 | BX12: 23292 | BY12: 22756 | BZ12: 30936 | CA12: 0.37 | CB12: 1072 | CC12: 33999 | CD12: 0.66 | CE12: 33969 | CF12: 0.66
A13: 2025年-10月陈琪 | H13: 651 | I13: 17360 | J13: 16109 | K13: 620 | L13: 28 | M13: 11 | N13: 12 | O13: 10 | P13: 9 | Q13: 12 | R13: 3 | S13: 7 | T13: 16464 | U13: 38447 | V13: 1 | W13: 5492 | X13: 0.393 | Y13: 0.909 | Z13: 0.357 | AA13: 0.9 | AB13: 1 | AC13: 0.333 | AD13: 0.107 | AE13: 0.25 | AF13: 26597 | AG13: 1.45 | AH13: 12 | AI13: 12 | AJ13: 15 | AK13: 1750 | AL13: 1707 | AM13: 4229 | AN13: 280 | AO13: 1271 | AP13: 0 | AQ13: 0 | AR13: 0 | AS13: 0 | AT13: 0 | AU13: 0 | AV13: 0 | AW13: 0 | AX13: 0 | AY13: 0 | BJ13: 0 | BK13: 0 | BL13: 0 | BM13: 0 | BN13: 0 | BO13: 0 | BP13: 0 | BQ13: 0 | BR13: 16464 | BS13: 38447 | BT13: 1 | BU13: 7488 | BV13: 4503 | BW13: 1750 | BX13: 17360 | BY13: 16645 | BZ13: 22898 | CA13: 0.72 | CB13: 1250 | CC13: 26597 | CD13: 1.45 | CE13: 26947 | CF13: 1.43
A14: 2025年-11月陈琪 | I14: 15316 | J14: 14780 | K14: 729 | L14: 21 | M14: 8 | N14: 9 | O14: 8 | P14: 6 | Q14: 8 | R14: 2 | S14: 3 | T14: 11318 | U14: 14817 | V14: 1 | W14: 4939 | X14: 0.381 | Y14: 1 | Z14: 0.381 | AA14: 0.75 | AB14: 1 | AC14: 0.333 | AD14: 0.095 | AE14: 0.143 | AF14: 20264 | AG14: 0.73 | AH14: 8 | AI14: 8 | AJ14: 8 | AK14: 1367 | AL14: 1063 | AM14: 1630 | AN14: 210 | AO14: 678 | AP14: 0 | AQ14: 0 | AR14: 0 | AS14: 0 | AT14: 0 | AU14: 0 | AV14: 0 | AW14: 0 | AX14: 0 | AY14: 0 | BJ14: 0 | BK14: 0 | BL14: 0 | BM14: 0 | BN14: 0 | BO14: 0 | BP14: 0 | BQ14: 0 | BR14: 11318 | BS14: 14817 | BT14: 1 | BU14: 3581 | BV14: 2908 | BW14: 1367 | BX14: 15316 | BY14: 15138 | BZ14: 19413 | CA14: 0.58 | CB14: 536 | CC14: 20264 | CD14: 0.73 | CE14: 20472 | CF14: 0.72
A15: 陈琪-汇总 | I15: 900815 | J15: 879674 | K15: 495 | L15: 1776 | M15: 885 | N15: 930 | O15: 862 | P15: 658 | Q15: 832 | R15: 255 | S15: 323 | T15: 1238076 | U15: 1533902 | W15: 4749 | X15: 0.4983 | Y15: 0.974 | Z15: 0.4854 | AA15: 0.7633 | AB15: 0.9703 | AC15: 0.3875 | AD15: 0.1436 | AE15: 0.1819 | AF15: 1365601 | AG15: 1.12 | AH15: 868 | AI15: 832 | AJ15: 912 | AK15: 135927 | AL15: 113240 | AM15: 147997 | AN15: 15669 | AO15: 77457 | AP15: 619 | AQ15: 175 | AR15: 197 | AS15: 185 | AT15: 104 | AU15: 120 | AV15: 10 | AW15: 11 | AX15: 37527 | AY15: 39407 | BA15: 3582 | BB15: 0.2827 | BC15: 1.0571 | BD15: 0.2989 | BE15: 0.5622 | BF15: 0.6056 | BG15: 0.0962 | BH15: 0.0162 | BI15: 0.0178 | BJ15: 205 | BK15: 120 | BL15: 124 | BM15: 42699 | BN15: 20262 | BO15: 3945 | BP15: 5577 | BQ15: 9922 | BR15: 1275603 | BS15: 1573309 | BU15: 394246 | BV15: 338966 | BW15: 178682 | BX15: 900815 | BY15: 894152 | BZ15: 1411800 | CA15: 0.9 | CB15: 21141 | CC15: 1473743 | CD15: 1.07 | CE15: 1449764 | CF15: 1.09
A16: 2025年-9月陈琪直播 | H16: 12912 | I16: 128084 | J16: 123440 | K16: 577 | L16: 222 | M16: 91 | N16: 91 | O16: 90 | P16: 69 | Q16: 69 | R16: 26 | S16: 26 | T16: 151688 | U16: 151688 | V16: 1 | W16: 5834 | X16: 0.41 | Y16: 0.989 | Z16: 0.405 | AA16: 0.767 | AB16: 0.972 | AC16: 0.377 | AD16: 0.117 | AE16: 0.117 | AF16: 183768 | AG16: 0.83 | AH16: 71 | AI16: 69 | AJ16: 76 | AK16: 16821 | AL16: 13158 | AM16: 17031 | AN16: 2220 | AO16: 6455 | AP16: 0 | AQ16: 0 | AR16: 0 | AS16: 0 | AT16: 0 | AU16: 0 | AV16: 0 | AW16: 0 | AX16: 0 | AY16: 0 | BJ16: 0 | BK16: 0 | BL16: 0 | BM16: 0 | BN16: 0 | BO16: 0 | BP16: 0 | BQ16: 0 | BR16: 151688 | BS16: 151688 | BT16: 1 | BU16: 38863 | BV16: 38863 | BW16: 16821 | BX16: 128084 | BY16: 128084 | BZ16: 183768 | CA16: 0.83 | CB16: 4645 | CC16: 183768 | CD16: 0.83 | CE16: 183598 | CF16: 0.83
A17: 2025年-10月陈琪直播 | H17: 12912 | I17: 173328 | J17: 168326 | K17: 510 | L17: 340 | M17: 105 | N17: 107 | O17: 107 | P17: 71 | Q17: 81 | R17: 25 | S17: 28 | T17: 161397 | U17: 177161 | V17: 1 | W17: 6327 | X17: 0.309 | Y17: 1.019 | Z17: 0.315 | AA17: 0.664 | AB17: 1 | AC17: 0.352 | AD17: 0.074 | AE17: 0.082 | AF17: 239886 | AG17: 0.74 | AH17: 81 | AI17: 81 | AJ17: 85 | AK17: 21245 | AL17: 15220 | AM17: 19488 | AN17: 3400 | AO17: 7205 | AP17: 0 | AQ17: 0 | AR17: 0 | AS17: 0 | AT17: 0 | AU17: 0 | AV17: 0 | AW17: 0 | AX17: 0 | AY17: 0 | BJ17: 0 | BK17: 0 | BL17: 0 | BM17: 0 | BN17: 0 | BO17: 0 | BP17: 0 | BQ17: 0 | BR17: 161397 | BS17: 177161 | BT17: 1 | BU17: 45314 | BV17: 42363 | BW17: 21245 | BX17: 173328 | BY17: 172792 | BZ17: 236400 | CA17: 0.68 | CB17: 5002 | CC17: 239886 | CD17: 0.74 | CE17: 244142 | CF17: 0.73
A18: 2025年-11月陈琪直播 | I18: 130335 | J18: 125331 | K18: 893 | L18: 146 | M18: 61 | N18: 67 | O18: 66 | P18: 47 | Q18: 59 | R18: 18 | S18: 28 | T18: 105840 | U18: 153659 | V18: 1 | W18: 5488 | X18: 0.418 | Y18: 1.082 | Z18: 0.452 | AA18: 0.712 | AB18: 0.983 | AC18: 0.383 | AD18: 0.123 | AE18: 0.192 | AF18: 171371 | AG18: 0.9 | AH18: 60 | AI18: 59 | AJ18: 62 | AK18: 9504 | AL18: 7913 | AM18: 16903 | AN18: 1460 | AO18: 5255 | AP18: 0 | AQ18: 0 | AR18: 0 | AS18: 0 | AT18: 0 | AU18: 0 | AV18: 0 | AW18: 0 | AX18: 0 | AY18: 0 | BJ18: 0 | BK18: 0 | BL18: 0 | BM18: 0 | BN18: 0 | BO18: 0 | BP18: 0 | BQ18: 0 | BR18: 105840 | BS18: 153659 | BT18: 1 | BU18: 31531 | BV18: 24291 | BW18: 9504 | BX18: 130335 | BY18: 128548 | BZ18: 162343 | CA18: 0.65 | CB18: 5004 | CC18: 171371 | CD18: 0.9 | CE18: 172817 | CF18: 0.89
A19: 陈琪直播-汇总 | I19: 431748 | J19: 417097 | K19: 589 | L19: 708 | M19: 257 | N19: 265 | O19: 263 | P19: 187 | Q19: 209 | R19: 69 | S19: 82 | T19: 418925 | U19: 482508 | W19: 5884 | X19: 0.363 | Y19: 1.0233 | Z19: 0.3715 | AA19: 0.711 | AB19: 0.9851 | AC19: 0.369 | AD19: 0.0975 | AE19: 0.1158 | AF19: 595025 | AG19: 0.81 | AH19: 212 | AI19: 209 | AJ19: 223 | AK19: 47569 | AL19: 36291 | AM19: 53422 | AN19: 7080 | AO19: 18915 | AP19: 0 | AQ19: 0 | AS19: 0 | AT19: 0 | AU19: 0 | AV19: 0 | AW19: 0 | AX19: 0 | AY19: 0 | BA19: #DIV/0! | BB19: #DIV/0! | BC19: #DIV/0! | BD19: #DIV/0! | BE19: #DIV/0! | BF19: #DIV/0! | BG19: #DIV/0! | BH19: #DIV/0! | BI19: #DIV/0! | BJ19: 0 | BK19: 0 | BL19: 0 | BM19: 0 | BN19: 0 | BO19: 0 | BP19: 0 | BQ19: 0 | BR19: 418925 | BS19: 482508 | BU19: 115708 | BV19: 105517 | BW19: 47569 | BX19: 431748 | BY19: 429425 | BZ19: 582511 | CA19: 0.72 | CB19: 14651 | CC19: 595025 | CD19: 0.81 | CE19: 600556 | CF19: 0.8
A20: 2025年-3月陈倩扬 | C20: 陈倩扬 | D20: KOLHK-香港-陈倩扬Skye-Shukei-思维&无 | E20: 思维 | F20: - | G20: CPT | I20: 92998 | J20: 92998 | K20: 522 | L20: 178 | M20: 84 | N20: 84 | O20: 97 | P20: 79 | Q20: 79 | R20: 33 | S20: 33 | T20: 156665 | U20: 156665 | V20: 1 | W20: 4747 | X20: 0.472 | Y20: 1.155 | Z20: 0.545 | AA20: 0.814 | AB20: 0.975 | AC20: 0.418 | AD20: 0.185 | AE20: 0.185 | AF20: 140389 | AG20: 1.12 | AH20: 81 | AI20: 79 | AJ20: 86 | AK20: 15910 | AL20: 8304 | AM20: 14998 | AN20: 1198 | AO20: 6981 | AP20: 0 | AQ20: 0 | AR20: 0 | AS20: 0 | AT20: 0 | AU20: 0 | AV20: 0 | AW20: 0 | AX20: 0 | AY20: 0 | BJ20: 0 | BK20: 0 | BL20: 0 | BM20: 0 | BN20: 0 | BO20: 0 | BP20: 0 | BQ20: 0 | BR20: 156665 | BS20: 156665 | BT20: 1 | BU20: 31569 | BV20: 31569 | BW20: 15992 | BX20: 92998 | BY20: 92998 | BZ20: 140559 | CA20: 1.11 | CC20: 140559 | CD20: 1.11 | CE20: 137992 | CF20: 1.14
A21: 2025年-4月陈倩扬 | I21: 48781 | J21: 48781 | K21: 1084 | L21: 45 | M21: 28 | N21: 31 | O21: 29 | P21: 21 | Q21: 28 | R21: 5 | S21: 11 | T21: 23940 | U21: 45568 | V21: 1 | W21: 4143 | X21: 0.622 | Y21: 1.036 | Z21: 0.644 | AA21: 0.724 | AB21: 0.933 | AC21: 0.238 | AD21: 0.111 | AE21: 0.244 | AF21: 65326 | AG21: 0.7 | AH21: 30 | AI21: 28 | AJ21: 29 | AK21: 4984 | AL21: 4592 | AM21: 4085 | AN21: 445 | AO21: 2439 | AP21: 0 | AQ21: 0 | AR21: 0 | AS21: 0 | AT21: 0 | AU21: 0 | AV21: 0 | AW21: 0 | AX21: 0 | AY21: 0 | BJ21: 0 | BK21: 0 | BL21: 0 | BM21: 0 | BN21: 0 | BO21: 0 | BP21: 0 | BQ21: 0 | BR21: 23940 | BS21: 45568 | BT21: 1 | BU21: 12047 | BV21: 8889 | BW21: 5193 | BX21: 48781 | BY21: 48781 | BZ21: 62863 | CA21: 0.38 | CC21: 66022 | CD21: 0.69 | CE21: 64354 | CF21: 0.71
A22: 2025年-5月陈倩扬 | I22: 69043 | J22: 69043 | K22: 794 | L22: 87 | M22: 44 | N22: 45 | O22: 44 | P22: 34 | Q22: 42 | R22: 11 | S22: 15 | T22: 47868 | U22: 69111 | V22: 1 | W22: 4607 | X22: 0.506 | Y22: 1 | Z22: 0.506 | AA22: 0.773 | AB22: 0.913 | AC22: 0.324 | AD22: 0.126 | AE22: 0.172 | AF22: 91365 | AG22: 0.76 | AH22: 46 | AI22: 42 | AJ22: 51 | AK22: 4933 | AL22: 5523 | AM22: 6628 | AN22: 809 | AO22: 4430 | AP22: 0 | AQ22: 0 | AR22: 0 | AS22: 0 | AT22: 0 | AU22: 0 | AV22: 0 | AW22: 0 | AX22: 0 | AY22: 0 | BJ22: 0 | BK22: 0 | BL22: 0 | BM22: 0 | BN22: 0 | BO22: 0 | BP22: 0 | BQ22: 0 | BR22: 47868 | BS22: 69111 | BT22: 1 | BU22: 17389 | BV22: 14187 | BW22: 4933 | BX22: 69043 | BY22: 69043 | BZ22: 88162 | CA22: 0.54 | CC22: 91365 | CD22: 0.76 | CE22: 92957 | CF22: 0.74
A23: 2025年-6月陈倩扬 | I23: 5499 | J23: 4609 | K23: 550 | L23: 10 | M23: 3 | N23: 3 | O23: 3 | P23: 3 | Q23: 8 | R23: 2 | S23: 5 | T23: 9776 | U23: 21340 | V23: 1 | W23: 4268 | X23: 0.3 | Y23: 1 | Z23: 0.3 | AA23: 1 | AB23: 1 | AC23: 0.667 | AD23: 0.2 | AE23: 0.5 | AF23: 9378 | AG23: 2.28 | AH23: 8 | AI23: 8 | AJ23: 9 | AK23: 624 | AL23: 337 | AM23: 2060 | AN23: 81 | AO23: 777 | AP23: 0 | AQ23: 0 | AR23: 0 | AS23: 0 | AT23: 0 | AU23: 0 | AV23: 0 | AW23: 0 | AX23: 0 | AY23: 0 | BJ23: 0 | BK23: 0 | BL23: 0 | BM23: 0 | BN23: 0 | BO23: 0 | BP23: 0 | BQ23: 0 | BR23: 9776 | BS23: 21340 | BT23: 1 | BU23: 3530 | BV23: 1896 | BW23: 736 | BX23: 5499 | BY23: 4965 | BZ23: 7597 | CA23: 1.29 | CB23: 890 | CC23: 9765 | CD23: 2.19 | CE23: 9929 | CF23: 2.15
A24: 陈倩扬-汇总 | I24: 216321 | J24: 215431 | K24: 673 | L24: 320 | M24: 159 | N24: 163 | O24: 173 | P24: 137 | Q24: 157 | R24: 51 | S24: 64 | T24: 238249 | U24: 292684 | W24: 4573 | X24: 0.4969 | Y24: 1.0881 | Z24: 0.5406 | AA24: 0.7919 | AB24: 0.9554 | AC24: 0.3723 | AD24: 0.1594 | AE24: 0.2 | AF24: 306458 | AG24: 0.96 | AH24: 165 | AI24: 157 | AJ24: 175 | AK24: 26451 | AL24: 18756 | AM24: 27771 | AN24: 2532 | AO24: 14627 | AP24: 0 | AQ24: 0 | AS24: 0 | AT24: 0 | AU24: 0 | AV24: 0 | AW24: 0 | AX24: 0 | AY24: 0 | BA24: #DIV/0! | BB24: #DIV/0! | BC24: #DIV/0! | BD24: #DIV/0! | BE24: #DIV/0! | BF24: #DIV/0! | BG24: #DIV/0! | BH24: #DIV/0! | BI24: #DIV/0! | BJ24: 0 | BK24: 0 | BL24: 0 | BM24: 0 | BN24: 0 | BO24: 0 | BP24: 0 | BQ24: 0 | BR24: 238249 | BS24: 292684 | BU24: 64536 | BV24: 56540 | BW24: 26854 | BX24: 216321 | BY24: 215787 | BZ24: 299181 | CA24: 0.8 | CB24: 890 | CC24: 307711 | CD24: 0.95 | CE24: 305232 | CF24: 0.96
A25: 2025年-3月孙慧雪 | C25: 孙慧雪 | D25: KOLHK-香港-孙慧雪-Shukei-思维&无 | E25: 思维 | F25: - | G25: CPT | I25: 107007 | J25: 107007 | K25: 442 | L25: 242 | M25: 129 | N25: 129 | O25: 140 | P25: 113 | Q25: 113 | R25: 42 | S25: 42 | T25: 195996 | U25: 195996 | V25: 1 | W25: 4667 | X25: 0.533 | Y25: 1.085 | Z25: 0.579 | AA25: 0.807 | AB25: 0.966 | AC25: 0.372 | AD25: 0.174 | AE25: 0.174 | AF25: 171279 | AG25: 1.14 | AH25: 117 | AI25: 113 | AJ25: 117 | AK25: 21631 | AL25: 12753 | AM25: 18763 | AN25: 1629 | AO25: 9497 | AP25: 0 | AQ25: 0 | AR25: 0 | AS25: 0 | AT25: 0 | AU25: 0 | AV25: 0 | AW25: 0 | AX25: 0 | AY25: 0 | BJ25: 0 | BK25: 0 | BL25: 0 | BM25: 0 | BN25: 0 | BO25: 0 | BP25: 0 | BQ25: 0 | BR25: 195996 | BS25: 195996 | BT25: 1 | BU25: 42730 | BV25: 42730 | BW25: 21712 | BX25: 107007 | BY25: 107007 | BZ25: 171449 | CA25: 1.14 | CC25: 171449 | CD25: 1.14 | CE25: 167962 | CF25: 1.17
A26: 2025年-4月孙慧雪 | I26: 80325 | J26: 80325 | K26: 893 | L26: 90 | M26: 48 | N26: 50 | O26: 48 | P26: 35 | Q26: 45 | R26: 14 | S26: 20 | T26: 58432 | U26: 80360 | V26: 1 | W26: 4018 | X26: 0.533 | Y26: 1 | Z26: 0.533 | AA26: 0.729 | AB26: 0.918 | AC26: 0.4 | AD26: 0.156 | AE26: 0.222 | AF26: 109747 | AG26: 0.73 | AH26: 49 | AI26: 45 | AJ26: 47 | AK26: 9968 | AL26: 7406 | AM26: 7205 | AN26: 890 | AO26: 3953 | AP26: 0 | AQ26: 0 | AR26: 0 | AS26: 0 | AT26: 0 | AU26: 0 | AV26: 0 | AW26: 0 | AX26: 0 | AY26: 0 | BJ26: 0 | BK26: 0 | BL26: 0 | BM26: 0 | BN26: 0 | BO26: 0 | BP26: 0 | BQ26: 0 | BR26: 58432 | BS26: 80360 | BT26: 1 | BU26: 19555 | BV26: 16350 | BW26: 9968 | BX26: 80325 | BY26: 80325 | BZ26: 106644 | CA26: 0.55 | CC26: 109849 | CD26: 0.73 | CE26: 106631 | CF26: 0.75
A27: 2025年-5月孙慧雪 | I27: 131099 | J27: 131099 | K27: 851 | L27: 154 | M27: 63 | N27: 68 | O27: 68 | P27: 59 | Q27: 68 | R27: 25 | S27: 26 | T27: 120500 | U27: 124088 | V27: 1 | W27: 4773 | X27: 0.409 | Y27: 1.079 | Z27: 0.442 | AA27: 0.868 | AB27: 0.971 | AC27: 0.424 | AD27: 0.162 | AE27: 0.169 | AF27: 167935 | AG27: 0.74 | AH27: 70 | AI27: 68 | AJ27: 74 | AK27: 8731 | AL27: 8345 | AM27: 11900 | AN27: 1432 | AO27: 6428 | AP27: 0 | AQ27: 0 | AR27: 0 | AS27: 0 | AT27: 0 | AU27: 0 | AV27: 0 | AW27: 0 | AX27: 0 | AY27: 0 | BJ27: 0 | BK27: 0 | BL27: 0 | BM27: 0 | BN27: 0 | BO27: 0 | BP27: 0 | BQ27: 0 | BR27: 120500 | BS27: 124088 | BT27: 1 | BU27: 28105 | BV27: 26366 | BW27: 8731 | BX27: 131099 | BY27: 131099 | BZ27: 166196 | CA27: 0.73 | CC27: 167935 | CD27: 0.74 | CE27: 170754 | CF27: 0.73
A28: 2025年-6月孙慧雪 | I28: 47816 | J28: 45304 | K28: 850 | L28: 56 | M28: 27 | N28: 29 | O28: 29 | P28: 22 | Q28: 31 | R28: 9 | S28: 13 | T28: 50492 | U28: 67344 | V28: 1 | W28: 5180 | X28: 0.482 | Y28: 1.074 | Z28: 0.518 | AA28: 0.759 | AB28: 1 | AC28: 0.409 | AD28: 0.161 | AE28: 0.232 | AF28: 64519 | AG28: 1.04 | AH28: 31 | AI28: 31 | AJ28: 37 | AK28: 3493 | AL28: 3259 | AM28: 6501 | AN28: 452 | AO28: 3195 | AP28: 20 | AQ28: 9 | AR28: 9 | AS28: 9 | AT28: 5 | AU28: 5 | AV28: 2 | AW28: 2 | AX28: 7987 | AY28: 7987 | AZ28: 1 | BA28: 3994 | BB28: 0.45 | BC28: 1 | BD28: 0.45 | BE28: 0.556 | BF28: 0.556 | BG28: 0.4 | BH28: 0.1 | BI28: 0.1 | BJ28: 9 | BK28: 5 | BL28: 7 | BM28: 1120 | BN28: 810 | BO28: 830 | BP28: 162 | BQ28: 553 | BR28: 58479 | BS28: 75331 | BT28: 1 | BU28: 15761 | BV28: 12874 | BW28: 4613 | BX28: 47816 | BY28: 47104 | BZ28: 64591 | CA28: 0.91 | CB28: 2512 | CC28: 68190 | CD28: 1.1 | CE28: 69278 | CF28: 1.09
A29: 2025年-7月孙慧雪 | I29: 52997 | J29: 50605 | K29: 928 | L29: 57 | M29: 24 | N29: 29 | O29: 26 | P29: 20 | Q29: 32 | R29: 11 | S29: 13 | T29: 56968 | U29: 64144 | V29: 1 | W29: 4934 | X29: 0.421 | Y29: 1.083 | Z29: 0.456 | AA29: 0.769 | AB29: 0.914 | AC29: 0.55 | AD29: 0.193 | AE29: 0.228 | AF29: 68602 | AG29: 0.94 | AH29: 35 | AI29: 32 | AJ29: 34 | AK29: 2508 | AL29: 3043 | AM29: 6568 | AN29: 587 | AO29: 2997 | AP29: 0 | AQ29: 0 | AR29: 1 | AS29: 0 | AT29: 0 | AU29: 1 | AV29: 0 | AW29: 1 | AX29: 0 | AY29: 1880 | AZ29: 1 | BA29: 1880 | BF29: 1 | BJ29: 1 | BK29: 1 | BL29: 1 | BM29: 0 | BN29: 95 | BO29: 197 | BP29: 0 | BQ29: 82 | BR29: 56968 | BS29: 66024 | BT29: 1 | BU29: 13569 | BV29: 10790 | BW29: 2508 | BX29: 52997 | BY29: 52546 | BZ29: 65844 | CA29: 0.87 | CB29: 2392 | CC29: 69075 | CD29: 0.96 | CE29: 70842 | CF29: 0.93
A30: 2025年-8月孙慧雪 | I30: 17564 | J30: 16857 | K30: 1171 | L30: 15 | M30: 6 | N30: 9 | O30: 6 | P30: 6 | Q30: 14 | R30: 2 | S30: 4 | T30: 12176 | U30: 21852 | V30: 1 | W30: 5463 | X30: 0.4 | Y30: 1 | Z30: 0.4 | AA30: 1 | AB30: 1 | AC30: 0.333 | AD30: 0.133 | AE30: 0.267 | AF30: 23740 | AG30: 0.92 | AH30: 14 | AI30: 14 | AJ30: 15 | AK30: 1354 | AL30: 1112 | AM30: 2238 | AN30: 150 | AO30: 1322 | AP30: 0 | AQ30: 0 | AR30: 0 | AS30: 0 | AT30: 0 | AU30: 0 | AV30: 0 | AW30: 0 | AX30: 0 | AY30: 0 | BJ30: 0 | BK30: 0 | BL30: 0 | BM30: 0 | BN30: 0 | BO30: 0 | BP30: 0 | BQ30: 0 | BR30: 12176 | BS30: 21852 | BT30: 1 | BU30: 4821 | BV30: 2667 | BW30: 1354 | BX30: 17564 | BY30: 17211 | BZ30: 21232 | CA30: 0.57 | CB30: 707 | CC30: 23740 | CD30: 0.92 | CE30: 23511 | CF30: 0.93
A31: 孙慧雪-汇总 | D31: 总计 | E31: - | F31: - | G31: - | I31: 437511 | J31: 431721 | K31: 699 | L31: 618 | M31: 298 | N31: 315 | O31: 318 | P31: 256 | Q31: 305 | R31: 104 | S31: 119 | T31: 500652 | U31: 559872 | W31: 4705 | X31: 0.4822 | Y31: 1.0671 | Z31: 0.5146 | AA31: 0.805 | AB31: 0.9671 | AC31: 0.4063 | AD31: 0.1683 | AE31: 0.1926 | AF31: 607911 | AG31: 0.92 | AH31: 318 | AI31: 305 | AJ31: 326 | AK31: 48081 | AL31: 36050 | AM31: 53826 | AN31: 5179 | AO31: 27560 | AP31: 20 | AQ31: 9 | AS31: 9 | AT31: 5 | AU31: 6 | AV31: 2 | AW31: 3 | AX31: 7987 | AY31: 9867 | BA31: 3289 | BB31: 0.45 | BC31: 1 | BD31: 0.45 | BE31: 0.5556 | BF31: 0.7778 | BG31: 0.4 | BH31: 0.1 | BI31: 0.15 | BJ31: 10 | BK31: 6 | BL31: 8 | BM31: 1120 | BN31: 904 | BO31: 1027 | BP31: 162 | BQ31: 635 | BR31: 508639 | BS31: 569739 | BU31: 125534 | BV31: 112683 | BW31: 49283 | BX31: 437511 | BY31: 435994 | BZ31: 597960 | CA31: 0.85 | CB31: 5790 | CC31: 612328 | CD31: 0.93 | CE31: 610971 | CF31: 0.93
A32: 2025年-4月Bob | I32: 46342 | J32: 46342 | K32: 311 | L32: 149 | M32: 82 | N32: 82 | O32: 79 | P32: 57 | Q32: 57 | R32: 22 | S32: 22 | T32: 96736 | U32: 96736 | V32: 1 | W32: 4397 | X32: 0.55 | Y32: 0.963 | Z32: 0.53 | AA32: 0.722 | AB32: 0.966 | AC32: 0.386 | AD32: 0.148 | AE32: 0.148 | AF32: 90014 | AG32: 1.07 | AH32: 59 | AI32: 57 | AJ32: 58 | AK32: 16503 | AL32: 12146 | AM32: 8673 | AN32: 1473 | AO32: 4878 | AP32: 0 | AQ32: 0 | AR32: 0 | AS32: 0 | AT32: 0 | AU32: 0 | AV32: 0 | AW32: 0 | AX32: 0 | AY32: 0 | BJ32: 0 | BK32: 0 | BL32: 0 | BM32: 0 | BN32: 0 | BO32: 0 | BP32: 0 | BQ32: 0 | BR32: 96736 | BS32: 96736 | BT32: 1 | BU32: 27169 | BV32: 27169 | BW32: 16503 | BX32: 46342 | BY32: 46342 | BZ32: 90014 | CA32: 1.07 | CC32: 90014 | CD32: 1.07 | CE32: 84686 | CF32: 1.14
A33: 2025年-5月Bob | I33: 164736 | J33: 164736 | K33: 752 | L33: 219 | M33: 85 | N33: 92 | O33: 89 | P33: 68 | Q33: 86 | R33: 23 | S33: 27 | T33: 131124 | U33: 145576 | V33: 1 | W33: 5392 | X33: 0.388 | Y33: 1.047 | Z33: 0.406 | AA33: 0.764 | AB33: 0.977 | AC33: 0.338 | AD33: 0.105 | AE33: 0.123 | AF33: 212258 | AG33: 0.69 | AH33: 88 | AI33: 86 | AJ33: 90 | AK33: 12417 | AL33: 11290 | AM33: 13961 | AN33: 2037 | AO33: 7817 | AP33: 0 | AQ33: 0 | AR33: 0 | AS33: 0 | AT33: 0 | AU33: 0 | AV33: 0 | AW33: 0 | AX33: 0 | AY33: 0 | BJ33: 0 | BK33: 0 | BL33: 0 | BM33: 0 | BN33: 0 | BO33: 0 | BP33: 0 | BQ33: 0 | BR33: 131124 | BS33: 145576 | BT33: 1 | BU33: 35106 | BV33: 31210 | BW33: 12417 | BX33: 164736 | BY33: 164736 | BZ33: 208363 | CA33: 0.63 | CC33: 212258 | CD33: 0.69 | CE33: 216267 | CF33: 0.67
A34: 2025年-6月Bob | I34: 105683 | J34: 100124 | K34: 975 | L34: 108 | M34: 66 | N34: 70 | O34: 69 | P34: 54 | Q34: 63 | R34: 23 | S34: 29 | T34: 124424 | U34: 155552 | V34: 1 | W34: 5364 | X34: 0.611 | Y34: 1.045 | Z34: 0.639 | AA34: 0.783 | AB34: 0.926 | AC34: 0.426 | AD34: 0.213 | AE34: 0.269 | AF34: 141650 | AG34: 1.1 | AH34: 68 | AI34: 63 | AJ34: 68 | AK34: 6736 | AL34: 7867 | AM34: 15016 | AN34: 872 | AO34: 5872 | AP34: 72 | AQ34: 32 | AR34: 32 | AS34: 32 | AT34: 24 | AU34: 24 | AV34: 4 | AW34: 4 | AX34: 13404 | AY34: 13404 | AZ34: 1 | BA34: 3351 | BB34: 0.444 | BC34: 1 | BD34: 0.444 | BE34: 0.75 | BF34: 0.75 | BG34: 0.167 | BH34: 0.056 | BI34: 0.0556 | BJ34: 32 | BK34: 24 | BL34: 28 | BM34: 4030 | BN34: 2879 | BO34: 1393 | BP34: 581 | BQ34: 2211 | BR34: 137828 | BS34: 168956 | BT34: 1 | BU34: 36691 | BV34: 32373 | BW34: 10767 | BX34: 105683 | BY34: 104615 | BZ34: 147755 | CA34: 0.93 | CB34: 5558 | CC34: 153141 | CD34: 1.1 | CE34: 155874 | CF34: 1.08
A35: 2025年-7月Bob | I35: 53515 | J35: 52280 | K35: 1274 | L35: 42 | M35: 21 | N35: 28 | O35: 21 | P35: 18 | Q35: 25 | R35: 4 | S35: 7 | T35: 26852 | U35: 44916 | V35: 1 | W35: 6417 | X35: 0.5 | Y35: 1 | Z35: 0.5 | AA35: 0.857 | AB35: 0.962 | AC35: 0.222 | AD35: 0.095 | AE35: 0.167 | AF35: 65977 | AG35: 0.68 | AH35: 26 | AI35: 25 | AJ35: 30 | AK35: 1848 | AL35: 2938 | AM35: 4599 | AN35: 432 | AO35: 2644 | AP35: 0 | AQ35: 0 | AR35: 0 | AS35: 0 | AT35: 0 | AU35: 1 | AV35: 0 | AW35: 0 | AX35: 0 | AY35: 0 | BF35: 1 | BJ35: 1 | BK35: 1 | BL35: 1 | BM35: 0 | BN35: 0 | BO35: 0 | BP35: 0 | BQ35: 82 | BR35: 26852 | BS35: 44916 | BT35: 1 | BU35: 10696 | BV35: 7237 | BW35: 1848 | BX35: 53515 | BY35: 52986 | BZ35: 62070 | CA35: 0.43 | CB35: 1235 | CC35: 66059 | CD35: 0.68 | CE35: 67361 | CF35: 0.67
A36: 2025-11月Bob | I36: 19015 | J36: 18657 | K36: 1729 | L36: 11 | M36: 4 | N36: 4 | O36: 4 | P36: 2 | Q36: 2 | R36: 2 | S36: 2 | T36: 10598 | U36: 10598 | V36: 1 | W36: 5299 | X36: 0.364 | Y36: 1 | Z36: 0.364 | AA36: 0.5 | AB36: 1 | AC36: 1 | AD36: 0.182 | AE36: 0.182 | AF36: 21733 | AG36: 0.49 | AH36: 2 | AI36: 2 | AJ36: 3 | AK36: 716 | AL36: 472 | AM36: 1166 | AN36: 110 | AO36: 254 | AP36: 0 | AQ36: 0 | AR36: 0 | AS36: 0 | AT36: 0 | AU36: 0 | AV36: 0 | AW36: 0 | AX36: 0 | AY36: 0 | BJ36: 0 | BK36: 0 | BL36: 0 | BM36: 0 | BN36: 0 | BO36: 0 | BP36: 0 | BQ36: 0 | BR36: 10598 | BS36: 10598 | BT36: 1 | BU36: 2003 | BV36: 2003 | BW36: 716 | BX36: 19015 | BY36: 19015 | BZ36: 21733 | CA36: 0.49 | CB36: 357 | CC36: 21733 | CD36: 0.49 | CE36: 21842 | CF36: 0.49
A37: Bob-汇总 | I37: 389290 | J37: 382139 | K37: 722 | L37: 529 | M37: 258 | N37: 276 | O37: 262 | P37: 199 | Q37: 233 | R37: 74 | S37: 87 | T37: 389734 | U37: 453378 | W37: 5211 | X37: 0.4877 | Y37: 1.0155 | Z37: 0.4953 | AA37: 0.7595 | AB37: 0.9663 | AC37: 0.3719 | AD37: 0.1399 | AE37: 0.1645 | AF37: 531633 | AG37: 0.85 | AH37: 243 | AI37: 233 | AJ37: 249 | AK37: 38220 | AL37: 34714 | AM37: 43415 | AN37: 4924 | AO37: 21466 | AP37: 72 | AQ37: 32 | AS37: 32 | AT37: 24 | AU37: 25 | AV37: 4 | AW37: 4 | AX37: 13404 | AY37: 13404 | BA37: 3351 | BB37: 0.4444 | BC37: 1 | BD37: 0.4444 | BE37: 0.75 | BF37: 0.875 | BG37: 0.1667 | BH37: 0.0556 | BI37: 0.0556 | BJ37: 33 | BK37: 25 | BL37: 29 | BM37: 4030 | BN37: 2879 | BO37: 1393 | BP37: 581 | BQ37: 2293 | BR37: 403138 | BS37: 466782 | BU37: 111665 | BV37: 99991 | BW37: 42251 | BX37: 389290 | BY37: 387693 | BZ37: 529935 | CA37: 0.76 | CB37: 7151 | CC37: 543206 | CD37: 0.86 | CE37: 546030 | CF37: 0.85
A38: 2025年-4月叶翠翠 | I38: 15481 | J38: 15481 | K38: 418 | L38: 37 | M38: 15 | N38: 15 | O38: 15 | P38: 9 | Q38: 9 | R38: 4 | S38: 4 | T38: 16752 | U38: 16752 | V38: 1 | W38: 4188 | X38: 0.405 | Y38: 1 | Z38: 0.405 | AA38: 0.6 | AB38: 1 | AC38: 0.444 | AD38: 0.108 | AE38: 0.108 | AF38: 24425 | AG38: 0.69 | AH38: 9 | AI38: 9 | AJ38: 9 | AK38: 4098 | AL38: 2222 | AM38: 1502 | AN38: 366 | AO38: 757 | AP38: 0 | AQ38: 0 | AR38: 0 | AS38: 0 | AT38: 0 | AU38: 0 | AV38: 0 | AW38: 0 | AX38: 0 | AY38: 0 | BJ38: 0 | BK38: 0 | BL38: 0 | BM38: 0 | BN38: 0 | BO38: 0 | BP38: 0 | BQ38: 0 | BR38: 16752 | BS38: 16752 | BT38: 1 | BU38: 4846 | BV38: 4846 | BW38: 4098 | BX38: 15481 | BY38: 15481 | BZ38: 24425 | CA38: 0.69 | CC38: 24425 | CD38: 0.69 | CE38: 23102 | CF38: 0.73
A39: 2025年-5月叶翠翠 | I39: 73877 | J39: 73877 | K39: 1192 | L39: 62 | M39: 29 | N39: 32 | O39: 28 | P39: 18 | Q39: 24 | R39: 5 | S39: 5 | T39: 18140 | U39: 18140 | V39: 1 | W39: 3628 | X39: 0.468 | Y39: 0.966 | Z39: 0.452 | AA39: 0.643 | AB39: 0.889 | AC39: 0.278 | AD39: 0.081 | AE39: 0.081 | AF39: 85894 | AG39: 0.21 | AH39: 27 | AI39: 24 | AJ39: 26 | AK39: 3515 | AL39: 3927 | AM39: 1740 | AN39: 577 | AO39: 2258 | AP39: 0 | AQ39: 0 | AR39: 0 | AS39: 0 | AT39: 0 | AU39: 0 | AV39: 0 | AW39: 0 | AX39: 0 | AY39: 0 | BJ39: 0 | BK39: 0 | BL39: 0 | BM39: 0 | BN39: 0 | BO39: 0 | BP39: 0 | BQ39: 0 | BR39: 18140 | BS39: 18140 | BT39: 1 | BU39: 8502 | BV39: 7439 | BW39: 3515 | BX39: 73877 | BY39: 73877 | BZ39: 84831 | CA39: 0.21 | CC39: 85894 | CD39: 0.21 | CE39: 87029 | CF39: 0.21
A40: 2025年-6月叶翠翠 | I40: 27428 | J40: 26538 | K40: 2286 | L40: 12 | M40: 7 | N40: 7 | O40: 7 | P40: 7 | Q40: 8 | R40: 4 | S40: 5 | T40: 14252 | U40: 17840 | V40: 1 | W40: 3568 | X40: 0.583 | Y40: 1 | Z40: 0.583 | AA40: 1 | AB40: 0.889 | AC40: 0.571 | AD40: 0.333 | AE40: 0.417 | AF40: 31473 | AG40: 0.57 | AH40: 9 | AI40: 8 | AJ40: 8 | AK40: 748 | AL40: 787 | AM40: 1722 | AN40: 97 | AO40: 691 | AP40: 0 | AQ40: 0 | AR40: 0 | AS40: 0 | AT40: 0 | AU40: 0 | AV40: 0 | AW40: 0 | AX40: 0 | AY40: 0 | BJ40: 0 | BK40: 0 | BL40: 0 | BM40: 0 | BN40: 0 | BO40: 0 | BP40: 0 | BQ40: 0 | BR40: 14252 | BS40: 17840 | BT40: 1 | BU40: 3297 | BV40: 2864 | BW40: 748 | BX40: 27428 | BY40: 27250 | BZ40: 30862 | CA40: 0.46 | CB40: 890 | CC40: 31473 | CD40: 0.57 | CE40: 31624 | CF40: 0.56
A41: 2025年-7月叶翠翠 | I41: 13816 | J41: 13640 | L41: 0 | M41: 0 | N41: 1 | O41: 0 | P41: 0 | Q41: 1 | R41: 0 | S41: 1 | T41: 0 | U41: 3588 | V41: 1 | W41: 3588 | AB41: 1 | AF41: 14377 | AG41: 0.25 | AH41: 1 | AI41: 1 | AJ41: 1 | AK41: 0 | AL41: 105 | AM41: 367 | AN41: 0 | AO41: 88 | AP41: 0 | AQ41: 0 | AR41: 0 | AS41: 0 | AT41: 0 | AU41: 0 | AV41: 0 | AW41: 0 | AX41: 0 | AY41: 0 | BJ41: 0 | BK41: 0 | BL41: 0 | BM41: 0 | BN41: 0 | BO41: 0 | BP41: 0 | BQ41: 0 | BR41: 0 | BS41: 3588 | BT41: 1 | BU41: 560 | BV41: 0 | BW41: 0 | BX41: 13816 | BY41: 13640 | BZ41: 13640 | CB41: 176 | CC41: 14377 | CD41: 0.25 | CE41: 14377 | CF41: 0.25
A42: 叶翠翠-汇总 | I42: 130601 | J42: 129535 | K42: 1167 | L42: 111 | M42: 51 | N42: 55 | O42: 50 | P42: 34 | Q42: 42 | R42: 13 | S42: 15 | T42: 49144 | U42: 56320 | W42: 3755 | X42: 0.4595 | Y42: 0.9804 | Z42: 0.4505 | AA42: 0.68 | AB42: 0.9444 | AC42: 0.3824 | AD42: 0.1171 | AE42: 0.1351 | AF42: 156168 | AG42: 0.36 | AH42: 46 | AI42: 42 | AJ42: 44 | AK42: 8362 | AL42: 7041 | AM42: 5331 | AN42: 1039 | AO42: 3794 | AP42: 0 | AQ42: 0 | AS42: 0 | AT42: 0 | AU42: 0 | AV42: 0 | AW42: 0 | AX42: 0 | AY42: 0 | BA42: #DIV/0! | BB42: #DIV/0! | BC42: #DIV/0! | BD42: #DIV/0! | BE42: #DIV/0! | BF42: #DIV/0! | BG42: #DIV/0! | BH42: #DIV/0! | BI42: #DIV/0! | BJ42: 0 | BK42: 0 | BL42: 0 | BM42: 0 | BN42: 0 | BO42: 0 | BP42: 0 | BQ42: 0 | BR42: 49144 | BS42: 56320 | BU42: 17205 | BV42: 15149 | BW42: 8362 | BX42: 130601 | BY42: 130247 | BZ42: 153758 | CA42: 0.32 | CB42: 1066 | CC42: 156168 | CD42: 0.36 | CE42: 156131 | CF42: 0.36
A43: 2025年-5月陈山聪 | I43: 139976 | J43: 139976 | K43: 467 | L43: 300 | M43: 133 | N43: 133 | O43: 135 | P43: 94 | Q43: 94 | R43: 34 | S43: 34 | T43: 172292 | U43: 172292 | V43: 1 | W43: 5067 | X43: 0.443 | Y43: 1.015 | Z43: 0.45 | AA43: 0.696 | AB43: 0.904 | AC43: 0.362 | AD43: 0.113 | AE43: 0.113 | AF43: 201653 | AG43: 0.85 | AH43: 104 | AI43: 94 | AJ43: 104 | AK43: 17009 | AL43: 16322 | AM43: 16523 | AN43: 2790 | AO43: 9034 | AP43: 0 | AQ43: 0 | AR43: 0 | AS43: 0 | AT43: 0 | AU43: 0 | AV43: 0 | AW43: 0 | AX43: 0 | AY43: 0 | BJ43: 0 | BK43: 0 | BL43: 0 | BM43: 0 | BN43: 0 | BO43: 0 | BP43: 0 | BQ43: 0 | BR43: 172292 | BS43: 172292 | BT43: 1 | BU43: 44669 | BV43: 44669 | BW43: 17009 | BX43: 139976 | BY43: 139976 | BZ43: 201653 | CA43: 0.85 | CC43: 201653 | CD43: 0.85 | CE43: 207144 | CF43: 0.83
A44: 2025年-6月陈山聪 | I44: 109228 | J44: 104223 | K44: 1148 | L44: 95 | M44: 47 | N44: 53 | O44: 47 | P44: 33 | Q44: 63 | R44: 13 | S44: 27 | T44: 55144 | U44: 122076 | V44: 1 | W44: 4521 | X44: 0.495 | Y44: 1 | Z44: 0.495 | AA44: 0.702 | AB44: 0.875 | AC44: 0.394 | AD44: 0.137 | AE44: 0.284 | AF44: 139767 | AG44: 0.87 | AH44: 72 | AI44: 63 | AJ44: 73 | AK44: 5926 | AL44: 5956 | AM44: 11784 | AN44: 767 | AO44: 6304 | AP44: 37 | AQ44: 18 | AR44: 18 | AS44: 19 | AT44: 10 | AU44: 10 | AV44: 2 | AW44: 2 | AX44: 6817 | AY44: 6817 | AZ44: 1 | BA44: 3409 | BB44: 0.486 | BC44: 1.056 | BD44: 0.514 | BE44: 0.526 | BF44: 0.526 | BG44: 0.2 | BH44: 0.054 | BI44: 0.0541 | BJ44: 19 | BK44: 10 | BL44: 10 | BM44: 2071 | BN44: 1619 | BO44: 709 | BP44: 299 | BQ44: 789 | BR44: 61961 | BS44: 128893 | BT44: 1 | BU44: 28228 | BV44: 18070 | BW44: 7997 | BX44: 109228 | BY44: 106736 | BZ44: 132803 | CA44: 0.47 | CB44: 5004 | CC44: 145452 | CD44: 0.89 | CE44: 147356 | CF44: 0.87
A45: 2025年-7月陈山聪 | I45: 84509 | J45: 81686 | K45: 994 | L45: 85 | M45: 47 | N45: 49 | O45: 47 | P45: 34 | Q45: 44 | R45: 8 | S45: 16 | T45: 31304 | U45: 74108 | V45: 1 | W45: 4632 | X45: 0.5529 | Y45: 1 | Z45: 0.5529 | AA45: 0.7234 | AB45: 1 | AC45: 0.2353 | AD45: 0.0941 | AE45: 0.1882 | AF45: 106173 | AG45: 0.7 | AH45: 44 | AI45: 44 | AJ45: 49 | AK45: 3740 | AL45: 5142 | AM45: 7589 | AN45: 875 | AO45: 4319 | AP45: 0 | AQ45: 0 | AR45: 0 | AS45: 0 | AT45: 0 | AU45: 0 | AV45: 0 | AW45: 0 | AX45: 0 | AY45: 0 | BJ45: 0 | BK45: 0 | BL45: 0 | BM45: 0 | BN45: 0 | BO45: 0 | BP45: 0 | BQ45: 0 | BR45: 31304 | BS45: 74108 | BT45: 1 | BU45: 17924 | BV45: 12274 | BW45: 3740 | BX45: 84509 | BY45: 83097 | BZ45: 99111 | CA45: 0.32 | CB45: 2823 | CC45: 106173 | CD45: 0.7 | CE45: 108808 | CF45: 0.68
A46: 2025年-8月陈山聪 | I46: 9753 | J46: 9753 | K46: 813 | L46: 12 | M46: 2 | N46: 2 | O46: 2 | P46: 1 | Q46: 6 | R46: 0 | S46: 1 | T46: 0 | U46: 3588 | V46: 1 | W46: 3588 | X46: 0.167 | Y46: 1 | Z46: 0.167 | AA46: 0.5 | AB46: 1 | AC46: 0 | AD46: 0 | AE46: 0.083 | AF46: 12212 | AG46: 0.29 | AH46: 6 | AI46: 6 | AJ46: 6 | AK46: 1187 | AL46: 263 | AM46: 384 | AN46: 120 | AO46: 505 | AP46: 0 | AQ46: 0 | AR46: 0 | AS46: 0 | AT46: 0 | AU46: 0 | AV46: 0 | AW46: 0 | AX46: 0 | AY46: 0 | BJ46: 0 | BK46: 0 | BL46: 0 | BM46: 0 | BN46: 0 | BO46: 0 | BP46: 0 | BQ46: 0 | BR46: 0 | BS46: 3588 | BT46: 1 | BU46: 1272 | BV46: 467 | BW46: 1187 | BX46: 9753 | BY46: 9753 | BZ46: 11408 | CA46: 0 | CB46: - | CC46: 12212 | CD46: 0.29 | CE46: 11925 | CF46: 0.3
A47: 2025年-9月陈山聪 | H47: 2480 | I47: 22183 | J47: 21826 | K47: 693 | L47: 32 | M47: 9 | N47: 9 | O47: 9 | P47: 5 | Q47: 10 | R47: 1 | S47: 2 | T47: 3588 | U47: 7176 | V47: 1 | W47: 3588 | X47: 0.281 | Y47: 1 | Z47: 0.281 | AA47: 0.556 | AB47: 1 | AC47: 0.2 | AD47: 0.031 | AE47: 0.063 | AF47: 28054 | AG47: 0.26 | AH47: 10 | AI47: 10 | AJ47: 12 | AK47: 2425 | AL47: 1301 | AM47: 806 | AN47: 320 | AO47: 1019 | AP47: 0 | AQ47: 0 | AR47: 0 | AS47: 0 | AT47: 0 | AU47: 0 | AV47: 0 | AW47: 0 | AX47: 0 | AY47: 0 | BJ47: 0 | BK47: 0 | BL47: 0 | BM47: 0 | BN47: 0 | BO47: 0 | BP47: 0 | BQ47: 0 | BR47: 3588 | BS47: 7176 | BT47: 1 | BU47: 3446 | BV47: 2534 | BW47: 2425 | BX47: 22183 | BY47: 22005 | BZ47: 26963 | CA47: 0.13 | CB47: 357 | CC47: 28054 | CD47: 0.26 | CE47: 28030 | CF47: 0.26
A48: 2025年-10月陈山聪 | I48: 14376 | J48: 14198 | K48: 899 | L48: 16 | M48: 1 | N48: 1 | O48: 1 | P48: 1 | Q48: 2 | R48: 0 | S48: 1 | T48: 0 | U48: 5888 | V48: 1 | W48: 5888 | X48: 0.063 | Y48: 1 | Z48: 0.063 | AA48: 1 | AB48: 1 | AC48: 0 | AD48: 0 | AE48: 0.063 | AF48: 16496 | AG48: 0.36 | AH48: 2 | AI48: 2 | AJ48: 2 | AK48: 1000 | AL48: 142 | AM48: 648 | AN48: 160 | AO48: 170 | AP48: 0 | AQ48: 0 | AR48: 0 | AS48: 0 | AT48: 0 | AU48: 0 | AV48: 0 | AW48: 0 | AX48: 0 | AY48: 0 | BJ48: 0 | BK48: 0 | BL48: 0 | BM48: 0 | BN48: 0 | BO48: 0 | BP48: 0 | BQ48: 0 | BR48: 0 | BS48: 5888 | BT48: 1 | BU48: 1119 | BV48: 387 | BW48: 1000 | BX48: 14376 | BY48: 14198 | BZ48: 15584 | CA48: 0 | CB48: 179 | CC48: 16496 | CD48: 0.36 | CE48: 16696 | CF48: 0.35
A49: 陈山聪-汇总 | I49: 418827 | J49: 408873 | K49: 699 | L49: 585 | M49: 260 | N49: 272 | O49: 263 | P49: 185 | Q49: 239 | R49: 64 | S49: 89 | T49: 312132 | U49: 434932 | W49: 4887 | X49: 0.4444 | Y49: 1.0115 | Z49: 0.4496 | AA49: 0.7034 | AB49: 0.9631 | AC49: 0.3459 | AD49: 0.1094 | AE49: 0.1521 | AF49: 559728 | AG49: 0.78 | AH49: 258 | AI49: 239 | AJ49: 271 | AK49: 36054 | AL49: 33048 | AM49: 43064 | AN49: 5482 | AO49: 23452 | AP49: 37 | AQ49: 18 | AS49: 19 | AT49: 10 | AU49: 10 | AV49: 2 | AW49: 2 | AX49: 6817 | AY49: 6817 | BA49: 3409 | BB49: 0.4865 | BC49: 1.0556 | BD49: 0.5135 | BE49: 0.5263 | BF49: 0.5263 | BG49: 0.2 | BH49: 0.0541 | BI49: 0.0541 | BJ49: 19 | BK49: 10 | BL49: 10 | BM49: 2071 | BN49: 1619 | BO49: 709 | BP49: 299 | BQ49: 789 | BR49: 318949 | BS49: 441749 | BU49: 108462 | BV49: 89079 | BW49: 38125 | BX49: 418827 | BY49: 414389 | BZ49: 541594 | CA49: 0.59 | CB49: 9954 | CC49: 565413 | CD49: 0.78 | CE49: 573938 | CF49: 0.77
A50: 2025年-6月陈敏之 | I50: 175980 | J50: 168939 | K50: 660 | L50: 256 | M50: 137 | N50: 137 | O50: 141 | P50: 103 | Q50: 103 | R50: 39 | S50: 39 | T50: 190732 | U50: 190732 | W50: 4891 | X50: 0.5352 | Y50: 1.0292 | Z50: 0.5508 | AA50: 0.7305 | AB50: 0.9626 | AC50: 0.3786 | AD50: 0.1523 | AE50: 0.1523 | AF50: 237743 | AG50: 0.8 | AH50: 107 | AI50: 103 | AJ50: 116 | AK50: 15968 | AL50: 15397 | AM50: 18412 | AN50: 2067 | AO50: 10017 | AP50: 135 | AQ50: 46 | AS50: 46 | AT50: 24 | AU50: 24 | AV50: 1 | AW50: 1 | AX50: 3588 | AY50: 3588 | BA50: 3588 | BB50: 0.3407 | BC50: 1 | BD50: 0.3407 | BE50: 0.5217 | BF50: 0.5217 | BG50: 0.0417 | BH50: 0.0074 | BI50: 0.0074 | BJ50: 46 | BK50: 24 | BL50: 24 | BM50: 7557 | BN50: 4138 | BO50: 373 | BP50: 1090 | BQ50: 1895 | BR50: 194320 | BS50: 194320 | BU50: 53389 | BV50: 53389 | BW50: 23525 | BX50: 175980 | BY50: 175980 | BZ50: 252895 | CA50: 0.77 | CB50: 7041 | CC50: 252895 | CD50: 0.77 | CE50: 258695 | CF50: 0.75
A51: 2025年-7月陈敏之 | I51: 160447 | J51: 153115 | K51: 922 | L51: 174 | M51: 105 | N51: 109 | O51: 113 | P51: 89 | Q51: 105 | R51: 33 | S51: 41 | T51: 148304 | U51: 185408 | V51: 1 | W51: 4522 | X51: 0.603 | Y51: 1.076 | Z51: 0.649 | AA51: 0.788 | AB51: 0.938 | AC51: 0.371 | AD51: 0.19 | AE51: 0.236 | AF51: 210268 | AG51: 0.88 | AH51: 112 | AI51: 105 | AJ51: 114 | AK51: 7657 | AL51: 11438 | AM51: 18985 | AN51: 1791 | AO51: 10048 | AP51: 0 | AQ51: 0 | AR51: 0 | AS51: 0 | AT51: 0 | AU51: 0 | AV51: 0 | AW51: 1 | AX51: 0 | AY51: 1880 | AZ51: 1 | BA51: 1880 | BJ51: 0 | BK51: 0 | BL51: 0 | BM51: 0 | BN51: 0 | BO51: 197 | BP51: 0 | BQ51: 0 | BR51: 148304 | BS51: 187288 | BT51: 1 | BU51: 42460 | BV51: 36721 | BW51: 7657 | BX51: 160447 | BY51: 158937 | BZ51: 203315 | CA51: 0.73 | CB51: 7332 | CC51: 210564 | CD51: 0.89 | CE51: 215957 | CF51: 0.87
A52: 2025年-8月陈敏之 | I52: 107876 | J52: 103455 | K52: 627 | L52: 172 | M52: 46 | N52: 48 | O52: 49 | P52: 37 | Q52: 54 | R52: 17 | S52: 25 | T52: 81896 | U52: 110600 | V52: 1 | W52: 4424 | X52: 0.267 | Y52: 1.065 | Z52: 0.285 | AA52: 0.755 | AB52: 1 | AC52: 0.459 | AD52: 0.099 | AE52: 0.145 | AF52: 147578 | AG52: 0.75 | AH52: 54 | AI52: 54 | AJ52: 59 | AK52: 15528 | AL52: 5929 | AM52: 11325 | AN52: 1720 | AO52: 5200 | AP52: 0 | AQ52: 0 | AR52: 0 | AS52: 0 | AT52: 0 | AU52: 0 | AV52: 0 | AW52: 0 | AX52: 0 | AY52: 0 | BJ52: 0 | BK52: 0 | BL52: 0 | BM52: 0 | BN52: 0 | BO52: 0 | BP52: 0 | BQ52: 0 | BR52: 81896 | BS52: 110600 | BT52: 1 | BU52: 24174 | BV52: 19314 | BW52: 15528 | BX52: 107876 | BY52: 106461 | BZ52: 141303 | CA52: 0.58 | CB52: 4421 | CC52: 147578 | CD52: 0.75 | CE52: 144950 | CF52: 0.76
A53: 2025年-9月陈敏之 | H53: 2790 | I53: 150854 | J53: 145673 | K53: 435 | L53: 347 | M53: 77 | N53: 77 | O53: 80 | P53: 63 | Q53: 66 | R53: 25 | S53: 29 | T53: 132300 | U53: 149952 | V53: 1 | W53: 5171 | X53: 0.222 | Y53: 1.039 | Z53: 0.231 | AA53: 0.788 | AB53: 0.971 | AC53: 0.397 | AD53: 0.072 | AE53: 0.084 | AF53: 214955 | AG53: 0.7 | AH53: 68 | AI53: 66 | AJ53: 75 | AK53: 26292 | AL53: 11133 | AM53: 16836 | AN53: 3470 | AO53: 6370 | AP53: 0 | AQ53: 0 | AR53: 0 | AS53: 0 | AT53: 0 | AU53: 0 | AV53: 0 | AW53: 0 | AX53: 0 | AY53: 0 | BJ53: 0 | BK53: 0 | BL53: 0 | BM53: 0 | BN53: 0 | BO53: 0 | BP53: 0 | BQ53: 0 | BR53: 132300 | BS53: 149952 | BT53: 1 | BU53: 37809 | BV53: 35573 | BW53: 26292 | BX53: 150854 | BY53: 150139 | BZ53: 212004 | CA53: 0.62 | CB53: 5181 | CC53: 214955 | CD53: 0.7 | CE53: 214688 | CF53: 0.7
A54: 2025年-10月陈敏之 | I54: 32842 | J54: 30877 | K54: 586 | L54: 56 | M54: 19 | N54: 20 | O54: 22 | P54: 18 | Q54: 23 | R54: 9 | S54: 11 | T54: 52203 | U54: 63979 | V54: 1 | W54: 5816 | X54: 0.339 | Y54: 1.158 | Z54: 0.393 | AA54: 0.818 | AB54: 0.958 | AC54: 0.5 | AD54: 0.161 | AE54: 0.196 | AF54: 48818 | AG54: 1.31 | AH54: 24 | AI54: 23 | AJ54: 24 | AK54: 3499 | AL54: 2845 | AM54: 7038 | AN54: 560 | AO54: 2034 | AP54: 0 | AQ54: 0 | AR54: 0 | AS54: 0 | AT54: 0 | AU54: 0 | AV54: 0 | AW54: 0 | AX54: 0 | AY54: 0 | BJ54: 0 | BK54: 0 | BL54: 0 | BM54: 0 | BN54: 0 | BO54: 0 | BP54: 0 | BQ54: 0 | BR54: 52203 | BS54: 63979 | BT54: 1 | BU54: 12477 | BV54: 10616 | BW54: 3499 | BX54: 32842 | BY54: 32485 | BZ54: 46599 | CA54: 1.12 | CB54: 1965 | CC54: 48818 | CD54: 1.31 | CE54: 49519 | CF54: 1.29
A55: 陈敏之汇总 | I55: 627999 | J55: 602060 | K55: 599 | L55: 1005 | M55: 384 | N55: 391 | O55: 405 | P55: 310 | Q55: 351 | R55: 123 | S55: 145 | T55: 605435 | U55: 700671 | W55: 4832 | X55: 0.3821 | Y55: 1.0547 | Z55: 0.403 | AA55: 0.7654 | AB55: 0.9658 | AC55: 0.3968 | AD55: 0.1224 | AE55: 0.1443 | AF55: 859362 | AG55: 0.82 | AH55: 365 | AI55: 351 | AJ55: 388 | AK55: 68944 | AL55: 46742 | AM55: 72597 | AN55: 9609 | AO55: 33670 | AP55: 135 | AQ55: 46 | AS55: 46 | AT55: 24 | AU55: 24 | AV55: 1 | AW55: 2 | AX55: 3588 | AY55: 5468 | BA55: 2734 | BB55: 0.3407 | BC55: 1 | BD55: 0.3407 | BE55: 0.5217 | BF55: 0.5217 | BG55: 0.0417 | BH55: 0.0074 | BI55: 0.0148 | BJ55: 46 | BK55: 24 | BL55: 24 | BM55: 7557 | BN55: 4138 | BO55: 570 | BP55: 1090 | BQ55: 1895 | BR55: 609023 | BS55: 706139 | BU55: 170310 | BV55: 155612 | BW55: 76501 | BX55: 627999 | BY55: 624003 | BZ55: 856116 | CA55: 0.71 | CB55: 25939 | CC55: 874810 | CD55: 0.81 | CE55: 883809 | CF55: 0.8
A56: 2025年-6月林子善 | I56: 113220 | J56: 108216 | K56: 510 | L56: 212 | M56: 97 | N56: 97 | O56: 99 | P56: 75 | Q56: 75 | R56: 27 | S56: 27 | T56: 118357 | U56: 118357 | W56: 4384 | X56: 0.4575 | Y56: 1.0206 | Z56: 0.467 | AA56: 0.7576 | AB56: 0.9615 | AC56: 0.36 | AD56: 0.1274 | AE56: 0.1274 | AF56: 157365 | AG56: 0.75 | AH56: 78 | AI56: 75 | AJ56: 82 | AK56: 13223 | AL56: 10901 | AM56: 11425 | AN56: 1712 | AO56: 7081 | AP56: 29 | AQ56: 29 | AS56: 29 | AT56: 15 | AU56: 15 | AV56: 2 | AW56: 2 | AX56: 7176 | AY56: 7176 | BA56: 3588 | BB56: 1 | BC56: 1 | BD56: 1 | BE56: 0.5172 | BF56: 0.5172 | BG56: 0.1333 | BH56: 0.069 | BI56: 0.069 | BJ56: 29 | BK56: 15 | BL56: 15 | BM56: 1623 | BN56: 2609 | BO56: 746 | BP56: 234 | BQ56: 1184 | BR56: 125533 | BS56: 125533 | BU56: 35893 | BV56: 35893 | BW56: 14847 | BX56: 113220 | BY56: 113220 | BZ56: 163960 | CA56: 0.77 | CB56: 5004 | CC56: 163960 | CD56: 0.77 | CE56: 167188 | CF56: 0.75
A57: 2025年-7月林子善 | I57: 79184 | J57: 77596 | K57: 1148 | L57: 69 | M57: 32 | N57: 37 | O57: 32 | P57: 25 | Q57: 35 | R57: 4 | S57: 9 | T57: 24352 | U57: 47892 | V57: 1 | W57: 5321 | X57: 0.464 | Y57: 1 | Z57: 0.464 | AA57: 0.781 | AB57: 0.946 | AC57: 0.16 | AD57: 0.058 | AE57: 0.13 | AF57: 95155 | AG57: 0.5 | AH57: 37 | AI57: 35 | AJ57: 39 | AK57: 3036 | AL57: 3883 | AM57: 4904 | AN57: 710 | AO57: 3438 | AP57: 0 | AQ57: 0 | AR57: 0 | AS57: 0 | AT57: 0 | AU57: 0 | AV57: 0 | AW57: 0 | AX57: 0 | AY57: 0 | BJ57: 0 | BK57: 0 | BL57: 0 | BM57: 0 | BN57: 0 | BO57: 0 | BP57: 0 | BQ57: 0 | BR57: 24352 | BS57: 47892 | BT57: 1 | BU57: 12934 | BV57: 8942 | BW57: 3036 | BX57: 79184 | BY57: 78302 | BZ57: 90280 | CA57: 0.27 | CB57: 1588 | CC57: 95155 | CD57: 0.5 | CE57: 97294 | CF57: 0.49
A58: 2025年-8月林子善 | I58: 44759 | J58: 43521 | K58: 1492 | L58: 30 | M58: 17 | N58: 21 | O58: 17 | P58: 15 | Q58: 19 | R58: 5 | S58: 7 | T58: 27940 | U58: 35116 | V58: 1 | W58: 5017 | X58: 0.567 | Y58: 1 | Z58: 0.567 | AA58: 0.882 | AB58: 1 | AC58: 0.333 | AD58: 0.167 | AE58: 0.233 | AF58: 55719 | AG58: 0.63 | AH58: 19 | AI58: 19 | AJ58: 20 | AK58: 2708 | AL58: 2594 | AM58: 3596 | AN58: 300 | AO58: 1763 | AP58: 0 | AQ58: 0 | AR58: 0 | AS58: 0 | AT58: 0 | AU58: 0 | AV58: 0 | AW58: 0 | AX58: 0 | AY58: 0 | BJ58: 0 | BK58: 0 | BL58: 0 | BM58: 0 | BN58: 0 | BO58: 0 | BP58: 0 | BQ58: 0 | BR58: 27940 | BS58: 35116 | BT58: 1 | BU58: 8253 | BV58: 6671 | BW58: 2708 | BX58: 44759 | BY58: 44405 | BZ58: 53784 | CA58: 0.52 | CB58: 1238 | CC58: 55719 | CD58: 0.63 | CE58: 55261 | CF58: 0.64
A59: 林子善汇总 | I59: 242003 | J59: 233816 | K59: 735 | L59: 318 | M59: 150 | N59: 159 | O59: 152 | P59: 117 | Q59: 133 | R59: 37 | S59: 45 | T59: 179237 | U59: 218541 | W59: 4856 | X59: 0.4717 | Y59: 1.0133 | Z59: 0.478 | AA59: 0.7697 | AB59: 0.9769 | AC59: 0.3162 | AD59: 0.1164 | AE59: 0.1415 | AF59: 316628 | AG59: 0.69 | AH59: 138 | AI59: 133 | AJ59: 146 | AK59: 19661 | AL59: 17904 | AM59: 21764 | AN59: 2792 | AO59: 12702 | AP59: 29 | AQ59: 29 | AS59: 29 | AT59: 15 | AU59: 15 | AV59: 2 | AW59: 2 | AX59: 7176 | AY59: 7176 | BA59: 3588 | BB59: 1 | BC59: 1 | BD59: 1 | BE59: 0.5172 | BF59: 0.5172 | BG59: 0.1333 | BH59: 0.069 | BI59: 0.069 | BJ59: 29 | BK59: 15 | BL59: 15 | BM59: 1623 | BN59: 2609 | BO59: 746 | BP59: 234 | BQ59: 1184 | BR59: 186413 | BS59: 225717 | BU59: 59935 | BV59: 53190 | BW59: 21284 | BX59: 242003 | BY59: 240589 | BZ59: 315062 | CA59: 0.59 | CB59: 8187 | CC59: 323222 | CD59: 0.7 | CE59: 327963 | CF59: 0.69
A60: 2025年-6月mamidaily | I60: 39073 | J60: 37827 | K60: 923 | L60: 41 | M60: 25 | N60: 25 | O60: 24 | P60: 21 | Q60: 21 | R60: 7 | S60: 7 | T60: 35916 | U60: 35916 | W60: 5131 | X60: 0.6098 | Y60: 0.96 | Z60: 0.5854 | AA60: 0.875 | AB60: 0.913 | AC60: 0.3333 | AD60: 0.1707 | AE60: 0.1707 | AF60: 49111 | AG60: 0.73 | AH60: 23 | AI60: 21 | AJ60: 21 | AK60: 1616 | AL60: 2810 | AM60: 3467 | AN60: 331 | AO60: 1813 | AP60: 23 | AQ60: 7 | AS60: 7 | AT60: 1 | AU60: 1 | AV60: 0 | AW60: 0 | AX60: 0 | AY60: 0 | BA60: #DIV/0! | BB60: 0.3043 | BC60: 1 | BD60: 0.3043 | BE60: 0.1429 | BF60: 0.1429 | BG60: 0 | BH60: 0 | BI60: 0 | BJ60: 7 | BK60: 1 | BL60: 1 | BM60: 907 | BN60: 630 | BO60: 0 | BP60: 186 | BQ60: 79 | BR60: 35916 | BS60: 35916 | BU60: 9316 | BV60: 9316 | BW60: 2523 | BX60: 39073 | BY60: 39073 | BZ60: 50912 | CA60: 0.71 | CB60: 1246 | CC60: 50912 | CD60: 0.71 | CE60: 53189 | CF60: 0.68
A61: 2025年-7月mamidaily | I61: 50216 | J61: 49158 | K61: 1522 | L61: 33 | M61: 18 | N61: 20 | O61: 19 | P61: 16 | Q61: 19 | R61: 5 | S61: 6 | T61: 25440 | U61: 34028 | V61: 1 | W61: 5671 | X61: 0.545 | Y61: 1.056 | Z61: 0.576 | AA61: 0.842 | AB61: 0.905 | AC61: 0.313 | AD61: 0.152 | AE61: 0.182 | AF61: 59354 | AG61: 0.57 | AH61: 21 | AI61: 19 | AJ61: 20 | AK61: 1452 | AL61: 2099 | AM61: 3484 | AN61: 340 | AO61: 1763 | AP61: 0 | AQ61: 0 | AR61: 0 | AS61: 0 | AT61: 0 | AU61: 0 | AV61: 0 | AW61: 0 | AX61: 0 | AY61: 0 | BJ61: 0 | BK61: 0 | BL61: 0 | BM61: 0 | BN61: 0 | BO61: 0 | BP61: 0 | BQ61: 0 | BR61: 25440 | BS61: 34028 | BT61: 1 | BU61: 7686 | BV61: 6244 | BW61: 1452 | BX61: 50216 | BY61: 50040 | BZ61: 57736 | CA61: 0.44 | CB61: 1059 | CC61: 59354 | CD61: 0.57 | CE61: 60377 | CF61: 0.56
A62: 2025年-10月mamidaily | H62: 6148 | I62: 22910 | J62: 22374 | K62: 388 | L62: 59 | M62: 9 | N62: 9 | O62: 9 | P62: 7 | Q62: 9 | R62: 3 | S62: 3 | T62: 15664 | U62: 15664 | V62: 1 | W62: 5221 | X62: 0.153 | Y62: 1 | Z62: 0.153 | AA62: 0.778 | AB62: 1 | AC62: 0.429 | AD62: 0.051 | AE62: 0.051 | AF62: 28876 | AG62: 0.54 | AH62: 9 | AI62: 9 | AJ62: 9 | AK62: 1610 | AL62: 1280 | AM62: 1723 | AN62: 590 | AO62: 763 | AP62: 0 | AQ62: 0 | AR62: 0 | AS62: 0 | AT62: 0 | AU62: 0 | AV62: 0 | AW62: 0 | AX62: 0 | AY62: 0 | BJ62: 0 | BK62: 0 | BL62: 0 | BM62: 0 | BN62: 0 | BO62: 0 | BP62: 0 | BQ62: 0 | BR62: 15664 | BS62: 15664 | BT62: 1 | BU62: 4356 | BV62: 4187 | BW62: 1610 | BX62: 22910 | BY62: 22910 | BZ62: 28706 | CA62: 0.55 | CB62: 536 | CC62: 28876 | CD62: 0.54 | CE62: 31691 | CF62: 0.49
A63: mamidaily汇总 | I63: 162859 | J63: 158951 | K63: 919 | L63: 173 | M63: 70 | N63: 72 | O63: 70 | P63: 59 | Q63: 69 | R63: 20 | S63: 22 | T63: 97460 | U63: 114636 | W63: 5211 | X63: 0.4046 | Y63: 1 | Z63: 0.4046 | AA63: 0.8429 | AB63: 0.9636 | AC63: 0.339 | AD63: 0.1156 | AE63: 0.1272 | AF63: 197825 | AG63: 0.58 | AH63: 73 | AI63: 69 | AJ63: 74 | AK63: 6425 | AL63: 8623 | AM63: 11838 | AN63: 1661 | AO63: 6419 | AP63: 23 | AQ63: 7 | AS63: 7 | AT63: 1 | AU63: 1 | AV63: 0 | AW63: 0 | AX63: 0 | AY63: 0 | BA63: #DIV/0! | BB63: 0.3043 | BC63: 1 | BD63: 0.3043 | BE63: 0.1429 | BF63: 0.1429 | BG63: 0 | BH63: 0 | BI63: 0 | BJ63: 7 | BK63: 1 | BL63: 1 | BM63: 907 | BN63: 630 | BO63: 0 | BP63: 186 | BQ63: 79 | BR63: 97460 | BS63: 114636 | BU63: 29435 | BV63: 26340 | BW63: 7332 | BX63: 162859 | BY63: 162504 | BZ63: 196177 | CA63: 0.5 | CB63: 3909 | CC63: 199627 | CD63: 0.57 | CE63: 206994 | CF63: 0.55
A64: 2025年-7月吴若希 | I64: 68696 | J64: 67637 | K64: 1205 | L64: 57 | M64: 28 | N64: 28 | O64: 29 | P64: 25 | Q64: 25 | R64: 6 | S64: 6 | T64: 26528 | U64: 26528 | V64: 1 | W64: 4421 | X64: 0.491 | Y64: 1.036 | Z64: 0.509 | AA64: 0.862 | AB64: 0.962 | AC64: 0.24 | AD64: 0.105 | AE64: 0.105 | AF64: 79737 | AG64: 0.33 | AH64: 26 | AI64: 25 | AJ64: 26 | AK64: 2508 | AL64: 2938 | AM64: 2716 | AN64: 587 | AO64: 2292 | AP64: 0 | AQ64: 0 | AR64: 0 | AS64: 0 | AT64: 0 | AU64: 0 | AV64: 0 | AW64: 0 | AX64: 0 | AY64: 0 | BJ64: 0 | BK64: 0 | BL64: 0 | BM64: 0 | BN64: 0 | BO64: 0 | BP64: 0 | BQ64: 0 | BR64: 26528 | BS64: 26528 | BT64: 1 | BU64: 8533 | BV64: 8533 | BW64: 2508 | BX64: 68696 | BY64: 68696 | BZ64: 79737 | CA64: 0.33 | CB64: 1059 | CC64: 79737 | CD64: 0.33 | CE64: 81504 | CF64: 0.33
A65: 2025年-8月吴若希 | I65: 42366 | J65: 42189 | K65: 1461 | L65: 29 | M65: 10 | N65: 11 | O65: 11 | P65: 6 | Q65: 9 | R65: 1 | S65: 1 | T65: 3588 | U65: 3588 | V65: 1 | W65: 3588 | X65: 0.345 | Y65: 1.1 | Z65: 0.379 | AA65: 0.545 | AB65: 1 | AC65: 0.167 | AD65: 0.034 | AE65: 0.034 | AF65: 47882 | AG65: 0.07 | AH65: 9 | AI65: 9 | AJ65: 10 | AK65: 2618 | AL65: 1359 | AM65: 367 | AN65: 290 | AO65: 881 | AP65: 0 | AQ65: 0 | AR65: 0 | AS65: 0 | AT65: 0 | AU65: 0 | AV65: 0 | AW65: 0 | AX65: 0 | AY65: 0 | BJ65: 0 | BK65: 0 | BL65: 0 | BM65: 0 | BN65: 0 | BO65: 0 | BP65: 0 | BQ65: 0 | BR65: 3588 | BS65: 3588 | BT65: 1 | BU65: 2898 | BV65: 2421 | BW65: 2618 | BX65: 42366 | BY65: 42366 | BZ65: 47406 | CA65: 0.08 | CB65: 177 | CC65: 47882 | CD65: 0.07 | CE65: 47439 | CF65: 0.08
A66: 2025年-9月吴若希 | H66: 4919 | I66: 28378 | J66: 27842 | K66: 2183 | L66: 13 | M66: 8 | N66: 9 | O66: 7 | P66: 5 | Q66: 7 | R66: 3 | S66: 3 | T66: 10764 | U66: 10764 | V66: 1 | W66: 3588 | X66: 0.615 | Y66: 0.875 | Z66: 0.538 | AA66: 0.714 | AB66: 1 | AC66: 0.6 | AD66: 0.231 | AE66: 0.231 | AF66: 32774 | AG66: 0.33 | AH66: 7 | AI66: 7 | AJ66: 7 | AK66: 1307 | AL66: 1219 | AM66: 1152 | AN66: 130 | AO66: 589 | AP66: 0 | AQ66: 0 | AR66: 0 | AS66: 0 | AT66: 0 | AU66: 0 | AV66: 0 | AW66: 0 | AX66: 0 | AY66: 0 | BJ66: 0 | BK66: 0 | BL66: 0 | BM66: 0 | BN66: 0 | BO66: 0 | BP66: 0 | BQ66: 0 | BR66: 10764 | BS66: 10764 | BT66: 1 | BU66: 3090 | BV66: 2786 | BW66: 1307 | BX66: 28378 | BY66: 28378 | BZ66: 32470 | CA66: 0.33 | CB66: 536 | CC66: 32774 | CD66: 0.33 | CE66: 32442 | CF66: 0.33
A67: 吴若希-汇总 | I67: 139440 | J67: 137669 | K67: 1391 | L67: 99 | M67: 46 | N67: 48 | O67: 47 | P67: 36 | Q67: 41 | R67: 10 | S67: 10 | T67: 40880 | U67: 40880 | W67: 4088 | X67: 0.4646 | Y67: 1.0217 | Z67: 0.4747 | AA67: 0.766 | AB67: 0.9872 | AC67: 0.2778 | AD67: 0.101 | AE67: 0.101 | AF67: 160393 | AG67: 0.25 | AH67: 42 | AI67: 41 | AJ67: 43 | AK67: 6433 | AL67: 5516 | AM67: 4236 | AN67: 1007 | AO67: 3762 | AP67: 0 | AQ67: 0 | AS67: 0 | AT67: 0 | AU67: 0 | AV67: 0 | AW67: 0 | AX67: 0 | AY67: 0 | BA67: #DIV/0! | BB67: #DIV/0! | BC67: #DIV/0! | BD67: #DIV/0! | BE67: #DIV/0! | BF67: #DIV/0! | BG67: #DIV/0! | BH67: #DIV/0! | BI67: #DIV/0! | BJ67: 0 | BK67: 0 | BL67: 0 | BM67: 0 | BN67: 0 | BO67: 0 | BP67: 0 | BQ67: 0 | BR67: 40880 | BS67: 40880 | BU67: 14520 | BV67: 13741 | BW67: 6433 | BX67: 139440 | BY67: 139440 | BZ67: 159613 | CA67: 0.26 | CB67: 1771 | CC67: 160393 | CD67: 0.25 | CE67: 161385 | CF67: 0.25
A68: 2025年-7月张美妮 | I68: 10611 | J68: 10434 | K68: 1061 | L68: 10 | M68: 8 | N68: 8 | O68: 8 | P68: 4 | Q68: 4 | R68: 1 | S68: 1 | T68: 3588 | U68: 3588 | V68: 1 | W68: 3588 | X68: 0.8 | Y68: 1 | Z68: 0.8 | AA68: 0.5 | AB68: 0.667 | AC68: 0.25 | AD68: 0.1 | AE68: 0.1 | AF68: 12713 | AG68: 0.28 | AH68: 6 | AI68: 4 | AJ68: 4 | AK68: 440 | AL68: 839 | AM68: 367 | AN68: 103 | AO68: 353 | AP68: 0 | AQ68: 0 | AR68: 0 | AS68: 0 | AT68: 0 | AU68: 0 | AV68: 0 | AW68: 0 | AX68: 0 | AY68: 0 | BJ68: 0 | BK68: 0 | BL68: 0 | BM68: 0 | BN68: 0 | BO68: 0 | BP68: 0 | BQ68: 0 | BR68: 3588 | BS68: 3588 | BT68: 1 | BU68: 1662 | BV68: 1662 | BW68: 440 | BX68: 10611 | BY68: 10611 | BZ68: 12713 | CA68: 0.28 | CB68: 176 | CC68: 12713 | CD68: 0.28 | CE68: 13023 | CF68: 0.28
A69: 2025年-8月张美妮 | I69: 26906 | J69: 26906 | K69: 961 | L69: 28 | M69: 4 | N69: 4 | O69: 3 | P69: 1 | Q69: 3 | R69: 0 | S69: 0 | T69: 0 | U69: 0 | X69: 0.143 | Y69: 0.75 | Z69: 0.107 | AA69: 0.333 | AB69: 1 | AC69: 0 | AD69: 0 | AE69: 0 | AF69: 3566 | AG69: 0 | AH69: 3 | AI69: 3 | AJ69: 3 | AK69: 2528 | AL69: 494 | AM69: 0 | AN69: 280 | AO69: 264 | AP69: 0 | AQ69: 0 | AR69: 0 | AS69: 0 | AT69: 0 | AU69: 0 | AV69: 0 | AW69: 0 | AX69: 0 | AY69: 0 | BJ69: 0 | BK69: 0 | BL69: 0 | BM69: 0 | BN69: 0 | BO69: 0 | BP69: 0 | BQ69: 0 | BR69: 0 | BS69: 0 | BU69: 1038 | BV69: 862 | BW69: 2528 | BX69: 26906 | BY69: 26906 | BZ69: 3390 | CA69: 0 | CB69: 0 | CC69: 3566 | CD69: 0 | CE69: 3139 | CF69: 0
A70: 2025年-9月张美妮 | H70: 1953 | I70: 21504 | J70: 21325 | K70: 652 | L70: 33 | M70: 3 | N70: 3 | O70: 2 | P70: 0 | Q70: 0 | R70: 0 | S70: 1 | T70: 0 | U70: 4388 | V70: 1 | W70: 4388 | X70: 0.091 | Y70: 0.667 | Z70: 0.061 | AA70: 0 | AD70: 0 | AE70: 0.03 | AF70: 25260 | AG70: 0.17 | AH70: 0 | AI70: 0 | AJ70: 0 | AK70: 2500 | AL70: 434 | AM70: 493 | AN70: 330 | AO70: 0 | AP70: 0 | AQ70: 0 | AR70: 0 | AS70: 0 | AT70: 0 | AU70: 0 | AV70: 0 | AW70: 0 | AX70: 0 | AY70: 0 | BJ70: 0 | BK70: 0 | BL70: 0 | BM70: 0 | BN70: 0 | BO70: 0 | BP70: 0 | BQ70: 0 | BR70: 0 | BS70: 4388 | BT70: 1 | BU70: 1256 | BV70: 764 | BW70: 2500 | BX70: 21504 | BY70: 21325 | BZ70: 24589 | CA70: 0 | CB70: 179 | CC70: 25260 | CD70: 0.17 | CE70: 25235 | CF70: 0.17
A71: 2025年-10月张美妮 | I71: 8042 | J71: 7863 | K71: 670 | L71: 12 | M71: 1 | N71: 1 | O71: 1 | P71: 1 | Q71: 2 | R71: 0 | S71: 1 | T71: 0 | U71: 6088 | V71: 1 | W71: 6088 | X71: 0.083 | Y71: 1 | Z71: 0.083 | AA71: 1 | AB71: 1 | AC71: 0 | AD71: 0 | AE71: 0.083 | AF71: 9893 | AG71: 0.62 | AH71: 2 | AI71: 2 | AJ71: 2 | AK71: 750 | AL71: 142 | AM71: 670 | AN71: 120 | AO71: 170 | AP71: 0 | AQ71: 0 | AR71: 0 | AS71: 0 | AT71: 0 | AU71: 0 | AV71: 0 | AW71: 0 | AX71: 0 | AY71: 0 | BJ71: 0 | BK71: 0 | BL71: 0 | BM71: 0 | BN71: 0 | BO71: 0 | BP71: 0 | BQ71: 0 | BR71: 0 | BS71: 6088 | BT71: 1 | BU71: 1101 | BV71: 347 | BW71: 750 | BX71: 8042 | BY71: 7863 | BZ71: 8960 | CA71: 0 | CB71: 179 | CC71: 9893 | CD71: 0.62 | CE71: 10043 | CF71: 0.61
A72: 张美妮-汇总 | I72: 67062 | J72: 66528 | K72: 802 | L72: 83 | M72: 16 | N72: 16 | O72: 14 | P72: 6 | Q72: 9 | R72: 1 | S72: 3 | T72: 3588 | U72: 14064 | W72: 4688 | X72: 0.1928 | Y72: 0.875 | Z72: 0.1687 | AA72: 0.4286 | AB72: 0.8889 | AC72: 0.1667 | AD72: 0.012 | AE72: 0.0361 | AF72: 51433 | AG72: 0.27 | AH72: 11 | AI72: 9 | AJ72: 9 | AK72: 6218 | AL72: 1910 | AM72: 1530 | AN72: 833 | AO72: 787 | AP72: 0 | AQ72: 0 | AS72: 0 | AT72: 0 | AU72: 0 | AV72: 0 | AW72: 0 | AX72: 0 | AY72: 0 | BA72: #DIV/0! | BB72: #DIV/0! | BC72: #DIV/0! | BD72: #DIV/0! | BE72: #DIV/0! | BF72: #DIV/0! | BG72: #DIV/0! | BH72: #DIV/0! | BI72: #DIV/0! | BJ72: 0 | BK72: 0 | BL72: 0 | BM72: 0 | BN72: 0 | BO72: 0 | BP72: 0 | BQ72: 0 | BR72: 3588 | BS72: 14064 | BU72: 5059 | BV72: 3635 | BW72: 6218 | BX72: 67062 | BY72: 66705 | BZ72: 49652 | CA72: 0.07 | CB72: 534 | CC72: 51433 | CD72: 0.27 | CE72: 51440 | CF72: 0.27
A73: 2025年-8月钟嘉欣 | I73: 247270 | J73: 238429 | K73: 512 | L73: 466 | M73: 167 | N73: 167 | O73: 167 | P73: 127 | Q73: 127 | R73: 50 | S73: 50 | T73: 256600 | U73: 256600 | W73: 5132 | X73: 0.3584 | Y73: 1 | Z73: 0.3584 | AA73: 0.7605 | AB73: 0.995 | AC73: 0.3937 | AD73: 0.1073 | AE73: 0.1073 | AF73: 353419 | AG73: 0.73 | AH73: 128 | AI73: 127 | AJ73: 142 | AK73: 42070 | AL73: 20628 | AM73: 26275 | AN73: 4660 | AO73: 12516 | AP73: 0 | AQ73: 0 | AS73: 0 | AT73: 0 | AU73: 0 | AV73: 0 | AW73: 0 | AX73: 0 | AY73: 0 | BA73: #DIV/0! | BB73: #DIV/0! | BC73: #DIV/0! | BD73: #DIV/0! | BE73: #DIV/0! | BF73: #DIV/0! | BG73: #DIV/0! | BH73: #DIV/0! | BI73: #DIV/0! | BJ73: 0 | BK73: 0 | BL73: 0 | BM73: 0 | BN73: 0 | BO73: 0 | BP73: 0 | BQ73: 0 | BR73: 256600 | BS73: 256600 | BU73: 64079 | BV73: 64079 | BW73: 42070 | BX73: 247270 | BY73: 247270 | BZ73: 353419 | CA73: 0.73 | CB73: 8841 | CC73: 353419 | CD73: 0.73 | CE73: 346299 | CF73: 0.74
A74: 2025年-9月钟嘉欣 | I74: 232765 | J74: 224011 | K74: 546 | L74: 410 | M74: 120 | N74: 128 | O74: 115 | P74: 91 | Q74: 112 | R74: 40 | S74: 49 | T74: 195020 | U74: 234812 | W74: 4792 | X74: 0.293 | Y74: 0.958 | Z74: 0.28 | AA74: 0.791 | AB74: 0.991 | AC74: 0.44 | AD74: 0.098 | AE74: 0.12 | AF74: 323333 | AG74: 0.73 | AH74: 113 | AI74: 112 | AJ74: 124 | AK74: 31065 | AL74: 18507 | AM74: 26364 | AN74: 4100 | AO74: 10531 | AP74: 0 | AQ74: 0 | AS74: 0 | AT74: 0 | AU74: 0 | AV74: 0 | AW74: 0 | AX74: 0 | AY74: 0 | BA74: #DIV/0! | BB74: #DIV/0! | BC74: #DIV/0! | BD74: #DIV/0! | BE74: #DIV/0! | BF74: #DIV/0! | BG74: #DIV/0! | BH74: #DIV/0! | BI74: #DIV/0! | BJ74: 0 | BK74: 0 | BL74: 0 | BM74: 0 | BN74: 0 | BO74: 0 | BP74: 0 | BQ74: 0 | BR74: 195020 | BS74: 234812 | BU74: 59503 | BV74: 51755 | BW74: 31065 | BX74: 232765 | BY74: 231157 | BZ74: 313977 | CA74: 0.62 | CB74: 8753 | CC74: 323333 | CD74: 0.73 | CE74: 323018 | CF74: 0.73
A75: 2025年-10月钟嘉欣 | I75: 179213 | J75: 175283 | K75: 482 | L75: 364 | M75: 81 | N75: 84 | O75: 78 | P75: 60 | Q75: 67 | R75: 20 | S75: 22 | T75: 130215 | U75: 138191 | W75: 6281 | X75: 0.223 | Y75: 0.963 | Z75: 0.214 | AA75: 0.769 | AB75: 0.991 | AC75: 0.333 | AD75: 0.055 | AE75: 0.06 | AF75: 239020 | AG75: 0.58 | AH75: 68 | AI75: 67 | AJ75: 74 | AK75: 22744 | AL75: 11949 | AM75: 15201 | AN75: 3640 | AO75: 6273 | AP75: 0 | AQ75: 0 | AS75: 0 | AT75: 0 | AU75: 0 | AV75: 0 | AW75: 0 | AX75: 0 | AY75: 0 | BA75: #DIV/0! | BB75: #DIV/0! | BC75: #DIV/0! | BD75: #DIV/0! | BE75: #DIV/0! | BF75: #DIV/0! | BG75: #DIV/0! | BH75: #DIV/0! | BI75: #DIV/0! | BJ75: 0 | BK75: 0 | BL75: 0 | BM75: 0 | BN75: 0 | BO75: 0 | BP75: 0 | BQ75: 0 | BR75: 130215 | BS75: 138191 | BU75: 37063 | BV75: 35080 | BW75: 22744 | BX75: 179213 | BY75: 178856 | BZ75: 236680 | CA75: 0.55 | CB75: 3930 | CC75: 239020 | CD75: 0.58 | CE75: 243576 | CF75: 0.57
A76: 2025年-11月钟嘉欣 | I76: 81092 | J76: 78232 | K76: 652 | L76: 120 | M76: 64 | N76: 65 | O76: 60 | P76: 41 | Q76: 47 | R76: 14 | S76: 16 | T76: 80793 | U76: 96791 | W76: 6049 | X76: 0.5333 | Y76: 0.9375 | Z76: 0.5 | AA76: 0.6833 | AB76: 0.9825 | AC76: 0.3415 | AD76: 0.1167 | AE76: 0.1333 | AF76: 112750 | AG76: 0.86 | AH76: 48 | AI76: 47 | AJ76: 51 | AK76: 7811 | AL76: 7677 | AM76: 10647 | AN76: 1200 | AO76: 4323 | AP76: 0 | AQ76: 0 | AS76: 0 | AT76: 0 | AU76: 0 | AV76: 0 | AW76: 0 | AX76: 0 | AY76: 0 | BA76: #DIV/0! | BB76: #DIV/0! | BC76: #DIV/0! | BD76: #DIV/0! | BE76: #DIV/0! | BF76: #DIV/0! | BG76: #DIV/0! | BH76: #DIV/0! | BI76: #DIV/0! | BJ76: 0 | BK76: 0 | BL76: 0 | BM76: 0 | BN76: 0 | BO76: 0 | BP76: 0 | BQ76: 0 | BR76: 80793 | BS76: 96791 | BU76: 23847 | BV76: 21461 | BW76: 7811 | BX76: 81092 | BY76: 80734 | BZ76: 110006 | CA76: 0.73 | CB76: 2860 | CC76: 112750 | CD76: 0.86 | CE76: 113939 | CF76: 0.85
A77: 钟嘉欣-汇总 | H77: 7233 | I77: 740339 | J77: 715955 | K77: 526 | L77: 1360 | M77: 432 | N77: 444 | O77: 420 | P77: 319 | Q77: 353 | R77: 124 | S77: 137 | T77: 662628 | U77: 726394 | W77: 5302 | X77: 0.3176 | Y77: 0.9722 | Z77: 0.3088 | AA77: 0.7595 | AB77: 0.99 | AC77: 0.3887 | AD77: 0.0912 | AE77: 0.1007 | AF77: 1028522 | AG77: 0.71 | AH77: 357 | AI77: 353 | AJ77: 391 | AK77: 103691 | AL77: 58761 | AM77: 78488 | AN77: 13600 | AO77: 33643 | AP77: 0 | AQ77: 0 | AS77: 0 | AT77: 0 | AU77: 0 | AV77: 0 | AW77: 0 | AX77: 0 | AY77: 0 | BA77: #DIV/0! | BB77: #DIV/0! | BC77: #DIV/0! | BD77: #DIV/0! | BE77: #DIV/0! | BF77: #DIV/0! | BG77: #DIV/0! | BH77: #DIV/0! | BI77: #DIV/0! | BJ77: 0 | BK77: 0 | BL77: 0 | BM77: 0 | BN77: 0 | BO77: 0 | BP77: 0 | BQ77: 0 | BR77: 662628 | BS77: 726394 | BU77: 184492 | BV77: 172375 | BW77: 103691 | BX77: 740339 | BY77: 738016 | BZ77: 1014083 | CA77: 0.65 | CB77: 24384 | CC77: 1028522 | CD77: 0.71 | CE77: 1026831 | CF77: 0.71
A78: 2025年-8月蔡雪莹 | I78: 44423 | J78: 43716 | K78: 397 | L78: 110 | M78: 42 | N78: 42 | O78: 40 | P78: 27 | Q78: 27 | R78: 4 | S78: 4 | T78: 19352 | U78: 19352 | W78: 4838 | X78: 0.3818 | Y78: 0.9524 | Z78: 0.3636 | AA78: 0.675 | AB78: 1 | AC78: 0.1481 | AD78: 0.0364 | AE78: 0.0364 | AF78: 65444 | AG78: 0.3 | AH78: 27 | AI78: 27 | AJ78: 32 | AK78: 9931 | AL78: 5188 | AM78: 1982 | AN78: 1100 | AO78: 2821 | AP78: 0 | AQ78: 0 | AS78: 0 | AT78: 0 | AU78: 0 | AV78: 0 | AW78: 0 | AX78: 0 | AY78: 0 | BA78: #DIV/0! | BB78: #DIV/0! | BC78: #DIV/0! | BD78: #DIV/0! | BE78: #DIV/0! | BF78: #DIV/0! | BG78: #DIV/0! | BH78: #DIV/0! | BI78: #DIV/0! | BJ78: 0 | BK78: 0 | BL78: 0 | BM78: 0 | BN78: 0 | BO78: 0 | BP78: 0 | BQ78: 0 | BR78: 19352 | BS78: 19352 | BU78: 11090 | BV78: 11090 | BW78: 9931 | BX78: 44423 | BY78: 44423 | BZ78: 65444 | CA78: 0.3 | CB78: 707 | CC78: 65444 | CD78: 0.3 | CE78: 63763 | CF78: 0.3
A79: 2025年-9月蔡雪莹 | H79: 2025 | I79: 139122 | J79: 134656 | K79: 548 | L79: 254 | M79: 77 | N79: 81 | O79: 76 | P79: 60 | Q79: 70 | R79: 19 | S79: 25 | T79: 87372 | U79: 109900 | V79: 1 | W79: 4396 | X79: 0.303 | Y79: 0.987 | Z79: 0.299 | AA79: 0.789 | AB79: 0.986 | AC79: 0.317 | AD79: 0.075 | AE79: 0.098 | AF79: 191752 | AG79: 0.57 | AH79: 71 | AI79: 70 | AJ79: 80 | AK79: 19245 | AL79: 11712 | AM79: 12339 | AN79: 2540 | AO79: 6794 | AP79: 0 | AQ79: 0 | AR79: 0 | AS79: 0 | AT79: 0 | AU79: 0 | AV79: 0 | AW79: 0 | AX79: 0 | AY79: 0 | BJ79: 0 | BK79: 0 | BL79: 0 | BM79: 0 | BN79: 0 | BO79: 0 | BP79: 0 | BQ79: 0 | BR79: 87372 | BS79: 109900 | BT79: 1 | BU79: 33385 | BV79: 29089 | BW79: 19245 | BX79: 139122 | BY79: 138050 | BZ79: 186384 | CA79: 0.47 | CB79: 4466 | CC79: 191752 | CD79: 0.57 | CE79: 191557 | CF79: 0.57
A80: 2025年-10月蔡雪莹 | I80: 99220 | J80: 98505 | K80: 335 | L80: 296 | M80: 25 | N80: 31 | O80: 26 | P80: 18 | Q80: 25 | R80: 2 | S80: 4 | T80: 13707 | U80: 23183 | V80: 1 | W80: 5796 | X80: 0.084 | Y80: 1.04 | Z80: 0.088 | AA80: 0.692 | AB80: 1 | AC80: 0.111 | AD80: 0.007 | AE80: 0.014 | AF80: 130263 | AG80: 0.18 | AH80: 25 | AI80: 25 | AJ80: 31 | AK80: 18495 | AL80: 4410 | AM80: 2550 | AN80: 2960 | AO80: 2628 | AP80: 0 | AQ80: 0 | AR80: 0 | AS80: 0 | AT80: 0 | AU80: 0 | AV80: 0 | AW80: 0 | AX80: 0 | AY80: 0 | BJ80: 0 | BK80: 0 | BL80: 0 | BM80: 0 | BN80: 0 | BO80: 0 | BP80: 0 | BQ80: 0 | BR80: 13707 | BS80: 23183 | BT80: 1 | BU80: 12548 | BV80: 9719 | BW80: 18495 | BX80: 99220 | BY80: 98862 | BZ80: 127077 | CA80: 0.11 | CB80: 715 | CC80: 130263 | CD80: 0.18 | CE80: 133967 | CF80: 0.17
A81: 2025年-11月蔡雪莹 | I81: 40378 | J81: 38948 | K81: 721 | L81: 56 | M81: 25 | N81: 28 | O81: 24 | P81: 13 | Q81: 15 | R81: 7 | S81: 8 | T81: 34802 | U81: 40101 | V81: 1 | W81: 5013 | X81: 0.446 | Y81: 0.96 | Z81: 0.429 | AA81: 0.542 | AB81: 0.938 | AC81: 0.538 | AD81: 0.125 | AE81: 0.143 | AF81: 53658 | AG81: 0.75 | AH81: 16 | AI81: 15 | AJ81: 16 | AK81: 3645 | AL81: 3307 | AM81: 4411 | AN81: 560 | AO81: 1356 | AP81: 0 | AQ81: 0 | AR81: 0 | AS81: 0 | AT81: 0 | AU81: 0 | AV81: 0 | AW81: 0 | AX81: 0 | AY81: 0 | BJ81: 0 | BK81: 0 | BL81: 0 | BM81: 0 | BN81: 0 | BO81: 0 | BP81: 0 | BQ81: 0 | BR81: 34802 | BS81: 40101 | BT81: 1 | BU81: 9634 | BV81: 8443 | BW81: 3645 | BX81: 40378 | BY81: 40199 | BZ81: 52287 | CA81: 0.67 | CB81: 1430 | CC81: 53658 | CD81: 0.75 | CE81: 54212 | CF81: 0.74
A82: 蔡雪莹-汇总 | I82: 323142 | J82: 315824 | K82: 441 | L82: 716 | M82: 169 | N82: 182 | O82: 166 | P82: 118 | Q82: 137 | R82: 32 | S82: 41 | T82: 155233 | U82: 192536 | W82: 4696 | X82: 0.236 | Y82: 0.9822 | Z82: 0.2318 | AA82: 0.7108 | AB82: 0.9809 | AC82: 0.2712 | AD82: 0.0447 | AE82: 0.0573 | AF82: 441116 | AG82: 0.44 | AH82: 139 | AI82: 137 | AJ82: 159 | AK82: 51317 | AL82: 24616 | AM82: 21282 | AN82: 7160 | AO82: 13599 | AP82: 0 | AQ82: 0 | AS82: 0 | AT82: 0 | AU82: 0 | AV82: 0 | AW82: 0 | AX82: 0 | AY82: 0 | BA82: #DIV/0! | BB82: #DIV/0! | BC82: #DIV/0! | BD82: #DIV/0! | BE82: #DIV/0! | BF82: #DIV/0! | BG82: #DIV/0! | BH82: #DIV/0! | BI82: #DIV/0! | BJ82: 0 | BK82: 0 | BL82: 0 | BM82: 0 | BN82: 0 | BO82: 0 | BP82: 0 | BQ82: 0 | BR82: 155233 | BS82: 192536 | BU82: 66657 | BV82: 58341 | BW82: 51317 | BX82: 323142 | BY82: 321534 | BZ82: 431192 | CA82: 0.36 | CB82: 7318 | CC82: 441116 | CD82: 0.44 | CE82: 443499 | CF82: 0.43
A83: 2025年-9月陈展鹏 | I83: 74915 | J83: 73844 | K83: 604 | L83: 124 | M83: 47 | N83: 47 | O83: 48 | P83: 30 | Q83: 30 | R83: 6 | S83: 6 | T83: 24828 | U83: 24828 | V83: 1 | W83: 4138 | X83: 0.379 | Y83: 1.021 | Z83: 0.387 | AA83: 0.625 | AB83: 0.968 | AC83: 0.2 | AD83: 0.048 | AE83: 0.048 | AF83: 97852 | AG83: 0.25 | AH83: 31 | AI83: 30 | AJ83: 32 | AK83: 9395 | AL83: 6796 | AM83: 2788 | AN83: 1240 | AO83: 2718 | AP83: 0 | AQ83: 0 | AR83: 0 | AS83: 0 | AT83: 0 | AU83: 0 | AV83: 0 | AW83: 0 | AX83: 0 | AY83: 0 | BJ83: 0 | BK83: 0 | BL83: 0 | BM83: 0 | BN83: 0 | BO83: 0 | BP83: 0 | BQ83: 0 | BR83: 24828 | BS83: 24828 | BT83: 1 | BU83: 13541 | BV83: 13541 | BW83: 9395 | BX83: 74915 | BY83: 74915 | BZ83: 97852 | CA83: 0.25 | CB83: 1072 | CC83: 97852 | CD83: 0.25 | CE83: 97756 | CF83: 0.25
A84: 2025年-10月陈展鹏 | I84: 178124 | J84: 175266 | K84: 522 | L84: 341 | M84: 68 | N84: 71 | O84: 68 | P84: 47 | Q84: 57 | R84: 13 | S84: 16 | T84: 85686 | U84: 104150 | V84: 1 | W84: 6509 | X84: 0.199 | Y84: 1 | Z84: 0.199 | AA84: 0.691 | AB84: 0.983 | AC84: 0.277 | AD84: 0.038 | AE84: 0.047 | AF84: 229653 | AG84: 0.45 | AH84: 58 | AI84: 57 | AJ84: 62 | AK84: 21307 | AL84: 10100 | AM84: 11457 | AN84: 3410 | AO84: 5255 | AP84: 0 | AQ84: 0 | AR84: 0 | AS84: 0 | AT84: 0 | AU84: 0 | AV84: 0 | AW84: 0 | AX84: 0 | AY84: 0 | BJ84: 0 | BK84: 0 | BL84: 0 | BM84: 0 | BN84: 0 | BO84: 0 | BP84: 0 | BQ84: 0 | BR84: 85686 | BS84: 104150 | BT84: 1 | BU84: 30222 | BV84: 26831 | BW84: 21307 | BX84: 178124 | BY84: 177588 | BZ84: 225727 | CA84: 0.38 | CB84: 2858 | CC84: 229653 | CD84: 0.45 | CE84: 233921 | CF84: 0.45
A85: 2025年-11月陈展鹏 | I85: 156971 | J85: 154469 | K85: 1098 | L85: 143 | M85: 61 | N85: 67 | O85: 61 | P85: 41 | Q85: 56 | R85: 12 | S85: 14 | T85: 74897 | U85: 83695 | V85: 1 | W85: 5978 | X85: 0.427 | Y85: 1 | Z85: 0.427 | AA85: 0.672 | AB85: 0.982 | AC85: 0.293 | AD85: 0.084 | AE85: 0.098 | AF85: 190000 | AG85: 0.44 | AH85: 57 | AI85: 56 | AJ85: 61 | AK85: 9308 | AL85: 7913 | AM85: 9207 | AN85: 1430 | AO85: 5171 | AP85: 0 | AQ85: 0 | AR85: 0 | AS85: 0 | AT85: 0 | AU85: 0 | AV85: 0 | AW85: 0 | AX85: 0 | AY85: 0 | BJ85: 0 | BK85: 0 | BL85: 0 | BM85: 0 | BN85: 0 | BO85: 0 | BP85: 0 | BQ85: 0 | BR85: 74897 | BS85: 83695 | BT85: 1 | BU85: 23721 | BV85: 20603 | BW85: 9308 | BX85: 156971 | BY85: 156613 | BZ85: 186525 | CA85: 0.4 | CB85: 2502 | CC85: 190000 | CD85: 0.44 | CE85: 191416 | CF85: 0.44
A86: 陈展鹏汇总 | I86: 410010 | J86: 403578 | K86: 664 | L86: 608 | M86: 176 | N86: 185 | O86: 177 | P86: 118 | Q86: 143 | R86: 31 | S86: 36 | T86: 185411 | U86: 212673 | W86: 5908 | X86: 0.2895 | Y86: 1.0057 | Z86: 0.2911 | AA86: 0.6667 | AB86: 0.9777 | AC86: 0.2627 | AD86: 0.051 | AE86: 0.0592 | AF86: 517504 | AG86: 0.41 | AH86: 146 | AI86: 143 | AJ86: 155 | AK86: 40011 | AL86: 24808 | AM86: 23451 | AN86: 6080 | AO86: 13144 | AP86: 0 | AQ86: 0 | AS86: 0 | AT86: 0 | AU86: 0 | AV86: 0 | AW86: 0 | AX86: 0 | AY86: 0 | BA86: #DIV/0! | BB86: #DIV/0! | BC86: #DIV/0! | BD86: #DIV/0! | BE86: #DIV/0! | BF86: #DIV/0! | BG86: #DIV/0! | BH86: #DIV/0! | BI86: #DIV/0! | BJ86: 0 | BK86: 0 | BL86: 0 | BM86: 0 | BN86: 0 | BO86: 0 | BP86: 0 | BQ86: 0 | BR86: 185411 | BS86: 212673 | BU86: 67483 | BV86: 60976 | BW86: 40011 | BX86: 410010 | BY86: 409117 | BZ86: 510103 | CA86: 0.36 | CB86: 6432 | CC86: 517504 | CD86: 0.41 | CE86: 523093 | CF86: 0.41
A87: 2025年-10月专家邓明仪 | I87: 100242 | J87: 99170 | K87: 481 | L87: 206 | M87: 43 | N87: 43 | O87: 42 | P87: 33 | Q87: 33 | R87: 6 | S87: 6 | T87: 24550 | U87: 24550 | W87: 4092 | X87: 0.2087 | Y87: 0.9767 | Z87: 0.2039 | AA87: 0.7857 | AB87: 1 | AC87: 0.1818 | AD87: 0.0291 | AE87: 0.0291 | AF87: 118377 | AG87: 0.21 | AH87: 33 | AI87: 33 | AJ87: 33 | AK87: 12872 | AL87: 6117 | AM87: 2701 | AN87: 2060 | AO87: 2797 | AP87: 0 | AQ87: 0 | AS87: 0 | AT87: 0 | AU87: 0 | AV87: 0 | AW87: 0 | AX87: 0 | AY87: 0 | BA87: #DIV/0! | BB87: #DIV/0! | BC87: #DIV/0! | BD87: #DIV/0! | BE87: #DIV/0! | BF87: #DIV/0! | BG87: #DIV/0! | BH87: #DIV/0! | BI87: #DIV/0! | BJ87: 0 | BK87: 0 | BL87: 0 | BM87: 0 | BN87: 0 | BO87: 0 | BP87: 0 | BQ87: 0 | BR87: 24550 | BS87: 24550 | BU87: 13674 | BV87: 13674 | BW87: 12872 | BX87: 100242 | BY87: 100242 | BZ87: 118377 | CA87: 0.21 | CB87: 1072 | CC87: 118377 | CD87: 0.21 | CE87: 120955 | CF87: 0.2
A88: 2025年-11月专家邓明仪 | I88: 88872 | J88: 85297 | K88: 717 | L88: 119 | M88: 46 | N88: 48 | O88: 47 | P88: 33 | Q88: 40 | R88: 14 | S88: 20 | T88: 81535 | U88: 111169 | W88: 5558 | X88: 0.3866 | Y88: 1.0217 | Z88: 0.395 | AA88: 0.7021 | AB88: 0.9833 | AC88: 0.4242 | AD88: 0.1176 | AE88: 0.1681 | AF88: 119351 | AG88: 0.93 | AH88: 41 | AI88: 40 | AJ88: 43 | AK88: 7746 | AL88: 5669 | AM88: 12229 | AN88: 1190 | AO88: 3645 | AP88: 0 | AQ88: 0 | AS88: 0 | AT88: 0 | AU88: 0 | AV88: 0 | AW88: 0 | AX88: 0 | AY88: 0 | BA88: #DIV/0! | BB88: #DIV/0! | BC88: #DIV/0! | BD88: #DIV/0! | BE88: #DIV/0! | BF88: #DIV/0! | BG88: #DIV/0! | BH88: #DIV/0! | BI88: #DIV/0! | BJ88: 0 | BK88: 0 | BL88: 0 | BM88: 0 | BN88: 0 | BO88: 0 | BP88: 0 | BQ88: 0 | BR88: 81535 | BS88: 111169 | BU88: 22733 | BV88: 18559 | BW88: 7746 | BX88: 88872 | BY88: 87800 | BZ88: 114104 | CA88: 0.71 | CB88: 3574 | CC88: 119351 | CD88: 0.93 | CE88: 120530 | CF88: 0.92
A89: 专家邓明仪-汇总 | I89: 189114 | J89: 184467 | K89: 568 | L89: 325 | M89: 89 | N89: 91 | O89: 89 | P89: 66 | Q89: 73 | R89: 20 | S89: 26 | T89: 106085 | U89: 135719 | W89: 5220 | X89: 0.2738 | Y89: 1 | Z89: 0.2738 | AA89: 0.7416 | AB89: 0.9917 | AC89: 0.303 | AD89: 0.0615 | AE89: 0.08 | AF89: 237727 | AG89: 0.57 | AH89: 74 | AI89: 73 | AJ89: 76 | AK89: 20618 | AL89: 11786 | AM89: 14929 | AN89: 3250 | AO89: 6442 | AP89: 0 | AQ89: 0 | AS89: 0 | AT89: 0 | AU89: 0 | AV89: 0 | AW89: 0 | AX89: 0 | AY89: 0 | BA89: #DIV/0! | BB89: #DIV/0! | BC89: #DIV/0! | BD89: #DIV/0! | BE89: #DIV/0! | BF89: #DIV/0! | BG89: #DIV/0! | BH89: #DIV/0! | BI89: #DIV/0! | BJ89: 0 | BK89: 0 | BL89: 0 | BM89: 0 | BN89: 0 | BO89: 0 | BP89: 0 | BQ89: 0 | BR89: 106085 | BS89: 135719 | BU89: 36407 | BV89: 32233 | BW89: 20618 | BX89: 189114 | BY89: 188041 | BZ89: 232481 | CA89: 0.46 | CB89: 4646 | CC89: 237727 | CD89: 0.57 | CE89: 241484 | CF89: 0.56
A90: 2025年-10月陳凱琳 | I90: 78812 | J90: 78098 | K90: 685 | L90: 115 | M90: 15 | N90: 15 | O90: 14 | P90: 11 | Q90: 11 | R90: 4 | S90: 4 | T90: 21483 | U90: 21483 | V90: 1 | W90: 5371 | X90: 0.13 | Y90: 0.933 | Z90: 0.122 | AA90: 0.786 | AB90: 1 | AC90: 0.364 | AD90: 0.035 | AE90: 0.035 | AF90: 92577 | AG90: 0.23 | AH90: 11 | AI90: 11 | AJ90: 11 | AK90: 7186 | AL90: 2134 | AM90: 2363 | AN90: 1150 | AO90: 932 | AP90: 0 | AQ90: 0 | AR90: 0 | AS90: 0 | AT90: 0 | AU90: 0 | AV90: 0 | AW90: 0 | AX90: 0 | AY90: 0 | BJ90: 0 | BK90: 0 | BL90: 0 | BM90: 0 | BN90: 0 | BO90: 0 | BP90: 0 | BQ90: 0 | BR90: 21483 | BS90: 21483 | BT90: 1 | BU90: 6579 | BV90: 6579 | BW90: 7186 | BX90: 78812 | BY90: 78812 | BZ90: 92577 | CA90: 0.23 | CB90: 715 | CC90: 92577 | CD90: 0.23 | CE90: 94017 | CF90: 0.23
A91: 2025年-11月陳凱琳 | I91: 109602 | J91: 107993 | K91: 1858 | L91: 59 | M91: 33 | N91: 36 | O91: 34 | P91: 25 | Q91: 29 | R91: 7 | S91: 9 | T91: 30613 | U91: 41931 | V91: 1 | W91: 4659 | X91: 0.559 | Y91: 1.03 | Z91: 0.576 | AA91: 0.735 | AB91: 1 | AC91: 0.28 | AD91: 0.119 | AE91: 0.153 | AF91: 125609 | AG91: 0.33 | AH91: 29 | AI91: 29 | AJ91: 32 | AK91: 3841 | AL91: 4252 | AM91: 4612 | AN91: 590 | AO91: 2713 | AP91: 0 | AQ91: 0 | AR91: 0 | AS91: 0 | AT91: 0 | AU91: 0 | AV91: 0 | AW91: 0 | AX91: 0 | AY91: 0 | BJ91: 0 | BK91: 0 | BL91: 0 | BM91: 0 | BN91: 0 | BO91: 0 | BP91: 0 | BQ91: 0 | BR91: 30613 | BS91: 41931 | BT91: 1 | BU91: 12167 | BV91: 10228 | BW91: 3841 | BX91: 109602 | BY91: 109244 | BZ91: 123313 | CA91: 0.25 | CB91: 1609 | CC91: 125609 | CD91: 0.33 | CE91: 126194 | CF91: 0.33
A92: 陳凱琳-汇总 | I92: 188414 | J92: 186091 | K92: 1069 | L92: 174 | M92: 48 | N92: 51 | O92: 48 | P92: 36 | Q92: 40 | R92: 11 | S92: 13 | T92: 52096 | U92: 63414 | W92: 4878 | X92: 0.2759 | Y92: 1 | Z92: 0.2759 | AA92: 0.75 | AB92: 1 | AC92: 0.3056 | AD92: 0.0632 | AE92: 0.0747 | AF92: 218187 | AG92: 0.29 | AH92: 40 | AI92: 40 | AJ92: 43 | AK92: 11026 | AL92: 6386 | AM92: 6976 | AN92: 1740 | AO92: 3645 | AP92: 0 | AQ92: 0 | AS92: 0 | AT92: 0 | AU92: 0 | AV92: 0 | AW92: 0 | AX92: 0 | AY92: 0 | BA92: #DIV/0! | BB92: #DIV/0! | BC92: #DIV/0! | BD92: #DIV/0! | BE92: #DIV/0! | BF92: #DIV/0! | BG92: #DIV/0! | BH92: #DIV/0! | BI92: #DIV/0! | BJ92: 0 | BK92: 0 | BL92: 0 | BM92: 0 | BN92: 0 | BO92: 0 | BP92: 0 | BQ92: 0 | BR92: 52096 | BS92: 63414 | BU92: 18746 | BV92: 16808 | BW92: 11026 | BX92: 188414 | BY92: 188057 | BZ92: 215891 | CA92: 0.24 | CB92: 2323 | CC92: 218187 | CD92: 0.29 | CE92: 220210 | CF92: 0.29
A93: 2025年-11月麥雅緻直播 | I93: 187930 | J93: 183819 | K93: 1128 | L93: 163 | M93: 84 | N93: 84 | O93: 83 | P93: 61 | Q93: 61 | R93: 23 | S93: 23 | T93: 133397 | U93: 133397 | W93: 5800 | X93: 0.5153 | Y93: 0.9881 | Z93: 0.5092 | AA93: 0.7349 | AB93: 0.9839 | AC93: 0.377 | AD93: 0.1411 | AE93: 0.1411 | AF93: 229936 | AG93: 0.58 | AH93: 62 | AI93: 61 | AJ93: 61 | AK93: 10610 | AL93: 9921 | AM93: 14674 | AN93: 1630 | AO93: 5171 | AP93: 0 | AQ93: 0 | AS93: 0 | AT93: 0 | AU93: 0 | AV93: 0 | AW93: 0 | AX93: 0 | AY93: 0 | BA93: #DIV/0! | BB93: #DIV/0! | BC93: #DIV/0! | BD93: #DIV/0! | BE93: #DIV/0! | BF93: #DIV/0! | BG93: #DIV/0! | BH93: #DIV/0! | BI93: #DIV/0! | BJ93: 0 | BK93: 0 | BL93: 0 | BM93: 0 | BN93: 0 | BO93: 0 | BP93: 0 | BQ93: 0 | BR93: 133397 | BS93: 133397 | BU93: 31396 | BV93: 31396 | BW93: 10610 | BX93: 187930 | BY93: 187930 | BZ93: 229936 | CA93: 0.58 | CB93: 4111 | CC93: 229936 | CD93: 0.58 | CE93: 231551 | CF93: 0.58
A94: 2025年-11月呂慧儀直播 | I94: 61236 | J94: 60163 | K94: 1055 | L94: 57 | M94: 30 | N94: 30 | O94: 30 | P94: 18 | Q94: 18 | R94: 6 | S94: 6 | T94: 32514 | U94: 32514 | W94: 5419 | X94: 0.5263 | Y94: 1 | Z94: 0.5263 | AA94: 0.6 | AB94: 1 | AC94: 0.3333 | AD94: 0.1053 | AE94: 0.1053 | AF94: 74162 | AG94: 0.44 | AH94: 18 | AI94: 18 | AJ94: 18 | AK94: 3710 | AL94: 3543 | AM94: 3577 | AN94: 570 | AO94: 1526 | AP94: 0 | AQ94: 0 | AS94: 0 | AT94: 0 | AU94: 0 | AV94: 0 | AW94: 0 | AX94: 0 | AY94: 0 | BA94: #DIV/0! | BB94: #DIV/0! | BC94: #DIV/0! | BD94: #DIV/0! | BE94: #DIV/0! | BF94: #DIV/0! | BG94: #DIV/0! | BH94: #DIV/0! | BI94: #DIV/0! | BJ94: 0 | BK94: 0 | BL94: 0 | BM94: 0 | BN94: 0 | BO94: 0 | BP94: 0 | BQ94: 0 | BR94: 32514 | BS94: 32514 | BU94: 9216 | BV94: 9216 | BW94: 3710 | BX94: 61236 | BY94: 61236 | BZ94: 74162 | CA94: 0.44 | CB94: 1072 | CC94: 74162 | CD94: 0.44 | CE94: 74726 | CF94: 0.44
A95: 2025年3月-KOL汇总 | J95: 313255 | K95: 436 | L95: 718 | M95: 355 | N95: 359 | O95: 389 | P95: 309 | Q95: 324 | R95: 122 | S95: 130 | T95: 596497 | U95: 628301 | W95: 4833 | Z95: 0.5418 | AA95: 0.7943 | AC95: 0.4207 | AD95: 0.1699 | AE95: 0.1811 | AG95: 1.21
A96: 2025年4月-KOL汇总 | J96: 322661 | K96: 571 | L96: 565 | M96: 295 | N96: 306 | O96: 298 | P96: 222 | Q96: 263 | R96: 86 | S96: 105 | T96: 376568 | U96: 450840 | W96: 4294 | X96: 0.5221 | Y96: 1.0102 | Z96: 0.5274 | AA96: 0.745 | AB96: 0.9604 | AC96: 0.3874 | AD96: 0.1522 | AE96: 0.1858 | AF96: 499865 | AG96: 0.9 | AH96: 273 | AI96: 263 | AJ96: 277 | AK96: 62579 | AL96: 45324 | AM96: 40420 | AN96: 5584 | AO96: 23297 | AP96: 20 | AQ96: 18 | AS96: 18 | AT96: 11 | AU96: 13 | AV96: 0 | AW96: 0 | AX96: 0 | AY96: 0 | BA96: #DIV/0! | BB96: 0.9 | BC96: 1 | BD96: 0.9 | BE96: 0.6111 | BF96: 0.65 | BG96: 0 | BH96: 0 | BI96: 0 | BJ96: 20 | BK96: 13 | BL96: 14 | BM96: 2093 | BN96: 2050 | BO96: 0 | BP96: 198 | BQ96: 1114 | BR96: 376568 | BS96: 450840 | BU96: 118576 | BV96: 106102 | BW96: 64881 | BX96: 322661 | BY96: 322661 | BZ96: 493644 | CA96: 0.76 | CC96: 506118 | CD96: 0.89 | CE96: 485262 | CF96: 0.93
A97: 2025年5月-KOL汇总 | J97: 741958 | K97: 687 | L97: 1080 | M97: 473 | N97: 494 | O97: 480 | P97: 357 | Q97: 420 | R97: 132 | S97: 152 | T97: 661648 | U97: 751499 | V97: 1 | W97: 4944 | X97: 0.438 | Y97: 1.015 | Z97: 0.444 | AA97: 0.744 | AB97: 0.94 | AC97: 0.37 | AD97: 0.122 | AE97: 0.141 | AF97: 985972 | AG97: 0.76 | AH97: 447 | AI97: 420 | AJ97: 461 | AK97: 61232 | AL97: 60625 | AM97: 72071 | AN97: 10043 | AO97: 40043 | AP97: 6 | AQ97: 5 | AR97: 6 | AS97: 5 | AT97: 3 | AU97: 6 | AV97: 0 | AW97: 0 | AX97: 0 | AY97: 0 | BB97: 0.833 | BC97: 1 | BD97: 0.833 | BE97: 0.6 | BF97: 0.75 | BG97: 0 | BH97: 0 | BI97: 0 | BJ97: 8 | BK97: 6 | BL97: 6 | BM97: 281 | BN97: 656 | BO97: 0 | BP97: 56 | BQ97: 466 | BR97: 661648 | BS97: 751499 | BT97: 1 | BU97: 183959 | BV97: 166082 | BW97: 61514 | BX97: 741958 | BY97: 741958 | BZ97: 969554 | CA97: 0.68 | CC97: 987431 | CD97: 0.76 | CE97: 1007367 | CF97: 0.75
A98: 2025年6月-KOL汇总 | I98: 739702 | J98: 703268 | K98: 773 | L98: 956 | M98: 500 | N98: 522 | O98: 514 | P98: 395 | Q98: 484 | R98: 160 | S98: 198 | T98: 772461 | U98: 948905 | V98: 1 | W98: 4792 | X98: 0.523 | Y98: 1.028 | Z98: 0.538 | AA98: 0.768 | AB98: 0.938 | AC98: 0.405 | AD98: 0.167 | AE98: 0.207 | AF98: 1003279 | AG98: 0.95 | AH98: 516 | AI98: 484 | AJ98: 546 | AK98: 59630 | AL98: 58665 | AM98: 91601 | AN98: 7721 | AO98: 47150 | AP98: 392 | AQ98: 164 | AR98: 164 | AS98: 164 | AT98: 95 | AU98: 98 | AV98: 12 | AW98: 12 | AX98: 42561 | AY98: 42561 | AZ98: 1 | BA98: 3547 | BB98: 0.418 | BC98: 1 | BD98: 0.418 | BE98: 0.579 | BF98: 0.587 | BG98: 0.126 | BH98: 0.031 | BI98: 0.031 | BJ98: 167 | BK98: 98 | BL98: 104 | BM98: 21944 | BN98: 14753 | BO98: 4423 | BP98: 3166 | BQ98: 8210 | BR98: 815022 | BS98: 991466 | BT98: 1 | BU98: 236141 | BV98: 206727 | BW98: 81742 | BX98: 739702 | BY98: 732937 | BZ98: 1021406 | CA98: 0.8 | CB98: 36434 | CC98: 1057584 | CD98: 0.94 | CE98: 1077167 | CF98: 0.92
A99: 2025年7月-KOL汇总 | I99: 644963 | J99: 621204 | K99: 969 | L99: 665 | M99: 345 | N99: 376 | O99: 359 | P99: 282 | Q99: 367 | R99: 93 | S99: 133 | T99: 449484 | U99: 631604 | V99: 1 | W99: 4749 | X99: 0.519 | Y99: 1.041 | Z99: 0.54 | AA99: 0.786 | AB99: 0.951 | AC99: 0.33 | AD99: 0.14 | AE99: 0.2 | AF99: 820604 | AG99: 0.77 | AH99: 386 | AI99: 367 | AJ99: 405 | AK99: 29263 | AL99: 39455 | AM99: 64675 | AN99: 6845 | AO99: 35697 | AP99: 4 | AQ99: 3 | AR99: 5 | AS99: 4 | AT99: 2 | AU99: 4 | AV99: 0 | AW99: 3 | AX99: 0 | AY99: 5640 | AZ99: 1 | BA99: 1880 | BB99: 0.75 | BC99: 1.333 | BD99: 1 | BE99: 0.5 | BF99: 0.5 | BG99: 0 | BH99: 0 | BI99: 0.75 | BJ99: 8 | BK99: 4 | BL99: 4 | BM99: 0 | BN99: 474 | BO99: 592 | BP99: 41 | BQ99: 329 | BR99: 449484 | BS99: 637244 | BT99: 1 | BU99: 148109 | BV99: 116888 | BW99: 29263 | BX99: 644963 | BY99: 637611 | BZ99: 783762 | CA99: 0.57 | CB99: 23760 | CC99: 822336 | CD99: 0.77 | CE99: 843248 | CF99: 0.76
A100: 2025年8月-KOL汇总 | I100: 626588 | J100: 604308 | K100: 644 | L100: 973 | M100: 355 | N100: 379 | O100: 357 | P100: 267 | Q100: 340 | R100: 101 | S100: 126 | T100: 519388 | U100: 619388 | V100: 1 | W100: 4916 | X100: 0.365 | Y100: 1.006 | Z100: 0.367 | AA100: 0.748 | AB100: 0.997 | AC100: 0.378 | AD100: 0.104 | AE100: 0.129 | AF100: 867715 | AG100: 0.71 | AH100: 341 | AI100: 340 | AJ100: 378 | AK100: 87842 | AL100: 46813 | AM100: 63424 | AN100: 9730 | AO100: 33317 | AP100: 0 | AQ100: 0 | AR100: 0 | AS100: 0 | AT100: 0 | AU100: 1 | AV100: 0 | AW100: 0 | AX100: 0 | AY100: 0 | BF100: 1 | BJ100: 1 | BK100: 1 | BL100: 1 | BM100: 0 | BN100: 0 | BO100: 0 | BP100: 0 | BQ100: 80 | BR100: 519388 | BS100: 619388 | BT100: 1 | BU100: 153365 | BV100: 132941 | BW100: 87842 | BX100: 626588 | BY100: 622167 | BZ100: 842951 | CA100: 0.62 | CB100: 22279 | CC100: 867795 | CD100: 0.71 | CE100: 852928 | CF100: 0.73
...

Sheet 商场具体计划（待更新）
A1: 10月商場排期及計畫
A2: 項目 | B2: 地点 | C2: 时间 | D2: 人员安排 | E2: 推广形式 | F2: 话术卖点 | G2: 例子目标 | H2: 備注
A3: inno4life(科技创意展) | B3: 灣仔會議展覽中心 | C3: 3天 3/4/5 | D3: 4人+3人 | E3: 展銷/流動 | F3: 9.9小课包 | G3: 200 | H3: 準備工作完成，總部派4人，兼職3人
A4: 商场活动 | B4: 皇后山商場/葵芳商場 | C4: 中旬 （10.11.12） | D4: 3人 | E4: 展銷 | F4: 9.9小课包 | G4: 70 | H4: 地理比較偏遠，商場較大，附近人群比較集中，計畫在本週內完成調研和場地確認，備選葵芳商場
B5: 屯門市中心/蝴蝶廣場 | C5: 下旬 (17.18.19) | D5: 3人 | E5: 展銷 | F5: 9.9小课包 | G5: 70 | H5: 人流量較大，葵盛東類似，如時間衝突與皇后山商場二選一，備選蝴蝶廣場，計畫下週完成場地確定
B6: 愉景新城 | C6: 下旬 （25.26） | D6: 10人 | E6: 中庭活動/闖關/遊戲 | F6: 數學遊戲/集印章/發禮物 | G6: 70 | H6: 兒童主題商場，計畫在下週完成場地確認及活動計畫，初步形式在中庭做遊戲闖關活動
A7: 地推 | B7: 學校路口 | C7: 第三周/第四周 （周一/週五） 計畫2場 | D7: 2人 | E7: 流動點位 | F7: 註冊送小禮物 | G7: 20 | H7: 計畫2場學校地推，每場10-15個註冊
A8: 1.計畫展會一場，商場2場，學校地推2場 2.策劃中庭主題活動，需商場確定方案是否可行 3.招募兼職3-5人，如果愉景新城活動方案通過，需總部派人支援活動

Sheet 展会ROI测算
F2: 主投思维 | I2: 2025/2/14-16日 | L2: 2025年5月3-5日 | M2: 2025年5月23-25日 | N2: 2025年10月3-5 | O2: 2025年12月12-24 | Q2: 2026年前平均值 | R2: 2025年3月27-29日 | S2: 2025年5月22-24日 | T2: 2025年5月16-17日 | U2: 2025年6月12-14日
B3: 参数：8月初 | C3: 益智 | D3: 美术 | H3: 9月兒童書展 | I3: 12月兒童書展 | J3: 12月較9月跌幅 | K3: BB展 | L3: 課外活動展 | M3: 5月兒童展 | N3: 10月兒童展 | O3: 12月兒童展 | Q3: 兒童書展平均值 | R3: 3月兒童展 | S3: 5月兒童展 | T3: 5月課外活動展 | U3: 6月澳門展
B4: 单例子销售固定人工成本 | C4: 144 | D4: 130 | F4: 链路合计 | G4: ROI 2 | H4: =H5/H6 | I4: =I5/I6 | K4: =K5/K6 | L4: =L5/L6 | M4: =M5/M6 | N4: =N5/N6 | O4: =O5/O6 | Q4: =Q5/Q6 | R4: =R5/R6 | S4: =S5/S6 | T4: =T5/T6 | U4: =U5/U6
B5: 单例子TMK人工成本 | C5: 10 | D5: 10 | F5: 链路合计 | G5: GMV | H5: =H17+H36 | I5: =I17+I36 | K5: =K17+K36 | L5: =L17+L36 | M5: =M17+M36 | N5: =N17+N36 | O5: =O17+O36 | Q5: =AVERAGE(O5,N5,M5,I5,H5) | R5: =R17+R36 | S5: =S17+S36 | T5: =T17+T36 | U5: =U17+U36
B6: 销售提成比例 | C6: 0.065 | D6: 0.0839 | F6: 链路合计 | G6: ROI 2成本项 | H6: =H37+H19 | I6: =I37+I19 | K6: =K37+K19 | L6: =L37+L19 | M6: =M37+M19 | N6: =N37+N19 | O6: =O37+O19 | Q6: =Q37+Q19 | R6: =R37+R19 | S6: =S37+S19 | T6: =T37+T19 | U6: =U37+U19
B7: 礼品及其他费用比例 | C7: 0.018 | D7: 0.0155 | F7: 链路合计 | G7: 參展成本 | H7: 97616 | I7: 145759.8 | K7: 41427.9 | L7: 51452.7 | M7: 60000 | N7: =[2]開支總表!C18 | O7: 81026.5 | Q7: =AVERAGE(O7,N7,M7,I7,H7) | R7: 44783.718 | S7: =[3]開支總表!C15 | T7: =[3]開支總表!D15 | U7: =展会数据测算!$AG$30
B8: 试听课单课时成本 | C8: 81.2 | D8: 74.31 | F8: 链路合计 | G8: \
B9: 单例子市场运营人工及日常成本 | C9: 88.76 | D9: 100 | F9: 主投 | G9: 例子数 | H9: 420 | I9: 360 | K9: 235 | L9: 303 | M9: 301 | N9: 298 | O9: 537 | Q9: =AVERAGE(O9,N9,M9,I9,H9) | R9: 371 | S9: 350 | T9: 300 | U9: 100
F10: 主投 | G10: 例子分发率 | H10: =H14/H9 | I10: =H10 | K10: =H10 | L10: =I10 | M10: =L10 | N10: 0.8557 | O10: 0.7933 | Q10: =AVERAGE(O10,N10,M10,I10,H10) | R10: 0.7898 | S10: 0.7898 | T10: 0.7898 | U10: 0.7898
F11: 主投 | G11: 例子到课率 | H11: =H15/H9 | I11: 0.517 | J11: =(H11-I11)/H11 | K11: 0.51 | L11: =82.8%*86.9% | M11: =77.7%*77.8% | N11: 0.661 | O11: 0.556 | P11: =(N11-O11)/N11 | Q11: =AVERAGE(O11,N11,M11,I11,H11) | R11: 0.539 | S11: =N11 | T11: 0.7 | U11: 0.7
F12: 主投 | G12: 滚动转化率 | H12: =H16/H9 | I12: 0.094 | J12: =(H12-I12)/H12 | K12: 0.085 | L12: 0.139 | M12: 0.09 | N12: 0.08724 | O12: 0.070764 | P12: =(N12-O12)/N12 | Q12: =AVERAGE(O12,N12,M12,I12,H12) | R12: 0.04043 | S12: 0.075 | T12: 0.115 | U12: 0.115
F13: 主投 | G13: ASP | H13: =H17/H16 | I13: 3943 | J13: =(H13-I13)/H13 | K13: 4444 | L13: 4220 | M13: 4898 | N13: 6019 | O13: 5287 | P13: =(N13-O13)/N13 | Q13: =AVERAGE(O13,N13,M13,I13,H13) | R13: 5195 | S13: 5195 | T13: 4900 | U13: 4900
F14: 主投 | G14: 分发数 | H14: 416 | I14: =I$9*I10 | K14: =K$9*K10 | L14: =L$9*L10 | M14: =M$9*M10 | N14: =N$9*N10 | O14: =O$9*O10 | Q14: =Q$9*Q10 | R14: =R$9*R10 | S14: =S$9*S10 | T14: =T$9*T10 | U14: =U$9*U10
F15: 主投 | G15: 到课数 | H15: 281 | I15: =I$9*I11 | K15: =K$9*K11 | L15: =L$9*L11 | M15: =M$9*M11 | N15: =N$9*N11 | O15: =O$9*O11 | Q15: =Q$9*Q11 | R15: =R$9*R11 | S15: =S$9*S11 | T15: =T$9*T11 | U15: =U$9*U11
F16: 主投 | G16: 转化数 | H16: 43 | I16: =I$9*I12 | K16: =K$9*K12 | L16: =L$9*L12 | M16: =M$9*M12 | N16: =N$9*N12 | O16: =O$9*O12 | Q16: =Q$9*Q12 | R16: =R$9*R12 | S16: =S$9*S12 | T16: =T$9*T12 | U16: =U$9*U12
F17: 主投 | G17: GMV | H17: 181744 | I17: =I13*I16 | J17: =(H17-I17)/H17 | K17: =K13*K16 | L17: =L13*L16 | M17: =M13*M16 | N17: =N13*N16 | O17: =O13*O16 | P17: \ | Q17: =Q13*Q16 | R17: =R13*R16 | S17: =S13*S16 | T17: =T13*T16 | U17: =U13*U16
G18: GMV/leads | H18: =H17/H9 | I18: =I17/I9 | K18: =K17/K9 | L18: =L17/L9 | M18: =M17/M9 | N18: =N17/N9 | O18: =O17/O9 | P18: =(N18-O18)/N18 | Q18: =Q17/Q9 | R18: =R17/R9 | S18: =S17/S9 | T18: =T17/T9 | U18: =U17/U9
F19: 主投 | G19: ROI 2成本项 | H19: =SUM(H20:H24)+H7 | I19: =SUM(I20:I24)+I7 | K19: =SUM(K20:K24)+K7 | L19: =SUM(L20:L24)+L7 | M19: =SUM(M20:M24)+M7 | N19: =SUM(N20:N24)+N7 | O19: =SUM(O20:O24)+O7 | Q19: =SUM(Q20:Q24)+Q7 | R19: =SUM(R20:R24)+R7 | S19: =SUM(S20:S24)+S7 | T19: =SUM(T20:T24)+T7 | U19: =SUM(U20:U24)+U7
F20: 主投 | G20: 销售固定成本 | H20: =H14*$C$4 | I20: =I14*$C$4 | K20: =K14*$C$4 | L20: =L14*$C$4 | M20: =M14*$C$4 | N20: =N14*$C$4 | O20: =O14*$C$4 | Q20: =Q14*$C$4 | R20: =R14*$C$4 | S20: =S14*$C$4 | T20: =T14*$C$4 | U20: =U14*$C$4
F21: 主投 | G21: 销售变动成本 | H21: =H17*($C$6+$C$7) | I21: =I17*($C$6+$C$7) | K21: =K17*($C$6+$C$7) | L21: =L17*($C$6+$C$7) | M21: =M17*($C$6+$C$7) | N21: =N17*($C$6+$C$7) | O21: =O17*($C$6+$C$7) | Q21: =Q17*($C$6+$C$7) | R21: =R17*($C$6+$C$7) | S21: =S17*($C$6+$C$7) | T21: =T17*($C$6+$C$7) | U21: =U17*($C$6+$C$7)
F22: 主投 | G22: TMK费用 | H22: =H9*$C$5 | I22: =I9*$C$5 | K22: =K9*$C$5 | L22: =L9*$C$5 | M22: =M9*$C$5 | N22: =N9*$C$5 | O22: =O9*$C$5 | Q22: =Q9*$C$5 | R22: =R9*$C$5 | S22: =S9*$C$5 | T22: =T9*$C$5 | U22: =U9*$C$5
F23: 主投 | G23: DEMO费用 | H23: =H15*$C$8 | I23: =I15*$C$8 | K23: =K15*$C$8 | L23: =L15*$C$8 | M23: =M15*$C$8 | N23: =N15*$C$8 | O23: =O15*$C$8 | Q23: =Q15*$C$8 | R23: =R15*$C$8 | S23: =S15*$C$8 | T23: =T15*$C$8 | U23: =U15*$C$8
F24: 主投 | G24: 运营人工成本 | H24: =H9*$C$9/2 | I24: =I9*$C$9/2 | K24: =K9*$C$9/2 | L24: =L9*$C$9/2 | M24: =M9*$C$9/2 | N24: =N9*$C$9/2 | O24: =O9*$C$9/2 | Q24: =Q9*$C$9/2 | R24: =R9*$C$9/2 | S24: =S9*$C$9/2 | T24: =T9*$C$9/2 | U24: =U9*$C$9/2
F25: 主投 | G25: ROI 2 | H25: =H17/H19 | I25: =I17/I19 | K25: =K17/K19 | L25: =L17/L19 | M25: =M17/M19 | N25: =N17/N19 | O25: =O17/O19 | Q25: =Q17/Q19 | R25: =R17/R19 | S25: =S17/S19 | T25: =T17/T19 | U25: =U17/U19
F27: 辅投 | G27: 联投率
F28: 辅投 | G28: 例子数
F29: 辅投 | G29: 例子分发率
F30: 辅投 | G30: 例子到课率
F31: 辅投 | G31: 滚动转化率
F32: 辅投 | G32: ASP
F33: 辅投 | G33: 分发数
F34: 辅投 | G34: 到课数
F35: 辅投 | G35: 转化数
F36: 辅投 | G36: GMV
F37: 辅投 | G37: ROI 2成本项
F38: 辅投 | G38: 销售固定成本
... F43: 辅投 | G43: ROI 2

Sheet Sheet1
E1: 10 | F1: 50 | G1: 50 | L1: 20 | M1: 40 | N1: 40 | O1: 20 | R1: 20 | S1: 40 | T1: 40 | U1: 20 | V1: 20 | Y1: 20 | Z1: 20 | AA1: 40 | AB1: 20 | AE1: 230 | AF1: 230 | AG1: 0 | AH1: 179.4 | AI1: 164 | AJ1: -15.4
L2: 20 | M2: 40 | N2: 40
A3: 20 | B3: 20 | C3: 20 | H3: 40 | I3: 40 | J3: 40 | O3: 40 | P3: 40 | Q3: 40 | V3: 20 | W3: 20 | X3: 20 | AC3: 20 | AD3: 20 | AE3: 20
P4: 100 | Q4: 160 | V4: 100 | W4: 130 | X4: 120
A5: =A3+A4 | B5: =B3+B4 | C5: =C3+C4 | D5: =D3+D4 | E5: =E3+E4 | F5: =F3+F4 | G5: =G3+G4 | H5: =H3+H4 | ... AE5: =AE3+AE4
J6: 15 | K6: 20 | L6: 20 | M6: 0 | N6: 0 | O6: 0 | P6: 0 | Q6: 40 | R6: 40 | S6: 40 | T6: 0 | U6: 0 | V6: 0 | W6: 0 | X6: 40 | Y6: 140 | Z6: 200 | AA6: 0 | AB6: 0 | AC6: 0 | AD6: 0 | AE6: 120 | AF6: 150 | AG6: 140 | AH6: 0 | AI6: 0 | AJ6: 0 | AK6: 0 | AL6: 20 | AM6: 20 | AN6: 20
A7: 26 | J7: 16 | K7: 1 | N7: 20 | Q7: 40 | V7: =T7+U7 | X7: 18 | AB7: =Z7+AA7
A8: 20 | J8: 16 | K8: 1 | N8: 20 | Q8: 20 | V8: =T8+U8 | X8: 19 | AB8: =Z8+AA8
A9: 20 | J9: 16 | K9: 1 | N9: 20 | Q9: 20 | V9: =T9+U9 | X9: 20 | AB9: =Z9+AA9
A10: 21 | J10: 15 | K10: 1 | N10: 0 | Q10: 0 | V10: =T10+U10 | X10: 20 | AB10: =Z10+AA10
A11: 21 | J11: 20 | K11: 1 | N11: 0 | Q11: 0 | V11: =T11+U11 | X11: 20 | Z11: 10 | AB11: =Z11+AA11
A12: 21 | J12: 21 | K12: 1 | N12: 0 | Q12: 20 | V12: =T12+U12 | X12: 21 | Z12: 50 | AB12: =Z12+AA12
A13: 26 | J13: 20 | K13: 1 | N13: 0 | Q13: 40 | T13: 1 | V13: =T13+U13 | X13: 21 | Z13: 50 | AB13: =Z13+AA13
A14: 26 | J14: 21 | K14: 1 | N14: 40 | Q14: 40 | T14: 1 | V14: =T14+U14 | X14: 18 | AB14: =Z14+AA14
A15: 27 | D15: 40 | J15: 21 | K15: 1 | N15: 40 | Q15: 0 | T15: 1 | V15: =T15+U15 | X15: 19 | AB15: =Z15+AA15
A16: 26 | D16: 50 | J16: 21 | K16: 1 | N16: 40 | Q16: 0 | T16: 1 | V16: =T16+U16 | X16: 20 | AB16: =Z16+AA16
A17: 26 | D17: 40 | J17: 20 | K17: 1 | N17: 0 | Q17: 0 | T17: 2 | V17: =T17+U17 | X17: 20 | AB17: =Z17+AA17
A18: 26 | J18: 20 | K18: 1 | N18: 0 | Q18: 0 | T18: 2 | V18: =T18+U18 | X18: 20 | Z18: 20 | AA18: 20 | AB18: =Z18+AA18
A19: 26 | J19: 21 | K19: 1 | N19: 0 | Q19: 40 | T19: 1 | V19: =T19+U19 | X19: 21 | Z19: 40 | AA19: 40 | AB19: =Z19+AA19
A20: 26 | J20: 22 | K20: 1 | N20: 0 | Q20: 60 | T20: 1 | V20: =T20+U20 | X20: 21 | Z20: 40 | AA20: 40 | AB20: =Z20+AA20
A21: 26 | J21: 23 | K21: 1 | N21: 40 | Q21: 60 | T21: 1 | V21: =T21+U21 | X21: 18 | Z21: 20 | AB21: =Z21+AA21
A22: 26 | D22: 60 | J22: 23 | K22: 1 | N22: 140 | Q22: 0 | T22: 1 | V22: =T22+U22 | X22: 19 | AB22: =Z22+AA22
A23: 26 | D23: 80 | J23: 23 | K23: 1 | N23: 200 | Q23: 0 | T23: 1 | V23: =T23+U23 | X23: 20 | AB23: =Z23+AA23
A24: 26 | D24: 70 | J24: 22 | K24: 1 | N24: 0 | Q24: 0 | T24: 2 | V24: =T24+U24 | X24: 20 | Z24: 20 | AB24: =Z24+AA24
A25: 26 | J25: 22 | K25: 1 | N25: 0 | Q25: 0 | T25: 2 | V25: =T25+U25 | X25: 20 | Z25: 40 | AB25: =Z25+AA25
A26: 26 | J26: 23 | K26: 1 | N26: 0 | Q26: 40 | T26: 1 | V26: =T26+U26 | X26: 21 | Z26: 40 | AB26: =Z26+AA26
A27: 26 | J27: 22 | K27: 1 | N27: 0 | Q27: 40 | T27: 1 | U27: 1 | V27: =T27+U27 | X27: 21 | Z27: 20 | AB27: =Z27+AA27
A28: 26 | J28: 23 | K28: 1 | N28: 120 | Q28: 40 | T28: 1 | U28: 1 | V28: =T28+U28 | X28: 18 | Z28: 20 | AB28: =Z28+AA28
A29: 26 | D29: 50 | J29: 23 | K29: 1 | N29: 150 | Q29: 0 | T29: 1 | U29: 1 | V29: =T29+U29 | X29: 19 | AB29: =Z29+AA29
A30: 26 | D30: 50 | J30: 19 | K30: 1 | N30: 140 | Q30: 0 | T30: 1 | U30: 1 | V30: =T30+U30 | X30: 20 | AB30: =Z30+AA30
A31: 26 | D31: 40 | J31: 18 | K31: 1 | N31: 0 | Q31: 0 | T31: 2 | U31: 1 | V31: =T31+U31 | X31: 20 | Z31: 20 | AB31: =Z31+AA31
A32: 24 | J32: 18 | K32: 1 | N32: 0 | Q32: 0 | T32: 2 | U32: 1 | V32: =T32+U32 | X32: 20 | Z32: 20 | AB32: =Z32+AA32
A33: 24 | J33: 18 | K33: 1 | N33: 0 | Q33: 130 | T33: 1 | U33: 1 | V33: =T33+U33 | X33: 21 | Z33: 40 | AB33: =Z33+AA33
A34: 24 | J34: 17 | K34: 1 | N34: 0 | Q34: 190 | T34: 1 | U34: 1 | V34: =T34+U34 | X34: 21 | Z34: 20 | AB34: =Z34+AA34
A35: 24 | J35: 18 | K35: 1 | N35: 20 | Q35: 190 | T35: 1 | U35: 1 | V35: =T35+U35 | X35: 19 | AB35: =Z35+AA35
A36: 25 | D36: 20 | J36: 18 | K36: 1 | N36: 20 | Q36: 0 | T36: 1 | U36: 1 | V36: =T36+U36 | X36: 20 | AB36: =Z36+AA36
A37: 24 | D37: 20 | N37: 20 | Q37: 0
A42: 26 | B42: 20 | C42: 20 | D42: 21 | E42: 21 | F42: 21 | G42: 26 | H42: 26 | I42: 27 | J42: 26 | K42: 26 | L42: 26 | M42: 26 | N42: 26 | O42: 26 | P42: 26 | Q42: 26 | R42: 26 | S42: 26 | T42: 26 | U42: 26 | V42: 26 | W42: 26 | X42: 26 | Y42: 26 | AB42: 24 | AC42: 24 | AD42: 25
A44: 26 | C44: 1
A45: 20 | G45: 40 | H45: 60 | I45: 60 | N45: 20 | O45: 40 | P45: 20 | U45: 40 | V45: 40 | W45: 40 | AB45: 40 | AC45: 40 | AD45: 40
A46: 20 | C46: 1 | N46: 30 | O46: 40 | P46: 40
A47: 21 | E47: 0 | F47: 0 | G47: 40 | H47: 60 | I47: 60 | J47: 0 | K47: 0 | L47: 0 | M47: 0 | N47: 50 | O47: 80 | P47: 60 | Q47: 0 | R47: 0 | S47: 0 | T47: 0 | U47: 40 | V47: 40 | W47: 40 | X47: 0 | Y47: 0 | Z47: 0 | AA47: 0 | AB47: 40 | AC47: 40 | AD47: 40 | AE47: 0 | AF47: 0 | AG47: 0 | AH47: 0
A48: 21 | C48: 1
A49: 21
A50: 26 | C50: 1 | H50: 0
A51: 26 | H51: 0
A52: 27 | C52: 1 | H52: 40
A53: 26 | C53: 1 | H53: 60
A54: 26 | H54: 60
A55: 26 | C55: 1 | H55: 0
A56: 26 | H56: 0
A57: 26 | C57: 1 | H57: 0
A58: 26 | C58: 1 | H58: 0
A59: 26 | H59: 50
A60: 26 | C60: 1 | H60: 80
A61: 26 | H61: 60
A62: 26 | C62: 1 | H62: 0
A63: 26 | H63: 0
A64: 26 | C64: 1 | H64: 0
A65: 26 | H65: 0
A66: 26 | C66: 1 | H66: 40
A67: 26 | C67: 1 | H67: 40
A68: 26 | C68: 1 | H68: 40
A69: 24 | C69: 1 | H69: 0
A70: 24 | C70: 1 | H70: 0
A71: 24 | C71: 1 | H71: 0
A72: 24 | C72: 1 | H72: 0
A73: 25 | C73: 1 | H73: 40
H74: 40
H75: 40
H76: 0
H77: 0
H78: 0
H79: 0
