Workbook

Sheet 陈琪
I1: 主投 | AR1: 辅投 | BW1: 汇总
B2: 渠道组 | C2: 供应商 | D2: 渠道名称 | E2: 主投 | F2: 辅投 | G2: 结算方式 | I2: 滚动消耗 | J2: 单例子成本 | K2: 例子数 | L2: 分发数 | M2: 剔除毛例子 分发数 | N2: 约课数 | Q2: 到课数 | R2: 滚动到课数 | S2: 当月成交数 | T2: 滚动成交数 | U2: 当月GMV | V2: 滚动GMV | W2: 海外GMV占比 | X2: 滚动ASP | Y2: 例子分发率 | Z2: 分发约课率 | AA2: 例子约课率 | AB2: 约课到课率 | AD2: 滚动应到课率 | AE2: 到课转化率 | AF2: 注册转化率 | AG2: 滚动转化率 | AH2: 滚动ROI2总成本 | AI2: 滚动ROI2 | AJ2: 滚动应到课人数 | AK2: 滚动到课人数 | AL2: 滚动到课人次 | AM2: 滚动其他成本 | AN2: 同源其他成本 | AO2: 运营成本 | AP2: 同源消耗 | AR2: 例子数 | AS2: 分发数 | AT2: 剔除毛例子 分发数 | AU2: 约课数 | AX2: 到课数 | AY2: 滚动到课数 | AZ2: 当月成交 | BA2: 滚动成交数 | BB2: 当月GMV | BC2: 滚动GMV | BD2: 海外GMV占比 | BE2: 滚动ASP | BF2: 例子分发率 | BG2: 分发约课率 | BH2: 例子约课率 | BI2: 约课到课率 | BK2: 滚动应到课率 | BL2: 到课转化率 | BM2: 注册转化率 | BN2: 滚动转化率 | BO2: 滚动应到课人数 | BP2: 滚动到课人数 | BQ2: 到课人次 | BR2: 滚动其他成本 | BS2: 同源其他成本 | BT2: 运营成本 | BU2: 滚动消耗 | BV2: 同源消耗 | BW2: 当月GMV | BX2: 滚动GMV | BY2: 海外GMV占比 | BZ2: 滚动其他成本 | CA2: 同源其他成本 | CB2: 运营成本 | CC2: 滚动消耗 | CD2: 同源消耗 | CE2: 当月ROI2总成本 | CF2: 当月ROI2 | CH2: 滚动ROI2总成本 | CI2: 滚动ROI2 | CJ2: O-ROI总成本 | CK2: O-ROI
A3: 45627 | C3: 陈琪 | D3: KOLHK-香港-陈琪-Shukei-思维&美术 | E3: 思维 | F3: 美术 | G3: CPT | I3: =8433.33333333333+25306 | J3: =I3/K3 | K3: 191 | L3: 163 | M3: 139 | N3: 91 | Q3: 63 | R3: 63 | S3: 15 | T3: 15 | U3: 59520 | V3: 59520 | W3: 1 | X3: 3968 | Y3: 0.85340314 | Z3: 0.55828221 | AA3: 0.47643979 | AB3: 0.69230769 | AD3: 0.95454545 | AE3: 0.23809524 | AF3: 0.078534031 | AG3: 0.078534031 | AH3: =AM3+AO3+AP3 | AI3: 1.2898729 | AJ3: 66 | AK3: 63 | AL3: 69 | AM3: 30997.944 | AN3: 33376.19 | AO3: 6712.8027 | AP3: 33739.333 | AR3: 190 | AS3: 28 | AT3: 28 | AU3: 31 | AX3: 23 | AY3: 23 | AZ3: 3 | BA3: 3 | BB3: 12498.4 | BC3: 12498.4 | BD3: 1 | BE3: 4166.1333 | BF3: 0.14736842 | BG3: 1.1071429 | BH3: 0.16315789 | BI3: 0.74193548 | BK3: 0.79310345 | BL3: 0.13043478 | BM3: 0.015789474 | BN3: 0.015789474 | BO3: 29 | BP3: 23 | BQ3: 23 | BR3: 9466.1202 | BS3: 9466.1202 | BT3: 5723.5105 | BU3: 0 | BV3: 0 | BW3: 72018.4 | BX3: 72018.4 | BY3: 1 | BZ3: 40464.065 | CA3: 42842.31 | CB3: 12436.313 | CC3: 33739.333 | CD3: 33739.333 | CE3: =CA3+CB3+CD3 | CF3: =BW3/CE3 | CH3: =BZ3+CB3+CC3 | CI3: =BX3/CH3 | CJ3: 77472.398 | CK3: 0.92960076
A4: 45658 | C4: 陈琪 | D4: KOLHK-香港-陈琪-Shukei-思维&美术 | E4: 思维 | F4: 美术 | G4: CPT | I4: 40591.523 | J4: 343.99596 | K4: 118 | L4: 83 | M4: 48 | N4: 48 | Q4: 40 | R4: 51 | S4: 14 | T4: 15 | U4: 69532 | V4: 73220 | W4: 1 | X4: 4881.3333 | Y4: 0.70338983 | Z4: 0.57831325 | AA4: 0.40677966 | AB4: 0.83333333 | AD4: 0.82258065 | AE4: 0.35 | AF4: 0.11864407 | AG4: 0.12711864 | AH4: 70880.038 | AI4: 1.033013 | AJ4: 62 | AK4: 51 | AL4: 57 | AM4: 18845.028 | AN4: 22163.958 | AO4: 11443.487 | AP4: 40591.523 | AR4: 118 | AS4: 31 | AT4: 36 | AU4: 29 | AX4: 17 | AY4: 19 | AZ4: 2 | BA4: 2 | BB4: 6529.2 | BC4: 6529.2 | BD4: 1 | BE4: 3264.6 | BF4: 0.26271186 | BG4: 0.93548387 | BH4: 0.24576271 | BI4: 0.5862069 | BK4: 0.55882353 | BL4: 0.11764706 | BM4: 0.016949153 | BN4: 0.016949153 | BO4: 34 | BP4: 19 | BQ4: 20 | BR4: 7421.2655 | BS4: 6639.2255 | BT4: 11443.487 | BU4: 0 | BV4: 0 | BW4: 76061.2 | BX4: 79749.2 | BY4: 1 | BZ4: 26266.293 | CA4: 28803.184 | CB4: 22886.974 | CC4: 40591.523 | CD4: 40591.523 | CE4: 92281.681 | CF4: 0.82422859 | CH4: 89744.79 | CI4: 0.88862206 | CJ4: 84557.816 | CK4: 0.94313221
A5: 45690 | C5: 陈琪 | D5: KOLHK-香港-陈琪-Shukei-思维&美术 | E5: 思维 | F5: 美术 | G5: CPT | I5: 48635.086 | J5: 268.70213 | K5: 181 | L5: 122 | M5: 86 | N5: 90 | Q5: 64 | R5: 72 | S5: 23 | T5: 27 | U5: 118186.4 | V5: 138838.4 | W5: 1 | X5: 5142.163 | Y5: 0.67403315 | Z5: 0.73770492 | AA5: 0.49723757 | AB5: 0.71111111 | AD5: 0.77419355 | AE5: 0.359375 | AF5: 0.12707182 | AG5: 0.14917127 | AH5: 90105.691 | AI5: 1.5408394 | AJ5: 93 | AK5: 72 | AL5: 78 | AM5: 31707.907 | AN5: 32950.219 | AO5: 9762.6975 | AP5: 48635.086 | AR5: 164 | AS5: 46 | AT5: 49 | AU5: 52 | AX5: 21 | AY5: 24 | AZ5: 2 | BA5: 2 | BB5: 7176 | BC5: 7176 | BD5: 1 | BE5: 3588 | BF5: 0.2804878 | BG5: 1.1304348 | BH5: 0.31707317 | BI5: 0.40384615 | BK5: 0.45283019 | BL5: 0.095238095 | BM5: 0.012195122 | BN5: 0.012195122 | BO5: 53 | BP5: 24 | BQ5: 25 | BR5: 8064.9318 | BS5: 7487.9811 | BT5: 8845.7591 | BU5: 0 | BV5: 0 | BW5: 125362.4 | BX5: 146014.4 | BY5: 1 | BZ5: 39772.839 | CA5: 40438.2 | CB5: 18608.457 | CC5: 48635.086 | CD5: 48635.086 | CE5: 107681.74 | CF5: 1.1641936 | CH5: 107016.38 | CI5: 1.3644117 | CJ5: 114282.93 | CK5: 1.2776572
A6: 45718 | C6: 陈琪 | D6: KOLHK-香港-陈琪-Shukei-思维&美术 | E6: 思维 | F6: 美术 | G6: CPT | I6: 110033.47 | J6: 374.26351 | K6: 294 | L6: 140 | M6: 144 | N6: 150 | Q6: 114 | R6: 129 | S6: 41 | T6: 49 | U6: 213308 | V6: 245112 | W6: 1 | X6: 5002.2857 | Y6: 0.47619048 | Z6: 1.0714286 | AA6: 0.51020408 | AB6: 0.76 | AD6: 0.94160584 | AE6: 0.35964912 | AF6: 0.13945578 | AG6: 0.16666667 | AH6: 215177.03 | AI6: 1.1391179 | AJ6: 137 | AK6: 129 | AL6: 133 | AM6: 50828.352 | AN6: 16883.591 | AO6: 23897.061 | AP6: 2738.6332 | AQ6: 10795.924 | AR6: 16 | AS6: 16 | AT6: 24 | AU6: 16 | AX6: 10 | AY6: 13 | AZ6: 2 | BA6: 2 | BB6: 7735.2 | BC6: 7735.2 | BD6: 1 | BE6: 3867.6 | BF6: 1 | BG6: 1 | BH6: 1 | BI6: 0.625 | BK6: 0.54166667 | BL6: 0.2 | BM6: 0.125 | BN6: 0.125 | BO6: 24 | BP6: 13 | BQ6: 14 | BR6: 2631.4887 | BS6: 2476.231 | BT6: 764.50317 | BU6: 149.04126 | BV6: 1141.7321 | BW6: 221043.2 | BX6: 252847.2 | BY6: 1 | BZ6: 58846.717 | CA6: 52989.362 | CB6: 53459.841 | CC6: 110033.47 | CD6: 110033.47 | CE6: 216482.67 | CF6: 1.0210665 | CH6: 222340.03 | CI6: 1.1372095 | CJ6: 192130.19 | CK6: 1.3160202
A8: 陈琪-汇总 | I8: =SUM(I3:I6) | J8: =I8/K8 | K8: =SUM(K3:K6) | L8: =SUM(L3:L6) | M8: =SUM(M3:M6) | N8: =SUM(N3:N6) | Q8: =SUM(Q3:Q6) | R8: =SUM(R3:R6) | S8: =SUM(S3:S6) | T8: =SUM(T3:T6) | U8: =SUM(U3:U6) | V8: =SUM(V3:V6) | X8: =V8/T8 | Y8: =L8/K8 | Z8: =N8/L8 | AA8: =N8/K8 | AB8: =Q8/N8 | AD8: =AVERAGE(AD3:AD6) | AE8: =S8/Q8 | AF8: =S8/K8 | AG8: =T8/K8 | AH8: =SUM(AH3:AH6) | AI8: =V8/AH8 | AJ8: =SUM(AJ3:AJ6) | AK8: =SUM(AK3:AK6) | AL8: =SUM(AL3:AL6) | AM8: =SUM(AM3:AM6) | AN8: =SUM(AN3:AN6) | AO8: =SUM(AO3:AO6) | AP8: =SUM(AP3:AP6) | AR8: =SUM(AR3:AR6) | AS8: =SUM(AS3:AS6) | AU8: =SUM(AU3:AU6) | AX8: =SUM(AX3:AX6) | AY8: =SUM(AY3:AY6) | AZ8: =SUM(AZ3:AZ6) | BA8: =SUM(BA3:BA6) | BB8: =SUM(BB3:BB6) | BC8: =SUM(BC3:BC6) | BE8: =BC8/BA8 | BF8: =AS8/AR8 | BG8: =AU8/AS8 | BH8: =AU8/AR8 | BI8: =AX8/AU8 | BK8: =AVERAGE(BK3:BK6) | BL8: =AZ8/AX8 | BM8: =AZ8/AR8 | BN8: =BA8/AR8 | BO8: =SUM(BO3:BO6) | BP8: =SUM(BP3:BP6) | BQ8: =SUM(BQ3:BQ6) | BR8: =SUM(BR3:BR6) | BS8: =SUM(BS3:BS6) | BT8: =SUM(BT3:BT6) | BU8: =SUM(BU3:BU6) | BV8: =SUM(BV3:BV6) | ... BX8: =SUM(BX3:BX6) | BZ8: =SUM(BZ3:BZ6) | CA8: =SUM(CA3:CA6) | CB8: =SUM(CB3:CB6) | CC8: =SUM(CC3:CC6) | CD8: =SUM(CD3:CD6) | CE8: =SUM(CE3:CE6) | CF8: =BW8/CE8 | CH8: =SUM(CH3:CH6) | CI8: =BX8/CH8 | CJ8: =SUM(CJ3:CJ6) | CK8: =BX8/CJ8
I11: 主投 | AR11: 辅投 | BW11: 汇总
B12: 渠道组 | C12: 供应商 | D12: 渠道名称 | E12: 主投 | F12: 辅投 | G12: 结算方式 | H12: 滚动消耗 | I12: 滚动消耗(不含赠课成本) | J12: 单例子成本 | K12: 例子数 | L12: 分发数 | M12: 剔除毛例子 分发数 | N12: 约课数 | O12: 应到课数 | P12: 滚动应到课数 | Q12: 到课数 | R12: 滚动到课数 | S12: 当月成交数 | T12: 滚动成交数 | U12: 当月GMV | V12: 滚动GMV | W12: 海外GMV占比 | X12: 滚动ASP | Y12: 例子分发率 | Z12: 分发约课率 | AA12: 例子约课率 | AB12: 约课到课率 | AC12: 应到课率 | AD12: 滚动应到课率 | AE12: 到课转化率 | AF12: 注册转化率 | AG12: 滚动转化率 | AH12: 滚动ROI2总成本 | AI12: 滚动ROI2 | AJ12: 滚动应到课人数 | AK12: 滚动到课人数 | AL12: 滚动到课人次 | AM12: 运营成本 | AN12: 销售固定成本 | AO12: 销售变动成本 | AP12: TMK费用 | AQ12: DEMO费用 | AR12: 例子数 | AS12: 分发数 | AT12: 剔除毛例子分发数 | AU12: 约课数 | AV12: 应到课数 | AW12: 滚动应到课数 | AX12: 到课数 | AY12: 滚动到课数 | AZ12: 当月成交 | BA12: 滚动成交数 | BB12: 当月GMV | BC12: 滚动GMV | BD12: 海外GMV占比 | BE12: 滚动ASP | BF12: 例子分发率 | BG12: 分发约课率 | BH12: 例子约课率 | BI12: 约课到课率 | BJ12: 应到课率 | BK12: 滚动应到课率 | BL12: 到课转化率 | BM12: 注册转化率 | BN12: 滚动转化率 | BO12: 滚动应到课人数 | BP12: 滚动到课人数 | BQ12: 滚动到课人次 | BR12: 运营成本 | BS12: 销售固定成本 | BT12: 销售变动成本 | BU12: TMK费用 | BV12: DEMO费用 | BW12: 当月GMV | BX12: 滚动GMV | BY12: 海外GMV占比 | BZ12: 滚动其他成本 | CA12: 同源其他成本 | CB12: 运营成本 | CC12: 滚动消耗 | CD12: 同源消耗 | CE12: 当月ROI2总成本 | CF12: 当月ROI2 | CG12: 滚动赠课成本 | CH12: 滚动ROI2总成本 | CI12: 滚动ROI2 | CJ12: O-ROI总成本 | CK12: O-ROI
A13: 45627 | D13: 总计 | E13: - | F13: - | G13: - | H13: =I13 | I13: =8433.33333333333+25306 | J13: =I13/K13 | K13: 191 | L13: 138 | M13: 139 | N13: 91 | Q13: 63 | R13: 63 | S13: 15 | T13: 15 | U13: 59520 | V13: 59520 | W13: 1 | X13: 3968 | Y13: 0.72251309 | Z13: 0.65942029 | AA13: 0.47643979 | AB13: 0.69230769 | AD13: 0.95454545 | AE13: 0.23809524 | AF13: 0.078534031 | AG13: 0.078534031 | AH13: 50677.94 | AI13: 1.1744755 | AJ13: 66 | AK13: 63 | AL13: 69 | AM13: 11246.663 | AN13: 16717.383 | AO13: 6655.1707 | AP13: 1780.9884 | AQ13: 5844.4024 | AR13: 190 | AS13: 26 | AT13: 26 | AU13: 31 | AX13: 23 | AY13: 23 | AZ13: 3 | BA13: 3 | BB13: 12498.4 | BC13: 12498.4 | BD13: 1 | BE13: 4166.1333 | BF13: 0.13684211 | BG13: 1.1923077 | BH13: 0.16315789 | BI13: 0.74193548 | BK13: 0.76666667 | BL13: 0.13043478 | BM13: 0.015789474 | BN13: 0.015789474 | BO13: 30 | BP13: 23 | BQ13: 23 | BR13: 8938.1178 | BS13: 4012.0066 | BT13: 1313.2814 | BU13: 1852.5288 | BV13: 1979.6875 | BW13: 72018.4 | BX13: 72018.4 | BY13: 1 | BZ13: 40155.449 | CA13: 40035.18 | CB13: 20184.781 | CC13: 33739.333 | CD13: 33739.333 | CE13: =CA13+CB13+CD13 | CF13: =BW13/CE13 | CH13: =BZ13+CB13+CC13 | CI13: =BX13/CH13 | CJ13: 77472.398 | CK13: 0.92960076
A14: 45658 | D14: 总计 | E14: - | F14: - | G14: - | H14: =I14 | I14: 40591.523 | J14: =I14/K14 | K14: 118 | L14: 45 | M14: 48 | N14: 48 | Q14: 40 | R14: 51 | S14: 14 | T14: 15 | U14: 69532 | V14: 73220 | W14: 1 | X14: 4881.3333 | Y14: 0.38135593 | Z14: 1.0666667 | AA14: 0.40677966 | AB14: 0.83333333 | AD14: 0.96226415 | AE14: 0.35 | AF14: 0.11864407 | AG14: 0.12711864 | AH14: 73894.233 | AI14: 0.99087571 | AJ14: 53 | AK14: 51 | AL14: 57 | AM14: 14457.682 | AN14: 6861.7592 | AO14: 6045.5177 | AP14: 1310.926 | AQ14: 4626.8247 | AR14: 118 | AS14: 30 | AT14: 36 | AU14: 29 | AX14: 17 | AY14: 19 | AZ14: 2 | BA14: 2 | BB14: 6529.2 | BC14: 6529.2 | BD14: 1 | BE14: 3264.6 | BF14: 0.25423729 | BG14: 0.96666667 | BH14: 0.24576271 | BI14: 0.5862069 | BK14: 0.55882353 | BL14: 0.11764706 | BM14: 0.016949153 | BN14: 0.016949153 | BO14: 34 | BP14: 19 | BQ14: 20 | BR14: 13719.917 | BS14: 3869.1587 | BT14: 610.13502 | BU14: 1310.926 | BV14: 1631.0459 | BW14: 76061.2 | BX14: 79749.2 | BY14: 1 | BZ14: 26266.293 | CA14: 23750.895 | CB14: 28177.598 | CC14: 40591.523 | CD14: 40591.523 | CE14: 92520.017 | CF14: 0.82210534 | CH14: 95035.415 | CI14: 0.83915244 | CJ14: 84557.816 | CK14: 0.94313221
A15: 45690 | D15: 总计 | E15: - | F15: - | G15: - | H15: =I15 | I15: 48635.086 | J15: =I15/K15 | K15: 181 | L15: 85 | M15: 86 | N15: 90 | Q15: 64 | R15: 72 | S15: 23 | T15: 27 | U15: 118186.4 | V15: 138838.4 | W15: 1 | X15: 5142.163 | Y15: 0.46961326 | Z15: 1.0588235 | AA15: 0.49723757 | AB15: 0.71111111 | AD15: 0.94736842 | AE15: 0.359375 | AF15: 0.12707182 | AG15: 0.14917127 | AH15: 93016.863 | AI15: 1.4926154 | AJ15: 76 | AK15: 72 | AL15: 78 | AM15: 12471.987 | AN15: 11124.357 | AO15: 12886.159 | AP15: 1250.3664 | AQ15: 6648.908 | AR15: 164 | AS15: 46 | AT15: 49 | AU15: 52 | AX15: 21 | AY15: 24 | AZ15: 2 | BA15: 2 | BB15: 7176 | BC15: 7176 | BD15: 1 | BE15: 3588 | BF15: 0.2804878 | BG15: 1.1304348 | BH15: 0.31707317 | BI15: 0.40384615 | BK15: 0.45283019 | BL15: 0.095238095 | BM15: 0.012195122 | BN15: 0.012195122 | BO15: 53 | BP15: 24 | BQ15: 25 | BR15: 10653.537 | BS15: 4401.1099 | BT15: 691.26004 | BU15: 1198.424 | BV15: 1846.5914 | BW15: 125362.4 | BX15: 146014.4 | BY15: 1 | BZ15: 40047.176 | CA15: 36742.798 | CB15: 23125.524 | CC15: 48635.086 | CD15: 48635.086 | CE15: 108503.41 | CF15: 1.1553775 | CH15: 111807.79 | CI15: 1.3059413 | CJ15: 114557.26 | CK15: 1.2745975
A16: 45718 | D16: 总计 | E16: - | F16: - | G16: - | H16: =I16 | I16: 113250.48 | J16: 380.03515 | K16: 298 | L16: 142 | M16: 146 | N16: 152 | Q16: 117 | R16: 132 | S16: 47 | T16: 55 | U16: 243836 | V16: 275640 | W16: 1 | X16: 5011.6364 | Y16: 0.47651007 | Z16: 1.0704225 | AA16: 0.51006711 | AB16: 0.76973684 | AD16: 0.94964029 | AE16: 0.4017094 | AF16: 0.15771812 | AG16: 0.18456376 | AH16: 193914.57 | AI16: 1.4214507 | AJ16: 139 | AK16: 132 | AL16: 138 | AM16: 26635.972 | AN16: 14433.456 | AO16: 26387.439 | AP16: 2005.4387 | AQ16: 11201.786 | AR16: 18 | AS16: 17 | AT16: 25 | AU16: 17 | AX16: 10 | AY16: 13 | AZ16: 2 | BA16: 2 | BB16: 7735.2 | BC16: 7735.2 | BD16: 1 | BE16: 3867.6 | BF16: 0.94444444 | BG16: 1 | BH16: 0.94444444 | BI16: 0.58823529 | BK16: 0.54166667 | BL16: 0.2 | BM16: 0.11111111 | BN16: 0.11111111 | BO16: 24 | BP16: 13 | BQ16: 14 | BR16: 1471.4819 | BS16: 2100.202 | BT16: 760.24777 | BU16: 121.13388 | BV16: 1141.7321 | BW16: 251571.2 | BX16: 283375.2 | BY16: 1 | BZ16: 58151.435 | CA16: 52577.046 | CB16: 28107.454 | CC16: 113250.48 | CD16: 113250.48 | CE16: 193934.98 | CF16: 1.2971936 | CH16: 199509.37 | CI16: 1.4203604 | CJ16: 195101.91 | CK16: 1.4524471
A17: 45749 | H17: =I17 | I17: 131731.98 | J17: 539.88517 | K17: 244 | L17: 122 | M17: 128 | N17: 127 | Q17: 100 | R17: 124 | S17: 41 | T17: 48 | U17: 180708 | V17: 211424 | W17: 1 | X17: 4404.6667 | Y17: 0.5 | Z17: 1.0409836 | AA17: 0.5204918 | AB17: 0.78740157 | AD17: 0.98412698 | AE17: 0.41 | AF17: 0.16803279 | AG17: 0.19672131 | AH17: 210352.89 | AI17: 1.005092 | AJ17: 126 | AK17: 124 | AL17: 134 | AM17: 27025.104 | AN17: 18959.254 | AO17: 18955.011 | AP17: 2411.5963 | AQ17: 11269.939 | AR17: 20 | AS17: 18 | AT17: 20 | AU17: 18 | AX17: 11 | AY17: 13 | AZ17: 0 | BA17: 0 | BB17: 0 | BC17: 0 | BF17: 0.9 | BG17: 1 | BH17: 0.9 | BI17: 0.61111111 | BK17: 0.65 | BL17: 0 | BM17: 0 | BN17: 0 | BO17: 20 | BP17: 13 | BQ17: 14 | BR17: 2092.9385 | BS17: 2050.2685 | BT17: 0 | BU17: 197.67183 | BV17: 1114.1083 | BW17: 180708 | BX17: 211424 | BY17: 1 | BZ17: 54957.85 | CA17: 48848.536 | CB17: 29118.043 | CC17: 131731.98 | CD17: 131731.98 | CE17: 209698.56 | CF17: 0.86175127 | CH17: 215807.87 | CI17: 0.97968622 | CJ17: 206489.83 | CK17: 1.0238955
A18: 45779 | H18: =I18 | I18: 163228.27 | J18: 632.66773 | K18: 258 | L18: 119 | M18: 124 | N18: 116 | Q18: 84 | R18: 106 | S18: 34 | T18: 45 | U18: 171724 | V18: 222292 | W18: 1 | X18: 4939.8222 | Y18: 0.46124031 | Z18: 0.97478992 | AA18: 0.4496124 | AB18: 0.72413793 | AD18: 0.95495495 | AE18: 0.4047619 | AF18: 0.13178295 | AG18: 0.1744186 | AH18: 226867.01 | AI18: 0.97983395 | AJ18: 111 | AK18: 106 | AL18: 116 | AM18: 14627.721 | AN18: 15217.58 | AO18: 21318.363 | AP18: 2399.1923 | AQ18: 10075.88 | AR18: 6 | AS18: 5 | AT18: 6 | AU18: 5 | AX18: 3 | AY18: 6 | AZ18: 0 | BA18: 0 | BB18: 0 | BC18: 0 | BF18: 0.83333333 | BG18: 1 | BH18: 0.83333333 | BI18: 0.6 | BK18: 0.75 | BL18: 0 | BM18: 0 | BN18: 0 | BO18: 8 | BP18: 6 | BQ18: 6 | BR18: 281.4866 | BS18: 656.08636 | BT18: 0 | BU18: 55.795171 | BV18: 465.60811 | BW18: 171724 | BX18: 222292 | BY18: 1 | BZ18: 50188.505 | CA18: 42211.616 | CB18: 14909.208 | CC18: 163228.27 | CD18: 163228.27 | CE18: 220349.1 | CF18: 0.77932699 | CH18: 228325.99 | CI18: 0.97357293 | CJ18: 233216.78 | CK18: 0.95315612
A19: 45810 | H19: 154847.15 | I19: 145313.96 | J19: 758.5688 | K19: 204 | L19: 114 | M19: 124 | N19: 116 | Q19: 96 | R19: 130 | S19: 43 | T19: 53 | U19: 209284 | V19: 255664 | W19: 1 | X19: 4823.8491 | Y19: 0.55882353 | Z19: 1.0175439 | AA19: 0.56862745 | AB19: 0.82758621 | AD19: 0.92857143 | AE19: 0.44791667 | AF19: 0.21078431 | AG19: 0.25980392 | AH19: 220689.03 | AI19: 1.1584808 | AJ19: 140 | AK19: 130 | AL19: 150 | AM19: 12724.406 | AN19: 13935.795 | AO19: 24680.086 | AP19: 1647.4886 | AQ19: 12953.219 | AR19: 99 | AS19: 30 | AT19: 30 | AU19: 29 | AX19: 17 | AY19: 20 | AZ19: 1 | BA19: 1 | BB19: 3588 | BC19: 3588 | BD19: 1 | BE19: 3588 | BF19: 0.3030303 | BG19: 0.96666667 | BH19: 0.29292929 | BI19: 0.5862069 | BK19: 0.625 | BL19: 0.058823529 | BM19: 0.01010101 | BN19: 0.01010101 | BO19: 32 | BP19: 20 | BQ19: 20 | BR19: 5541.8712 | BS19: 2698.7077 | BT19: 372.89882 | BU19: 799.51651 | BV19: 1578.9348 | BW19: 212872 | BX19: 259252 | BY19: 1 | BZ19: 58843.626 | CA19: 48947.043 | CB19: 18322.256 | CC19: 154847.15 | CD19: 153067.13 | CE19: 220336.43 | CF19: 0.96612257 | CG19: 9533.1911 | CH19: 232013.03 | CI19: 1.1174028 | CJ19: 236490.77 | CK19: 1.0962457
A20: 45841 | H20: 120482.45 | I20: 114209.1 | J20: 813.40499 | K20: 148 | L20: 62 | M20: 69 | N20: 64 | Q20: 52 | R20: 77 | S20: 24 | T20: 35 | U20: 121912 | V20: 163880 | W20: 1 | X20: 4682.2857 | Y20: 0.41891892 | Z20: 1.0322581 | AA20: 0.43243243 | AB20: 0.8125 | AD20: 0.9625 | AE20: 0.46153846 | AF20: 0.16216216 | AG20: 0.23648649 | AH20: 160109.83 | AI20: 1.0235474 | AJ20: 80 | AK20: 77 | AL20: 87 | AM20: 6512.6513 | AN20: 7240.4441 | AO20: 16780.999 | AP20: 1523.4822 | AQ20: 7668.3132 | AR20: 4 | AS20: 3 | AT20: 4 | AU20: 4 | AX20: 2 | AY20: 2 | AZ20: 0 | BA20: 1 | BB20: 0 | BC20: 1880 | BD20: 1 | BE20: 1880 | BF20: 0.75 | BG20: 1.3333333 | BH20: 1 | BI20: 0.5 | BK20: 0.5 | BL20: 0 | BM20: 0 | BN20: 0.25 | BO20: 4 | BP20: 2 | BQ20: 2 | BR20: 0 | BS20: 379.4598 | BT20: 197.37392 | BU20: 41.175195 | BV20: 164.36677 | BW20: 121912 | BX20: 165760 | BY20: 1 | BZ20: 33995.614 | CA20: 26115.29 | CB20: 6512.6513 | CC20: 120482.45 | CD20: 118443.28 | CE20: 151071.22 | CF20: 0.80698364 | CG20: 6273.3514 | CH20: 160990.72 | CI20: 1.0296246 | CJ20: 165878.07 | CK20: 0.99928824
A21: 45872 | H21: 38341.074 | I21: 35865.584 | J21: 833.5016 | K21: 46 | L21: 21 | M21: 25 | N21: 21 | Q21: 16 | R21: 36 | S21: 6 | T21: 14 | U21: 24028 | V21: 57832 | W21: 1 | X21: 4130.8571 | Y21: 0.45652174 | Z21: 1 | AA21: 0.45652174 | AB21: 0.76190476 | AD21: 1 | AE21: 0.375 | AF21: 0.13043478 | AG21: 0.30434783 | AH21: 55313.157 | AI21: 1.0455379 | AJ21: 36 | AK21: 36 | AL21: 38 | AM21: 4152.8585 | AN21: 3087.9608 | AO21: 5921.8862 | AP21: 460 | AQ21: 3349.3782 | AR21: 0 | AS21: 0 | AT21: 0 | AU21: 0 | AX21: 0 | AY21: 0 | AZ21: 0 | BA21: 0 | BB21: 0 | BC21: 0 | BO21: 0 | BP21: 0 | BQ21: 0 | BR21: 0 | BS21: 0 | BT21: 0 | BU21: 0 | BV21: 0 | BW21: 24028 | BX21: 57832 | BY21: 1 | BZ21: 12819.225 | CA21: 7100.8559 | CB21: 4152.8585 | CC21: 38341.074 | CD21: 36926.508 | CE21: 48180.223 | CF21: 0.49871086 | CG21: 2475.4893 | CH21: 55313.157 | CI21: 1.0455379 | CJ21: 54610.299 | CK21: 1.0589944
A22: 45903 | H22: 23291.661 | I22: =H22-CG22 | J22: 597.22208 | K22: 39 | L22: 18 | M22: 20 | N22: 19 | Q22: 11 | R22: 21 | S22: 3 | T22: 6 | U22: 11564 | V22: 22328 | W22: 1 | X22: 3721.3333 | Y22: 0.46153846 | Z22: 1.0555556 | AA22: 0.48717949 | AB22: 0.57894737 | AD22: 1 | AE22: 0.27272727 | AF22: 0.076923077 | AG22: 0.15384615 | AH22: 33903.815 | AI22: 0.65856895 | AJ22: 21 | AK22: 21 | AL22: 22 | AM22: 2954.9847 | AN22: 2891.7842 | AO22: 2506.9331 | AP22: 390 | AQ22: 1868.452 | AR22: 0 | AS22: 0 | AT22: 1 | AU22: 0 | AX22: 0 | AY22: 0 | AZ22: 0 | BA22: 0 | BB22: 0 | BC22: 0 | BO22: 0 | BP22: 0 | BQ22: 0 | BR22: 0 | BS22: 95 | BT22: 0 | BU22: 0 | BV22: 0 | BW22: 11564 | BX22: 22328 | BY22: 1 | BZ22: 7752.1693 | CA22: 5225.2093 | CB22: 2954.9847 | CC22: 23291.661 | CD22: 22755.744 | CE22: 30935.938 | CF22: 0.37380473 | CG22: 1071.8348 | CH22: 33998.815 | CI22: 0.65672877 | CJ22: 33968.831 | CK22: 0.65730847
A23: 45931 | H23: 17359.655 | I23: =H23-CG23 | J23: 619.98769 | K23: 28 | L23: 11 | M23: 12 | N23: 10 | Q23: 9 | R23: 12 | S23: 3 | T23: 7 | U23: 16464 | V23: 38447 | W23: 1 | X23: 5492.4286 | Y23: 0.39285714 | Z23: 0.90909091 | AA23: 0.35714286 | AB23: 0.9 | AD23: 1 | AE23: 0.33333333 | AF23: 0.10714286 | AG23: 0.25 | AH23: 26596.919 | AI23: 1.4455434 | AJ23: 12 | AK23: 12 | AL23: 15 | AM23: 1749.5713 | AN23: 1706.9683 | AO23: 4229.235 | AP23: 280 | AQ23: 1271.4886 | AR23: 0 | AS23: 0 | AT23: 0 | AU23: 0 | AX23: 0 | AY23: 0 | AZ23: 0 | BA23: 0 | BB23: 0 | BC23: 0 | BO23: 0 | BP23: 0 | BQ23: 0 | BR23: 0 | BS23: 0 | BT23: 0 | BU23: 0 | BV23: 0 | BW23: 16464 | BX23: 38447 | BY23: 1 | BZ23: 7487.6919 | CA23: 4503.4478 | CB23: 1749.5713 | CC23: 17359.655 | CD23: 16645.099 | CE23: 22898.118 | CF23: 0.71901105 | CG23: 1250.474 | CH23: 26596.919 | CI23: 1.4455434 | CJ23: 26947.347 | CK23: 1.4267453
A24: 45962 | H24: 20294.266 | I24: =H24-CG24 | J24: 780.5487 | K24: 26 | L24: 9 | M24: 10 | N24: 9 | Q24: 7 | R24: 10 | S24: 2 | T24: 4 | U24: 11318 | V24: 20116 | W24: 1 | X24: 5029 | Y24: 0.34615385 | Z24: 1 | AA24: 0.34615385 | AB24: 0.77777778 | AD24: 1 | AE24: 0.28571429 | AF24: 0.076923077 | AG24: 0.15384615 | AH24: 26488.23 | AI24: 0.75943164 | AJ24: 10 | AK24: 10 | AL24: 10 | AM24: 1692.4313 | AN24: 1181.0796 | AO24: 2212.794 | AP24: 260 | AQ24: 847.65904 | AR24: 0 | AS24: 0 | AT24: 0 | AU24: 0 | AX24: 0 | AY24: 0 | AZ24: 0 | BA24: 0 | BB24: 0 | BC24: 0 | BO24: 0 | BP24: 0 | BQ24: 0 | BR24: 0 | BS24: 0 | BT24: 0 | BU24: 0 | BV24: 0 | BW24: 11318 | BX24: 20116 | BY24: 1 | BZ24: 4501.5327 | CA24: 3161.3321 | CB24: 1692.4313 | CC24: 20294.266 | CD24: 19936.821 | CE24: 24790.585 | CF24: 0.45654429 | CG24: 714.88942 | CH24: 26488.23 | CI24: 0.75943164 | CJ24: 26745.799 | CK24: 0.75211812
A25: 45992 | H25: 10835.454 | I25: =H25-CG25 | J25: 3611.8179 | K25: 3 | L25: 1 | M25: 1 | N25: 2 | O25: 2 | P25: 5 | Q25: 1 | R25: 5 | S25: 0 | T25: 0 | U25: 0 | V25: 0 | Y25: 0.33333333 | Z25: 2 | AA25: 0.66666667 | AB25: 0.5 | AC25: 0.5 | AD25: 1 | AE25: 0 | AF25: 0 | AG25: 0 | AH25: 906.06055 | AI25: 0 | AJ25: 5 | AK25: 5 | AL25: 6 | AM25: 223.84966 | AN25: 147.22787 | AO25: 0 | AP25: 30 | AQ25: 504.98302 | AR25: 0 | AS25: 0 | AT25: 0 | AU25: 0 | AV25: 0 | AW25: 0 | AX25: 0 | AY25: 0 | AZ25: 0 | BA25: 0 | BB25: 0 | BC25: 0 | BO25: 0 | BP25: 0 | BQ25: 0 | BR25: 0 | BS25: 0 | BT25: 0 | BU25: 0 | BV25: 0 | BW25: 0 | BX25: 0 | BZ25: 682.21089 | CA25: 345.55554 | CB25: 223.84966 | CC25: 10835.454 | CD25: 10835.454 | CE25: 569.40521 | CF25: 0 | CG25: 0 | CH25: 906.06055 | CI25: 0 | CJ25: 907.21089 | CK25: 0
A26: 46023 | H26: 2266.5659 | I26: =H26-CG26 | J26: 566.64146 | K26: 4 | L26: 4 | M26: 4 | N26: 3 | O26: 3 | P26: 2 | Q26: 2 | R26: 2 | S26: 1 | T26: 1 | U26: 4588 | V26: 4588 | W26: 1 | X26: 4588 | Y26: 1 | Z26: 0.75 | AA26: 0.75 | AB26: 0.66666667 | AC26: 0.66666667 | AD26: 1 | AE26: 0.5 | AF26: 0.25 | AG26: 0.25 | AH26: 4042.3411 | AI26: 1.1349859 | AJ26: 2 | AK26: 2 | AL26: 2 | AM26: 374.59392 | AN26: 625.33018 | AO26: 567.52352 | AP26: 40 | AQ26: 168.32767 | AR26: 0 | AS26: 0 | AT26: 0 | AU26: 0 | AV26: 0 | AW26: 0 | AX26: 0 | AY26: 0 | AZ26: 0 | BA26: 0 | BB26: 0 | BC26: 0 | BO26: 0 | BP26: 0 | BQ26: 0 | BR26: 0 | BS26: 0 | BT26: 0 | BU26: 0 | BV26: 0 | BW26: 4588 | BX26: 4588 | BY26: 1 | BZ26: 1401.1814 | CA26: 1401.1814 | CB26: 374.59392 | CC26: 2266.5659 | CD26: 2266.5659 | CE26: 4042.3411 | CF26: 1.1349859 | CG26: 0 | CH26: 4042.3411 | CI26: 1.1349859 | CJ26: 3967.7472 | CK26: 1.1563237
A27: 陈琪-汇总 | H27: =SUM(H13:H26) | I27: =SUM(I13:I26) | J27: =I27/K27 | K27: =SUM(K13:K26) | L27: =SUM(L13:L26) | M27: =SUM(M13:M26) | N27: =SUM(N13:N26) | O27: =SUM(O13:O26) | P27: =SUM(P13:P26) | Q27: =SUM(Q13:Q26) | R27: =SUM(R13:R26) | ... V27: =SUM(V13:V26) | X27: =V27/T27 | Y27: =L27/K27 | Z27: =N27/L27 | AA27: =N27/K27 | AB27: =Q27/N27 | AD27: =AVERAGE(AD13:AD26) | AE27: =S27/Q27 | AF27: =S27/K27 | AG27: =T27/K27 | AH27: =SUM(AH13:AH26) | AI27: =V27/AH27 | AJ27: =SUM(AJ13:AJ26) | AK27: =SUM(AK13:AK26) | AL27: =SUM(AL13:AL26) | AM27: =SUM(AM13:AM26) | AN27: =SUM(AN13:AN26) | AO27: =SUM(AO13:AO26) | AP27: =SUM(AP13:AP26) | AQ27: =SUM(AQ13:AQ26) | ... AU27: =SUM(AU13:AU26) | AX27: =SUM(AX13:AX26) | AY27: =SUM(AY13:AY26) | AZ27: =SUM(AZ13:AZ26) | BA27: =SUM(BA13:BA26) | BB27: =SUM(BB13:BB26) | BC27: =SUM(BC13:BC26) | BE27: =BC27/BA27 | BF27: =AS27/AR27 | BG27: =AU27/AS27 | BH27: =AU27/AR27 | BI27: =AX27/AU27 | BK27: =AVERAGE(BK13:BK26) | BL27: =AZ27/AX27 | BM27: =AZ27/AR27 | BN27: =BA27/AR27 | BO27: =SUM(BO13:BO26) | BP27: =SUM(BP13:BP26) | BQ27: =SUM(BQ13:BQ26) | BR27: =SUM(BR13:BR26) | BS27: =SUM(BS13:BS26) | BT27: =SUM(BT13:BT26) | BU27: =SUM(BU13:BU26) | BV27: =SUM(BV13:BV26) | ... BX27: =SUM(BX13:BX26) | BZ27: =SUM(BZ13:BZ26) | CA27: =SUM(CA13:CA26) | CB27: =SUM(CB13:CB26) | CC27: =SUM(CC13:CC26) | CD27: =SUM(CD13:CD26) | CE27: =SUM(CE13:CE26) | CF27: =BW27/CE27 | CG27: =SUM(CG13:CG26) | CH27: =SUM(CH13:CH26) | CI27: =BX27/CH27 | CJ27: =SUM(CJ13:CJ26) | CK27: =BX27/CJ27

Sheet 陈琪直播
I1: 主投 | AR1: 辅投 | BW1: 汇总
B2: 渠道组 | C2: 供应商 | D2: 渠道名称 | E2: 主投 | F2: 辅投 | G2: 结算方式 | H2: 滚动消耗 | I2: 滚动消耗(不含赠课成本) | J2: 单例子成本 | K2: 例子数 | L2: 分发数 | M2: 剔除毛例子 分发数 | N2: 约课数 | O2: 应到课数 | P2: 滚动应到课数 | Q2: 到课数 | R2: 滚动到课数 | S2: 当月成交数 | T2: 滚动成交数 | U2: 当月GMV | V2: 滚动GMV | W2: 海外GMV占比 | X2: 滚动ASP | Y2: 例子分发率 | Z2: 分发约课率 | AA2: 例子约课率 | AB2: 约课到课率 | AD2: 滚动应到课率 | AE2: 到课转化率 | AF2: 注册转化率 | AG2: 滚动转化率 | AH2: 滚动ROI2总成本 | AI2: 滚动ROI2 | AJ2: 滚动应到课人数 | AK2: 滚动到课人数 | AL2: 滚动到课人次 | AM2: 运营成本 | AN2: 销售固定成本 | AO2: 销售变动成本 | AP2: TMK费用 | AQ2: DEMO费用 | AR2: 例子数 | AS2: 分发数 | AT2: 剔除毛例子分发数 | AU2: 约课数 | AX2: 到课数 | AY2: 滚动到课数 | AZ2: 当月成交 | BA2: 滚动成交数 | BB2: 当月GMV | BC2: 滚动GMV | BD2: 海外GMV占比 | BE2: 滚动ASP | BF2: 例子分发率 | BG2: 分发约课率 | BH2: 例子约课率 | BI2: 约课到课率 | BK2: 滚动应到课率 | BL2: 到课转化率 | BM2: 注册转化率 | BN2: 滚动转化率 | BO2: 滚动应到课人数 | BP2: 滚动到课人数 | BQ2: 滚动到课人次 | BR2: 运营成本 | BS2: 销售固定成本 | BT2: 销售变动成本 | BU2: TMK费用 | BV2: DEMO费用 | BW2: 当月GMV | BX2: 滚动GMV | BY2: 海外GMV占比 | BZ2: 滚动其他成本 | CA2: 同源其他成本 | CB2: 运营成本 | CC2: 滚动消耗 | CD2: 同源消耗 | CE2: 当月ROI2总成本 | CF2: 当月ROI2 | CG2: 滚动赠课成本 | CH2: 滚动ROI2总成本 | CI2: 滚动ROI2 | CJ2: O-ROI总成本 | CK2: O-ROI
A3: 45904 | H3: 128084.36 | I3: 123439.75 | J3: 576.9566 | K3: 222 | L3: 91 | M3: 91 | N3: 90 | Q3: 69 | R3: 69 | S3: 26 | T3: 26 | U3: 151688 | V3: 151688 | W3: 1 | X3: 5834.1538 | Y3: 0.40990991 | Z3: 0.98901099 | AA3: 0.40540541 | AB3: 0.76666667 | AD3: 0.97183099 | AE3: 0.37681159 | AF3: 0.11711712 | AG3: 0.11711712 | AH3: 183768.47 | AI3: 0.82542994 | AJ3: 71 | AK3: 69 | AL3: 76 | AM3: 16820.682 | AN3: 13157.618 | AO3: 17031.157 | AP3: 2220 | AQ3: 6454.6523 | AR3: 0 | AS3: 0 | AT3: 0 | AU3: 0 | AX3: 0 | AY3: 0 | AZ3: 0 | BA3: 0 | BB3: 0 | BC3: 0 | BO3: 0 | BP3: 0 | BQ3: 0 | BR3: 0 | BS3: 0 | BT3: 0 | BU3: 0 | BV3: 0 | BW3: 151688 | BX3: 151688 | BY3: 1 | BZ3: 38863.427 | CA3: 38863.427 | CB3: 16820.682 | CC3: 128084.36 | CD3: 128084.36 | CE3: 183768.47 | CF3: 0.82542994 | CG3: 4644.6176 | CH3: 183768.47 | CI3: 0.82542994 | CJ3: 183597.79 | CK3: 0.8261973
A4: 45931 | H4: 173328.07 | I4: =H4-CG4 | J4: 509.78844 | K4: 340 | L4: 105 | M4: 107 | N4: 107 | Q4: 71 | R4: 81 | S4: 25 | T4: 28 | U4: 161397 | V4: 177161 | W4: 1 | X4: 6327.1786 | Y4: 0.30882353 | Z4: 1.0190476 | AA4: 0.31470588 | AB4: 0.6635514 | AD4: 1 | AE4: 0.35211268 | AF4: 0.073529412 | AG4: 0.082352941 | AH4: 239886.44 | AI4: 0.73852027 | AJ4: 81 | AK4: 81 | AL4: 85 | AM4: 21244.795 | AN4: 15220.468 | AO4: 19488.009 | AP4: 3400 | AQ4: 7205.1019 | AR4: 0 | AS4: 0 | AT4: 0 | AU4: 0 | AX4: 0 | AY4: 0 | AZ4: 0 | BA4: 0 | BB4: 0 | BC4: 0 | BO4: 0 | BP4: 0 | BQ4: 0 | BR4: 0 | BS4: 0 | BT4: 0 | BU4: 0 | BV4: 0 | BW4: 161397 | BX4: 177161 | BY4: 1 | BZ4: 45313.579 | CA4: 42362.593 | CB4: 21244.795 | CC4: 173328.07 | CD4: 172792.15 | CE4: 236399.54 | CF4: 0.68272976 | CG4: 5001.8958 | CH4: 239886.44 | CI4: 0.73852027 | CJ4: 244141.65 | CK4: 0.72564842
A5: 45962 | H5: 162240.1 | I5: =H5-CG5 | J5: 965.71489 | K5: 168 | L5: 74 | M5: 80 | N5: 79 | Q5: 55 | R5: 68 | S5: 22 | T5: 33 | U5: 123436 | V5: 176554 | W5: 1 | X5: 5350.1212 | Y5: 0.44047619 | Z5: 1.0675676 | AA5: 0.4702381 | AB5: 0.69620253 | AD5: 0.98550725 | AE5: 0.4 | AF5: 0.13095238 | AG5: 0.19642857 | AH5: 209744.07 | AI5: 0.84175921 | AJ5: 69 | AK5: 68 | AL5: 71 | AM5: 10935.71 | AN5: 9448.6372 | AO5: 19421.238 | AP5: 1680 | AQ5: 6018.3792 | AR5: 0 | AS5: 0 | AT5: 0 | AU5: 0 | AX5: 0 | AY5: 0 | AZ5: 0 | BA5: 0 | BB5: 0 | BC5: 0 | BO5: 0 | BP5: 0 | BQ5: 0 | BR5: 0 | BS5: 0 | BT5: 0 | BU5: 0 | BV5: 0 | BW5: 123436 | BX5: 176554 | BY5: 1 | BZ5: 36568.255 | CA5: 28660.283 | CB5: 10935.71 | CC5: 162240.1 | CD5: 160274.16 | CE5: 199870.15 | CF5: 0.61758097 | CG5: 5897.8377 | CH5: 209744.07 | CI5: 0.84175921 | CJ5: 211408.36 | CK5: 0.83513255
A6: 45992 | H6: 88525.162 | I6: =H6-CG6 | J6: 1041.4725 | K6: 85 | L6: 51 | M6: 51 | N6: 49 | O6: 48 | P6: 47 | Q6: 37 | R6: 46 | S6: 19 | T6: 22 | U6: 100699 | V6: 111196 | W6: 1 | X6: 5054.3636 | Y6: 0.6 | Z6: 0.96078431 | AA6: 0.57647059 | AB6: 0.75510204 | AC6: 0.77083333 | AD6: 0.9787234 | AE6: 0.51351351 | AF6: 0.22352941 | AG6: 0.25882353 | AH6: 121104.87 | AI6: 0.91817942 | AJ6: 47 | AK6: 46 | AL6: 49 | AM6: 6342.4071 | AN6: 7508.6214 | AO6: 13754.652 | AP6: 850 | AQ6: 4124.028 | AR6: 0 | AS6: 0 | AT6: 0 | AU6: 0 | AV6: 0 | AW6: 0 | AX6: 0 | AY6: 0 | AZ6: 0 | BA6: 0 | BB6: 0 | BC6: 0 | BO6: 0 | BP6: 0 | BQ6: 0 | BR6: 0 | BS6: 0 | BT6: 0 | BU6: 0 | BV6: 0 | BW6: 100699 | BX6: 111196 | BY6: 1 | BZ6: 26237.302 | CA6: 24097.212 | CB6: 6342.4071 | CC6: 88525.162 | CD6: 87939.744 | CE6: 118379.36 | CF6: 0.85064657 | CG6: 4293.0648 | CH6: 121104.87 | CI6: 0.91817942 | CJ6: 121137.46 | CK6: 0.91793237
A7: 46023 | H7: 47898.546 | I7: =H7-CG7 | J7: 630.24403 | K7: 76 | L7: 32 | M7: 35 | N7: 34 | O7: 31 | P7: 36 | Q7: 30 | R7: 36 | S7: 9 | T7: 12 | U7: 46392 | V7: 64056 | W7: 1 | X7: 5338 | Y7: 0.42105263 | Z7: 1.0625 | AA7: 0.44736842 | AB7: 0.88235294 | AC7: 0.96774194 | AD7: 1 | AE7: 0.3 | AF7: 0.11842105 | AG7: 0.15789474 | AH7: 75130.884 | AI7: 0.85259212 | AJ7: 36 | AK7: 36 | AL7: 37 | AM7: 8266.3079 | AN7: 6776.2569 | AO7: 8397.2231 | AP7: 760 | AQ7: 3032.5499 | AR7: 0 | AS7: 0 | AT7: 0 | AU7: 0 | AV7: 0 | AW7: 0 | AX7: 0 | AY7: 0 | AZ7: 0 | BA7: 0 | BB7: 0 | BC7: 0 | BO7: 0 | BP7: 0 | BQ7: 0 | BR7: 0 | BS7: 0 | BT7: 0 | BU7: 0 | BV7: 0 | BW7: 46392 | BX7: 64056 | BY7: 1 | BZ7: 18966.03 | CA7: 15495.875 | CB7: 8266.3079 | CC7: 47898.546 | CD7: 47898.546 | CE7: 71660.729 | CF7: 0.64738387 | CG7: 0 | CH7: 75130.884 | CI7: 0.85259212 | CJ7: 72564.576 | CK7: 0.88274477
A8: 46054 | H8: 43300.376 | I8: =H8-CG8 | J8: 849.02699 | K8: 51 | L8: 30 | M8: 33 | N8: 31 | O8: 26 | P8: 28 | Q8: 19 | R8: 27 | S8: 5 | T8: 8 | U8: 21140 | V8: 34204 | W8: 1 | X8: 4275.5 | Y8: 0.58823529 | Z8: 1.0333333 | AA8: 0.60784314 | AB8: 0.61290323 | AC8: 0.73076923 | AD8: 0.96428571 | AE8: 0.26315789 | AF8: 0.098039216 | AG8: 0.15686275 | AH8: 63873.732 | AI8: 0.535494 | AJ8: 28 | AK8: 27 | AL8: 30 | AM8: 6721.8597 | AN8: 6398.804 | AO8: 4483.8675 | AP8: 510 | AQ8: 2458.8243 | AR8: 0 | AS8: 0 | AT8: 0 | AU8: 0 | AV8: 0 | AW8: 0 | AX8: 0 | AY8: 0 | AZ8: 0 | BA8: 0 | BB8: 0 | BC8: 0 | BO8: 0 | BP8: 0 | BQ8: 0 | BR8: 0 | BS8: 0 | BT8: 0 | BU8: 0 | BV8: 0 | BW8: 21140 | BX8: 34204 | BY8: 1 | BZ8: 13851.496 | CA8: 10819.554 | CB8: 6721.8597 | CC8: 43300.376 | CD8: 43300.376 | CE8: 60841.79 | CF8: 0.34745854 | CG8: 0 | CH8: 63873.732 | CI8: 0.535494 | CJ8: 60976.872 | CK8: 0.56093399
A9: 46082 | H9: 22967.944 | I9: =H9-CG9 | J9: 637.99845 | K9: 36 | L9: 16 | M9: 17 | N9: 17 | O9: 16 | P9: 21 | Q9: 14 | R9: 21 | S9: 5 | T9: 10 | U9: 21740 | V9: 45980 | W9: 1 | X9: 4598 | Y9: 0.44444444 | Z9: 1.0625 | AA9: 0.47222222 | AB9: 0.82352941 | AC9: 0.875 | AD9: 1 | AE9: 0.35714286 | AF9: 0.13888889 | AG9: 0.27777778 | AH9: 36063.321 | AI9: 1.2749796 | AJ9: 21 | AK9: 21 | AL9: 21 | AM9: 3172.8682 | AN9: 2350.6079 | AO9: 5456.432 | AP9: 360 | AQ9: 1755.4687 | AR9: 0 | AS9: 0 | AT9: 0 | AU9: 0 | AV9: 0 | AW9: 0 | AX9: 0 | AY9: 0 | AZ9: 0 | BA9: 0 | BB9: 0 | BC9: 0 | BO9: 0 | BP9: 0 | BQ9: 0 | BR9: 0 | BS9: 0 | BT9: 0 | BU9: 0 | BV9: 0 | BW9: 21740 | BX9: 45980 | BY9: 1 | BZ9: 9922.5087 | CA9: 6322.5283 | CB9: 3172.8682 | CC9: 22967.944 | CD9: 21961.872 | CE9: 31457.269 | CF9: 0.69109623 | CG9: 2012.1437 | CH9: 36063.321 | CI9: 1.2749796 | CJ9: 35590.453 | CK9: 1.2919195
A10: 46113 | H10: 22967.944 | I10: =H10-CG10 | J10: 637.99845 | K10: 36 | L10: 16 | M10: 17 | N10: 17 | O10: 16 | P10: 21 | Q10: 14 | R10: 21 | S10: 5 | T10: 10 | U10: 21740 | V10: 45980 | W10: 1 | X10: 4598 | Y10: 0.44444444 | Z10: 1.0625 | AA10: 0.47222222 | AB10: 0.82352941 | AC10: 0.875 | AD10: 1 | AE10: 0.35714286 | AF10: 0.13888889 | AG10: 0.27777778 | AH10: 36063.321 | AI10: 1.2749796 | AJ10: 21 | AK10: 21 | AL10: 21 | AM10: 3172.8682 | AN10: 2350.6079 | AO10: 5456.432 | AP10: 360 | AQ10: 1755.4687 | AR10: 0 | AS10: 0 | AT10: 0 | AU10: 0 | AV10: 0 | AW10: 0 | AX10: 0 | AY10: 0 | AZ10: 0 | BA10: 0 | BB10: 0 | BC10: 0 | BO10: 0 | BP10: 0 | BQ10: 0 | BR10: 0 | BS10: 0 | BT10: 0 | BU10: 0 | BV10: 0 | BW10: 21740 | BX10: 45980 | BY10: 1 | BZ10: 9922.5087 | CA10: 6322.5283 | CB10: 3172.8682 | CC10: 22967.944 | CD10: 21961.872 | CE10: 31457.269 | CF10: 0.69109623 | CG10: 2012.1437 | CH10: 36063.321 | CI10: 1.2749796 | CJ10: 35590.453 | CK10: 1.2919195
A11: 陈琪直播-汇总 | H11: =SUM(H3:H10) | I11: =SUM(I3:I10) | J11: =I11/K11 | K11: =SUM(K3:K10) | L11: =SUM(L3:L10) | M11: =SUM(M3:M10) | N11: =SUM(N3:N10) | Q11: =SUM(Q3:Q10) | R11: =SUM(R3:R10) | S11: =SUM(S3:S10) | T11: =SUM(T3:T10) | U11: =SUM(U3:U10) | V11: =SUM(V3:V10) | X11: =V11/T11 | Y11: =L11/K11 | Z11: =N11/L11 | AA11: =N11/K11 | AB11: =Q11/N11 | AD11: =AVERAGE(AD3:AD10) | AE11: =S11/Q11 | AF11: =S11/K11 | AG11: =T11/K11 | AH11: =SUM(AH3:AH10) | AI11: =V11/AH11 | AJ11: =SUM(AJ3:AJ10) | AK11: =SUM(AK3:AK10) | AL11: =SUM(AL3:AL10) | AM11: =SUM(AM3:AM10) | AN11: =SUM(AN3:AN10) | AO11: =SUM(AO3:AO10) | AP11: =SUM(AP3:AP10) | AQ11: =SUM(AQ3:AQ10) | ... AS11: =SUM(AS3:AS10) | AU11: =SUM(AU3:AU10) | AX11: =SUM(AX3:AX10) | AY11: =SUM(AY3:AY10) | AZ11: =SUM(AZ3:AZ10) | BA11: =SUM(BA3:BA10) | BB11: =SUM(BB3:BB10) | BC11: =SUM(BC3:BC10) | BE11: =BC11/BA11 | BF11: =AS11/AR11 | BG11: =AU11/AS11 | BH11: =AU11/AR11 | BI11: =AX11/AU11 | BK11: =AVERAGE(BK3:BK10) | BL11: =AZ11/AX11 | BM11: =AZ11/AR11 | BN11: =BA11/AR11 | BO11: =SUM(BO3:BO10) | BP11: =SUM(BP3:BP10) | BQ11: =SUM(BQ3:BQ10) | BR11: =SUM(BR3:BR10) | BS11: =SUM(BS3:BS10) | BT11: =SUM(BT3:BT10) | BU11: =SUM(BU3:BU10) | BV11: =SUM(BV3:BV10) | ... BX11: =SUM(BX3:BX10) | BZ11: =SUM(BZ3:BZ10) | CA11: =SUM(CA3:CA10) | CB11: =SUM(CB3:CB10) | CC11: =SUM(CC3:CC10) | CD11: =SUM(CD3:CD10) | CE11: =SUM(CE3:CE10) | CF11: =BW11/CE11 | CG11: =SUM(CG3:CG10) | CH11: =SUM(CH3:CH10) | CI11: =BX11/CH11 | CJ11: =SUM(CJ3:CJ10) | CK11: =BX11/CJ11

Sheet 孙慧雪
I1: 主投 | AO1: 辅投 | BQ1: 汇总
B2: 渠道组 | C2: 供应商 | D2: 渠道名称 | E2: 主投 | F2: 辅投 | G2: 结算方式 | H2: 滚动消耗 | I2: 滚动消耗(不含赠课成本) | J2: 单例子成本 | K2: 例子数 | L2: 分发数 | M2: 剔除毛例子 分发数 | N2: 约课数 | O2: 到课数 | P2: 滚动到课数 | Q2: 当月成交数 | R2: 滚动成交数 | S2: 当月GMV | T2: 滚动GMV | U2: 海外GMV占比 | V2: 滚动ASP | W2: 例子分发率 | X2: 分发约课率 | Y2: 例子约课率 | Z2: 约课到课率 | AA2: 滚动应到课率 | AB2: 到课转化率 | AC2: 注册转化率 | AD2: 滚动转化率 | AE2: 滚动ROI2总成本 | AF2: 滚动ROI2 | AG2: 滚动应到课人数 | AH2: 滚动到课人数 | AI2: 滚动到课人次 | AJ2: 运营成本 | AK2: 销售固定成本 | AL2: 销售变动成本 | AM2: TMK费用 | AN2: DEMO费用 | AO2: 例子数 | AP2: 分发数 | AQ2: 剔除毛例子分发数 | AR2: 约课数 | AS2: 到课数 | AT2: 滚动到课数 | AU2: 当月成交 | AV2: 滚动成交数 | AW2: 当月GMV | AX2: 滚动GMV | AY2: 海外GMV占比 | AZ2: 滚动ASP | BA2: 例子分发率 | BB2: 分发约课率 | BC2: 例子约课率 | BD2: 约课到课率 | BE2: 滚动应到课率 | BF2: 到课转化率 | BG2: 注册转化率 | BH2: 滚动转化率 | BI2: 滚动应到课人数 | BJ2: 滚动到课人数 | BK2: 滚动到课人次 | BL2: 运营成本 | BM2: 销售固定成本 | BN2: 销售变动成本 | BO2: TMK费用 | BP2: DEMO费用 | BQ2: 当月GMV | BR2: 滚动GMV | BS2: 海外GMV占比 | BT2: 滚动其他成本 | BU2: 同源其他成本 | BV2: 运营成本 | BW2: 滚动消耗 | BX2: 同源消耗 | BY2: 当月ROI2总成本 | BZ2: 当月ROI2 | CA2: 滚动赠课成本 | CB2: 滚动ROI2总成本 | CC2: 滚动ROI2 | CD2: O-ROI总成本 | CE2: O-ROI
A3: 45718 | C3: 孙慧雪 | D3: KOLHK-香港-孙慧雪-Shukei-思维&无 | E3: - | F3: - | G3: - | H3: =I3 | I3: 107006.99 | J3: 442.17765 | K3: 242 | L3: 129 | M3: 129 | N3: 140 | O3: 113 | P3: 113 | Q3: 42 | R3: 42 | S3: 195996 | T3: 195996 | U3: 1 | V3: 4666.5714 | W3: 0.53305785 | X3: 1.0852713 | Y3: 0.5785124 | Z3: 0.80714286 | AA3: 0.96581197 | AB3: 0.37168142 | AC3: 0.17355372 | AD3: 0.17355372 | AE3: 171279.14 | AF3: 1.1443075 | AG3: 117 | AH3: 113 | AI3: 117 | AJ3: 21630.555 | AK3: 12752.848 | AL3: 18762.997 | AM3: 1628.5778 | AN3: 9497.1665 | AO3: 0 | AP3: 0 | AQ3: 0 | AR3: 0 | AS3: 0 | AT3: 0 | AU3: 0 | AV3: 0 | AW3: 0 | AX3: 0 | BI3: 0 | BJ3: 0 | BK3: 0 | BL3: 0 | BM3: 0 | BN3: 0 | BO3: 0 | BP3: 0 | BQ3: 195996 | BR3: 195996 | BS3: 1 | BT3: 42729.871 | BU3: 42729.871 | BV3: 21712.304 | BW3: 107006.99 | BX3: 107006.99 | BY3: 171449.17 | BZ3: 1.1431727 | CB3: 171449.17 | CC3: 1.1431727 | CD3: 167961.86 | CE3: 1.1669077
A4: 45750 | D4: KOLHK-香港-孙慧雪-Shukei-思维&无 | E4: - | F4: - | G4: - | H4: =I4 | I4: 80325.479 | J4: 892.50532 | K4: 90 | L4: 48 | M4: 50 | N4: 48 | O4: 35 | P4: 45 | Q4: 14 | R4: 20 | S4: 58432 | T4: 80360 | U4: 1 | V4: 4018 | W4: 0.53333333 | X4: 1 | Y4: 0.53333333 | Z4: 0.72916667 | AA4: 0.91836735 | AB4: 0.4 | AC4: 0.15555556 | AD4: 0.22222222 | AE4: 109746.72 | AF4: 0.73223143 | AG4: 49 | AH4: 45 | AI4: 47 | AJ4: 9968.2761 | AK4: 7405.9586 | AL4: 7204.5969 | AM4: 889.52324 | AN4: 3952.8892 | AO4: 0 | AP4: 0 | AQ4: 0 | AR4: 0 | AS4: 0 | AT4: 0 | AU4: 0 | AV4: 0 | AW4: 0 | AX4: 0 | BI4: 0 | BJ4: 0 | BK4: 0 | BL4: 0 | BM4: 0 | BN4: 0 | BO4: 0 | BP4: 0 | BQ4: 58432 | BR4: 80360 | BS4: 1 | BT4: 19555.481 | BU4: 16349.756 | BV4: 9968.2761 | BW4: 80325.479 | BX4: 80325.479 | BY4: 106643.51 | BZ4: 0.54791894 | CB4: 109849.24 | CC4: 0.7315481 | CD4: 106630.96 | CE4: 0.75362728
A5: 45780 | H5: =I5 | I5: 131098.62 | J5: 851.28974 | K5: 154 | L5: 63 | M5: 68 | N5: 68 | O5: 59 | P5: 68 | Q5: 25 | R5: 26 | S5: 120500 | T5: 124088 | U5: 1 | V5: 4772.6154 | W5: 0.40909091 | X5: 1.0793651 | Y5: 0.44155844 | Z5: 0.86764706 | AA5: 0.97142857 | AB5: 0.42372881 | AC5: 0.16233766 | AD5: 0.16883117 | AE5: 167935.16 | AF5: 0.73890421 | AG5: 70 | AH5: 68 | AI5: 74 | AJ5: 8731.2756 | AK5: 8345.1243 | AL5: 11900.352 | AM5: 1432.0761 | AN5: 6427.7168 | AO5: 0 | AP5: 0 | AQ5: 0 | AR5: 0 | AS5: 0 | AT5: 0 | AU5: 0 | AV5: 0 | AW5: 0 | AX5: 0 | BI5: 0 | BJ5: 0 | BK5: 0 | BL5: 0 | BM5: 0 | BN5: 0 | BO5: 0 | BP5: 0 | BQ5: 120500 | BR5: 124088 | BS5: 1 | BT5: 28105.269 | BU5: 26365.809 | BV5: 8731.2756 | BW5: 131098.62 | BX5: 131098.62 | BY5: 166195.7 | BZ5: 0.72504882 | CB5: 167935.16 | CC5: 0.73890421 | CD5: 170753.89 | CE5: 0.72670673
A6: 45811 | H6: 47816.49 | I6: 45304.246 | J6: 850.32616 | K6: 56 | L6: 27 | M6: 29 | N6: 29 | O6: 22 | P6: 31 | Q6: 9 | R6: 13 | S6: 50492 | T6: 67344 | U6: 1 | V6: 5180.3077 | W6: 0.48214286 | X6: 1.0740741 | Y6: 0.51785714 | Z6: 0.75862069 | AA6: 1 | AB6: 0.40909091 | AC6: 0.16071429 | AD6: 0.23214286 | AE6: 64518.734 | AF6: 1.0437899 | AG6: 31 | AH6: 31 | AI6: 37 | AJ6: 3492.9742 | AK6: 3259.1779 | AL6: 6500.9377 | AM6: 452.25177 | AN6: 3195.1273 | AO6: 20 | AP6: 9 | AQ6: 9 | AR6: 9 | AS6: 5 | AT6: 5 | AU6: 2 | AV6: 2 | AW6: 7987.2 | AX6: 7987.2 | AY6: 1 | AZ6: 3993.6 | BA6: 0.45 | BB6: 1 | BC6: 0.45 | BD6: 0.55555556 | BE6: 0.55555556 | BF6: 0.4 | BG6: 0.1 | BH6: 0.1 | BI6: 9 | BJ6: 5 | BK6: 7 | BL6: 1119.5699 | BM6: 809.61231 | BN6: 830.10519 | BO6: 161.51849 | BP6: 552.62717 | BQ6: 58479.2 | BR6: 75331.2 | BS6: 1 | BT6: 15761.358 | BU6: 12873.551 | BV6: 4612.5441 | BW6: 47816.49 | BX6: 47104.484 | BY6: 64590.578 | BZ6: 0.90538282 | CA6: 2512.2442 | CB6: 68190.392 | CC6: 1.1047187 | CD6: 69277.848 | CE6: 1.0873779
A7: 45842 | H7: 52997.374 | I7: 50605.35 | J7: 928.05021 | K7: 57 | L7: 24 | M7: 29 | N7: 26 | O7: 20 | P7: 32 | Q7: 11 | R7: 13 | S7: 56968 | T7: 64144 | U7: 1 | V7: 4934.1538 | W7: 0.42105263 | X7: 1.0833333 | Y7: 0.45614035 | Z7: 0.76923077 | AA7: 0.91428571 | AB7: 0.55 | AC7: 0.19298246 | AD7: 0.22807018 | AE7: 68601.979 | AF7: 0.93501675 | AG7: 35 | AH7: 32 | AI7: 34 | AJ7: 2508.2508 | AK7: 3043.0852 | AL7: 6568.2229 | AM7: 586.74653 | AN7: 2996.812 | AO7: 0 | AP7: 0 | AQ7: 1 | AR7: 0 | AS7: 0 | AT7: 1 | AU7: 0 | AV7: 1 | AW7: 0 | AX7: 1880 | AY7: 1 | AZ7: 1880 | BE7: 1 | BI7: 1 | BJ7: 1 | BK7: 1 | BL7: 0 | BM7: 94.86495 | BN7: 197.37392 | BO7: 0 | BP7: 82.183386 | BQ7: 56968 | BR7: 66024 | BS7: 1 | BT7: 13569.289 | BU7: 10789.548 | BV7: 2508.2508 | BW7: 52997.374 | BX7: 52546.014 | BY7: 65843.813 | BZ7: 0.86519898 | CA7: 2392.0239 | CB7: 69074.914 | CC7: 0.95583181 | CD7: 70841.663 | CE7: 0.93199393
A8: 45873 | H8: 17564.304 | I8: 16857.021 | J8: 1170.9536 | K8: 15 | L8: 6 | M8: 9 | N8: 6 | O8: 6 | P8: 14 | Q8: 2 | R8: 4 | S8: 12176 | T8: 21852 | U8: 1 | V8: 5463 | W8: 0.4 | X8: 1 | Y8: 0.4 | Z8: 1 | AA8: 1 | AB8: 0.33333333 | AC8: 0.13333333 | AD8: 0.26666667 | AE8: 23739.889 | AF8: 0.9204761 | AG8: 14 | AH8: 14 | AI8: 15 | AJ8: 1354.193 | AK8: 1111.6659 | AL8: 2237.603 | AM8: 150 | AN8: 1322.123 | AO8: 0 | AP8: 0 | AQ8: 0 | AR8: 0 | AS8: 0 | AT8: 0 | AU8: 0 | AV8: 0 | AW8: 0 | AX8: 0 | BI8: 0 | BJ8: 0 | BK8: 0 | BL8: 0 | BM8: 0 | BN8: 0 | BO8: 0 | BP8: 0 | BQ8: 12176 | BR8: 21852 | BS8: 1 | BT8: 4821.3918 | BU8: 2666.7589 | BV8: 1354.193 | BW8: 17564.304 | BX8: 17210.662 | BY8: 21231.614 | BZ8: 0.57348442 | CA8: 707.28265 | CB8: 23739.889 | CC8: 0.9204761 | CD8: 23510.696 | CE8: 0.92944932
A9: 45904 | H9: 905.74393 | I9: =H9-CA9 | J9: 226.43598 | K9: 4 | L9: 2 | M9: 2 | N9: 2 | O9: 2 | P9: 4 | Q9: 1 | R9: 2 | S9: 6088 | T9: 12176 | U9: 1 | V9: 6088 | W9: 0.5 | X9: 1 | Y9: 0.5 | Z9: 1 | AA9: 0.8 | AB9: 0.5 | AC9: 0.25 | AD9: 0.5 | AE9: 3329.7373 | AF9: 3.6567449 | AG9: 5 | AH9: 4 | AI9: 5 | AJ9: 303.07535 | AK9: 289.17842 | AL9: 1367.0914 | AM9: 40 | AN9: 424.64818 | AO9: 0 | AP9: 0 | AQ9: 0 | AR9: 0 | AS9: 0 | AT9: 0 | AU9: 0 | AV9: 0 | AW9: 0 | AX9: 0 | BI9: 0 | BJ9: 0 | BK9: 0 | BL9: 0 | BM9: 0 | BN9: 0 | BO9: 0 | BP9: 0 | BQ9: 6088 | BR9: 12176 | BS9: 1 | BT9: 2120.918 | BU9: 1267.513 | BV9: 303.07535 | BW9: 905.74393 | BX9: 727.10479 | BY9: 2297.6932 | BZ9: 2.649614 | CA9: 357.27827 | CB9: 3329.7373 | CC9: 3.6567449 | CD9: 3326.662 | CE9: 3.6601254
A10: 孙慧雪-汇总 | H10: =SUM(H3:H9) | I10: =SUM(I3:I9) | J10: =I10/K10 | K10: =SUM(K3:K9) | L10: =SUM(L3:L9) | M10: =SUM(M3:M9) | N10: =SUM(N3:N9) | O10: =SUM(O3:O9) | P10: =SUM(P3:P9) | Q10: =SUM(Q3:Q9) | R10: =SUM(R3:R9) | ... T10: =SUM(T3:T9) | V10: =T10/R10 | W10: =L10/K10 | X10: =N10/L10 | Y10: =N10/K10 | Z10: =O10/N10 | AA10: =AVERAGE(AA3:AA9) | AB10: =Q10/O10 | AC10: =Q10/K10 | AD10: =R10/K10 | AE10: =SUM(AE3:AE9) | AF10: =T10/AE10 | AG10: =SUM(AG3:AG9) | AH10: =SUM(AH3:AH9) | AI10: =SUM(AI3:AI9) | AJ10: =SUM(AJ3:AJ9) | AK10: =SUM(AK3:AK9) | AL10: =SUM(AL3:AL9) | AM10: =SUM(AM3:AM9) | AN10: =SUM(AN3:AN9) | ... AP10: =SUM(AP3:AP9) | AR10: =SUM(AR3:AR9) | AS10: =SUM(AS3:AS9) | AT10: =SUM(AT3:AT9) | AU10: =SUM(AU3:AU9) | AV10: =SUM(AV3:AV9) | AW10: =SUM(AW3:AW9) | AX10: =SUM(AX3:AX9) | AZ10: =AX10/AV10 | BA10: =AP10/AO10 | BB10: =AR10/AP10 | BC10: =AR10/AO10 | BD10: =AS10/AR10 | BE10: =AVERAGE(BE3:BE9) | BF10: =AU10/AS10 | BG10: =AU10/AO10 | BH10: =AV10/AO10 | BI10: =SUM(BI3:BI9) | BJ10: =SUM(BJ3:BJ9) | BK10: =SUM(BK3:BK9) | BL10: =SUM(BL3:BL9) | BM10: =SUM(BM3:BM9) | BN10: =SUM(BN3:BN9) | BO10: =SUM(BO3:BO9) | BP10: =SUM(BP3:BP9) | ... BR10: =SUM(BR3:BR9) | BT10: =SUM(BT3:BT9) | BU10: =SUM(BU3:BU9) | BV10: =SUM(BV3:BV9) | BW10: =SUM(BW3:BW9) | BX10: =SUM(BX3:BX9) | BY10: =SUM(BY3:BY9) | BZ10: =BQ10/BY10 | CA10: =SUM(CA3:CA9) | CB10: =SUM(CB3:CB9) | CC10: =BR10/CB10 | CD10: =SUM(CD3:CD9) | CE10: =BR10/CD10

Sheet 陈倩扬
I1: 主投 | AO1: 辅投 | BQ1: 汇总
B2: 渠道组 | C2: 供应商 | D2: 渠道名称 | E2: 主投 | F2: 辅投 | G2: 结算方式 | H2: 滚动消耗 | I2: 滚动消耗(不含赠课成本) | J2: 单例子成本 | K2: 例子数 | L2: 分发数 | M2: 剔除毛例子 分发数 | N2: 约课数 | O2: 到课数 | P2: 滚动到课数 | Q2: 当月成交数 | R2: 滚动成交数 | S2: 当月GMV | T2: 滚动GMV | U2: 海外GMV占比 | V2: 滚动ASP | W2: 例子分发率 | X2: 分发约课率 | Y2: 例子约课率 | Z2: 约课到课率 | AA2: 滚动应到课率 | AB2: 到课转化率 | AC2: 注册转化率 | AD2: 滚动转化率 | AE2: 滚动ROI2总成本 | AF2: 滚动ROI2 | AG2: 滚动应到课人数 | AH2: 滚动到课人数 | AI2: 滚动到课人次 | AJ2: 运营成本 | AK2: 销售固定成本 | AL2: 销售变动成本 | AM2: TMK费用 | AN2: DEMO费用 | AO2: 例子数 | AP2: 分发数 | AQ2: 剔除毛例子分发数 | AR2: 约课数 | AS2: 到课数 | AT2: 滚动到课数 | AU2: 当月成交 | AV2: 滚动成交数 | AW2: 当月GMV | AX2: 滚动GMV | AY2: 海外GMV占比 | AZ2: 滚动ASP | BA2: 例子分发率 | BB2: 分发约课率 | BC2: 例子约课率 | BD2: 约课到课率 | BE2: 滚动应到课率 | BF2: 到课转化率 | BG2: 注册转化率 | BH2: 滚动转化率 | BI2: 滚动应到课人数 | BJ2: 滚动到课人数 | BK2: 滚动到课人次 | BL2: 运营成本 | BM2: 销售固定成本 | BN2: 销售变动成本 | BO2: TMK费用 | BP2: DEMO费用 | BQ2: 当月GMV | BR2: 滚动GMV | BS2: 海外GMV占比 | BT2: 滚动其他成本 | BU2: 同源其他成本 | BV2: 运营成本 | BW2: 滚动消耗 | BX2: 同源消耗 | BY2: 当月ROI2总成本 | BZ2: 当月ROI2 | CA2: 滚动赠课成本 | CB2: 滚动ROI2总成本 | CC2: 滚动ROI2 | CD2: O-ROI总成本 | CE2: O-ROI
A3: 45718 | C3: 陈倩扬 | D3: KOLHK-香港-陈倩扬Skye-Shukei-思维&无 | E3: - | F3: - | G3: - | H3: =I3 | I3: 92998.238 | J3: 522.46201 | K3: 178 | L3: 84 | M3: 84 | N3: 97 | O3: 79 | P3: 79 | Q3: 33 | R3: 33 | S3: 156665.2 | T3: 156665.2 | U3: 1 | V3: 4747.4303 | W3: 0.47191011 | X3: 1.1547619 | Y3: 0.54494382 | Z3: 0.81443299 | AA3: 0.97530864 | AB3: 0.41772152 | AC3: 0.18539326 | AD3: 0.18539326 | AE3: 140389 | AF3: 1.1159365 | AG3: 81 | AH3: 79 | AI3: 86 | AJ3: 15910.078 | AK3: 8304.1801 | AL3: 14997.799 | AM3: 1197.8795 | AN3: 6980.8232 | AO3: 0 | AP3: 0 | AQ3: 0 | AR3: 0 | AS3: 0 | AT3: 0 | AU3: 0 | AV3: 0 | AW3: 0 | AX3: 0 | BI3: 0 | BJ3: 0 | BK3: 0 | BL3: 0 | BM3: 0 | BN3: 0 | BO3: 0 | BP3: 0 | BQ3: 156665.2 | BR3: 156665.2 | BS3: 1 | BT3: 31568.964 | BU3: 31568.964 | BV3: 15991.826 | BW3: 92998.238 | BX3: 92998.238 | BY3: 140559.03 | BZ3: 1.1145865 | CB3: 140559.03 | CC3: 1.1145865 | CD3: 137992.2 | CE3: 1.1353192
A4: 45750 | D4: KOLHK-香港-陈倩扬Skye-Shukei-思维&无 | E4: 思维 | F4: - | G4: CPT | H4: =I4 | I4: 48781.331 | J4: 1084.0296 | K4: 45 | L4: 28 | M4: 31 | N4: 29 | O4: 21 | P4: 28 | Q4: 5 | R4: 11 | S4: 23940 | T4: 45568 | U4: 1 | V4: 4142.5455 | W4: 0.62222222 | X4: 1.0357143 | Y4: 0.64444444 | Z4: 0.72413793 | AA4: 0.93333333 | AB4: 0.23809524 | AC4: 0.11111111 | AD4: 0.24444444 | AE4: 65326.296 | AF4: 0.69754453 | AG4: 30 | AH4: 28 | AI4: 29 | AJ4: 4984.1381 | AK4: 4591.6944 | AL4: 4085.3543 | AM4: 444.76162 | AN4: 2439.0168 | AO4: 0 | AP4: 0 | AQ4: 0 | AR4: 0 | AS4: 0 | AT4: 0 | AU4: 0 | AV4: 0 | AW4: 0 | AX4: 0 | BI4: 0 | BJ4: 0 | BK4: 0 | BL4: 0 | BM4: 0 | BN4: 0 | BO4: 0 | BP4: 0 | BQ4: 23940 | BR4: 45568 | BS4: 1 | BT4: 12047.293 | BU4: 8888.5526 | BV4: 5193.4319 | BW4: 48781.331 | BX4: 48781.331 | BY4: 62863.315 | BZ4: 0.38082624 | CB4: 66022.055 | CC4: 0.6901936 | CD4: 64353.623 | CE4: 0.70808756
A5: 45780 | H5: =I5 | I5: 69042.51 | J5: 793.59207 | K5: 87 | L5: 44 | M5: 45 | N5: 44 | O5: 34 | P5: 42 | Q5: 11 | R5: 15 | S5: 47868 | T5: 69111.2 | U5: 1 | V5: 4607.4133 | W5: 0.50574713 | X5: 1 | Y5: 0.50574713 | Z5: 0.77272727 | AA5: 0.91304348 | AB5: 0.32352941 | AC5: 0.12643678 | AD5: 0.17241379 | AE5: 91364.504 | AF5: 0.75643381 | AG5: 46 | AH5: 42 | AI5: 51 | AJ5: 4932.6037 | AK5: 5522.5087 | AL5: 6627.9381 | AM5: 809.02998 | AN5: 4429.9129 | AO5: 0 | AP5: 0 | AQ5: 0 | AR5: 0 | AS5: 0 | AT5: 0 | AU5: 0 | AV5: 0 | AW5: 0 | AX5: 0 | BI5: 0 | BJ5: 0 | BK5: 0 | BL5: 0 | BM5: 0 | BN5: 0 | BO5: 0 | BP5: 0 | BQ5: 47868 | BR5: 69111.2 | BS5: 1 | BT5: 17389.39 | BU5: 14187.059 | BV5: 4932.6037 | BW5: 69042.51 | BX5: 69042.51 | BY5: 88162.172 | BZ5: 0.54295395 | CB5: 91364.504 | CC5: 0.75643381 | CD5: 92956.9 | CE5: 0.74347574
A6: 45811 | H6: 5499.1814 | I6: 4609.174 | J6: 549.91814 | K6: 10 | L6: 3 | M6: 3 | N6: 3 | O6: 3 | P6: 8 | Q6: 2 | R6: 5 | S6: 9776 | T6: 21340 | U6: 1 | V6: 4268 | W6: 0.3 | X6: 1 | Y6: 0.3 | Z6: 1 | AA6: 1 | AB6: 0.66666667 | AC6: 0.2 | AD6: 0.5 | AE6: 9378.0558 | AF6: 2.2755249 | AG6: 8 | AH6: 8 | AI6: 9 | AJ6: 623.7454 | AK6: 337.15634 | AL6: 2060.0203 | AM6: 80.759244 | AN6: 777.19314 | AO6: 0 | AP6: 0 | AQ6: 0 | AR6: 0 | AS6: 0 | AT6: 0 | AU6: 0 | AV6: 0 | AW6: 0 | AX6: 0 | BI6: 0 | BJ6: 0 | BK6: 0 | BL6: 0 | BM6: 0 | BN6: 0 | BO6: 0 | BP6: 0 | BQ6: 9776 | BR6: 21340 | BS6: 1 | BT6: 3530.1415 | BU6: 1895.7018 | BV6: 735.70239 | BW6: 5499.1814 | BX6: 4965.1769 | BY6: 7596.5811 | BZ6: 1.2868947 | CA6: 890.00741 | CB6: 9765.0253 | CC6: 2.1853502 | CD6: 9929.3229 | CE6: 2.1491899
A8: 陈倩扬-汇总 | H8: =SUM(H3:H7) | I8: =SUM(I3:I7) | J8: =I8/K8 | K8: =SUM(K3:K7) | L8: =SUM(L3:L7) | M8: =SUM(M3:M7) | N8: =SUM(N3:N7) | O8: =SUM(O3:O7) | P8: =SUM(P3:P7) | Q8: =SUM(Q3:Q7) | R8: =SUM(R3:R7) | ... T8: =SUM(T3:T7) | V8: =T8/R8 | W8: =L8/K8 | X8: =N8/L8 | Y8: =N8/K8 | Z8: =O8/N8 | AA8: =AVERAGE(AA3:AA7) | AB8: =Q8/O8 | AC8: =Q8/K8 | AD8: =R8/K8 | AE8: =SUM(AE3:AE7) | AF8: =T8/AE8 | AG8: =SUM(AG3:AG7) | AH8: =SUM(AH3:AH7) | AI8: =SUM(AI3:AI7) | AJ8: =SUM(AJ3:AJ7) | AK8: =SUM(AK3:AK7) | AL8: =SUM(AL3:AL7) | AM8: =SUM(AM3:AM7) | AN8: =SUM(AN3:AN7) | ... AP8: =SUM(AP3:AP7) | AR8: =SUM(AR3:AR7) | AS8: =SUM(AS3:AS7) | AT8: =SUM(AT3:AT7) | AU8: =SUM(AU3:AU7) | AV8: =SUM(AV3:AV7) | AW8: =SUM(AW3:AW7) | AX8: =SUM(AX3:AX7) | AZ8: =AX8/AV8 | BA8: =AP8/AO8 | BB8: =AR8/AP8 | BC8: =AR8/AO8 | BD8: =AS8/AR8 | BE8: =AVERAGE(BE3:BE7) | BF8: =AU8/AS8 | BG8: =AU8/AO8 | BH8: =AV8/AO8 | BI8: =SUM(BI3:BI7) | BJ8: =SUM(BJ3:BJ7) | BK8: =SUM(BK3:BK7) | BL8: =SUM(BL3:BL7) | BM8: =SUM(BM3:BM7) | BN8: =SUM(BN3:BN7) | BO8: =SUM(BO3:BO7) | BP8: =SUM(BP3:BP7) | ... BR8: =SUM(BR3:BR7) | BT8: =SUM(BT3:BT7) | BU8: =SUM(BU3:BU7) | BV8: =SUM(BV3:BV7) | BW8: =SUM(BW3:BW7) | BX8: =SUM(BX3:BX7) | BY8: =SUM(BY3:BY7) | BZ8: =BQ8/BY8 | CA8: =SUM(CA3:CA7) | CB8: =SUM(CB3:CB7) | CC8: =BR8/CB8 | CD8: =SUM(CD3:CD7) | CE8: =BR8/CD8

Sheet Bob
I1: 主投 | AR1: 辅投 | BW1: 汇总
B2: 渠道组 | C2: 供应商 | D2: 渠道名称 | E2: 主投 | F2: 辅投 | G2: 结算方式 | H2: 滚动消耗 | I2: 滚动消耗(不含赠课成本) | J2: 单例子成本 | K2: 例子数 | L2: 分发数 | M2: 剔除毛例子 分发数 | N2: 约课数 | Q2: 到课数 | R2: 滚动到课数 | S2: 当月成交数 | T2: 滚动成交数 | U2: 当月GMV | V2: 滚动GMV | W2: 海外GMV占比 | X2: 滚动ASP | Y2: 例子分发率 | Z2: 分发约课率 | AA2: 例子约课率 | AB2: 约课到课率 | AD2: 滚动应到课率 | AE2: 到课转化率 | AF2: 注册转化率 | AG2: 滚动转化率 | AH2: 滚动ROI2总成本 | AI2: 滚动ROI2 | AJ2: 滚动应到课人数 | AK2: 滚动到课人数 | AL2: 滚动到课人次 | AM2: 运营成本 | AN2: 销售固定成本 | AO2: 销售变动成本 | AP2: TMK费用 | AQ2: DEMO费用 | AR2: 例子数 | AS2: 分发数 | AT2: 剔除毛例子分发数 | AU2: 约课数 | AX2: 到课数 | AY2: 滚动到课数 | AZ2: 当月成交 | BA2: 滚动成交数 | BB2: 当月GMV | BC2: 滚动GMV | BD2: 海外GMV占比 | BE2: 滚动ASP | BF2: 例子分发率 | BG2: 分发约课率 | BH2: 例子约课率 | BI2: 约课到课率 | BK2: 滚动应到课率 | BL2: 到课转化率 | BM2: 注册转化率 | BN2: 滚动转化率 | BO2: 滚动应到课人数 | BP2: 滚动到课人数 | BQ2: 滚动到课人次 | BR2: 运营成本 | BS2: 销售固定成本 | BT2: 销售变动成本 | BU2: TMK费用 | BV2: DEMO费用 | BW2: 当月GMV | BX2: 滚动GMV | BY2: 海外GMV占比 | BZ2: 滚动其他成本 | CA2: 同源其他成本 | CB2: 运营成本 | CC2: 滚动消耗 | CD2: 同源消耗 | CE2: 当月ROI2总成本 | CF2: 当月ROI2 | CG2: 滚动赠课成本 | CH2: 滚动ROI2总成本 | CI2: 滚动ROI2 | CJ2: O-ROI总成本 | CK2: O-ROI
A4: 45750 | D4: KOLHK-香港-Bob林盛斌-Shukei-思维&无01 | E4: - | F4: - | G4: - | H4: =I4 | I4: 46341.657 | J4: 311.01783 | K4: 149 | L4: 82 | M4: 82 | N4: 79 | Q4: 57 | R4: 57 | S4: 22 | T4: 22 | U4: 96736 | V4: 96736 | W4: 1 | X4: 4397.0909 | Y4: 0.55033557 | Z4: 0.96341463 | AA4: 0.53020134 | AB4: 0.72151899 | AD4: 0.96610169 | AE4: 0.38596491 | AF4: 0.14765101 | AG4: 0.14765101 | AH4: 90013.923 | AI4: 1.0746782 | AJ4: 59 | AK4: 57 | AL4: 58 | AM4: 16503.035 | AN4: 12145.772 | AO4: 8672.7711 | AP4: 1472.6551 | AQ4: 4878.0335 | AR4: 0 | AS4: 0 | AT4: 0 | AU4: 0 | AX4: 0 | AY4: 0 | AZ4: 0 | BA4: 0 | BB4: 0 | BC4: 0 | BO4: 0 | BP4: 0 | BQ4: 0 | BR4: 0 | BS4: 0 | BT4: 0 | BU4: 0 | BV4: 0 | BW4: 96736 | BX4: 96736 | BY4: 1 | BZ4: 27169.232 | CA4: 27169.232 | CB4: 16503.035 | CC4: 46341.657 | CD4: 46341.657 | CE4: 90013.923 | CF4: 1.0746782 | CH4: 90013.923 | CI4: 1.0746782 | CJ4: 84685.889 | CK4: 1.1422918
A5: 45780 | H5: =I5 | I5: 164736.25 | J5: 752.22034 | K5: 219 | L5: 85 | M5: 92 | N5: 89 | Q5: 68 | R5: 86 | S5: 23 | T5: 27 | U5: 131124 | V5: 145576 | W5: 1 | X5: 5391.7037 | Y5: 0.38812785 | Z5: 1.0470588 | AA5: 0.40639269 | AB5: 0.76404494 | AD5: 0.97727273 | AE5: 0.33823529 | AF5: 0.10502283 | AG5: 0.12328767 | AH5: 212258.39 | AI5: 0.68584332 | AJ5: 88 | AK5: 86 | AL5: 90 | AM5: 12416.554 | AN5: 11290.462 | AO5: 13961.105 | AP5: 2036.5237 | AQ5: 7817.4934 | AR5: 0 | AS5: 0 | AT5: 0 | AU5: 0 | AX5: 0 | AY5: 0 | AZ5: 0 | BA5: 0 | BB5: 0 | BC5: 0 | BO5: 0 | BP5: 0 | BQ5: 0 | BR5: 0 | BS5: 0 | BT5: 0 | BU5: 0 | BV5: 0 | BW5: 131124 | BX5: 145576 | BY5: 1 | BZ5: 35105.584 | CA5: 31210.185 | CB5: 12416.554 | CC5: 164736.25 | CD5: 164736.25 | CE5: 208362.99 | CF5: 0.62930561 | CH5: 212258.39 | CI5: 0.68584332 | CJ5: 216266.84 | CK5: 0.6731314
A6: 45811 | H6: 105682.87 | I6: 100124.38 | J6: 974.87429 | K6: 108 | L6: 66 | M6: 70 | N6: 69 | Q6: 54 | R6: 63 | S6: 23 | T6: 29 | U6: 124424 | V6: 155552 | W6: 1 | X6: 5363.8621 | Y6: 0.61111111 | Z6: 1.0454545 | AA6: 0.63888889 | AB6: 0.7826087 | AD6: 0.92647059 | AE6: 0.42592593 | AF6: 0.21296296 | AG6: 0.26851852 | AH6: 141650.13 | AI6: 1.0981423 | AJ6: 68 | AK6: 63 | AL6: 68 | AM6: 6736.4503 | AN6: 7866.9813 | AO6: 15015.946 | AP6: 872.19983 | AQ6: 5872.1259 | AR6: 72 | AS6: 32 | AT6: 32 | AU6: 32 | AX6: 24 | AY6: 24 | AZ6: 4 | BA6: 4 | BB6: 13404.4 | BC6: 13404.4 | BD6: 1 | BE6: 3351.1 | BF6: 0.44444444 | BG6: 1 | BH6: 0.44444444 | BI6: 0.75 | BK6: 0.75 | BL6: 0.16666667 | BM6: 0.055555556 | BN6: 0.055555556 | BO6: 32 | BP6: 24 | BQ6: 28 | BR6: 4030.4518 | BS6: 2878.6215 | BT6: 1393.1117 | BU6: 581.46656 | BV6: 2210.5087 | BW6: 137828.4 | BX6: 168956.4 | BY6: 1 | BZ6: 36690.961 | CA6: 32372.983 | CB6: 10766.902 | CC6: 105682.87 | CD6: 104614.86 | CE6: 147754.75 | CF6: 0.93281875 | CG6: 5558.4929 | CH6: 153140.74 | CI6: 1.1032754 | CJ6: 155873.83 | CK6: 1.0839305
A7: 45842 | H7: 53515.038 | I7: 52280.07 | J7: 1274.1676 | K7: 42 | L7: 21 | M7: 28 | N7: 21 | Q7: 18 | R7: 25 | S7: 4 | T7: 7 | U7: 26852 | V7: 44916 | W7: 1 | X7: 6416.5714 | Y7: 0.5 | Z7: 1 | AA7: 0.5 | AB7: 0.85714286 | AD7: 0.96153846 | AE7: 0.22222222 | AF7: 0.095238095 | AG7: 0.16666667 | AH7: 65977.272 | AI7: 0.68077989 | AJ7: 26 | AK7: 25 | AL7: 30 | AM7: 1848.1848 | AN7: 2938.1512 | AO7: 4599.3125 | AP7: 432.33955 | AQ7: 2644.2459 | AR7: 0 | AS7: 0 | AT7: 0 | AU7: 0 | AX7: 0 | AY7: 1 | AZ7: 0 | BA7: 0 | BB7: 0 | BC7: 0 | BK7: 1 | BO7: 1 | BP7: 1 | BQ7: 1 | BR7: 0 | BS7: 0 | BT7: 0 | BU7: 0 | BV7: 82.183386 | BW7: 26852 | BX7: 44916 | BY7: 1 | BZ7: 10696.233 | CA7: 7236.5186 | CB7: 1848.1848 | CC7: 53515.038 | CD7: 52985.766 | CE7: 62070.469 | CF7: 0.43260507 | CG7: 1234.9678 | CH7: 66059.455 | CI7: 0.67993295 | CJ7: 67361.27 | CK7: 0.66679265
A8: 45962 | H8: 21854.973 | I8: =H8-CG8 | J8: 1986.8157 | K8: 11 | L8: 4 | M8: 4 | N8: 4 | Q8: 2 | R8: 2 | S8: 2 | T8: 2 | U8: 10598 | V8: 10598 | W8: 1 | X8: 5299 | Y8: 0.36363636 | Z8: 1 | AA8: 0.36363636 | AB8: 0.5 | AD8: 1 | AE8: 1 | AF8: 0.18181818 | AG8: 0.18181818 | AH8: 24573.529 | AI8: 0.43127709 | AJ8: 2 | AK8: 2 | AL8: 3 | AM8: 716.02863 | AN8: 472.43186 | AO8: 1165.7979 | AP8: 110 | AQ8: 254.29771 | AR8: 0 | AS8: 0 | AT8: 0 | AU8: 0 | AX8: 0 | AY8: 0 | AZ8: 0 | BA8: 0 | BB8: 0 | BC8: 0 | BO8: 0 | BP8: 0 | BQ8: 0 | BR8: 0 | BS8: 0 | BT8: 0 | BU8: 0 | BV8: 0 | BW8: 10598 | BX8: 10598 | BY8: 1 | BZ8: 2002.5275 | CA8: 2002.5275 | CB8: 716.02863 | CC8: 21854.973 | CD8: 21854.973 | CE8: 24573.529 | CF8: 0.43127709 | CG8: 357.44471 | CH8: 24573.529 | CI8: 0.43127709 | CJ8: 24682.5 | CK8: 0.42937303
A9: 45992 | H9: 7697.7969 | I9: =H9-CG9 | J9: 2565.9323 | K9: 3 | L9: 1 | M9: 1 | N9: 1 | O9: 1 | P9: 1 | Q9: 1 | R9: 1 | S9: 1 | T9: 1 | U9: 5299 | V9: 5299 | W9: 1 | X9: 5299 | Y9: 0.33333333 | Z9: 1 | AA9: 0.33333333 | AB9: 1 | AC9: 1 | AD9: 1 | AE9: 1 | AF9: 0.33333333 | AG9: 0.33333333 | AH9: 8759.6463 | AI9: 0.6049331 | AJ9: 1 | AK9: 1 | AL9: 1 | AM9: 209.56949 | AN9: 130.28899 | AO9: 609.73789 | AP9: 30 | AQ9: 82.25303 | AR9: 0 | AS9: 0 | AT9: 0 | AU9: 0 | AV9: 0 | AW9: 0 | AX9: 0 | AY9: 0 | AZ9: 0 | BA9: 0 | BB9: 0 | BC9: 0 | BO9: 0 | BP9: 0 | BQ9: 0 | BR9: 0 | BS9: 0 | BT9: 0 | BU9: 0 | BV9: 0 | BW9: 5299 | BX9: 5299 | BY9: 1 | BZ9: 852.27991 | CA9: 852.27991 | CB9: 209.56949 | CC9: 7697.7969 | CD9: 7697.7969 | CE9: 8759.6463 | CF9: 0.6049331 | CG9: 195.13931 | CH9: 8759.6463 | CI9: 0.6049331 | CJ9: 8775.0768 | CK9: 0.60386936
A10: bob-汇总 | H10: =SUM(H3:H9) | I10: =SUM(I3:I9) | J10: =I10/K10 | K10: =SUM(K3:K9) | L10: =SUM(L3:L9) | M10: =SUM(M3:M9) | N10: =SUM(N3:N9) | Q10: =SUM(Q3:Q9) | R10: =SUM(R3:R9) | S10: =SUM(S3:S9) | T10: =SUM(T3:T9) | U10: =SUM(U3:U9) | V10: =SUM(V3:V9) | X10: =V10/T10 | Y10: =L10/K10 | Z10: =N10/L10 | AA10: =N10/K10 | AB10: =Q10/N10 | AD10: =AVERAGE(AD3:AD9) | AE10: =S10/Q10 | AF10: =S10/K10 | AG10: =T10/K10 | AH10: =SUM(AH3:AH9) | AI10: =V10/AH10 | AJ10: =SUM(AJ3:AJ9) | AK10: =SUM(AK3:AK9) | AL10: =SUM(AL3:AL9) | AM10: =SUM(AM3:AM9) | AN10: =SUM(AN3:AN9) | AO10: =SUM(AO3:AO9) | AP10: =SUM(AP3:AP9) | AQ10: =SUM(AQ3:AQ9) | ... AS10: =SUM(AS3:AS9) | AU10: =SUM(AU3:AU9) | AX10: =SUM(AX3:AX9) | AY10: =SUM(AY3:AY9) | AZ10: =SUM(AZ3:AZ9) | BA10: =SUM(BA3:BA9) | BB10: =SUM(BB3:BB9) | BC10: =SUM(BC3:BC9) | BE10: =BC10/BA10 | BF10: =AS10/AR10 | BG10: =AU10/AS10 | BH10: =AU10/AR10 | BI10: =AX10/AU10 | BK10: =AVERAGE(BK3:BK9) | BL10: =AZ10/AX10 | BM10: =AZ10/AR10 | BN10: =BA10/AR10 | BO10: =SUM(BO3:BO9) | BP10: =SUM(BP3:BP9) | BQ10: =SUM(BQ3:BQ9) | BR10: =SUM(BR3:BR9) | BS10: =SUM(BS3:BS9) | BT10: =SUM(BT3:BT9) | BU10: =SUM(BU3:BU9) | BV10: =SUM(BV3:BV9) | ... BX10: =SUM(BX3:BX9) | BZ10: =SUM(BZ3:BZ9) | CA10: =SUM(CA3:CA9) | CB10: =SUM(CB3:CB9) | CC10: =SUM(CC3:CC9) | CD10: =SUM(CD3:CD9) | CE10: =SUM(CE3:CE9) | CF10: =BW10/CE10 | CG10: =SUM(CG3:CG9) | CH10: =SUM(CH3:CH9) | CI10: =BX10/CH10 | CJ10: =SUM(CJ3:CJ9) | CK10: =BX10/CJ10

Sheet 叶翠翠
I1: 主投 | AO1: 辅投 | BQ1: 汇总
B2: 渠道组 | C2: 供应商 | D2: 渠道名称 | E2: 主投 | F2: 辅投 | G2: 结算方式 | H2: 滚动消耗 | I2: 滚动消耗(不含赠课成本) | J2: 单例子成本 | K2: 例子数 | L2: 分发数 | M2: 剔除毛例子 分发数 | N2: 约课数 | O2: 到课数 | P2: 滚动到课数 | Q2: 当月成交数 | R2: 滚动成交数 | S2: 当月GMV | T2: 滚动GMV | U2: 海外GMV占比 | V2: 滚动ASP | W2: 例子分发率 | X2: 分发约课率 | Y2: 例子约课率 | Z2: 约课到课率 | AA2: 滚动应到课率 | AB2: 到课转化率 | AC2: 注册转化率 | AD2: 滚动转化率 | AE2: 滚动ROI2总成本 | AF2: 滚动ROI2 | AG2: 滚动应到课人数 | AH2: 滚动到课人数 | AI2: 滚动到课人次 | AJ2: 运营成本 | AK2: 销售固定成本 | AL2: 销售变动成本 | AM2: TMK费用 | AN2: DEMO费用 | AO2: 例子数 | AP2: 分发数 | AQ2: 剔除毛例子分发数 | AR2: 约课数 | AS2: 到课数 | AT2: 滚动到课数 | AU2: 当月成交 | AV2: 滚动成交数 | AW2: 当月GMV | AX2: 滚动GMV | AY2: 海外GMV占比 | AZ2: 滚动ASP | BA2: 例子分发率 | BB2: 分发约课率 | BC2: 例子约课率 | BD2: 约课到课率 | BE2: 滚动应到课率 | BF2: 到课转化率 | BG2: 注册转化率 | BH2: 滚动转化率 | BI2: 滚动应到课人数 | BJ2: 滚动到课人数 | BK2: 滚动到课人次 | BL2: 运营成本 | BM2: 销售固定成本 | BN2: 销售变动成本 | BO2: TMK费用 | BP2: DEMO费用 | BQ2: 当月GMV | BR2: 滚动GMV | BS2: 海外GMV占比 | BT2: 滚动其他成本 | BU2: 同源其他成本 | BV2: 运营成本 | BW2: 滚动消耗 | BX2: 同源消耗 | BY2: 当月ROI2总成本 | BZ2: 当月ROI2 | CA2: 滚动赠课成本 | CB2: 滚动ROI2总成本 | CC2: 滚动ROI2 | CD2: O-ROI总成本 | CE2: O-ROI
A4: 45750 | D4: KOLHK-香港-Tracy葉翠翠-Shukei-思维&无 | E4: - | F4: - | G4: - | H4: =I4 | I4: 15480.518 | J4: 418.39239 | K4: 37 | L4: 15 | M4: 15 | N4: 15 | O4: 9 | P4: 9 | Q4: 4 | R4: 4 | S4: 16752 | T4: 16752 | U4: 1 | V4: 4188 | W4: 0.40540541 | X4: 1 | Y4: 0.40540541 | Z4: 0.6 | AA4: 1 | AB4: 0.44444444 | AC4: 0.10810811 | AD4: 0.10810811 | AE4: 24424.888 | AF4: 0.6858578 | AG4: 9 | AH4: 9 | AI4: 9 | AJ4: 4098.0691 | AK4: 2221.7876 | AL4: 1501.8841 | AM4: 365.69289 | AN4: 756.93623 | AO4: 0 | AP4: 0 | AQ4: 0 | AR4: 0 | AS4: 0 | AT4: 0 | AU4: 0 | AV4: 0 | AW4: 0 | AX4: 0 | BI4: 0 | BJ4: 0 | BK4: 0 | BL4: 0 | BM4: 0 | BN4: 0 | BO4: 0 | BP4: 0 | BQ4: 16752 | BR4: 16752 | BS4: 1 | BT4: 4846.3008 | BU4: 4846.3008 | BV4: 4098.0691 | BW4: 15480.518 | BX4: 15480.518 | BY4: 24424.888 | BZ4: 0.6858578 | CB4: 24424.888 | CC4: 0.6858578 | CD4: 23101.819 | CE4: 0.7251377
A5: 45780 | H5: =I5 | I5: 73876.847 | J5: 1191.562 | K5: 62 | L5: 29 | M5: 32 | N5: 28 | O5: 18 | P5: 24 | Q5: 5 | R5: 5 | S5: 18140 | T5: 18140 | U5: 1 | V5: 3628 | W5: 0.46774194 | X5: 0.96551724 | Y5: 0.4516129 | Z5: 0.64285714 | AA5: 0.88888889 | AB5: 0.27777778 | AC5: 0.080645161 | AD5: 0.080645161 | AE5: 85893.762 | AF5: 0.21119112 | AG5: 27 | AH5: 24 | AI5: 26 | AJ5: 3515.1889 | AK5: 3927.1173 | AL5: 1739.6717 | AM5: 576.5501 | AN5: 2258.387 | AO5: 0 | AP5: 0 | AQ5: 0 | AR5: 0 | AS5: 0 | AT5: 0 | AU5: 0 | AV5: 0 | AW5: 0 | AX5: 0 | BI5: 0 | BJ5: 0 | BK5: 0 | BL5: 0 | BM5: 0 | BN5: 0 | BO5: 0 | BP5: 0 | BQ5: 18140 | BR5: 18140 | BS5: 1 | BT5: 8501.7261 | BU5: 7438.6705 | BV5: 3515.1889 | BW5: 73876.847 | BX5: 73876.847 | BY5: 84830.706 | BZ5: 0.21383766 | CB5: 85893.762 | CC5: 0.21119112 | CD5: 87028.573 | CE5: 0.20843729
A6: 45811 | H6: 27427.561 | I6: 26537.554 | J6: 2285.6301 | K6: 12 | L6: 7 | M6: 7 | N6: 7 | O6: 7 | P6: 8 | Q6: 4 | R6: 5 | S6: 14252 | T6: 17840 | U6: 1 | V6: 3568 | W6: 0.58333333 | X6: 1 | Y6: 0.58333333 | Z6: 1 | AA6: 0.88888889 | AB6: 0.57142857 | AC6: 0.33333333 | AD6: 0.41666667 | AE6: 31472.657 | AF6: 0.56684124 | AG6: 9 | AH6: 8 | AI6: 8 | AJ6: 748.49447 | AK6: 786.69813 | AL6: 1722.1538 | AM6: 96.911093 | AN6: 690.83835 | AO6: 0 | AP6: 0 | AQ6: 0 | AR6: 0 | AS6: 0 | AT6: 0 | AU6: 0 | AV6: 0 | AW6: 0 | AX6: 0 | BI6: 0 | BJ6: 0 | BK6: 0 | BL6: 0 | BM6: 0 | BN6: 0 | BO6: 0 | BP6: 0 | BQ6: 14252 | BR6: 17840 | BS6: 1 | BT6: 3296.6014 | BU6: 2863.8852 | BV6: 748.49447 | BW6: 27427.561 | BX6: 27249.56 | BY6: 30861.939 | BZ6: 0.46179859 | CA6: 890.00741 | CB6: 31472.657 | CC6: 0.56684124 | CD6: 31624.162 | CE6: 0.56412561
A7: 45842 | H7: 13816.424 | I7: 13640 | K7: 0 | L7: 0 | M7: 1 | N7: 0 | O7: 0 | P7: 1 | Q7: 0 | R7: 1 | S7: 0 | T7: 3588 | U7: 1 | V7: 3588 | AA7: 1 | AE7: 14376.904 | AF7: 0.24956695 | AG7: 1 | AH7: 1 | AI7: 1 | AJ7: 0 | AK7: 104.93397 | AL7: 367.40434 | AM7: 0 | AN7: 88.141531 | AO7: 0 | AP7: 0 | AQ7: 0 | AR7: 0 | AS7: 0 | AT7: 0 | AU7: 0 | AV7: 0 | AW7: 0 | AX7: 0 | BI7: 0 | BJ7: 0 | BK7: 0 | BL7: 0 | BM7: 0 | BN7: 0 | BO7: 0 | BP7: 0 | BQ7: 0 | BR7: 3588 | BS7: 1 | BT7: 560.47984 | BU7: 0 | BV7: 0 | BW7: 13816.424 | BX7: 13640 | BY7: 13640 | CA7: 176.42398 | CB7: 14376.904 | CC7: 0.24956695 | CD7: 14376.904 | CE7: 0.24956695
A8: 叶翠翠-汇总 | H8: =SUM(H3:H7) | I8: =SUM(I3:I7) | J8: =I8/K8 | K8: =SUM(K3:K7) | L8: =SUM(L3:L7) | M8: =SUM(M3:M7) | N8: =SUM(N3:N7) | O8: =SUM(O3:O7) | P8: =SUM(P3:P7) | Q8: =SUM(Q3:Q7) | R8: =SUM(R3:R7) | ... T8: =SUM(T3:T7) | V8: =T8/R8 | W8: =L8/K8 | X8: =N8/L8 | Y8: =N8/K8 | Z8: =O8/N8 | AA8: =AVERAGE(AA3:AA7) | AB8: =Q8/O8 | AC8: =Q8/K8 | AD8: =R8/K8 | AE8: =SUM(AE3:AE7) | AF8: =T8/AE8 | AG8: =SUM(AG3:AG7) | AH8: =SUM(AH3:AH7) | AI8: =SUM(AI3:AI7) | AJ8: =SUM(AJ3:AJ7) | AK8: =SUM(AK3:AK7) | AL8: =SUM(AL3:AL7) | AM8: =SUM(AM3:AM7) | AN8: =SUM(AN3:AN7) | ... AP8: =SUM(AP3:AP7) | AR8: =SUM(AR3:AR7) | AS8: =SUM(AS3:AS7) | AT8: =SUM(AT3:AT7) | AU8: =SUM(AU3:AU7) | AV8: =SUM(AV3:AV7) | AW8: =SUM(AW3:AW7) | AX8: =SUM(AX3:AX7) | AZ8: =AX8/AV8 | BA8: =AP8/AO8 | BB8: =AR8/AP8 | BC8: =AR8/AO8 | BD8: =AS8/AR8 | BE8: =AVERAGE(BE3:BE7) | BF8: =AU8/AS8 | BG8: =AU8/AO8 | BH8: =AV8/AO8 | BI8: =SUM(BI3:BI7) | BJ8: =SUM(BJ3:BJ7) | BK8: =SUM(BK3:BK7) | BL8: =SUM(BL3:BL7) | BM8: =SUM(BM3:BM7) | BN8: =SUM(BN3:BN7) | BO8: =SUM(BO3:BO7) | BP8: =SUM(BP3:BP7) | ... BR8: =SUM(BR3:BR7) | BT8: =SUM(BT3:BT7) | BU8: =SUM(BU3:BU7) | BV8: =SUM(BV3:BV7) | BW8: =SUM(BW3:BW7) | BX8: =SUM(BX3:BX7) | BY8: =SUM(BY3:BY7) | BZ8: =BQ8/BY8 | CA8: =SUM(CA3:CA7) | CB8: =SUM(CB3:CB7) | CC8: =BR8/CB8 | CD8: =SUM(CD3:CD7) | CE8: =BR8/CD8

Sheet 陈山聪
I1: 主投 | AO1: 辅投 | BQ1: 汇总
B2: 渠道组 | C2: 供应商 | D2: 渠道名称 | E2: 主投 | F2: 辅投 | G2: 结算方式 | H2: 滚动消耗 | I2: 滚动消耗(不含赠课成本) | J2: 单例子成本 | K2: 例子数 | L2: 分发数 | M2: 剔除毛例子 分发数 | N2: 约课数 | O2: 到课数 | P2: 滚动到课数 | Q2: 当月成交数 | R2: 滚动成交数 | S2: 当月GMV | T2: 滚动GMV | U2: 海外GMV占比 | V2: 滚动ASP | W2: 例子分发率 | X2: 分发约课率 | Y2: 例子约课率 | Z2: 约课到课率 | AA2: 滚动应到课率 | AB2: 到课转化率 | AC2: 注册转化率 | AD2: 滚动转化率 | AE2: 滚动ROI2总成本 | AF2: 滚动ROI2 | AG2: 滚动应到课人数 | AH2: 滚动到课人数 | AI2: 滚动到课人次 | AJ2: 运营成本 | AK2: 销售固定成本 | AL2: 销售变动成本 | AM2: TMK费用 | AN2: DEMO费用 | AO2: 例子数 | AP2: 分发数 | AQ2: 剔除毛例子分发数 | AR2: 约课数 | AS2: 到课数 | AT2: 滚动到课数 | AU2: 当月成交 | AV2: 滚动成交数 | AW2: 当月GMV | AX2: 滚动GMV | AY2: 海外GMV占比 | AZ2: 滚动ASP | BA2: 例子分发率 | BB2: 分发约课率 | BC2: 例子约课率 | BD2: 约课到课率 | BE2: 滚动应到课率 | BF2: 到课转化率 | BG2: 注册转化率 | BH2: 滚动转化率 | BI2: 滚动应到课人数 | BJ2: 滚动到课人数 | BK2: 滚动到课人次 | BL2: 运营成本 | BM2: 销售固定成本 | BN2: 销售变动成本 | BO2: TMK费用 | BP2: DEMO费用 | BQ2: 当月GMV | BR2: 滚动GMV | BS2: 海外GMV占比 | BT2: 滚动其他成本 | BU2: 同源其他成本 | BV2: 运营成本 | BW2: 滚动消耗 | BX2: 同源消耗 | BY2: 当月ROI2总成本 | BZ2: 当月ROI2 | CA2: 滚动赠课成本 | CB2: 滚动ROI2总成本 | CC2: 滚动ROI2 | CD2: O-ROI总成本 | CE2: O-ROI
A3: 45780 | H3: =I3 | I3: 139975.77 | J3: 466.5859 | K3: 300 | L3: 133 | M3: 133 | N3: 135 | O3: 94 | P3: 94 | Q3: 34 | R3: 34 | S3: 172292 | T3: 172292 | U3: 1 | V3: 5067.4118 | W3: 0.44333333 | X3: 1.0150376 | Y3: 0.45 | Z3: 0.6962963 | AA3: 0.90384615 | AB3: 0.36170213 | AC3: 0.11333333 | AD3: 0.11333333 | AE3: 201653.37 | AF3: 0.85439682 | AG3: 104 | AH3: 94 | AI3: 104 | AJ3: 17008.978 | AK3: 16322.081 | AL3: 16523.237 | AM3: 2789.7585 | AN3: 9033.5479 | AO3: 0 | AP3: 0 | AQ3: 0 | AR3: 0 | AS3: 0 | AT3: 0 | AU3: 0 | AV3: 0 | AW3: 0 | AX3: 0 | BI3: 0 | BJ3: 0 | BK3: 0 | BL3: 0 | BM3: 0 | BN3: 0 | BO3: 0 | BP3: 0 | BQ3: 172292 | BR3: 172292 | BS3: 1 | BT3: 44668.624 | BU3: 44668.624 | BV3: 17008.978 | BW3: 139975.77 | BX3: 139975.77 | BY3: 201653.37 | BZ3: 0.85439682 | CB3: 201653.37 | CC3: 0.85439682 | CD3: 207144.39 | CE3: 0.83174831
A4: 45811 | H4: 109227.74 | I4: 104223.48 | J4: 1147.6791 | K4: 95 | L4: 47 | M4: 53 | N4: 47 | O4: 33 | P4: 63 | Q4: 13 | R4: 27 | S4: 55144 | T4: 122076 | U4: 1 | V4: 4521.3333 | W4: 0.49473684 | X4: 1 | Y4: 0.49473684 | Z4: 0.70212766 | AA4: 0.875 | AB4: 0.39393939 | AC4: 0.13684211 | AD4: 0.28421053 | AE4: 139767.04 | AF4: 0.87342482 | AG4: 72 | AH4: 63 | AI4: 73 | AJ4: 5925.5813 | AK4: 5956.4287 | AL4: 11784.397 | AM4: 767.21282 | AN4: 6303.8999 | AO4: 37 | AP4: 18 | AQ4: 18 | AR4: 19 | AS4: 10 | AT4: 10 | AU4: 2 | AV4: 2 | AW4: 6817.2 | AX4: 6817.2 | AY4: 1 | AZ4: 3408.6 | BA4: 0.48648649 | BB4: 1.0555556 | BC4: 0.51351351 | BD4: 0.52631579 | BE4: 0.52631579 | BF4: 0.2 | BG4: 0.054054054 | BH4: 0.054054054 | BI4: 19 | BJ4: 10 | BK4: 10 | BL4: 2071.2044 | BM4: 1619.2246 | BN4: 708.50775 | BO4: 298.8092 | BP4: 789.46739 | BQ4: 61961.2 | BR4: 128893.2 | BS4: 1 | BT4: 28227.948 | BU4: 18070.051 | BV4: 7996.7856 | BW4: 109227.74 | BX4: 106735.72 | BY4: 132802.56 | BZ4: 0.46656631 | CA4: 5004.265 | CB4: 145452.48 | CC4: 0.88615336 | CD4: 147355.69 | CE4: 0.87470799
A5: 45842 | H5: 84508.507 | I5: 81685.723 | J5: 994.21773 | K5: 85 | L5: 47 | M5: 49 | N5: 47 | O5: 34 | P5: 44 | Q5: 8 | R5: 16 | S5: 31304 | T5: 74108 | U5: 1 | V5: 4631.75 | W5: 0.55294118 | X5: 1 | Y5: 0.55294118 | Z5: 0.72340426 | AA5: 1 | AB5: 0.23529412 | AC5: 0.094117647 | AD5: 0.18823529 | AE5: 106173.07 | AF5: 0.69799243 | AG5: 44 | AH5: 44 | AI5: 49 | AJ5: 3740.374 | AK5: 5141.7647 | AL5: 7588.5174 | AM5: 874.97289 | AN5: 4318.935 | AO5: 0 | AP5: 0 | AQ5: 0 | AR5: 0 | AS5: 0 | AT5: 0 | AU5: 0 | AV5: 0 | AW5: 0 | AX5: 0 | BI5: 0 | BJ5: 0 | BK5: 0 | BL5: 0 | BM5: 0 | BN5: 0 | BO5: 0 | BP5: 0 | BQ5: 31304 | BR5: 74108 | BS5: 1 | BT5: 17924.19 | BU5: 12273.576 | BV5: 3740.374 | BW5: 84508.507 | BX5: 83097.115 | BY5: 99111.065 | BZ5: 0.31584768 | CA5: 2822.7837 | CB5: 106173.07 | CC5: 0.69799243 | CD5: 108807.7 | CE5: 0.68109152
A6: 45873 | H6: 48555.152 | I6: 46963.766 | J6: 851.84477 | K6: 57 | L6: 23 | M6: 27 | N6: 24 | O6: 18 | P6: 26 | Q6: 8 | R6: 9 | S6: 49804 | T6: 53392 | U6: 1 | V6: 5932.4444 | W6: 0.40350877 | X6: 1.0434783 | Y6: 0.42105263 | Z6: 0.75 | AA6: 1 | AB6: 0.44444444 | AC6: 0.14035088 | AD6: 0.15789474 | AE6: 67584.693 | AF6: 0.79000137 | AG6: 26 | AH6: 26 | AI6: 31 | AJ6: 5954.4309 | AK6: 4183.8927 | AL6: 5714.2158 | AM6: 570 | AN6: 2607.0017 | AO6: 0 | AP6: 0 | AQ6: 0 | AR6: 0 | AS6: 0 | AT6: 0 | AU6: 0 | AV6: 0 | AW6: 0 | AX6: 0 | BI6: 0 | BJ6: 0 | BK6: 0 | BL6: 0 | BM6: 0 | BN6: 0 | BO6: 0 | BP6: 0 | BQ6: 49804 | BR6: 53392 | BS6: 1 | BT6: 13075.11 | BU6: 11146.208 | BV6: 5954.4309 | BW6: 48555.152 | BX6: 48378.331 | BY6: 65478.97 | BZ6: 0.76061062 | CA6: 1591.386 | CB6: 67584.693 | CC6: 0.79000137 | CD6: 65905.262 | CE6: 0.81013258
A7: 45904 | H7: 22183.387 | I7: =H7-CA7 | J7: 693.23083 | K7: 32 | L7: 9 | M7: 9 | N7: 9 | O7: 5 | P7: 10 | Q7: 1 | R7: 2 | S7: 3588 | T7: 7176 | U7: 1 | V7: 3588 | W7: 0.28125 | X7: 1 | Y7: 0.28125 | Z7: 0.55555556 | AA7: 1 | AB7: 0.2 | AC7: 0.03125 | AD7: 0.0625 | AE7: 28054.152 | AF7: 0.25579102 | AG7: 10 | AH7: 10 | AI7: 12 | AJ7: 2424.6028 | AK7: 1301.3029 | AL7: 805.70369 | AM7: 320 | AN7: 1019.1556 | AO7: 0 | AP7: 0 | AQ7: 0 | AR7: 0 | AS7: 0 | AT7: 0 | AU7: 0 | AV7: 0 | AW7: 0 | AX7: 0 | BI7: 0 | BJ7: 0 | BK7: 0 | BL7: 0 | BM7: 0 | BN7: 0 | BO7: 0 | BP7: 0 | BQ7: 3588 | BR7: 7176 | BS7: 1 | BT7: 3446.1622 | BU7: 2533.7325 | BV7: 2424.6028 | BW7: 22183.387 | BX7: 22004.747 | BY7: 26963.083 | BZ7: 0.13307084 | CA7: 357.27827 | CB7: 28054.152 | CC7: 0.25579102 | CD7: 28029.549 | CE7: 0.25601554
A8: 45931 | H8: 14376.336 | I8: =H8-CA8 | J8: 898.52099 | K8: 16 | L8: 1 | M8: 1 | N8: 1 | O8: 1 | P8: 2 | Q8: 0 | R8: 1 | S8: 0 | T8: 5888 | U8: 1 | V8: 5888 | W8: 0.0625 | X8: 1 | Y8: 0.0625 | Z8: 1 | AA8: 1 | AB8: 0 | AC8: 0 | AD8: 0.0625 | AE8: 16495.56 | AF8: 0.35694453 | AG8: 2 | AH8: 2 | AI8: 2 | AJ8: 999.75505 | AK8: 142.24736 | AL8: 647.68995 | AM8: 160 | AN8: 169.53181 | AO8: 0 | AP8: 0 | AQ8: 0 | AR8: 0 | AS8: 0 | AT8: 0 | AU8: 0 | AV8: 0 | AW8: 0 | AX8: 0 | BI8: 0 | BJ8: 0 | BK8: 0 | BL8: 0 | BM8: 0 | BN8: 0 | BO8: 0 | BP8: 0 | BQ8: 0 | BR8: 5888 | BS8: 1 | BT8: 1119.4691 | BU8: 387.01327 | BV8: 999.75505 | BW8: 14376.336 | BX8: 14197.697 | BY8: 15584.465 | BZ8: 0 | CA8: 178.63914 | CB8: 16495.56 | CC8: 0.35694453 | CD8: 16695.805 | CE8: 0.35266344
A9: 45962
A10: 陈山聪-汇总 | H10: =SUM(H3:H9) | I10: =SUM(I3:I9) | J10: =I10/K10 | K10: =SUM(K3:K9) | L10: =SUM(L3:L9) | M10: =SUM(M3:M9) | N10: =SUM(N3:N9) | O10: =SUM(O3:O9) | P10: =SUM(P3:P9) | Q10: =SUM(Q3:Q9) | R10: =SUM(R3:R9) | ... T10: =SUM(T3:T9) | V10: =T10/R10 | W10: =L10/K10 | X10: =N10/L10 | Y10: =N10/K10 | Z10: =O10/N10 | AA10: =AVERAGE(AA3:AA9) | AB10: =Q10/O10 | AC10: =Q10/K10 | AD10: =R10/K10 | AE10: =SUM(AE3:AE9) | AF10: =T10/AE10 | AG10: =SUM(AG3:AG9) | AH10: =SUM(AH3:AH9) | AI10: =SUM(AI3:AI9) | AJ10: =SUM(AJ3:AJ9) | AK10: =SUM(AK3:AK9) | AL10: =SUM(AL3:AL9) | AM10: =SUM(AM3:AM9) | AN10: =SUM(AN3:AN9) | ... AP10: =SUM(AP3:AP9) | AR10: =SUM(AR3:AR9) | AS10: =SUM(AS3:AS9) | AT10: =SUM(AT3:AT9) | AU10: =SUM(AU3:AU9) | AV10: =SUM(AV3:AV9) | AW10: =SUM(AW3:AW9) | AX10: =SUM(AX3:AX9) | AZ10: =AX10/AV10 | BA10: =AP10/AO10 | BB10: =AR10/AP10 | BC10: =AR10/AO10 | BD10: =AS10/AR10 | BE10: =AVERAGE(BE3:BE9) | BF10: =AU10/AS10 | BG10: =AU10/AO10 | BH10: =AV10/AO10 | BI10: =SUM(BI3:BI9) | BJ10: =SUM(BJ3:BJ9) | BK10: =SUM(BK3:BK9) | BL10: =SUM(BL3:BL9) | BM10: =SUM(BM3:BM9) | BN10: =SUM(BN3:BN9) | BO10: =SUM(BO3:BO9) | BP10: =SUM(BP3:BP9) | ... BR10: =SUM(BR3:BR9) | BT10: =SUM(BT3:BT9) | BU10: =SUM(BU3:BU9) | BV10: =SUM(BV3:BV9) | BW10: =SUM(BW3:BW9) | BX10: =SUM(BX3:BX9) | BY10: =SUM(BY3:BY9) | BZ10: =BQ10/BY10 | CA10: =SUM(CA3:CA9) | CB10: =SUM(CB3:CB9) | CC10: =BR10/CB10 | CD10: =SUM(CD3:CD9) | CE10: =BR10/CD10

Sheet 陈敏之 
I1: 主投 | AO1: 辅投 | BQ1: 汇总
B2: 渠道组 | C2: 供应商 | D2: 渠道名称 | E2: 主投 | F2: 辅投 | G2: 结算方式 | H2: 滚动消耗 | I2: 滚动消耗(不含赠课成本) | J2: 单例子成本 | K2: 例子数 | L2: 分发数 | M2: 剔除毛例子 分发数 | N2: 约课数 | O2: 到课数 | P2: 滚动到课数 | Q2: 当月成交数 | R2: 滚动成交数 | S2: 当月GMV | T2: 滚动GMV | U2: 海外GMV占比 | V2: 滚动ASP | W2: 例子分发率 | X2: 分发约课率 | Y2: 例子约课率 | Z2: 约课到课率 | AA2: 滚动应到课率 | AB2: 到课转化率 | AC2: 注册转化率 | AD2: 滚动转化率 | AE2: 滚动ROI2总成本 | AF2: 滚动ROI2 | AG2: 滚动应到课人数 | AH2: 滚动到课人数 | AI2: 滚动到课人次 | AJ2: 运营成本 | AK2: 销售固定成本 | AL2: 销售变动成本 | AM2: TMK费用 | AN2: DEMO费用 | AO2: 例子数 | AP2: 分发数 | AQ2: 剔除毛例子分发数 | AR2: 约课数 | AS2: 到课数 | AT2: 滚动到课数 | AU2: 当月成交 | AV2: 滚动成交数 | AW2: 当月GMV | AX2: 滚动GMV | AY2: 海外GMV占比 | AZ2: 滚动ASP | BA2: 例子分发率 | BB2: 分发约课率 | BC2: 例子约课率 | BD2: 约课到课率 | BE2: 滚动应到课率 | BF2: 到课转化率 | BG2: 注册转化率 | BH2: 滚动转化率 | BI2: 滚动应到课人数 | BJ2: 滚动到课人数 | BK2: 滚动到课人次 | BL2: 运营成本 | BM2: 销售固定成本 | BN2: 销售变动成本 | BO2: TMK费用 | BP2: DEMO费用 | BQ2: 当月GMV | BR2: 滚动GMV | BS2: 海外GMV占比 | BT2: 滚动其他成本 | BU2: 同源其他成本 | BV2: 运营成本 | BW2: 滚动消耗 | BX2: 同源消耗 | BY2: 当月ROI2总成本 | BZ2: 当月ROI2 | CA2: 滚动赠课成本 | CB2: 滚动ROI2总成本 | CC2: 滚动ROI2 | CD2: O-ROI总成本 | CE2: O-ROI
A3: 45811 | H3: 175980.49 | I3: 168939.32 | J3: 687.03661 | K3: 256 | L3: 137 | M3: 137 | N3: 141 | O3: 103 | P3: 103 | Q3: 39 | R3: 39 | S3: 190732 | T3: 190732 | U3: 1 | V3: 4890.5641 | W3: 0.53515625 | X3: 1.0291971 | Y3: 0.55078125 | Z3: 0.73049645 | AA3: 0.96261682 | AB3: 0.37864078 | AC3: 0.15234375 | AD3: 0.15234375 | AE3: 237742.64 | AF3: 0.80226248 | AG3: 107 | AH3: 103 | AI3: 116 | AJ3: 15967.882 | AK3: 15396.806 | AL3: 18411.987 | AM3: 2067.4366 | AN3: 10017.156 | AO3: 135 | AP3: 46 | AQ3: 46 | AR3: 46 | AS3: 24 | AT3: 24 | AU3: 1 | AV3: 1 | AW3: 3588 | AX3: 3588 | AY3: 1 | AZ3: 3588 | BA3: 0.34074074 | BB3: 1 | BC3: 0.34074074 | BD3: 0.52173913 | BE3: 0.52173913 | BF3: 0.041666667 | BG3: 0.0074074074 | BH3: 0.0074074074 | BI3: 46 | BJ3: 24 | BK3: 24 | BL3: 7557.097 | BM3: 4138.0185 | BN3: 372.89882 | BO3: 1090.2498 | BP3: 1894.7217 | BQ3: 194320 | BR3: 194320 | BS3: 1 | BT3: 53389.274 | BU3: 53389.274 | BV3: 23524.979 | BW3: 175980.49 | BX3: 175980.49 | BY3: 252894.74 | BZ3: 0.76838293 | CA3: 7041.1703 | CB3: 252894.74 | CC3: 0.76838293 | CD3: 258694.76 | CE3: 0.75115553
A4: 45842 | H4: 160447 | I4: 153115.1 | J4: 921.54301 | K4: 174 | L4: 105 | M4: 109 | N4: 113 | O4: 89 | P4: 105 | Q4: 33 | R4: 41 | S4: 148304 | T4: 185408 | U4: 1 | V4: 4522.1463 | W4: 0.60344828 | X4: 1.0761905 | Y4: 0.64942529 | Z4: 0.78761062 | AA4: 0.9375 | AB4: 0.37078652 | AC4: 0.18965517 | AD4: 0.23563218 | AE4: 210267.73 | AF4: 0.88177106 | AG4: 112 | AH4: 105 | AI4: 114 | AJ4: 7656.7657 | AK4: 11437.803 | AL4: 18985.425 | AM4: 1791.121 | AN4: 10048.135 | AO4: 0 | AP4: 0 | AQ4: 0 | AR4: 0 | AS4: 0 | AT4: 0 | AU4: 0 | AV4: 1 | AW4: 0 | AX4: 1880 | AY4: 1 | AZ4: 1880 | BI4: 0 | BJ4: 0 | BK4: 0 | BL4: 0 | BM4: 0 | BN4: 197.37392 | BO4: 0 | BP4: 0 | BQ4: 148304 | BR4: 187288 | BS4: 1 | BT4: 42459.857 | BU4: 36721.246 | BV4: 7656.7657 | BW4: 160447 | BX4: 158937.09 | BY4: 203315.1 | BZ4: 0.72942933 | CA4: 7331.8953 | CB4: 210563.62 | CC4: 0.8894604 | CD4: 215956.85 | CE4: 0.86724731
A5: 45873 | H5: 107875.61 | I5: 103455.1 | J5: 627.18379 | K5: 172 | L5: 46 | M5: 48 | N5: 49 | O5: 37 | P5: 54 | Q5: 17 | R5: 25 | S5: 81896 | T5: 110600 | U5: 1 | V5: 4424 | W5: 0.26744186 | X5: 1.0652174 | Y5: 0.28488372 | Z5: 0.75510204 | AA5: 1 | AB5: 0.45945946 | AC5: 0.098837209 | AD5: 0.14534884 | AE5: 147578.15 | AF5: 0.74943341 | AG5: 54 | AH5: 54 | AI5: 59 | AJ5: 15528.079 | AK5: 5928.8847 | AL5: 11325.228 | AM5: 1720 | AN5: 5200.3503 | AO5: 0 | AP5: 0 | AQ5: 0 | AR5: 0 | AS5: 0 | AT5: 0 | AU5: 0 | AV5: 0 | AW5: 0 | AX5: 0 | BI5: 0 | BJ5: 0 | BK5: 0 | BL5: 0 | BM5: 0 | BN5: 0 | BO5: 0 | BP5: 0 | BQ5: 81896 | BR5: 110600 | BS5: 1 | BT5: 24174.463 | BU5: 19313.503 | BV5: 15528.079 | BW5: 107875.61 | BX5: 106461.05 | BY5: 141302.63 | BZ5: 0.57957874 | CA5: 4420.5166 | CB5: 147578.15 | CC5: 0.74943341 | CD5: 144950.08 | CE5: 0.76302134
A6: 45904 | H6: 150853.93 | I6: =H6-CA6 | J6: 434.73754 | K6: 347 | L6: 77 | M6: 77 | N6: 80 | O6: 63 | P6: 66 | Q6: 25 | R6: 29 | S6: 132300 | T6: 149952 | U6: 1 | V6: 5170.7586 | W6: 0.22190202 | X6: 1.038961 | Y6: 0.23054755 | Z6: 0.7875 | AA6: 0.97058824 | AB6: 0.3968254 | AC6: 0.07204611 | AD6: 0.083573487 | AE6: 214955.05 | AF6: 0.69759702 | AG6: 68 | AH6: 66 | AI6: 75 | AJ6: 26291.787 | AK6: 11133.369 | AL6: 16836.243 | AM6: 3470 | AN6: 6369.7226 | AO6: 0 | AP6: 0 | AQ6: 0 | AR6: 0 | AS6: 0 | AT6: 0 | AU6: 0 | AV6: 0 | AW6: 0 | AX6: 0 | BI6: 0 | BJ6: 0 | BK6: 0 | BL6: 0 | BM6: 0 | BN6: 0 | BO6: 0 | BP6: 0 | BQ6: 132300 | BR6: 149952 | BS6: 1 | BT6: 37809.335 | BU6: 35572.623 | BV6: 26291.787 | BW6: 150853.93 | BX6: 150139.37 | BY6: 212003.78 | BZ6: 0.62404548 | CA6: 5180.535 | CB6: 214955.05 | CC6: 0.69759702 | CD6: 214688.26 | CE6: 0.6984639
A7: 45931 | H7: 32841.866 | I7: =H7-CA7 | J7: 586.46189 | K7: 56 | L7: 19 | M7: 20 | N7: 22 | O7: 18 | P7: 23 | Q7: 9 | R7: 11 | S7: 52203 | T7: 63979 | U7: 1 | V7: 5816.2727 | W7: 0.33928571 | X7: 1.1578947 | Y7: 0.39285714 | Z7: 0.81818182 | AA7: 0.95833333 | AB7: 0.5 | AC7: 0.16071429 | AD7: 0.19642857 | AE7: 48818.135 | AF7: 1.310558 | AG7: 24 | AH7: 23 | AI7: 24 | AJ7: 3499.1427 | AK7: 2844.9472 | AL7: 7037.7981 | AM7: 560 | AN7: 2034.3817 | AO7: 0 | AP7: 0 | AQ7: 0 | AR7: 0 | AS7: 0 | AT7: 0 | AU7: 0 | AV7: 0 | AW7: 0 | AX7: 0 | BI7: 0 | BJ7: 0 | BK7: 0 | BL7: 0 | BM7: 0 | BN7: 0 | BO7: 0 | BP7: 0 | BQ7: 52203 | BR7: 63979 | BS7: 1 | BT7: 12477.127 | BU7: 10615.67 | BV7: 3499.1427 | BW7: 32841.866 | BX7: 32484.587 | BY7: 46599.4 | BZ7: 1.1202505 | CA7: 1965.0305 | CB7: 48818.135 | CC7: 1.310558 | CD7: 49518.993 | CE7: 1.2920093
A8: 45962
A9: 陈敏之-汇总 | H9: =SUM(H3:H8) | I9: =SUM(I3:I8) | J9: =I9/K9 | K9: =SUM(K3:K8) | L9: =SUM(L3:L8) | M9: =SUM(M3:M8) | N9: =SUM(N3:N8) | O9: =SUM(O3:O8) | P9: =SUM(P3:P8) | Q9: =SUM(Q3:Q8) | R9: =SUM(R3:R8) | ... T9: =SUM(T3:T8) | V9: =T9/R9 | W9: =L9/K9 | X9: =N9/L9 | Y9: =N9/K9 | Z9: =O9/N9 | AA9: =AVERAGE(AA3:AA8) | AB9: =Q9/O9 | AC9: =Q9/K9 | AD9: =R9/K9 | AE9: =SUM(AE3:AE8) | AF9: =T9/AE9 | AG9: =SUM(AG3:AG8) | AH9: =SUM(AH3:AH8) | AI9: =SUM(AI3:AI8) | AJ9: =SUM(AJ3:AJ8) | AK9: =SUM(AK3:AK8) | AL9: =SUM(AL3:AL8) | AM9: =SUM(AM3:AM8) | AN9: =SUM(AN3:AN8) | ... AP9: =SUM(AP3:AP8) | AR9: =SUM(AR3:AR8) | AS9: =SUM(AS3:AS8) | AT9: =SUM(AT3:AT8) | AU9: =SUM(AU3:AU8) | AV9: =SUM(AV3:AV8) | AW9: =SUM(AW3:AW8) | AX9: =SUM(AX3:AX8) | AZ9: =AX9/AV9 | BA9: =AP9/AO9 | BB9: =AR9/AP9 | BC9: =AR9/AO9 | BD9: =AS9/AR9 | BE9: =AVERAGE(BE3:BE8) | BF9: =AU9/AS9 | BG9: =AU9/AO9 | BH9: =AV9/AO9 | BI9: =SUM(BI3:BI8) | BJ9: =SUM(BJ3:BJ8) | BK9: =SUM(BK3:BK8) | BL9: =SUM(BL3:BL8) | BM9: =SUM(BM3:BM8) | BN9: =SUM(BN3:BN8) | BO9: =SUM(BO3:BO8) | BP9: =SUM(BP3:BP8) | ... BR9: =SUM(BR3:BR8) | BT9: =SUM(BT3:BT8) | BU9: =SUM(BU3:BU8) | BV9: =SUM(BV3:BV8) | BW9: =SUM(BW3:BW8) | BX9: =SUM(BX3:BX8) | BY9: =SUM(BY3:BY8) | BZ9: =BQ9/BY9 | CA9: =SUM(CA3:CA8) | CB9: =SUM(CB3:CB8) | CC9: =BR9/CB9 | CD9: =SUM(CD3:CD8) | CE9: =BR9/CD9

Sheet 林子善
I1: 主投 | AO1: 辅投 | BQ1: 汇总
B2: 渠道组 | C2: 供应商 | D2: 渠道名称 | E2: 主投 | F2: 辅投 | G2: 结算方式 | H2: 滚动消耗 | I2: 滚动消耗(不含赠课成本) | J2: 单例子成本 | K2: 例子数 | L2: 分发数 | M2: 剔除毛例子 分发数 | N2: 约课数 | O2: 到课数 | P2: 滚动到课数 | Q2: 当月成交数 | R2: 滚动成交数 | S2: 当月GMV | T2: 滚动GMV | U2: 海外GMV占比 | V2: 滚动ASP | W2: 例子分发率 | X2: 分发约课率 | Y2: 例子约课率 | Z2: 约课到课率 | AA2: 滚动应到课率 | AB2: 到课转化率 | AC2: 注册转化率 | AD2: 滚动转化率 | AE2: 滚动ROI2总成本 | AF2: 滚动ROI2 | AG2: 滚动应到课人数 | AH2: 滚动到课人数 | AI2: 滚动到课人次 | AJ2: 运营成本 | AK2: 销售固定成本 | AL2: 销售变动成本 | AM2: TMK费用 | AN2: DEMO费用 | AO2: 例子数 | AP2: 分发数 | AQ2: 剔除毛例子分发数 | AR2: 约课数 | AS2: 到课数 | AT2: 滚动到课数 | AU2: 当月成交 | AV2: 滚动成交数 | AW2: 当月GMV | AX2: 滚动GMV | AY2: 海外GMV占比 | AZ2: 滚动ASP | BA2: 例子分发率 | BB2: 分发约课率 | BC2: 例子约课率 | BD2: 约课到课率 | BE2: 滚动应到课率 | BF2: 到课转化率 | BG2: 注册转化率 | BH2: 滚动转化率 | BI2: 滚动应到课人数 | BJ2: 滚动到课人数 | BK2: 滚动到课人次 | BL2: 运营成本 | BM2: 销售固定成本 | BN2: 销售变动成本 | BO2: TMK费用 | BP2: DEMO费用 | BQ2: 当月GMV | BR2: 滚动GMV | BS2: 海外GMV占比 | BT2: 滚动其他成本 | BU2: 同源其他成本 | BV2: 运营成本 | BW2: 滚动消耗 | BX2: 同源消耗 | BY2: 当月ROI2总成本 | BZ2: 当月ROI2 | CA2: 滚动赠课成本 | CB2: 滚动ROI2总成本 | CC2: 滚动ROI2 | CD2: O-ROI总成本 | CE2: O-ROI
A3: 45811 | H3: 113220.07 | I3: 108215.81 | J3: 533.12193 | K3: 212 | L3: 97 | M3: 97 | N3: 99 | O3: 75 | P3: 75 | Q3: 27 | R3: 27 | S3: 118357.2 | T3: 118357.2 | U3: 1 | V3: 4383.6 | W3: 0.45754717 | X3: 1.0206186 | Y3: 0.46698113 | Z3: 0.75757576 | AA3: 0.96153846 | AB3: 0.36 | AC3: 0.12735849 | AD3: 0.12735849 | AE3: 157365.24 | AF3: 0.75211782 | AG3: 78 | AH3: 75 | AI3: 82 | AJ3: 13223.402 | AK3: 10901.388 | AL3: 11425.41 | AM3: 1712.096 | AN3: 7081.093 | AO3: 29 | AP3: 29 | AQ3: 29 | AR3: 29 | AS3: 15 | AT3: 15 | AU3: 2 | AV3: 2 | AW3: 7176 | AX3: 7176 | AY3: 1 | AZ3: 3588 | BA3: 1 | BB3: 1 | BC3: 1 | BD3: 0.51724138 | BE3: 0.51724138 | BF3: 0.13333333 | BG3: 0.068965517 | BH3: 0.068965517 | BI3: 29 | BJ3: 15 | BK3: 15 | BL3: 1623.3764 | BM3: 2608.7508 | BN3: 745.79763 | BO3: 234.20181 | BP3: 1184.2011 | BQ3: 125533.2 | BR3: 125533.2 | BS3: 1 | BT3: 35892.938 | BU3: 35892.938 | BV3: 14846.779 | BW3: 113220.07 | BX3: 113220.07 | BY3: 163959.79 | BZ3: 0.76563406 | CA3: 5004.265 | CB3: 163959.79 | CC3: 0.76563406 | CD3: 167188.01 | CE3: 0.75085049
A4: 45842 | H4: 79184.236 | I4: 77596.42 | J4: 1147.5976 | K4: 69 | L4: 32 | M4: 37 | N4: 32 | O4: 25 | P4: 35 | Q4: 4 | R4: 9 | S4: 24352 | T4: 47892 | U4: 1 | V4: 5321.3333 | W4: 0.46376812 | X4: 1 | Y4: 0.46376812 | Z4: 0.78125 | AA4: 0.94594595 | AB4: 0.16 | AC4: 0.057971014 | AD4: 0.13043478 | AE4: 95154.937 | AF4: 0.50330546 | AG4: 37 | AH4: 35 | AI4: 39 | AJ4: 3036.3036 | AK4: 3882.557 | AL4: 4904.0492 | AM4: 710.27211 | AN4: 3437.5197 | AO4: 0 | AP4: 0 | AQ4: 0 | AR4: 0 | AS4: 0 | AT4: 0 | AU4: 0 | AV4: 0 | AW4: 0 | AX4: 0 | BI4: 0 | BJ4: 0 | BK4: 0 | BL4: 0 | BM4: 0 | BN4: 0 | BO4: 0 | BP4: 0 | BQ4: 24352 | BR4: 47892 | BS4: 1 | BT4: 12934.398 | BU4: 8941.5788 | BV4: 3036.3036 | BW4: 79184.236 | BX4: 78302.116 | BY4: 90279.998 | BZ4: 0.2697386 | CA4: 1587.8158 | CB4: 95154.937 | CC4: 0.50330546 | CD4: 97293.634 | CE4: 0.49224187
A5: 45873 | H5: 44758.548 | I5: 43520.803 | J5: 1491.9516 | K5: 30 | L5: 17 | M5: 21 | N5: 17 | O5: 15 | P5: 19 | Q5: 5 | R5: 7 | S5: 27940 | T5: 35116 | U5: 1 | V5: 5016.5714 | W5: 0.56666667 | X5: 1 | Y5: 0.56666667 | Z5: 0.88235294 | AA5: 1 | AB5: 0.33333333 | AC5: 0.16666667 | AD5: 0.23333333 | AE5: 55719.463 | AF5: 0.63022862 | AG5: 19 | AH5: 19 | AI5: 20 | AJ5: 2708.386 | AK5: 2593.8871 | AL5: 3595.8112 | AM5: 300 | AN5: 1762.8306 | AO5: 0 | AP5: 0 | AQ5: 0 | AR5: 0 | AS5: 0 | AT5: 0 | AU5: 0 | AV5: 0 | AW5: 0 | AX5: 0 | BI5: 0 | BJ5: 0 | BK5: 0 | BL5: 0 | BM5: 0 | BN5: 0 | BO5: 0 | BP5: 0 | BQ5: 27940 | BR5: 35116 | BS5: 1 | BT5: 8252.5289 | BU5: 6671.0804 | BV5: 2708.386 | BW5: 44758.548 | BX5: 44404.907 | BY5: 53784.373 | BZ5: 0.51948175 | CA5: 1237.7446 | CB5: 55719.463 | CC5: 0.63022862 | CD5: 55261.077 | CE5: 0.63545631
A6: 45904 | H6: 11879.687 | I6: =H6-CA6 | J6: 625.24667 | K6: 19 | L6: 9 | M6: 9 | N6: 9 | O6: 6 | P6: 9 | Q6: 2 | R6: 3 | S6: 14676 | T6: 23264 | U6: 1 | V6: 7754.6667 | W6: 0.47368421 | X6: 1 | Y6: 0.47368421 | Z6: 0.66666667 | AA6: 1 | AB6: 0.33333333 | AC6: 0.10526316 | AD6: 0.15789474 | AE6: 18271.919 | AF6: 1.2732106 | AG6: 9 | AH6: 9 | AI6: 10 | AJ6: 1439.6079 | AK6: 1301.3029 | AL6: 2612.0249 | AM6: 190 | AN6: 849.29635 | AO6: 0 | AP6: 0 | AQ6: 0 | AR6: 0 | AS6: 0 | AT6: 0 | AU6: 0 | AV6: 0 | AW6: 0 | AX6: 0 | BI6: 0 | BJ6: 0 | BK6: 0 | BL6: 0 | BM6: 0 | BN6: 0 | BO6: 0 | BP6: 0 | BQ6: 14676 | BR6: 23264 | BS6: 1 | BT6: 4952.6241 | BU6: 3648.666 | BV6: 1439.6079 | BW6: 11879.687 | BX6: 11701.048 | BY6: 16789.321 | BZ6: 0.87412705 | CA6: 535.91741 | CB6: 18271.919 | CC6: 1.2732106 | CD6: 18257.311 | CE6: 1.2742293
A7: 45931 | H7: 9344.6632 | I7: =H7-CA7 | J7: 227.91862 | K7: 41 | L7: 4 | M7: 4 | N7: 4 | O7: 2 | P7: 3 | Q7: 2 | R7: 2 | S7: 17376 | T7: 17376 | U7: 1 | V7: 8688 | W7: 0.097560976 | X7: 1 | Y7: 0.097560976 | Z7: 0.5 | AA7: 1 | AB7: 1 | AC7: 0.048780488 | AD7: 0.048780488 | AE7: 15051.212 | AF7: 1.1544585 | AG7: 3 | AH7: 3 | AI7: 3 | AJ7: 2561.8723 | AK7: 568.98945 | AL7: 1911.3894 | AM7: 410 | AN7: 254.29771 | AO7: 0 | AP7: 0 | AQ7: 0 | AR7: 0 | AS7: 0 | AT7: 1 | AU7: 0 | AV7: 0 | AW7: 0 | AX7: 0 | BE7: 1 | BI7: 1 | BJ7: 1 | BK7: 2 | BL7: 0 | BM7: 0 | BN7: 0 | BO7: 0 | BP7: 160 | BQ7: 17376 | BR7: 17376 | BS7: 1 | BT7: 3304.6765 | BU7: 3059.9106 | BV7: 2561.8723 | BW7: 9344.6632 | BX7: 9344.6632 | BY7: 14966.446 | BZ7: 1.1609971 | CA7: 357.27827 | CB7: 15211.212 | CC7: 1.1423153 | CD7: 15724.34 | CE7: 1.1050384
A8: 45962
A9: 林子善-汇总 | H9: =SUM(H3:H8) | I9: =SUM(I3:I8) | J9: =I9/K9 | K9: =SUM(K3:K8) | L9: =SUM(L3:L8) | M9: =SUM(M3:M8) | N9: =SUM(N3:N8) | O9: =SUM(O3:O8) | P9: =SUM(P3:P8) | Q9: =SUM(Q3:Q8) | R9: =SUM(R3:R8) | ... T9: =SUM(T3:T8) | V9: =T9/R9 | W9: =L9/K9 | X9: =N9/L9 | Y9: =N9/K9 | Z9: =O9/N9 | AA9: =AVERAGE(AA3:AA8) | AB9: =Q9/O9 | AC9: =Q9/K9 | AD9: =R9/K9 | AE9: =SUM(AE3:AE8) | AF9: =T9/AE9 | AG9: =SUM(AG3:AG8) | AH9: =SUM(AH3:AH8) | AI9: =SUM(AI3:AI8) | AJ9: =SUM(AJ3:AJ8) | AK9: =SUM(AK3:AK8) | AL9: =SUM(AL3:AL8) | AM9: =SUM(AM3:AM8) | AN9: =SUM(AN3:AN8) | ... AP9: =SUM(AP3:AP8) | AR9: =SUM(AR3:AR8) | AS9: =SUM(AS3:AS8) | AT9: =SUM(AT3:AT8) | AU9: =SUM(AU3:AU8) | AV9: =SUM(AV3:AV8) | AW9: =SUM(AW3:AW8) | AX9: =SUM(AX3:AX8) | AZ9: =AX9/AV9 | BA9: =AP9/AO9 | BB9: =AR9/AP9 | BC9: =AR9/AO9 | BD9: =AS9/AR9 | BE9: =AVERAGE(BE3:BE8) | BF9: =AU9/AS9 | BG9: =AU9/AO9 | BH9: =AV9/AO9 | BI9: =SUM(BI3:BI8) | BJ9: =SUM(BJ3:BJ8) | BK9: =SUM(BK3:BK8) | BL9: =SUM(BL3:BL8) | BM9: =SUM(BM3:BM8) | BN9: =SUM(BN3:BN8) | BO9: =SUM(BO3:BO8) | BP9: =SUM(BP3:BP8) | ... BR9: =SUM(BR3:BR8) | BT9: =SUM(BT3:BT8) | BU9: =SUM(BU3:BU8) | BV9: =SUM(BV3:BV8) | BW9: =SUM(BW3:BW8) | BX9: =SUM(BX3:BX8) | BY9: =SUM(BY3:BY8) | BZ9: =BQ9/BY9 | CA9: =SUM(CA3:CA8) | CB9: =SUM(CB3:CB8) | CC9: =BR9/CB9 | CD9: =SUM(CD3:CD8) | CE9: =BR9/CD9

Sheet mamidaily
I1: 主投 | AO1: 辅投 | BQ1: 汇总
B2: 渠道组 | C2: 供应商 | D2: 渠道名称 | E2: 主投 | F2: 辅投 | G2: 结算方式 | H2: 滚动消耗 | I2: 滚动消耗(不含赠课成本) | J2: 单例子成本 | K2: 例子数 | L2: 分发数 | M2: 剔除毛例子 分发数 | N2: 约课数 | O2: 到课数 | P2: 滚动到课数 | Q2: 当月成交数 | R2: 滚动成交数 | S2: 当月GMV | T2: 滚动GMV | U2: 海外GMV占比 | V2: 滚动ASP | W2: 例子分发率 | X2: 分发约课率 | Y2: 例子约课率 | Z2: 约课到课率 | AA2: 滚动应到课率 | AB2: 到课转化率 | AC2: 注册转化率 | AD2: 滚动转化率 | AE2: 滚动ROI2总成本 | AF2: 滚动ROI2 | AG2: 滚动应到课人数 | AH2: 滚动到课人数 | AI2: 滚动到课人次 | AJ2: 运营成本 | AK2: 销售固定成本 | AL2: 销售变动成本 | AM2: TMK费用 | AN2: DEMO费用 | AO2: 例子数 | AP2: 分发数 | AQ2: 剔除毛例子分发数 | AR2: 约课数 | AS2: 到课数 | AT2: 滚动到课数 | AU2: 当月成交 | AV2: 滚动成交数 | AW2: 当月GMV | AX2: 滚动GMV | AY2: 海外GMV占比 | AZ2: 滚动ASP | BA2: 例子分发率 | BB2: 分发约课率 | BC2: 例子约课率 | BD2: 约课到课率 | BE2: 滚动应到课率 | BF2: 到课转化率 | BG2: 注册转化率 | BH2: 滚动转化率 | BI2: 滚动应到课人数 | BJ2: 滚动到课人数 | BK2: 滚动到课人次 | BL2: 运营成本 | BM2: 销售固定成本 | BN2: 销售变动成本 | BO2: TMK费用 | BP2: DEMO费用 | BQ2: 当月GMV | BR2: 滚动GMV | BS2: 海外GMV占比 | BT2: 滚动其他成本 | BU2: 同源其他成本 | BV2: 运营成本 | BW2: 滚动消耗 | BX2: 同源消耗 | BY2: 当月ROI2总成本 | BZ2: 当月ROI2 | CA2: 滚动赠课成本 | CB2: 滚动ROI2总成本 | CC2: 滚动ROI2 | CD2: O-ROI总成本 | CE2: O-ROI
A3: 45811 | H3: 39072.853 | I3: 37826.842 | J3: 952.9964 | K3: 41 | L3: 25 | M3: 25 | N3: 24 | O3: 21 | P3: 21 | Q3: 7 | R3: 7 | S3: 35916 | T3: 35916 | U3: 1 | V3: 5130.8571 | W3: 0.6097561 | X3: 0.96 | Y3: 0.58536585 | Z3: 0.875 | AA3: 0.91304348 | AB3: 0.33333333 | AC3: 0.17073171 | AD3: 0.17073171 | AE3: 49110.563 | AF3: 0.73132942 | AG3: 23 | AH3: 21 | AI3: 21 | AJ3: 1616.4216 | AK3: 2809.6362 | AL3: 3467.0895 | AM3: 331.1129 | AN3: 1813.4507 | AO3: 23 | AP3: 7 | AQ3: 7 | AR3: 7 | AS3: 1 | AT3: 1 | AU3: 0 | AV3: 0 | AW3: 0 | AX3: 0 | BA3: 0.30434783 | BB3: 1 | BC3: 0.30434783 | BD3: 0.14285714 | BE3: 0.14285714 | BF3: 0 | BG3: 0 | BH3: 0 | BI3: 7 | BJ3: 1 | BK3: 1 | BL3: 906.77312 | BM3: 629.69846 | BN3: 0 | BO3: 185.74626 | BP3: 78.946739 | BQ3: 35916 | BR3: 35916 | BS3: 1 | BT3: 9315.6807 | BU3: 9315.6807 | BV3: 2523.1948 | BW3: 39072.853 | BX3: 39072.853 | BY3: 50911.728 | BZ3: 0.70545631 | CA3: 1246.0104 | CB3: 50911.728 | CC3: 0.70545631 | CD3: 53188.533 | CE3: 0.67525833
A4: 45842 | H4: 50216.427 | I4: 49157.883 | J4: 1521.7099 | K4: 33 | L4: 18 | M4: 20 | N4: 19 | O4: 16 | P4: 19 | Q4: 5 | R4: 6 | S4: 25440 | T4: 34028 | U4: 1 | V4: 5671.3333 | W4: 0.54545455 | X4: 1.0555556 | Y4: 0.57575758 | Z4: 0.84210526 | AA4: 0.9047619 | AB4: 0.3125 | AC4: 0.15151515 | AD4: 0.18181818 | AE4: 59354.18 | AF4: 0.57330419 | AG4: 21 | AH4: 19 | AI4: 20 | AJ4: 1452.1452 | AK4: 2098.6795 | AL4: 3484.4021 | AM4: 339.69536 | AN4: 1762.8306 | AO4: 0 | AP4: 0 | AQ4: 0 | AR4: 0 | AS4: 0 | AT4: 0 | AU4: 0 | AV4: 0 | AW4: 0 | AX4: 0 | BI4: 0 | BJ4: 0 | BK4: 0 | BL4: 0 | BM4: 0 | BN4: 0 | BO4: 0 | BP4: 0 | BQ4: 25440 | BR4: 34028 | BS4: 1 | BT4: 7685.6075 | BU4: 6243.7787 | BV4: 1452.1452 | BW4: 50216.427 | BX4: 50040.003 | BY4: 57735.927 | BZ4: 0.44062686 | CA4: 1058.5439 | CB4: 59354.18 | CC4: 0.57330419 | CD4: 60377.035 | CE4: 0.56359177
A5: 45873 | H5: 32407.746 | I5: 32054.105 | J5: 1906.338 | K5: 17 | L5: 8 | M5: 8 | N5: 8 | O5: 7 | P5: 9 | Q5: 2 | R5: 2 | S5: 9676 | T5: 9676 | U5: 1 | V5: 4838 | W5: 0.47058824 | X5: 1 | Y5: 0.47058824 | Z5: 0.875 | AA5: 1 | AB5: 0.28571429 | AC5: 0.11764706 | AD5: 0.11764706 | AE5: 36574.333 | AF5: 0.26455712 | AG5: 9 | AH5: 9 | AI5: 13 | AJ5: 871.79487 | AK5: 988.14745 | AL5: 990.80389 | AM5: 170 | AN5: 1145.8399 | AO5: 0 | AP5: 0 | AQ5: 0 | AR5: 0 | AS5: 0 | AT5: 0 | AU5: 0 | AV5: 0 | AW5: 0 | AX5: 0 | BI5: 0 | BJ5: 0 | BK5: 0 | BL5: 0 | BM5: 0 | BN5: 0 | BO5: 0 | BP5: 0 | BQ5: 9676 | BR5: 9676 | BS5: 1 | BT5: 3294.7912 | BU5: 3030.3667 | BV5: 871.79487 | BW5: 32407.746 | BX5: 32407.746 | BY5: 36309.908 | BZ5: 0.26648374 | CA5: 353.64132 | CB5: 36574.333 | CC5: 0.26455712 | CD5: 36977.538 | CE5: 0.26167237
A6: 45904 | H6: 18252.12 | I6: =H6-CA6 | J6: 793.57043 | K6: 23 | L6: 10 | M6: 10 | N6: 10 | O6: 8 | P6: 11 | Q6: 3 | R6: 4 | S6: 10764 | T6: 19352 | U6: 1 | V6: 4838 | W6: 0.43478261 | X6: 1 | Y6: 0.43478261 | Z6: 0.8 | AA6: 1 | AB6: 0.375 | AC6: 0.13043478 | AD6: 0.17391304 | AE6: 23910.509 | AF6: 0.80935124 | AG6: 11 | AH6: 11 | AI6: 11 | AJ6: 875.4758 | AK6: 1445.8921 | AL6: 2172.7951 | AM6: 230 | AN6: 934.22599 | AO6: 0 | AP6: 0 | AQ6: 0 | AR6: 0 | AS6: 0 | AT6: 0 | AU6: 0 | AV6: 0 | AW6: 0 | AX6: 0 | BI6: 0 | BJ6: 0 | BK6: 0 | BL6: 0 | BM6: 0 | BN6: 0 | BO6: 0 | BP6: 0 | BQ6: 10764 | BR6: 19352 | BS6: 1 | BT6: 4782.9132 | BU6: 3563.8847 | BV6: 875.4758 | BW6: 18252.12 | BX6: 18073.481 | BY6: 22512.841 | BZ6: 0.47812712 | CA6: 714.55655 | CB6: 23910.509 | CC6: 0.80935124 | CD6: 24760.033 | CE6: 0.78158216
A7: 45931 | H7: 22910.083 | I7: =H7-CA7 | J7: 388.3065 | K7: 59 | L7: 9 | M7: 9 | N7: 9 | O7: 7 | P7: 9 | Q7: 3 | R7: 3 | S7: 15664 | T7: 15664 | U7: 1 | V7: 5221.3333 | W7: 0.15254237 | X7: 1 | Y7: 0.15254237 | Z7: 0.77777778 | AA7: 1 | AB7: 0.42857143 | AC7: 0.050847458 | AD7: 0.050847458 | AE7: 28875.778 | AF7: 0.54246157 | AG7: 9 | AH7: 9 | AI7: 9 | AJ7: 1609.509 | AK7: 1280.2263 | AL7: 1723.0665 | AM7: 590 | AN7: 762.89314 | AO7: 0 | AP7: 0 | AQ7: 0 | AR7: 0 | AS7: 0 | AT7: 0 | AU7: 0 | AV7: 0 | AW7: 0 | AX7: 0 | BI7: 0 | BJ7: 0 | BK7: 0 | BL7: 0 | BM7: 0 | BN7: 0 | BO7: 0 | BP7: 0 | BQ7: 15664 | BR7: 15664 | BS7: 1 | BT7: 4356.1859 | BU7: 4186.654 | BV7: 1609.509 | BW7: 22910.083 | BX7: 22910.083 | BY7: 28706.246 | BZ7: 0.54566521 | CA7: 535.91741 | CB7: 28875.778 | CC7: 0.54246157 | CD7: 31691.269 | CE7: 0.49426862
A8: 45962 | H8: 1629.056 | I8: =H8-CA8 | J8: 814.528 | K8: 2 | L8: 1 | M8: 1 | N8: 1 | O8: 0 | P8: 1 | Q8: 0 | R8: 0 | S8: 0 | T8: 0 | W8: 0.5 | X8: 1 | Y8: 0.5 | Z8: 0 | AA8: 1 | AC8: 0 | AD8: 0 | AE8: 281.9456 | AF8: 0 | AG8: 1 | AH8: 1 | AI8: 1 | AJ8: 59.07173 | AK8: 118.10796 | AL8: 0 | AM8: 20 | AN8: 84.765904 | AO8: 0 | AP8: 0 | AQ8: 0 | AR8: 0 | AS8: 0 | AT8: 0 | AU8: 0 | AV8: 0 | AW8: 0 | AX8: 0 | BI8: 0 | BJ8: 0 | BK8: 0 | BL8: 0 | BM8: 0 | BN8: 0 | BO8: 0 | BP8: 0 | BQ8: 0 | BR8: 0 | BT8: 222.87387 | BU8: 138.10796 | BV8: 59.07173 | BW8: 1629.056 | BX8: 1629.056 | BY8: 197.17969 | BZ8: 0 | CA8: 0 | CB8: 281.9456 | CC8: 0 | CD8: 372.87387 | CE8: 0
A9: mamidaily-汇总 | H9: =SUM(H3:H8) | I9: =SUM(I3:I8) | J9: =I9/K9 | K9: =SUM(K3:K8) | L9: =SUM(L3:L8) | M9: =SUM(M3:M8) | N9: =SUM(N3:N8) | O9: =SUM(O3:O8) | P9: =SUM(P3:P8) | Q9: =SUM(Q3:Q8) | R9: =SUM(R3:R8) | ... T9: =SUM(T3:T8) | V9: =T9/R9 | W9: =L9/K9 | X9: =N9/L9 | Y9: =N9/K9 | Z9: =O9/N9 | AA9: =AVERAGE(AA3:AA8) | AB9: =Q9/O9 | AC9: =Q9/K9 | AD9: =R9/K9 | AE9: =SUM(AE3:AE8) | AF9: =T9/AE9 | AG9: =SUM(AG3:AG8) | AH9: =SUM(AH3:AH8) | AI9: =SUM(AI3:AI8) | AJ9: =SUM(AJ3:AJ8) | AK9: =SUM(AK3:AK8) | AL9: =SUM(AL3:AL8) | AM9: =SUM(AM3:AM8) | AN9: =SUM(AN3:AN8) | ... AP9: =SUM(AP3:AP8) | AR9: =SUM(AR3:AR8) | AS9: =SUM(AS3:AS8) | AT9: =SUM(AT3:AT8) | AU9: =SUM(AU3:AU8) | AV9: =SUM(AV3:AV8) | AW9: =SUM(AW3:AW8) | AX9: =SUM(AX3:AX8) | AZ9: =AX9/AV9 | BA9: =AP9/AO9 | BB9: =AR9/AP9 | BC9: =AR9/AO9 | BD9: =AS9/AR9 | BE9: =AVERAGE(BE3:BE8) | BF9: =AU9/AS9 | BG9: =AU9/AO9 | BH9: =AV9/AO9 | BI9: =SUM(BI3:BI8) | BJ9: =SUM(BJ3:BJ8) | BK9: =SUM(BK3:BK8) | BL9: =SUM(BL3:BL8) | BM9: =SUM(BM3:BM8) | BN9: =SUM(BN3:BN8) | BO9: =SUM(BO3:BO8) | BP9: =SUM(BP3:BP8) | ... BR9: =SUM(BR3:BR8) | BT9: =SUM(BT3:BT8) | BU9: =SUM(BU3:BU8) | BV9: =SUM(BV3:BV8) | BW9: =SUM(BW3:BW8) | BX9: =SUM(BX3:BX8) | BY9: =SUM(BY3:BY8) | BZ9: =BQ9/BY9 | CA9: =SUM(CA3:CA8) | CB9: =SUM(CB3:CB8) | CC9: =BR9/CB9 | CD9: =SUM(CD3:CD8) | CE9: =BR9/CD9

Sheet 吴若希
I1: 主投 | AO1: 辅投 | BQ1: 汇总
B2: 渠道组 | C2: 供应商 | D2: 渠道名称 | E2: 主投 | F2: 辅投 | G2: 结算方式 | H2: 滚动消耗 | I2: 滚动消耗(不含赠课成本) | J2: 单例子成本 | K2: 例子数 | L2: 分发数 | M2: 剔除毛例子 分发数 | N2: 约课数 | O2: 到课数 | P2: 滚动到课数 | Q2: 当月成交数 | R2: 滚动成交数 | S2: 当月GMV | T2: 滚动GMV | U2: 海外GMV占比 | V2: 滚动ASP | W2: 例子分发率 | X2: 分发约课率 | Y2: 例子约课率 | Z2: 约课到课率 | AA2: 滚动应到课率 | AB2: 到课转化率 | AC2: 注册转化率 | AD2: 滚动转化率 | AE2: 滚动ROI2总成本 | AF2: 滚动ROI2 | AG2: 滚动应到课人数 | AH2: 滚动到课人数 | AI2: 滚动到课人次 | AJ2: 运营成本 | AK2: 销售固定成本 | AL2: 销售变动成本 | AM2: TMK费用 | AN2: DEMO费用 | AO2: 例子数 | AP2: 分发数 | AQ2: 剔除毛例子分发数 | AR2: 约课数 | AS2: 到课数 | AT2: 滚动到课数 | AU2: 当月成交 | AV2: 滚动成交数 | AW2: 当月GMV | AX2: 滚动GMV | AY2: 海外GMV占比 | AZ2: 滚动ASP | BA2: 例子分发率 | BB2: 分发约课率 | BC2: 例子约课率 | BD2: 约课到课率 | BE2: 滚动应到课率 | BF2: 到课转化率 | BG2: 注册转化率 | BH2: 滚动转化率 | BI2: 滚动应到课人数 | BJ2: 滚动到课人数 | BK2: 滚动到课人次 | BL2: 运营成本 | BM2: 销售固定成本 | BN2: 销售变动成本 | BO2: TMK费用 | BP2: DEMO费用 | BQ2: 当月GMV | BR2: 滚动GMV | BS2: 海外GMV占比 | BT2: 滚动其他成本 | BU2: 同源其他成本 | BV2: 运营成本 | BW2: 滚动消耗 | BX2: 同源消耗 | BY2: 当月ROI2总成本 | BZ2: 当月ROI2 | CA2: 滚动赠课成本 | CB2: 滚动ROI2总成本 | CC2: 滚动ROI2 | CD2: O-ROI总成本 | CE2: O-ROI
A3: 45842 | H3: 68696.001 | I3: 67637.457 | J3: 1205.193 | K3: 57 | L3: 28 | M3: 28 | N3: 29 | O3: 25 | P3: 25 | Q3: 6 | R3: 6 | S3: 26528 | T3: 26528 | U3: 1 | V3: 4421.3333 | W3: 0.49122807 | X3: 1.0357143 | Y3: 0.50877193 | Z3: 0.86206897 | AA3: 0.96153846 | AB3: 0.24 | AC3: 0.10526316 | AD3: 0.10526316 | AE3: 79737.245 | AF3: 0.33269271 | AG3: 26 | AH3: 25 | AI3: 26 | AJ3: 2508.2508 | AK3: 2938.1512 | AL3: 2716.4165 | AM3: 586.74653 | AN3: 2291.6798 | AO3: 0 | AP3: 0 | AQ3: 0 | AR3: 0 | AS3: 0 | AT3: 0 | AU3: 0 | AV3: 0 | AW3: 0 | AX3: 0 | BI3: 0 | BJ3: 0 | BK3: 0 | BL3: 0 | BM3: 0 | BN3: 0 | BO3: 0 | BP3: 0 | BQ3: 26528 | BR3: 26528 | BS3: 1 | BT3: 8532.994 | BU3: 8532.994 | BV3: 2508.2508 | BW3: 68696.001 | BX3: 68696.001 | BY3: 79737.245 | BZ3: 0.33269271 | CA3: 1058.5439 | CB3: 79737.245 | CC3: 0.33269271 | CD3: 81503.995 | CE3: 0.32548098
A4: 45873 | H4: 42366.298 | I4: 42189.478 | J4: 1460.9068 | K4: 29 | L4: 10 | M4: 11 | N4: 11 | O4: 6 | P4: 9 | Q4: 1 | R4: 1 | S4: 3588 | T4: 3588 | U4: 1 | V4: 3588 | W4: 0.34482759 | X4: 1.1 | Y4: 0.37931034 | Z4: 0.54545455 | AA4: 1 | AB4: 0.16666667 | AC4: 0.034482759 | AD4: 0.034482759 | AE4: 47881.927 | AF4: 0.074934327 | AG4: 9 | AH4: 9 | AI4: 10 | AJ4: 2618.1064 | AK4: 1358.7027 | AL4: 367.40434 | AM4: 290 | AN4: 881.41531 | AO4: 0 | AP4: 0 | AQ4: 0 | AR4: 0 | AS4: 0 | AT4: 0 | AU4: 0 | AV4: 0 | AW4: 0 | AX4: 0 | BI4: 0 | BJ4: 0 | BK4: 0 | BL4: 0 | BM4: 0 | BN4: 0 | BO4: 0 | BP4: 0 | BQ4: 3588 | BR4: 3588 | BS4: 1 | BT4: 2897.5224 | BU4: 2421.4378 | BV4: 2618.1064 | BW4: 42366.298 | BX4: 42366.298 | BY4: 47405.842 | BZ4: 0.075686873 | CA4: 176.82066 | CB4: 47881.927 | CC4: 0.074934327 | CD4: 47438.821 | CE4: 0.075634258
A5: 45904 | H5: 29370.632 | I5: =H5-CA5 | J5: 2097.9023 | K5: 14 | L5: 8 | M5: 9 | N5: 7 | O5: 6 | P5: 8 | Q5: 3 | R5: 3 | S5: 10764 | T5: 10764 | U5: 1 | V5: 3588 | W5: 0.57142857 | X5: 0.875 | Y5: 0.5 | Z5: 0.85714286 | AA5: 1 | AB5: 0.5 | AC5: 0.21428571 | AD5: 0.21428571 | AE5: 33760.691 | AF5: 0.31883234 | AG5: 8 | AH5: 8 | AI5: 8 | AJ5: 1060.7637 | AK5: 1301.3029 | AL5: 1208.5555 | AM5: 140 | AN5: 679.43708 | AO5: 0 | AP5: 0 | AQ5: 0 | AR5: 0 | AS5: 0 | AT5: 0 | AU5: 0 | AV5: 0 | AW5: 0 | AX5: 0 | BI5: 0 | BJ5: 0 | BK5: 0 | BL5: 0 | BM5: 0 | BN5: 0 | BO5: 0 | BP5: 0 | BQ5: 10764 | BR5: 10764 | BS5: 1 | BT5: 3329.2955 | BU5: 3014.847 | BV5: 1060.7637 | BW5: 29370.632 | BX5: 29370.632 | BY5: 33446.243 | BZ5: 0.32182987 | CA5: 535.91741 | CB5: 33760.691 | CC5: 0.31883234 | CD5: 33749.927 | CE5: 0.31893402
A6: 45931 | H6: 3211.7104 | I6: =H6-CA6 | J6: 356.85672 | K6: 9 | L6: 4 | M6: 4 | N6: 4 | O6: 4 | P6: 4 | Q6: 0 | R6: 0 | S6: 0 | T6: 0 | W6: 0.44444444 | X6: 1 | Y6: 0.44444444 | Z6: 1 | AA6: 1 | AB6: 0 | AC6: 0 | AD6: 0 | AE6: 1560.4153 | AF6: 0 | AG6: 4 | AH6: 4 | AI6: 4 | AJ6: 562.36221 | AK6: 568.98945 | AL6: 0 | AM6: 90 | AN6: 339.06362 | AO6: 0 | AP6: 0 | AQ6: 0 | AR6: 0 | AS6: 0 | AT6: 0 | AU6: 0 | AV6: 0 | AW6: 0 | AX6: 0 | BI6: 0 | BJ6: 0 | BK6: 0 | BL6: 0 | BM6: 0 | BN6: 0 | BO6: 0 | BP6: 0 | BQ6: 0 | BR6: 0 | BT6: 998.05306 | BU6: 998.05306 | BV6: 562.36221 | BW6: 3211.7104 | BX6: 3211.7104 | BY6: 1560.4153 | BZ6: 0 | CA6: 0 | CB6: 1560.4153 | CC6: 0 | CD6: 1673.0531 | CE6: 0
A7: 45962
A8: 吴若希-汇总 | H8: =SUM(H3:H7) | I8: =SUM(I3:I7) | J8: =I8/K8 | K8: =SUM(K3:K7) | L8: =SUM(L3:L7) | M8: =SUM(M3:M7) | N8: =SUM(N3:N7) | O8: =SUM(O3:O7) | P8: =SUM(P3:P7) | Q8: =SUM(Q3:Q7) | R8: =SUM(R3:R7) | ... T8: =SUM(T3:T7) | V8: =T8/R8 | W8: =L8/K8 | X8: =N8/L8 | Y8: =N8/K8 | Z8: =O8/N8 | AA8: =AVERAGE(AA3:AA7) | AB8: =Q8/O8 | AC8: =Q8/K8 | AD8: =R8/K8 | AE8: =SUM(AE3:AE7) | AF8: =T8/AE8 | AG8: =SUM(AG3:AG7) | AH8: =SUM(AH3:AH7) | AI8: =SUM(AI3:AI7) | AJ8: =SUM(AJ3:AJ7) | AK8: =SUM(AK3:AK7) | AL8: =SUM(AL3:AL7) | AM8: =SUM(AM3:AM7) | AN8: =SUM(AN3:AN7) | ... AP8: =SUM(AP3:AP7) | AR8: =SUM(AR3:AR7) | AS8: =SUM(AS3:AS7) | AT8: =SUM(AT3:AT7) | AU8: =SUM(AU3:AU7) | AV8: =SUM(AV3:AV7) | AW8: =SUM(AW3:AW7) | AX8: =SUM(AX3:AX7) | AZ8: =AX8/AV8 | BA8: =AP8/AO8 | BB8: =AR8/AP8 | BC8: =AR8/AO8 | BD8: =AS8/AR8 | BE8: =AVERAGE(BE3:BE7) | BF8: =AU8/AS8 | BG8: =AU8/AO8 | BH8: =AV8/AO8 | BI8: =SUM(BI3:BI7) | BJ8: =SUM(BJ3:BJ7) | BK8: =SUM(BK3:BK7) | BL8: =SUM(BL3:BL7) | BM8: =SUM(BM3:BM7) | BN8: =SUM(BN3:BN7) | BO8: =SUM(BO3:BO7) | BP8: =SUM(BP3:BP7) | ... BR8: =SUM(BR3:BR7) | BT8: =SUM(BT3:BT7) | BU8: =SUM(BU3:BU7) | BV8: =SUM(BV3:BV7) | BW8: =SUM(BW3:BW7) | BX8: =SUM(BX3:BX7) | BY8: =SUM(BY3:BY7) | BZ8: =BQ8/BY8 | CA8: =SUM(CA3:CA7) | CB8: =SUM(CB3:CB7) | CC8: =BR8/CB8 | CD8: =SUM(CD3:CD7) | CE8: =BR8/CD8

Sheet 张美妮
I1: 主投 | AO1: 辅投 | BQ1: 汇总
B2: 渠道组 | C2: 供应商 | D2: 渠道名称 | E2: 主投 | F2: 辅投 | G2: 结算方式 | H2: 滚动消耗 | I2: 滚动消耗(不含赠课成本) | J2: 单例子成本 | K2: 例子数 | L2: 分发数 | M2: 剔除毛例子 分发数 | N2: 约课数 | O2: 到课数 | P2: 滚动到课数 | Q2: 当月成交数 | R2: 滚动成交数 | S2: 当月GMV | T2: 滚动GMV | U2: 海外GMV占比 | V2: 滚动ASP | W2: 例子分发率 | X2: 分发约课率 | Y2: 例子约课率 | Z2: 约课到课率 | AA2: 滚动应到课率 | AB2: 到课转化率 | AC2: 注册转化率 | AD2: 滚动转化率 | AE2: 滚动ROI2总成本 | AF2: 滚动ROI2 | AG2: 滚动应到课人数 | AH2: 滚动到课人数 | AI2: 滚动到课人次 | AJ2: 运营成本 | AK2: 销售固定成本 | AL2: 销售变动成本 | AM2: TMK费用 | AN2: DEMO费用 | AO2: 例子数 | AP2: 分发数 | AQ2: 剔除毛例子分发数 | AR2: 约课数 | AS2: 到课数 | AT2: 滚动到课数 | AU2: 当月成交 | AV2: 滚动成交数 | AW2: 当月GMV | AX2: 滚动GMV | AY2: 海外GMV占比 | AZ2: 滚动ASP | BA2: 例子分发率 | BB2: 分发约课率 | BC2: 例子约课率 | BD2: 约课到课率 | BE2: 滚动应到课率 | BF2: 到课转化率 | BG2: 注册转化率 | BH2: 滚动转化率 | BI2: 滚动应到课人数 | BJ2: 滚动到课人数 | BK2: 滚动到课人次 | BL2: 运营成本 | BM2: 销售固定成本 | BN2: 销售变动成本 | BO2: TMK费用 | BP2: DEMO费用 | BQ2: 当月GMV | BR2: 滚动GMV | BS2: 海外GMV占比 | BT2: 滚动其他成本 | BU2: 同源其他成本 | BV2: 运营成本 | BW2: 滚动消耗 | BX2: 同源消耗 | BY2: 当月ROI2总成本 | BZ2: 当月ROI2 | CA2: 滚动赠课成本 | CB2: 滚动ROI2总成本 | CC2: 滚动ROI2 | CD2: O-ROI总成本 | CE2: O-ROI
A3: 45842 | H3: 10610.734 | I3: 10434.31 | J3: 1061.0734 | K3: 10 | L3: 8 | M3: 8 | N3: 8 | O3: 4 | P3: 4 | Q3: 1 | R3: 1 | S3: 3588 | T3: 3588 | U3: 1 | V3: 3588 | W3: 0.8 | X3: 1 | Y3: 0.8 | Z3: 0.5 | AA3: 0.66666667 | AB3: 0.25 | AC3: 0.1 | AD3: 0.1 | AE3: 12713.158 | AF3: 0.28222728 | AG3: 6 | AH3: 4 | AI3: 4 | AJ3: 440.044 | AK3: 839.47178 | AL3: 367.40434 | AM3: 102.93799 | AN3: 352.56612 | AO3: 0 | AP3: 0 | AQ3: 0 | AR3: 0 | AS3: 0 | AT3: 0 | AU3: 0 | AV3: 0 | AW3: 0 | AX3: 0 | BI3: 0 | BJ3: 0 | BK3: 0 | BL3: 0 | BM3: 0 | BN3: 0 | BO3: 0 | BP3: 0 | BQ3: 3588 | BR3: 3588 | BS3: 1 | BT3: 1662.3802 | BU3: 1662.3802 | BV3: 440.044 | BW3: 10610.734 | BX3: 10610.734 | BY3: 12713.158 | BZ3: 0.28222728 | CA3: 176.42398 | CB3: 12713.158 | CC3: 0.28222728 | CD3: 13023.114 | CE3: 0.27551014
A4: 45873 | H4: 26905.87 | I4: 26905.87 | J4: 960.92394 | K4: 28 | L4: 4 | M4: 4 | N4: 3 | O4: 1 | P4: 3 | Q4: 0 | R4: 0 | S4: 0 | T4: 0 | W4: 0.14285714 | X4: 0.75 | Y4: 0.10714286 | Z4: 0.33333333 | AA4: 1 | AB4: 0 | AC4: 0 | AD4: 0 | AE4: 3566.3252 | AF4: 0 | AG4: 3 | AH4: 3 | AI4: 3 | AJ4: 2527.8269 | AK4: 494.07373 | AL4: 0 | AM4: 280 | AN4: 264.42459 | AO4: 0 | AP4: 0 | AQ4: 0 | AR4: 0 | AS4: 0 | AT4: 0 | AU4: 0 | AV4: 0 | AW4: 0 | AX4: 0 | BI4: 0 | BJ4: 0 | BK4: 0 | BL4: 0 | BM4: 0 | BN4: 0 | BO4: 0 | BP4: 0 | BQ4: 0 | BR4: 0 | BT4: 1038.4983 | BU4: 862.21526 | BV4: 2527.8269 | BW4: 26905.87 | BX4: 26905.87 | BY4: 3390.0421 | BZ4: 0 | CA4: 0 | CB4: 3566.3252 | CC4: 0 | CD4: 3138.4983 | CE4: 0
A5: 45904 | H5: 21503.675 | I5: =H5-CA5 | J5: 651.62651 | K5: 33 | L5: 3 | M5: 3 | N5: 2 | O5: 0 | P5: 0 | Q5: 0 | R5: 1 | S5: 0 | T5: 4388 | U5: 1 | V5: 4388 | W5: 0.090909091 | X5: 0.66666667 | Y5: 0.060606061 | Z5: 0 | AC5: 0 | AD5: 0.03030303 | AE5: 25260.488 | AF5: 0.17371002 | AG5: 0 | AH5: 0 | AI5: 0 | AJ5: 2500.3716 | AK5: 433.76763 | AL5: 492.67388 | AM5: 330 | AN5: 0 | AO5: 0 | AP5: 0 | AQ5: 0 | AR5: 0 | AS5: 0 | AT5: 0 | AU5: 0 | AV5: 0 | AW5: 0 | AX5: 0 | BI5: 0 | BJ5: 0 | BK5: 0 | BL5: 0 | BM5: 0 | BN5: 0 | BO5: 0 | BP5: 0 | BQ5: 0 | BR5: 4388 | BS5: 1 | BT5: 1256.4415 | BU5: 763.76763 | BV5: 2500.3716 | BW5: 21503.675 | BX5: 21325.036 | BY5: 24589.175 | BZ5: 0 | CA5: 178.63914 | CB5: 25260.488 | CC5: 0.17371002 | CD5: 25235.116 | CE5: 0.17388467
A6: 45934 | H6: 8041.9016 | I6: =H6-CA6 | J6: 670.15846 | K6: 12 | L6: 1 | M6: 1 | N6: 1 | O6: 1 | P6: 2 | Q6: 0 | R6: 1 | S6: 0 | T6: 6088 | U6: 1 | V6: 6088 | W6: 0.083333333 | X6: 1 | Y6: 0.083333333 | Z6: 1 | AA6: 1 | AB6: 0 | AC6: 0 | AD6: 0.083333333 | AE6: 9893.1873 | AF6: 0.61537296 | AG6: 2 | AH6: 2 | AI6: 2 | AJ6: 749.81628 | AK6: 142.24736 | AL6: 669.69029 | AM6: 120 | AN6: 169.53181 | AO6: 0 | AP6: 0 | AQ6: 0 | AR6: 0 | AS6: 0 | AT6: 0 | AU6: 0 | AV6: 0 | AW6: 0 | AX6: 0 | BI6: 0 | BJ6: 0 | BK6: 0 | BL6: 0 | BM6: 0 | BN6: 0 | BO6: 0 | BP6: 0 | BQ6: 0 | BR6: 6088 | BS6: 1 | BT6: 1101.4695 | BU6: 347.01327 | BV6: 749.81628 | BW6: 8041.9016 | BX6: 7863.2624 | BY6: 8960.092 | BZ6: 0 | CA6: 178.63914 | CB6: 9893.1873 | CC6: 0.61537296 | CD6: 10043.371 | CE6: 0.60617097
A7: 45965
A8: 张美妮-汇总 | H8: =SUM(H3:H7) | I8: =SUM(I3:I7) | J8: =I8/K8 | K8: =SUM(K3:K7) | L8: =SUM(L3:L7) | M8: =SUM(M3:M7) | N8: =SUM(N3:N7) | O8: =SUM(O3:O7) | P8: =SUM(P3:P7) | Q8: =SUM(Q3:Q7) | R8: =SUM(R3:R7) | ... T8: =SUM(T3:T7) | V8: =T8/R8 | W8: =L8/K8 | X8: =N8/L8 | Y8: =N8/K8 | Z8: =O8/N8 | AA8: =AVERAGE(AA3:AA7) | AB8: =Q8/O8 | AC8: =Q8/K8 | AD8: =R8/K8 | AE8: =SUM(AE3:AE7) | AF8: =T8/AE8 | AG8: =SUM(AG3:AG7) | AH8: =SUM(AH3:AH7) | AI8: =SUM(AI3:AI7) | AJ8: =SUM(AJ3:AJ7) | AK8: =SUM(AK3:AK7) | AL8: =SUM(AL3:AL7) | AM8: =SUM(AM3:AM7) | AN8: =SUM(AN3:AN7) | ... AP8: =SUM(AP3:AP7) | AR8: =SUM(AR3:AR7) | AS8: =SUM(AS3:AS7) | AT8: =SUM(AT3:AT7) | AU8: =SUM(AU3:AU7) | AV8: =SUM(AV3:AV7) | AW8: =SUM(AW3:AW7) | AX8: =SUM(AX3:AX7) | AZ8: =AX8/AV8 | BA8: =AP8/AO8 | BB8: =AR8/AP8 | BC8: =AR8/AO8 | BD8: =AS8/AR8 | BE8: =AVERAGE(BE3:BE7) | BF8: =AU8/AS8 | BG8: =AU8/AO8 | BH8: =AV8/AO8 | BI8: =SUM(BI3:BI7) | BJ8: =SUM(BJ3:BJ7) | BK8: =SUM(BK3:BK7) | BL8: =SUM(BL3:BL7) | BM8: =SUM(BM3:BM7) | BN8: =SUM(BN3:BN7) | BO8: =SUM(BO3:BO7) | BP8: =SUM(BP3:BP7) | ... BR8: =SUM(BR3:BR7) | BT8: =SUM(BT3:BT7) | BU8: =SUM(BU3:BU7) | BV8: =SUM(BV3:BV7) | BW8: =SUM(BW3:BW7) | BX8: =SUM(BX3:BX7) | BY8: =SUM(BY3:BY7) | BZ8: =BQ8/BY8 | CA8: =SUM(CA3:CA7) | CB8: =SUM(CB3:CB7) | CC8: =BR8/CB8 | CD8: =SUM(CD3:CD7) | CE8: =BR8/CD8

Sheet 钟嘉欣
K1: 主投 | AT1: 辅投 | BY1: 汇总
B2: 渠道组 | C2: 供应商 | D2: 渠道名称 | E2: 主投 | F2: 辅投 | G2: 结算方式 | H2: CPT合作成本消耗 | I2: CPM投放成本消耗 | J2: 滚动消耗 | K2: 滚动消耗(不含赠课成本) | L2: 单例子成本 | M2: 例子数 | N2: 分发数 | O2: 剔除毛例子 分发数 | P2: 约课数 | Q2: 到课数 | T2: 滚动到课数 | U2: 当月成交数 | V2: 滚动成交数 | W2: 当月GMV | X2: 滚动GMV | Y2: 海外GMV占比 | Z2: 滚动ASP | AA2: 例子分发率 | AB2: 分发约课率 | AC2: 例子约课率 | AD2: 约课到课率 | AF2: 滚动应到课率 | AG2: 到课转化率 | AH2: 注册转化率 | AI2: 滚动转化率 | AJ2: 滚动ROI2总成本 | AK2: 滚动ROI2 | AL2: 滚动应到课人数 | AM2: 滚动到课人数 | AN2: 滚动到课人次 | AO2: 运营成本 | AP2: 销售固定成本 | AQ2: 销售变动成本 | AR2: TMK费用 | AS2: DEMO费用 | AT2: 例子数 | AU2: 分发数 | AV2: 剔除毛例子分发数 | AW2: 约课数 | AZ2: 到课数 | BA2: 滚动到课数 | BB2: 当月成交 | BC2: 滚动成交数 | BD2: 当月GMV | BE2: 滚动GMV | BF2: 海外GMV占比 | BG2: 滚动ASP | BH2: 例子分发率 | BI2: 分发约课率 | BJ2: 例子约课率 | BK2: 约课到课率 | BM2: 滚动应到课率 | BN2: 到课转化率 | BO2: 注册转化率 | BP2: 滚动转化率 | BQ2: 滚动应到课人数 | BR2: 滚动到课人数 | BS2: 滚动到课人次 | BT2: 运营成本 | BU2: 销售固定成本 | BV2: 销售变动成本 | BW2: TMK费用 | BX2: DEMO费用 | BY2: 当月GMV | BZ2: 滚动GMV | CA2: 海外GMV占比 | CB2: 滚动其他成本 | CC2: 同源其他成本 | CD2: 运营成本 | CE2: 滚动消耗 | CF2: 同源消耗 | CG2: 当月ROI2总成本 | CH2: 当月ROI2 | CI2: 滚动赠课成本 | CJ2: 滚动ROI2总成本 | CK2: 滚动ROI2 | CL2: O-ROI总成本 | CM2: O-ROI
A3: 45873 | H3: =J3-I3 | I3: 131727 | J3: 171568.03 | K3: 162727 | L3: 349.19957 | M3: 466 | N3: 167 | O3: 167 | P3: 167 | Q3: 162 | R3: 128 | S3: 127 | T3: 127 | U3: 50 | V3: 50 | W3: 256600 | X3: 256600 | Z3: 5132 | AA3: 0.3583691 | AB3: 1 | AC3: 0.3583691 | AD3: 0.76047904 | AE3: 0.78395062 | AF3: 0.9950495 | AG3: 0.39370079 | AH3: 0.10729614 | AI3: 0.10729614 | AJ3: 267672.54 | AK3: 0.95863401 | AL3: 128 | AM3: 127 | AN3: 142 | AO3: 25732.782 | AP3: 25595.464 | AQ3: 28209.928 | AR3: 4319.5523 | AS3: 12246.78 | AT3: 0 | AU3: 0 | AW3: 0 | AZ3: 0 | BA3: 0 | BB3: 0 | BC3: 0 | BD3: 0 | BE3: 0 | BG3: #DIV/0! | BH3: #DIV/0! | BI3: #DIV/0! | BJ3: #DIV/0! | BK3: #DIV/0! | BM3: #DIV/0! | BN3: #DIV/0! | BO3: #DIV/0! | BP3: #DIV/0! | BQ3: 0 | BR3: 0 | BS3: 0 | BT3: 0 | BU3: 0 | BV3: 0 | BW3: 0 | BX3: 0 | BY3: 256600 | BZ3: 256600 | CB3: 70371.724 | CC3: 70371.724 | CD3: 25732.782 | CE3: 171568.03 | CF3: 171568.03 | CG3: 267672.54 | CH3: 0.95863401 | CI3: 8841.0331 | CJ3: 267672.54 | CK3: 0.95863401 | CL3: 276889.76 | CM3: 0.92672262
A4: 45904 | H4: =J4-I4 | I4: 156885 | J4: 196638.32 | K4: 187885 | L4: 458.2561 | M4: 410 | N4: 120 | O4: 128 | P4: 115 | Q4: 106 | R4: 113 | S4: 91 | T4: 112 | U4: 40 | V4: 49 | W4: 195020 | X4: 234812 | Z4: 4792.0816 | AA4: 0.29268293 | AB4: 0.95833333 | AC4: 0.2804878 | AD4: 0.79130435 | AE4: 0.85849057 | AF4: 0.99122807 | AG4: 0.43956044 | AH4: 0.097560976 | AI4: 0.1195122 | AJ4: 275288.76 | AK4: 0.85296616 | AL4: 113 | AM4: 112 | AN4: 124 | AO4: 19402.816 | AP4: 18734.203 | AQ4: 25385.431 | AR4: 3882.7517 | AS4: 11245.244 | AT4: 0 | AU4: 0 | AW4: 0 | AZ4: 0 | BA4: 0 | BB4: 0 | BC4: 0 | BD4: 0 | BE4: 0 | BG4: #DIV/0! | BH4: #DIV/0! | BI4: #DIV/0! | BJ4: #DIV/0! | BK4: #DIV/0! | BM4: #DIV/0! | BN4: #DIV/0! | BO4: #DIV/0! | BP4: #DIV/0! | BQ4: 0 | BR4: 0 | BS4: 0 | BT4: 0 | BU4: 0 | BV4: 0 | BW4: 0 | BX4: 0 | BY4: 195020 | BZ4: 234812 | CB4: 59247.63 | CC4: 51507.659 | CD4: 19402.816 | CE4: 196638.32 | CF4: 195030.57 | CG4: 265941.04 | CH4: 0.73332044 | CI4: 8753.3177 | CJ4: 275288.76 | CK4: 0.85296616 | CL4: 286635.95 | CM4: 0.81919941
A5: 45931 | H5: =J5-I5 | I5: 134343 | J5: 179212.87 | K5: 175282.81 | L5: 481.54617 | M5: 364 | N5: 81 | O5: 84 | P5: 78 | Q5: 60 | T5: 67 | U5: 20 | V5: 22 | W5: 130215 | X5: 138191 | Z5: 6281.4091 | AA5: 0.22252747 | AB5: 0.96296296 | AC5: 0.21428571 | AD5: 0.76923077 | AF5: 0.99107143 | AG5: 0.33333333 | AH5: 0.054945055 | AI5: 0.06043956 | AJ5: 239019.99 | AK5: 0.57815666 | AL5: 68 | AM5: 67 | AN5: 74 | AO5: 22744.427 | AP5: 11948.778 | AQ5: 15201.243 | AR5: 3640 | AS5: 6272.6769 | AT5: 0 | AU5: 0 | AW5: 0 | AZ5: 0 | BA5: 0 | BB5: 0 | BC5: 0 | BD5: 0 | BE5: 0 | BG5: #DIV/0! | BH5: #DIV/0! | BI5: #DIV/0! | BJ5: #DIV/0! | BK5: #DIV/0! | BM5: #DIV/0! | BN5: #DIV/0! | BO5: #DIV/0! | BP5: #DIV/0! | BQ5: 0 | BR5: 0 | BS5: 0 | BT5: 0 | BU5: 0 | BV5: 0 | BW5: 0 | BX5: 0 | BY5: 130215 | BZ5: 138191 | CB5: 37062.699 | CC5: 35080.456 | CD5: 22744.427 | CE5: 179212.87 | CF5: 178855.59 | CG5: 236680.47 | CH5: 0.55017213 | CI5: 3930.061 | CJ5: 239019.99 | CK5: 0.57815666 | CL5: 243575.57 | CM5: 0.56734344
A6: 45962 | H6: =J6-I6 | I6: 138315 | J6: 173496.47 | K6: 169385.86 | L6: 951.60593 | M6: 178 | N6: 100 | O6: 102 | P6: 96 | Q6: 90 | R6: 74 | S6: 67 | T6: 73 | U6: 21 | V6: 23 | W6: 119686 | X6: 135684 | Z6: 5899.3043 | AA6: 0.56179775 | AB6: 0.96 | AC6: 0.53932584 | AD6: 0.69791667 | AE6: 0.74444444 | AF6: 0.98484848 | AG6: 0.31343284 | AH6: 0.11797753 | AI6: 0.12921348 | AJ6: 224529.2 | AK6: 0.60430447 | AL6: 74 | AM6: 73 | AN6: 77 | AO6: 8946.2086 | AP6: 14734.641 | AQ6: 18429.915 | AR6: 1839.7091 | AS6: 7082.2557 | AT6: 0 | AU6: 0 | AW6: 0 | AZ6: 0 | BA6: 0 | BB6: 0 | BC6: 0 | BD6: 0 | BE6: 0 | BG6: #DIV/0! | BH6: #DIV/0! | BI6: #DIV/0! | BJ6: #DIV/0! | BK6: #DIV/0! | BM6: #DIV/0! | BN6: #DIV/0! | BO6: #DIV/0! | BP6: #DIV/0! | BQ6: 0 | BR6: 0 | BS6: 0 | BT6: 0 | BU6: 0 | BV6: 0 | BW6: 0 | BX6: 0 | BY6: 119686 | BZ6: 135684 | CB6: 42086.521 | CC6: 39072.739 | CD6: 8946.2086 | CE6: 173496.47 | CF6: 173139.03 | CG6: 221157.97 | CH6: 0.54117877 | CI6: 4110.6141 | CJ6: 224529.2 | CK6: 0.60430447 | CL6: 228932.99 | CM6: 0.59267998
A7: 45992 | H7: =J7-I7 | I7: 204236 | J7: 243212.41 | K7: 234236 | L7: 711.96353 | M7: 329 | N7: 162 | O7: 170 | P7: 164 | Q7: 160 | R7: 135 | S7: 116 | T7: 134 | U7: 35 | V7: 46 | W7: 190601 | X7: 248369.1 | Z7: 5399.3283 | AA7: 0.49240122 | AB7: 1.0123457 | AC7: 0.49848024 | AD7: 0.70731707 | AE7: 0.725 | AF7: 0.997151 | AG7: 0.30172414 | AH7: 0.10638298 | AI7: 0.13981763 | AJ7: 333004.09 | AK7: 0.745844 | AL7: 135 | AM7: 134 | AN7: 146 | AO7: 24548.846 | AP7: 25028.738 | AQ7: 30722.604 | AR7: 3290 | AS7: 12287.92 | AT7: 0 | AU7: 0 | AW7: 0 | AZ7: 0 | BA7: 0 | BB7: 0 | BC7: 0 | BD7: 0 | BE7: 0 | BG7: #DIV/0! | BH7: #DIV/0! | BI7: #DIV/0! | BJ7: #DIV/0! | BK7: #DIV/0! | BM7: #DIV/0! | BN7: #DIV/0! | BO7: #DIV/0! | BP7: #DIV/0! | BQ7: 0 | BR7: 0 | BS7: 0 | BT7: 0 | BU7: 0 | BV7: 0 | BW7: 0 | BX7: 0 | BY7: 190601 | BZ7: 248369.1 | CB7: 71329.262 | CC7: 61322.4 | CD7: 24548.846 | CE7: 272962.71 | CF7: 270816.18 | CG7: 356687.42 | CH7: 0.53436423 | CI7: 8976.4081 | CJ7: 368840.82 | CK7: 0.67337748 | CL7: 368966.97 | CM7: 0.67314724
A8: 46023 | H8: =J8-I8 | I8: 239756 | J8: 283662.3 | K8: 272563.73 | L8: 572.61287 | M8: 476 | N8: 254 | O8: 258 | P8: 257 | Q8: 247 | R8: 212 | S8: 186 | T8: 207 | U8: 49 | V8: 55 | W8: 247112 | X8: 279351.2 | Z8: 5079.1127 | AA8: 0.53361345 | AB8: 1.011811 | AC8: 0.53991597 | AD8: 0.72373541 | AE8: 0.75303644 | AF8: 0.945845 | AG8: 0.26344086 | AH8: 0.10294118 | AI8: 0.11554622 | AJ8: 403501.73 | AK8: 0.69231724 | AL8: 212 | AM8: 207 | AN8: 223 | AO8: 31595.488 | AP8: 43331.122 | AQ8: 25069.849 | AR8: 5351.4869 | AS8: 18299.209 | AT8: 0 | AU8: 0 | AW8: 0 | AZ8: 0 | BA8: 0 | BB8: 0 | BC8: 0 | BD8: 0 | BE8: 0 | BG8: #DIV/0! | BH8: #DIV/0! | BI8: #DIV/0! | BJ8: #DIV/0! | BK8: #DIV/0! | BM8: #DIV/0! | BN8: #DIV/0! | BO8: #DIV/0! | BP8: #DIV/0! | BQ8: 0 | BR8: 0 | BS8: 0 | BT8: 0 | BU8: 0 | BV8: 0 | BW8: 0 | BX8: 0 | BY8: 247112 | BZ8: 279351.2 | CB8: 92051.666 | CC8: 86517.198 | CD8: 31595.488 | CE8: 283662.3 | CF8: 282451.55 | CG8: 396756.5 | CH8: 0.62283037 | CI8: 11098.572 | CJ8: 403501.73 | CK8: 0.69231724 | CL8: 407606.24 | CM8: 0.68534574
A9: 46054 | H9: =J9-I9 | I9: 132054 | J9: 163904.96 | K9: 163904.96 | L9: 832.00486 | M9: 197 | N9: 90 | O9: 99 | P9: 94 | Q9: 84 | R9: 81 | S9: 54 | T9: 80 | U9: 16 | V9: 19 | W9: 80508 | X9: 92672 | Z9: 4877.4737 | AA9: 0.45685279 | AB9: 1.0444444 | AC9: 0.47715736 | AD9: 0.57446809 | AE9: 0.64285714 | AF9: 0.99367089 | AG9: 0.2962963 | AH9: 0.081218274 | AI9: 0.096446701 | AJ9: 196115.7 | AK9: 0.47253739 | AL9: 81 | AM9: 80 | AN9: 82 | AO9: 25964.831 | AP9: 19196.412 | AQ9: 12148.549 | AR9: 1970 | AS9: 6720.7864 | AT9: 0 | AU9: 0 | AW9: 0 | AZ9: 0 | BA9: 0 | BB9: 0 | BC9: 0 | BD9: 0 | BE9: 0 | BG9: #DIV/0! | BH9: #DIV/0! | BI9: #DIV/0! | BJ9: #DIV/0! | BK9: #DIV/0! | BM9: #DIV/0! | BN9: #DIV/0! | BO9: #DIV/0! | BP9: #DIV/0! | BQ9: 0 | BR9: 0 | BS9: 0 | BT9: 0 | BU9: 0 | BV9: 0 | BW9: 0 | BX9: 0 | BY9: 80508 | BZ9: 92672 | CB9: 40035.748 | CC9: 34483.075 | CD9: 25964.831 | CE9: 163904.96 | CF9: 163904.96 | CG9: 190563.03 | CH9: 0.4224744 | CI9: 0 | CJ9: 196115.7 | CK9: 0.47253739 | CL9: 184925.87 | CM9: 0.50113054
A10: 46082 | H10: =J10-I10 | I10: 228327 | J10: 261203.86 | K10: 253155.28 | L10: 545.59328 | M10: 464 | N10: 208 | O10: 212 | P10: 219 | Q10: 209 | R10: 184 | S10: 158 | T10: 179 | U10: 36 | V10: 40 | W10: 183568 | X10: 199220 | Z10: 4980.5 | AA10: 0.44827586 | AB10: 1.0528846 | AC10: 0.47198276 | AD10: 0.72146119 | AE10: 0.75598086 | AF10: 0.98075881 | AG10: 0.2278481 | AH10: 0.077586207 | AI10: 0.086206897 | AJ10: 375409.07 | AK10: 0.53067445 | AL10: 184 | AM10: 179 | AN10: 188 | AO10: 40894.746 | AP10: 29313.464 | AQ10: 23641.374 | AR10: 4640 | AS10: 15715.625 | AT10: 0 | AU10: 0 | AW10: 0 | AZ10: 0 | BA10: 0 | BB10: 0 | BC10: 0 | BD10: 0 | BE10: 0 | BG10: #DIV/0! | BH10: #DIV/0! | BI10: #DIV/0! | BJ10: #DIV/0! | BK10: #DIV/0! | BM10: #DIV/0! | BN10: #DIV/0! | BO10: #DIV/0! | BP10: #DIV/0! | BQ10: 0 | BR10: 0 | BS10: 0 | BT10: 0 | BU10: 0 | BV10: 0 | BW10: 0 | BX10: 0 | BY10: 183568 | BZ10: 199220 | CB10: 73310.463 | CC10: 68977.304 | CD10: 40894.746 | CE10: 261203.86 | CF10: 260399 | CG10: 370271.05 | CH10: 0.49576655 | CI10: 8048.5749 | CJ10: 375409.07 | CK10: 0.53067445 | CL10: 369314.32 | CM10: 0.5394321
A11: 46113 | H11: =J11-I11 | I11: 174361 | J11: 211333.41 | K11: 211333.41 | L11: 723.74456 | M11: 292 | N11: 127 | O11: 140 | P11: 133 | Q11: 131 | R11: 128 | S11: 98 | T11: 126 | U11: 38 | V11: 47 | W11: 184944 | X11: 228236 | Z11: 4856.0851 | AA11: 0.43493151 | AB11: 1.0472441 | AC11: 0.45547945 | AD11: 0.73684211 | AE11: 0.7480916 | AF11: 0.98765432 | AG11: 0.3877551 | AH11: 0.13013699 | AI11: 0.1609589 | AJ11: 297160.59 | AK11: 0.76805608 | AL11: 128 | AM11: 126 | AN11: 136 | AO11: 30292.458 | AP11: 17835.121 | AQ11: 23217.713 | AR11: 2920 | AS11: 11561.887 | AT11: 0 | AU11: 0 | AW11: 0 | AZ11: 0 | BA11: 0 | BB11: 0 | BC11: 0 | BD11: 0 | BE11: 0 | BG11: #DIV/0! | BH11: #DIV/0! | BI11: #DIV/0! | BJ11: #DIV/0! | BK11: #DIV/0! | BM11: #DIV/0! | BN11: #DIV/0! | BO11: #DIV/0! | BP11: #DIV/0! | BQ11: 0 | BR11: 0 | BS11: 0 | BT11: 0 | BU11: 0 | BV11: 0 | BW11: 0 | BX11: 0 | BY11: 184944 | BZ11: 228236 | CB11: 55534.721 | CC11: 46839.217 | CD11: 30292.458 | CE11: 211333.41 | CF11: 211333.41 | CG11: 288465.09 | CH11: 0.64113131 | CI11: 0 | CJ11: 297160.59 | CK11: 0.76805608 | CL11: 288768.13 | CM11: 0.79037807
A12: 46143 | H12: =J12-I12 | I12: 181258.63 | J12: 232785.21 | K12: 232785.21 | L12: 620.76056 | M12: 375 | N12: 132 | O12: 140 | P12: 139 | Q12: 133 | R12: 119 | S12: 101 | T12: 117 | U12: 29 | V12: 33 | W12: 138852 | X12: 154304 | Z12: 4675.8788 | AA12: 0.352 | AB12: 1.0530303 | AC12: 0.37066667 | AD12: 0.72661871 | AE12: 0.7593985 | AF12: 0.97720307 | AG12: 0.28712871 | AH12: 0.077333333 | AI12: 0.088 | AJ12: 315547.06 | AK12: 0.48900472 | AL12: 119 | AM12: 117 | AN12: 125 | AO12: 38288.634 | AP12: 15383.086 | AQ12: 14748.754 | AR12: 3750 | AS12: 10591.371 | AT12: 0 | AU12: 0 | AW12: 0 | AZ12: 0 | BA12: 0 | BB12: 0 | BC12: 0 | BD12: 0 | BE12: 0 | BG12: #DIV/0! | BH12: #DIV/0! | BI12: #DIV/0! | BJ12: #DIV/0! | BK12: #DIV/0! | BM12: #DIV/0! | BN12: #DIV/0! | BO12: #DIV/0! | BP12: #DIV/0! | BQ12: 0 | BR12: 0 | BS12: 0 | BT12: 0 | BU12: 0 | BV12: 0 | BW12: 0 | BX12: 0 | BY12: 138852 | BZ12: 154304 | CB12: 44473.211 | CC12: 40507.349 | CD12: 38288.634 | CE12: 232785.21 | CF12: 232785.21 | CG12: 311581.19 | CH12: 0.44563665 | CI12: 0 | CJ12: 315547.06 | CK12: 0.48900472 | CL12: 305383.42 | CM12: 0.50527956
A13: 46174 | J13: 100457.21 | K13: 100457.21 | L13: 525.95398 | M13: 191 | N13: 71 | P13: 83 | Q13: 43 | T13: 66 | U13: 12 | V13: 19 | W13: 85479.2 | X13: 118495.2 | Y13: 1 | Z13: 6236.5895 | AA13: 0.37172775 | AB13: 1.1690141 | AC13: 0.43455497 | AD13: 0.79518072 | AF13: 1 | AG13: 0.27906977 | AH13: 0.062827225 | AI13: 0.09947644 | AJ13: 150390.85 | AK13: 0.78791497 | AL13: 66 | AM13: 66 | AN13: 69 | AO13: 20272.401 | AP13: 9389.2951 | AQ13: 12422.162 | AR13: 1910 | AS13: 5939.7782
A14: 钟嘉欣-汇总 | H14: =SUM(H3:H12) | I14: =SUM(I3:I12) | J14: =SUM(J3:J12) | K14: =SUM(K3:K12) | L14: =K13/M13 | M14: =SUM(M3:M12) | N14: =SUM(N3:N12) | O14: =SUM(O3:O12) | P14: =SUM(P3:P12) | Q14: =SUM(Q3:Q12) | T14: =SUM(T3:T12) | U14: =SUM(U3:U12) | V14: =SUM(V3:V12) | W14: =SUM(W3:W12) | X14: =SUM(X3:X12) | Z14: =X13/V13 | AA14: =N13/M13 | AB14: =P13/N13 | AC14: =P13/M13 | AD14: =Q13/P13 | AF14: =AVERAGE(AF3:AF12) | AG14: =U13/Q13 | AH14: =U13/M13 | AI14: =V13/M13 | AJ14: =SUM(AJ3:AJ12) | AK14: =X13/AJ13 | AL14: =SUM(AL3:AL12) | AM14: =SUM(AM3:AM12) | AN14: =SUM(AN3:AN12) | AO14: =SUM(AO3:AO12) | AP14: =SUM(AP3:AP12) | AQ14: =SUM(AQ3:AQ12) | AR14: =SUM(AR3:AR12) | AS14: =SUM(AS3:AS12) | ... AU14: =SUM(AU3:AU12) | AW14: =SUM(AW3:AW12) | AZ14: =SUM(AZ3:AZ12) | BA14: =SUM(BA3:BA12) | BB14: =SUM(BB3:BB12) | BC14: =SUM(BC3:BC12) | BD14: =SUM(BD3:BD12) | BE14: =SUM(BE3:BE12) | BG14: =BE13/BC13 | BH14: =AU13/AT13 | BI14: =AW13/AU13 | BJ14: =AW13/AT13 | BK14: =AZ13/AW13 | BM14: =AVERAGE(BM3:BM12) | BN14: =BB13/AZ13 | BO14: =BB13/AT13 | BP14: =BC13/AT13 | BQ14: =SUM(BQ3:BQ12) | BR14: =SUM(BR3:BR12) | BS14: =SUM(BS3:BS12) | BT14: =SUM(BT3:BT12) | BU14: =SUM(BU3:BU12) | BV14: =SUM(BV3:BV12) | BW14: =SUM(BW3:BW12) | BX14: =SUM(BX3:BX12) | ... BZ14: =SUM(BZ3:BZ12) | CB14: =SUM(CB3:CB12) | CC14: =SUM(CC3:CC12) | CD14: =SUM(CD3:CD12) | CE14: =SUM(CE3:CE12) | CF14: =SUM(CF3:CF12) | CG14: =SUM(CG3:CG12) | CH14: =BY13/CG13 | CI14: =SUM(CI3:CI12) | CJ14: =SUM(CJ3:CJ12) | CK14: =BZ13/CJ13 | CL14: =SUM(CL3:CL12) | CM14: =BZ13/CL13

Sheet 钟嘉欣--求和
I1: 主投 | AR1: 辅投 | BW1: 汇总
B2: 渠道组 | C2: 供应商 | D2: 渠道名称 | E2: 主投 | F2: 辅投 | G2: 结算方式 | H2: 滚动消耗 | I2: 滚动消耗(不含赠课成本) | J2: 单例子成本 | K2: 例子数 | L2: 分发数 | M2: 剔除毛例子 分发数 | N2: 约课数 | O2: 应到课数 | P2: 滚动应到课数 | Q2: 到课数 | R2: 滚动到课数 | S2: 当月成交数 | T2: 滚动成交数 | U2: 当月GMV | V2: 滚动GMV | W2: 海外GMV占比 | X2: 滚动ASP | Y2: 例子分发率 | Z2: 分发约课率 | AA2: 例子约课率 | AB2: 约课到课率 | AC2: 应到课率 | AD2: 滚动应到课率 | AE2: 到课转化率 | AF2: 注册转化率 | AG2: 滚动转化率 | AH2: 滚动ROI2总成本 | AI2: 滚动ROI2 | AJ2: 滚动应到课人数 | AK2: 滚动到课人数 | AL2: 滚动到课人次 | AM2: 运营成本 | AN2: 销售固定成本 | AO2: 销售变动成本 | AP2: TMK费用 | AQ2: DEMO费用 | AR2: 例子数 | AS2: 分发数 | AT2: 剔除毛例子分发数 | AU2: 约课数 | AX2: 到课数 | AY2: 滚动到课数 | AZ2: 当月成交 | BA2: 滚动成交数 | BB2: 当月GMV | BC2: 滚动GMV | BD2: 海外GMV占比 | BE2: 滚动ASP | BF2: 例子分发率 | BG2: 分发约课率 | BH2: 例子约课率 | BI2: 约课到课率 | BK2: 滚动应到课率 | BL2: 到课转化率 | BM2: 注册转化率 | BN2: 滚动转化率 | BO2: 滚动应到课人数 | BP2: 滚动到课人数 | BQ2: 滚动到课人次 | BR2: 运营成本 | BS2: 销售固定成本 | BT2: 销售变动成本 | BU2: TMK费用 | BV2: DEMO费用 | BW2: 当月GMV | BX2: 滚动GMV | BY2: 海外GMV占比 | BZ2: 滚动其他成本 | CA2: 同源其他成本 | CB2: 运营成本 | CC2: 滚动消耗 | CD2: 同源消耗 | CE2: 当月ROI2总成本 | CF2: 当月ROI2 | CG2: 滚动赠课成本 | CH2: 滚动ROI2总成本 | CI2: 滚动ROI2 | CJ2: O-ROI总成本 | CK2: O-ROI
E3: 图片 | H3: 46805.12 | I3: 46805.12 | J3: 632.50162 | K3: 74 | L3: 40 | M3: 127 | N3: 45 | O3: 38 | P3: 36 | Q3: 22 | R3: 36 | S3: 5 | T3: 11 | U3: 32771.2 | V3: 62099.2 | W3: 1 | X3: 5645.3818 | Y3: 0.54054054 | Z3: 1.125 | AA3: 0.60810811 | AB3: 0.48888889 | AC3: 0.57894737 | AD3: 1 | AE3: 0.22727273 | AF3: 0.067567568 | AG3: 0.14864865 | AH3: 70597.453 | AI3: 0.8796238 | AJ3: 36 | AK3: 36 | AL3: 38 | AM3: 7854.2287 | AN3: 5416.901 | AO3: 6510.0218 | AP3: 740 | AQ3: 3271.1822 | AR3: 0 | AS3: 0 | AT3: 0 | AU3: 0 | AV3: 0 | AW3: 0 | AX3: 0 | AY3: 0 | AZ3: 0 | BA3: 0 | BB3: 0 | BC3: 0 | BO3: 0 | BP3: 0 | BQ3: 0 | BR3: 0 | BS3: 0 | BT3: 0 | BU3: 0 | BV3: 0 | BW3: 203508 | BX3: 203508 | BY3: 1 | BZ3: 15938.105 | CA3: 11056.524 | CB3: 16124.404 | CC3: 138019.65 | CD3: 46805.12 | CE3: 65715.872 | CF3: 0.49868014 | CG3: 0 | CH3: 208434.35 | CI3: 0.97636499 | CJ3: 68293.225 | CK3: 0.9093025
E4: 视频1 | H4: 32171.261 | I4: 32171.261 | J4: 518.8913 | K4: 62 | L4: 14 | M4: 40 | N4: 18 | O4: 12 | P4: 18 | Q4: 9 | R4: 18 | S4: 4 | T4: 5 | U4: 24152 | V4: 27840 | W4: 1 | X4: 5568 | Y4: 0.22580645 | Z4: 1.2857143 | AA4: 0.29032258 | AB4: 0.5 | AC4: 0.75 | AD4: 1 | AE4: 0.44444444 | AF4: 0.064516129 | AG4: 0.080645161 | AH4: 45851.971 | AI4: 0.60717128 | AJ4: 18 | AK4: 18 | AL4: 19 | AM4: 6580.57 | AN4: 1926.0093 | AO4: 2918.5401 | AP4: 620 | AQ4: 1635.5911 | AR4: 0 | AS4: 0 | AT4: 0 | AU4: 0 | AV4: 0 | AW4: 0 | AX4: 0 | AY4: 0 | AZ4: 0 | BA4: 0 | BB4: 0 | BC4: 0 | BO4: 0 | BP4: 0 | BQ4: 0 | BR4: 0 | BS4: 0 | BT4: 0 | BU4: 0 | BV4: 0 | BW4: 53092 | BX4: 53092 | BY4: 1 | BZ4: 7100.1405 | CA4: 5611.9292 | CB4: 9608.3778 | CC4: 33548.386 | CD4: 32171.261 | CE4: 44363.76 | CF4: 0.54440832 | CG4: 0 | CH4: 59238.191 | CI4: 0.89624613 | CJ4: 43921.401 | CK4: 0.63385956
E5: 视频2 | H5: 21480.83 | I5: 21480.83 | J5: 390.56055 | K5: 55 | L5: 17 | N5: 20 | O5: 15 | P5: 12 | Q5: 12 | R5: 12 | S5: 3 | T5: 3 | U5: 28556 | V5: 28556 | W5: 1 | X5: 9518.6667 | Y5: 0.30909091 | Z5: 1.1764706 | AA5: 0.36363636 | AB5: 0.6 | AC5: 0.8 | AD5: 1 | AE5: 0.25 | AF5: 0.054545455 | AG5: 0.054545455 | AH5: 33941.422 | AI5: 0.84133186 | AJ5: 12 | AK5: 12 | AL5: 12 | AM5: 5837.6024 | AN5: 2046.3848 | AO5: 2993.6003 | AP5: 550 | AQ5: 1033.0049 | AT5: 0 | AZ5: 0 | BZ5: 6622.99 | CA5: 6622.99 | CD5: 21480.83 | CE5: 33941.422 | CF5: 0.84133186 | CG5: 0 | CJ5: 32228.82 | CK5: 0.88603927
A6: 钟嘉欣-汇总 | E6: 汇总 | H6: =SUM(H3:H5) | I6: =SUM(I3:I5) | J6: =I6/K6 | K6: =SUM(K3:K5) | L6: =SUM(L3:L5) | M6: =SUM(M3:M5) | N6: =SUM(N3:N5) | O6: =SUM(O3:O5) | P6: =SUM(P3:P5) | Q6: =SUM(Q3:Q5) | R6: =SUM(R3:R5) | ... V6: =SUM(V3:V5) | X6: =V6/T6 | Y6: =L6/K6 | Z6: =N6/L6 | AA6: =N6/K6 | AB6: =Q6/N6 | AC6: =Q6/O6 | AD6: =R6/P6 | AE6: =S6/Q6 | AF6: =S6/K6 | AG6: =T6/K6 | AH6: =SUM(AH3:AH5) | AI6: =V6/AH6 | AJ6: =SUM(AJ3:AJ5) | AK6: =SUM(AK3:AK5) | AL6: =SUM(AL3:AL5) | AM6: =SUM(AM3:AM5) | AN6: =SUM(AN3:AN5) | AO6: =SUM(AO3:AO5) | AP6: =SUM(AP3:AP5) | AQ6: =SUM(AQ3:AQ5) | ... AS6: =SUM(AS3:AS5) | AU6: =SUM(AU3:AU5) | AX6: =SUM(AX3:AX5) | AY6: =SUM(AY3:AY5) | AZ6: =SUM(AZ3:AZ5) | BA6: =SUM(BA3:BA5) | BB6: =SUM(BB3:BB5) | BC6: =SUM(BC3:BC5) | BE6: =BC6/BA6 | BF6: =AS6/AR6 | BG6: =AU6/AS6 | BH6: =AU6/AR6 | BI6: =AX6/AU6 | BK6: =AVERAGE(BK3:BK5) | BL6: =AZ6/AX6 | BM6: =AZ6/AR6 | BN6: =BA6/AR6 | BO6: =SUM(BO3:BO5) | BP6: =SUM(BP3:BP5) | BQ6: =SUM(BQ3:BQ5) | BR6: =SUM(BR3:BR5) | BS6: =SUM(BS3:BS5) | BT6: =SUM(BT3:BT5) | BU6: =SUM(BU3:BU5) | BV6: =SUM(BV3:BV5) | ... BX6: =SUM(BX3:BX5) | BZ6: =SUM(BZ3:BZ5) | CA6: =SUM(CA3:CA5) | CB6: =SUM(CB3:CB5) | CC6: =SUM(CC3:CC5) | CD6: =SUM(CD3:CD5) | CE6: =SUM(CE3:CE5) | CF6: =BW6/CE6 | CG6: =SUM(CG3:CG5) | CH6: =SUM(CH3:CH5) | CI6: =BX6/CH6 | CJ6: =SUM(CJ3:CJ5) | CK6: =BX6/CJ6

Sheet 蔡雪莹
I1: 主投 | AR1: 辅投 | BW1: 汇总
B2: 渠道组 | C2: 供应商 | D2: 渠道名称 | E2: 主投 | F2: 辅投 | G2: 结算方式 | H2: 滚动消耗 | I2: 滚动消耗(不含赠课成本) | J2: 单例子成本 | K2: 例子数 | L2: 分发数 | M2: 剔除毛例子 分发数 | N2: 约课数 | Q2: 到课数 | R2: 滚动到课数 | S2: 当月成交数 | T2: 滚动成交数 | U2: 当月GMV | V2: 滚动GMV | W2: 海外GMV占比 | X2: 滚动ASP | Y2: 例子分发率 | Z2: 分发约课率 | AA2: 例子约课率 | AB2: 约课到课率 | AD2: 滚动应到课率 | AE2: 到课转化率 | AF2: 注册转化率 | AG2: 滚动转化率 | AH2: 滚动ROI2总成本 | AI2: 滚动ROI2 | AJ2: 滚动应到课人数 | AK2: 滚动到课人数 | AL2: 滚动到课人次 | AM2: 运营成本 | AN2: 销售固定成本 | AO2: 销售变动成本 | AP2: TMK费用 | AQ2: DEMO费用 | AR2: 例子数 | AS2: 分发数 | AT2: 剔除毛例子分发数 | AU2: 约课数 | AX2: 到课数 | AY2: 滚动到课数 | AZ2: 当月成交 | BA2: 滚动成交数 | BB2: 当月GMV | BC2: 滚动GMV | BD2: 海外GMV占比 | BE2: 滚动ASP | BF2: 例子分发率 | BG2: 分发约课率 | BH2: 例子约课率 | BI2: 约课到课率 | BK2: 滚动应到课率 | BL2: 到课转化率 | BM2: 注册转化率 | BN2: 滚动转化率 | BO2: 滚动应到课人数 | BP2: 滚动到课人数 | BQ2: 滚动到课人次 | BR2: 运营成本 | BS2: 销售固定成本 | BT2: 销售变动成本 | BU2: TMK费用 | BV2: DEMO费用 | BW2: 当月GMV | BX2: 滚动GMV | BY2: 海外GMV占比 | BZ2: 滚动其他成本 | CA2: 同源其他成本 | CB2: 运营成本 | CC2: 滚动消耗 | CD2: 同源消耗 | CE2: 当月ROI2总成本 | CF2: 当月ROI2 | CG2: 滚动赠课成本 | CH2: 滚动ROI2总成本 | CI2: 滚动ROI2 | CJ2: O-ROI总成本 | CK2: O-ROI
A3: 45873 | H3: 44422.947 | I3: 43715.664 | J3: 403.84497 | K3: 110 | L3: 42 | M3: 42 | N3: 40 | Q3: 27 | R3: 27 | S3: 4 | T3: 4 | U3: 19352 | V3: 19352 | W3: 1 | X3: 4838 | Y3: 0.38181818 | Z3: 0.95238095 | AA3: 0.36363636 | AB3: 0.675 | AD3: 1 | AE3: 0.14814815 | AF3: 0.036363636 | AG3: 0.036363636 | AH3: 65443.606 | AI3: 0.29570498 | AJ3: 27 | AK3: 27 | AL3: 32 | AM3: 9930.7485 | AN3: 5187.7741 | AO3: 1981.6078 | AP3: 1100 | AQ3: 2820.529 | AR3: 0 | AS3: 0 | AT3: 0 | AU3: 0 | AX3: 0 | AY3: 0 | AZ3: 0 | BA3: 0 | BB3: 0 | BC3: 0 | BO3: 0 | BP3: 0 | BQ3: 0 | BR3: 0 | BS3: 0 | BT3: 0 | BU3: 0 | BV3: 0 | BW3: 19352 | BX3: 19352 | BY3: 1 | BZ3: 11089.911 | CA3: 11089.911 | CB3: 9930.7485 | CC3: 44422.947 | CD3: 44422.947 | CE3: 65443.606 | CF3: 0.29570498 | CG3: 707.28265 | CH3: 65443.606 | CI3: 0.29570498 | CJ3: 63762.857 | CK3: 0.30349957
A4: 45904 | H4: 139121.59 | I4: =H4-CG4 | J4: 547.72278 | K4: 254 | L4: 77 | M4: 81 | N4: 76 | Q4: 60 | R4: 70 | S4: 19 | T4: 25 | U4: 87372 | V4: 109900 | W4: 1 | X4: 4396 | Y4: 0.30314961 | Z4: 0.98701299 | AA4: 0.2992126 | AB4: 0.78947368 | AD4: 0.98591549 | AE4: 0.31666667 | AF4: 0.07480315 | AG4: 0.098425197 | AH4: 191752.27 | AI4: 0.57313532 | AJ4: 71 | AK4: 70 | AL4: 80 | AM4: 19245.285 | AN4: 11711.726 | AO4: 12339.303 | AP4: 2540 | AQ4: 6794.3708 | AR4: 0 | AS4: 0 | AT4: 0 | AU4: 0 | AX4: 0 | AY4: 0 | AZ4: 0 | BA4: 0 | BB4: 0 | BC4: 0 | BO4: 0 | BP4: 0 | BQ4: 0 | BR4: 0 | BS4: 0 | BT4: 0 | BU4: 0 | BV4: 0 | BW4: 87372 | BX4: 109900 | BY4: 1 | BZ4: 33385.399 | CA4: 29088.639 | CB4: 19245.285 | CC4: 139121.59 | CD4: 138049.75 | CE4: 186383.68 | CF4: 0.46877496 | CG4: 4465.9784 | CH4: 191752.27 | CI4: 0.57313532 | CJ4: 191556.99 | CK4: 0.57371961
A5: 45931 | H5: 99219.522 | I5: =H5-CG5 | J5: 335.20109 | K5: 296 | L5: 25 | M5: 31 | N5: 26 | Q5: 18 | R5: 25 | S5: 2 | T5: 4 | U5: 13707 | V5: 23183 | W5: 1 | X5: 5795.75 | Y5: 0.084459459 | Z5: 1.04 | AA5: 0.087837838 | AB5: 0.69230769 | AD5: 1 | AE5: 0.11111111 | AF5: 0.0067567568 | AG5: 0.013513514 | AH5: 130262.57 | AI5: 0.17797131 | AJ5: 25 | AK5: 25 | AL5: 31 | AM5: 18495.468 | AN5: 4409.6682 | AO5: 2550.1692 | AP5: 2960 | AQ5: 2627.743 | AR5: 0 | AS5: 0 | AT5: 0 | AU5: 0 | AX5: 0 | AY5: 0 | AZ5: 0 | BA5: 0 | BB5: 0 | BC5: 0 | BO5: 0 | BP5: 0 | BQ5: 0 | BR5: 0 | BS5: 0 | BT5: 0 | BU5: 0 | BV5: 0 | BW5: 13707 | BX5: 23183 | BY5: 1 | BZ5: 12547.58 | CA5: 9719.2953 | CB5: 18495.468 | CC5: 99219.522 | CD5: 98862.244 | CE5: 127077.01 | CF5: 0.10786373 | CG5: 714.55655 | CH5: 130262.57 | CI5: 0.17797131 | CJ5: 133967.1 | CK5: 0.17304995
A6: 45962 | H6: 40744.125 | I6: =H6-CG6 | J6: 714.80921 | K6: 57 | L6: 26 | M6: 29 | N6: 25 | Q6: 16 | R6: 18 | S6: 7 | T6: 8 | U6: 34802 | V6: 40101 | W6: 1 | X6: 5012.625 | Y6: 0.45614035 | Z6: 0.96153846 | AA6: 0.43859649 | AB6: 0.64 | AD6: 0.94736842 | AE6: 0.4375 | AF6: 0.12280702 | AG6: 0.14035088 | AH6: 54471.316 | AI6: 0.73618562 | AJ6: 19 | AK6: 18 | AL6: 19 | AM6: 3710.3302 | AN6: 3425.131 | AO6: 4411.1778 | AP6: 570 | AQ6: 1610.5522 | AR6: 0 | AS6: 0 | AT6: 0 | AU6: 0 | AX6: 0 | AY6: 0 | AZ6: 0 | BA6: 0 | BB6: 0 | BC6: 0 | BO6: 0 | BP6: 0 | BQ6: 0 | BR6: 0 | BS6: 0 | BT6: 0 | BU6: 0 | BV6: 0 | BW6: 34802 | BX6: 40101 | BY6: 1 | BZ6: 10016.861 | CA6: 8825.3403 | CB6: 3710.3302 | CC6: 40744.125 | CD6: 40565.403 | CE6: 53101.073 | CF6: 0.65539165 | CG6: 1429.7788 | CH6: 54471.316 | CI6: 0.73618562 | CJ6: 55035.986 | CK6: 0.72863235
A7: 45992 | H7: 54031.12 | I7: =H7-CG7 | J7: 885.75606 | K7: 61 | L7: 33 | M7: 33 | N7: 31 | O7: 30 | P7: 25 | Q7: 20 | R7: 25 | S7: 9 | T7: 10 | U7: 44689 | V7: 49988 | W7: 1 | X7: 4998.8 | Y7: 0.54098361 | Z7: 0.93939394 | AA7: 0.50819672 | AB7: 0.64516129 | AC7: 0.66666667 | AD7: 1 | AE7: 0.45 | AF7: 0.14754098 | AG7: 0.16393443 | AH7: 72759.549 | AI7: 0.6870301 | AJ7: 25 | AK7: 25 | AL7: 30 | AM7: 4551.6098 | AN7: 4858.5197 | AO7: 6183.384 | AP7: 610 | AQ7: 2524.9151 | AR7: 0 | AS7: 0 | AT7: 0 | AU7: 0 | AV7: 0 | AW7: 0 | AX7: 0 | AY7: 0 | AZ7: 0 | BA7: 0 | BB7: 0 | BC7: 0 | BO7: 0 | BP7: 0 | BQ7: 0 | BR7: 0 | BS7: 0 | BT7: 0 | BU7: 0 | BV7: 0 | BW7: 44689 | BX7: 49988 | BY7: 1 | BZ7: 14176.819 | CA7: 13100.527 | CB7: 4551.6098 | CC7: 54031.12 | CD7: 53835.981 | CE7: 71488.118 | CF7: 0.62512487 | CG7: 1951.3931 | CH7: 72759.549 | CI7: 0.6870301 | CJ7: 72782.939 | CK7: 0.68680931
A8: 46023 | H8: 14181.22 | I8: =H8-CG8 | J8: 616.5748 | K8: 23 | L8: 11 | M8: 11 | N8: 11 | O8: 11 | P8: 10 | Q8: 7 | R8: 10 | S8: 1 | T8: 2 | U8: 5888 | V8: 9776 | W8: 1 | X8: 4888 | Y8: 0.47826087 | Z8: 1 | AA8: 0.47826087 | AB8: 0.63636364 | AC8: 0.63636364 | AD8: 1 | AE8: 0.14285714 | AF8: 0.043478261 | AG8: 0.086956522 | AH8: 20504.025 | AI8: 0.47678444 | AJ8: 10 | AK8: 10 | AL8: 12 | AM8: 2153.915 | AN8: 1719.658 | AO8: 1209.2655 | AP8: 230 | AQ8: 1009.966 | AR8: 0 | AS8: 0 | AT8: 0 | AU8: 0 | AV8: 0 | AW8: 0 | AX8: 0 | AY8: 0 | AZ8: 0 | BA8: 0 | BB8: 0 | BC8: 0 | BO8: 0 | BP8: 0 | BQ8: 0 | BR8: 0 | BS8: 0 | BT8: 0 | BU8: 0 | BV8: 0 | BW8: 5888 | BX8: 9776 | BY8: 1 | BZ8: 4168.8895 | CA8: 3267.1349 | CB8: 2153.915 | CC8: 14181.22 | CD8: 14181.22 | CE8: 19602.27 | CF8: 0.30037337 | CG8: 0 | CH8: 20504.025 | CI8: 0.47678444 | CJ8: 20075.11 | CK8: 0.48697118
A9: 蔡雪莹-汇总 | H9: =SUM(H3:H8) | I9: =SUM(I3:I8) | J9: =I9/K9 | K9: =SUM(K3:K8) | L9: =SUM(L3:L8) | M9: =SUM(M3:M8) | N9: =SUM(N3:N8) | Q9: =SUM(Q3:Q8) | R9: =SUM(R3:R8) | S9: =SUM(S3:S8) | T9: =SUM(T3:T8) | U9: =SUM(U3:U8) | V9: =SUM(V3:V8) | X9: =V9/T9 | Y9: =L9/K9 | Z9: =N9/L9 | AA9: =N9/K9 | AB9: =Q9/N9 | AD9: =AVERAGE(AD3:AD8) | AE9: =S9/Q9 | AF9: =S9/K9 | AG9: =T9/K9 | AH9: =SUM(AH3:AH8) | AI9: =V9/AH9 | AJ9: =SUM(AJ3:AJ8) | AK9: =SUM(AK3:AK8) | AL9: =SUM(AL3:AL8) | AM9: =SUM(AM3:AM8) | AN9: =SUM(AN3:AN8) | AO9: =SUM(AO3:AO8) | AP9: =SUM(AP3:AP8) | AQ9: =SUM(AQ3:AQ8) | ... AS9: =SUM(AS3:AS8) | AU9: =SUM(AU3:AU8) | AX9: =SUM(AX3:AX8) | AY9: =SUM(AY3:AY8) | AZ9: =SUM(AZ3:AZ8) | BA9: =SUM(BA3:BA8) | BB9: =SUM(BB3:BB8) | BC9: =SUM(BC3:BC8) | BE9: =BC9/BA9 | BF9: =AS9/AR9 | BG9: =AU9/AS9 | BH9: =AU9/AR9 | BI9: =AX9/AU9 | BK9: =AVERAGE(BK3:BK8) | BL9: =AZ9/AX9 | BM9: =AZ9/AR9 | BN9: =BA9/AR9 | BO9: =SUM(BO3:BO8) | BP9: =SUM(BP3:BP8) | BQ9: =SUM(BQ3:BQ8) | BR9: =SUM(BR3:BR8) | BS9: =SUM(BS3:BS8) | BT9: =SUM(BT3:BT8) | BU9: =SUM(BU3:BU8) | BV9: =SUM(BV3:BV8) | ... BX9: =SUM(BX3:BX8) | BZ9: =SUM(BZ3:BZ8) | CA9: =SUM(CA3:CA8) | CB9: =SUM(CB3:CB8) | CC9: =SUM(CC3:CC8) | CD9: =SUM(CD3:CD8) | CE9: =SUM(CE3:CE8) | CF9: =BW9/CE9 | CG9: =SUM(CG3:CG8) | CH9: =SUM(CH3:CH8) | CI9: =BX9/CH9 | CJ9: =SUM(CJ3:CJ8) | CK9: =BX9/CJ9

Sheet 陈展鹏
I1: 主投 | AR1: 辅投 | BW1: 汇总
B2: 渠道组 | C2: 供应商 | D2: 渠道名称 | E2: 主投 | F2: 辅投 | G2: 结算方式 | H2: 滚动消耗 | I2: 滚动消耗(不含赠课成本) | J2: 单例子成本 | K2: 例子数 | L2: 分发数 | M2: 分发数 (剔除毛例子) | N2: 约课数 | O2: 应到课数 | P2: 滚动应到课数 | Q2: 到课数 | R2: 滚动到课数 | S2: 当月成交数 | T2: 滚动成交数 | U2: 当月GMV | V2: 滚动GMV | W2: 海外GMV占比 | X2: 滚动ASP | Y2: 例子分发率 | Z2: 分发约课率 | AA2: 例子约课率 | AB2: 约课到课率 | AC2: 应到课率 | AD2: 滚动应到课率 | AE2: 到课转化率 | AF2: 注册转化率 | AG2: 滚动转化率 | AH2: 滚动ROI2总成本 | AI2: 滚动ROI2 | AJ2: 滚动应到课人数 | AK2: 滚动到课人数 | AL2: 滚动到课人次 | AM2: 运营成本 | AN2: 销售固定成本 | AO2: 销售变动成本 | AP2: TMK费用 | AQ2: DEMO费用 | AR2: 例子数 | AS2: 分发数 | AT2: 剔除毛例子分发数 | AU2: 约课数 | AV2: 应到课数 | AW2: 滚动应到课数 | AX2: 到课数 | AY2: 滚动到课数 | AZ2: 当月成交 | BA2: 滚动成交数 | BB2: 当月GMV | BC2: 滚动GMV | BD2: 海外GMV占比 | BE2: 滚动ASP | BF2: 例子分发率 | BG2: 分发约课率 | BH2: 例子约课率 | BI2: 约课到课率 | BJ2: 应到课率 | BK2: 滚动应到课率 | BL2: 到课转化率 | BM2: 注册转化率 | BN2: 滚动转化率 | BO2: 滚动应到课人数 | BP2: 滚动到课人数 | BQ2: 滚动到课人次 | BR2: 运营成本 | BS2: 销售固定成本 | BT2: 销售变动成本 | BU2: TMK费用 | BV2: DEMO费用 | BW2: 当月GMV | BX2: 滚动GMV | BY2: 海外GMV占比 | BZ2: 滚动其他成本 | CA2: 同源其他成本 | CB2: 运营成本 | CC2: 滚动消耗 | CD2: 同源消耗 | CE2: 当月ROI2总成本 | CF2: 当月ROI2 | CG2: 滚动赠课成本 | CH2: 滚动ROI2总成本 | CI2: 滚动ROI2 | CJ2: O-ROI总成本 | CK2: O-ROI
A3: 45904 | H3: 74915.352 | I3: =H3-CG3 | J3: 604.15606 | K3: 124 | L3: 47 | M3: 47 | N3: 48 | Q3: 30 | R3: 30 | S3: 6 | T3: 6 | U3: 24828 | V3: 24828 | W3: 1 | X3: 4138 | Y3: 0.37903226 | Z3: 1.0212766 | AA3: 0.38709677 | AB3: 0.625 | AD3: 0.96774194 | AE3: 0.2 | AF3: 0.048387097 | AG3: 0.048387097 | AH3: 97851.756 | AI3: 0.25373076 | AJ3: 31 | AK3: 30 | AL3: 32 | AM3: 9395.3358 | AN3: 6795.6929 | AO3: 2787.627 | AP3: 1240 | AQ3: 2717.7483 | AR3: 0 | AS3: 0 | AT3: 0 | AU3: 0 | AX3: 0 | AY3: 0 | AZ3: 0 | BA3: 0 | BB3: 0 | BC3: 0 | BO3: 0 | BP3: 0 | BQ3: 0 | BR3: 0 | BS3: 0 | BT3: 0 | BU3: 0 | BV3: 0 | BW3: 24828 | BX3: 24828 | BY3: 1 | BZ3: 13541.068 | CA3: 13541.068 | CB3: 9395.3358 | CC3: 74915.352 | CD3: 74915.352 | CE3: 97851.756 | CF3: 0.25373076 | CG3: 1071.8348 | CH3: 97851.756 | CI3: 0.25373076 | CJ3: 97756.42 | CK3: 0.2539782
A4: 45931 | H4: 178123.87 | I4: =H4-CG4 | J4: 522.35739 | K4: 341 | L4: 68 | M4: 71 | N4: 68 | Q4: 47 | R4: 57 | S4: 13 | T4: 16 | U4: 85686 | V4: 104150 | W4: 1 | X4: 6509.375 | Y4: 0.19941349 | Z4: 1 | AA4: 0.19941349 | AB4: 0.69117647 | AD4: 0.98275862 | AE4: 0.27659574 | AF4: 0.038123167 | AG4: 0.046920821 | AH4: 229652.87 | AI4: 0.45351054 | AJ4: 58 | AK4: 57 | AL4: 62 | AM4: 21307.279 | AN4: 10099.563 | AO4: 11456.676 | AP4: 3410 | AQ4: 5255.4861 | AR4: 0 | AS4: 0 | AT4: 0 | AU4: 0 | AX4: 0 | AY4: 0 | AZ4: 0 | BA4: 0 | BB4: 0 | BC4: 0 | BO4: 0 | BP4: 0 | BQ4: 0 | BR4: 0 | BS4: 0 | BT4: 0 | BU4: 0 | BV4: 0 | BW4: 85686 | BX4: 104150 | BY4: 1 | BZ4: 30221.725 | CA4: 26831.486 | CB4: 21307.279 | CC4: 178123.87 | CD4: 177587.95 | CE4: 225726.72 | CF4: 0.37960061 | CG4: 2858.2262 | CH4: 229652.87 | CI4: 0.45351054 | CJ4: 233920.59 | CK4: 0.44523656
A5: 45962 | H5: 187458.02 | I5: =H5-CG5 | J5: 1225.2158 | K5: 153 | L5: 71 | M5: 77 | N5: 73 | Q5: 47 | R5: 62 | S5: 15 | T5: 18 | U5: 88994 | V5: 101291 | W5: 1 | X5: 5627.2778 | Y5: 0.46405229 | Z5: 1.028169 | AA5: 0.47712418 | AB5: 0.64383562 | AD5: 0.98412698 | AE5: 0.31914894 | AF5: 0.098039216 | AG5: 0.11764706 | AH5: 224947.9 | AI5: 0.45028648 | AJ5: 63 | AK5: 62 | AL5: 68 | AM5: 9959.3073 | AN5: 9094.3133 | AO5: 11142.181 | AP5: 1530 | AQ5: 5764.0815 | AR5: 0 | AS5: 0 | AT5: 0 | AU5: 0 | AX5: 0 | AY5: 0 | AZ5: 0 | BA5: 0 | BB5: 0 | BC5: 0 | BO5: 0 | BP5: 0 | BQ5: 0 | BR5: 0 | BS5: 0 | BT5: 0 | BU5: 0 | BV5: 0 | BW5: 88994 | BX5: 101291 | BY5: 1 | BZ5: 27530.576 | CA5: 24028.217 | CB5: 9959.3073 | CC5: 187458.02 | CD5: 186921.85 | CE5: 220909.38 | CF5: 0.40285298 | CG5: 3217.0024 | CH5: 224947.9 | CI5: 0.45028648 | CJ5: 226463.59 | CK5: 0.44727277
A6: 45992 | H6: 90191.303 | I6: =H6-CG6 | J6: 1218.8014 | K6: 74 | L6: 44 | M6: 46 | N6: 43 | O6: 41 | P6: 34 | Q6: 28 | R6: 34 | S6: 6 | T6: 8 | U6: 30003 | V6: 37001 | W6: 1 | X6: 4625.125 | Y6: 0.59459459 | Z6: 0.97727273 | AA6: 0.58108108 | AB6: 0.65116279 | AC6: 0.68292683 | AD6: 1 | AE6: 0.21428571 | AF6: 0.081081081 | AG6: 0.10810811 | AH6: 110832.23 | AI6: 0.33384692 | AJ6: 34 | AK6: 34 | AL6: 36 | AM6: 5521.625 | AN6: 6772.4821 | AO6: 4576.9263 | AP6: 740 | AQ6: 3029.8981 | AR6: 0 | AS6: 0 | AT6: 0 | AU6: 0 | AV6: 0 | AW6: 0 | AX6: 0 | AY6: 0 | AZ6: 0 | BA6: 0 | BB6: 0 | BC6: 0 | BO6: 0 | BP6: 0 | BQ6: 0 | BR6: 0 | BS6: 0 | BT6: 0 | BU6: 0 | BV6: 0 | BW6: 30003 | BX6: 37001 | BY6: 1 | BZ6: 15119.306 | CA6: 13370.07 | CB6: 5521.625 | CC6: 90191.303 | CD6: 89801.024 | CE6: 108692.72 | CF6: 0.27603505 | CG6: 1561.1145 | CH6: 110832.23 | CI6: 0.33384692 | CJ6: 110860.61 | CK6: 0.33376147
A7: 46023 | H7: 36728.556 | I7: =H7-CG7 | J7: 941.75785 | K7: 39 | L7: 22 | M7: 24 | N7: 22 | O7: 22 | P7: 21 | Q7: 17 | R7: 21 | S7: 6 | T7: 8 | U7: 26728 | V7: 39304 | W7: 1 | X7: 4913 | Y7: 0.56410256 | Z7: 1 | AA7: 0.56410256 | AB7: 0.77272727 | AC7: 0.77272727 | AD7: 1 | AE7: 0.35294118 | AF7: 0.15384615 | AG7: 0.20512821 | AH7: 51404.561 | AI7: 0.76460141 | AJ7: 21 | AK7: 21 | AL7: 24 | AM7: 3652.2907 | AN7: 3751.9811 | AO7: 4861.8013 | AP7: 390 | AQ7: 2019.9321 | AR7: 0 | AS7: 0 | AT7: 0 | AU7: 0 | AV7: 0 | AW7: 0 | AX7: 0 | AY7: 0 | AZ7: 0 | BA7: 0 | BB7: 0 | BC7: 0 | BO7: 0 | BP7: 0 | BQ7: 0 | BR7: 0 | BS7: 0 | BT7: 0 | BU7: 0 | BV7: 0 | BW7: 26728 | BX7: 39304 | BY7: 1 | BZ7: 11023.714 | CA7: 8734.6121 | CB7: 3652.2907 | CC7: 36728.556 | CD7: 36728.556 | CE7: 49115.459 | CF7: 0.54418712 | CG7: 0 | CH7: 51404.561 | CI7: 0.76460141 | CJ7: 50677.271 | CK7: 0.77557452
A8: 陈展鹏-汇总 | H8: =SUM(H3:H7) | I8: =SUM(I3:I7) | J8: =I8/K8 | K8: =SUM(K3:K7) | L8: =SUM(L3:L7) | M8: =SUM(M3:M7) | N8: =SUM(N3:N7) | Q8: =SUM(Q3:Q7) | R8: =SUM(R3:R7) | S8: =SUM(S3:S7) | T8: =SUM(T3:T7) | U8: =SUM(U3:U7) | V8: =SUM(V3:V7) | X8: =V8/T8 | Y8: =L8/K8 | Z8: =N8/L8 | AA8: =N8/K8 | AB8: =Q8/N8 | AD8: =AVERAGE(AD3:AD7) | AE8: =S8/Q8 | AF8: =S8/K8 | AG8: =T8/K8 | AH8: =SUM(AH3:AH7) | AI8: =V8/AH8 | AJ8: =SUM(AJ3:AJ7) | AK8: =SUM(AK3:AK7) | AL8: =SUM(AL3:AL7) | AM8: =SUM(AM3:AM7) | AN8: =SUM(AN3:AN7) | AO8: =SUM(AO3:AO7) | AP8: =SUM(AP3:AP7) | AQ8: =SUM(AQ3:AQ7) | ... AS8: =SUM(AS3:AS7) | AU8: =SUM(AU3:AU7) | AX8: =SUM(AX3:AX7) | AY8: =SUM(AY3:AY7) | AZ8: =SUM(AZ3:AZ7) | BA8: =SUM(BA3:BA7) | BB8: =SUM(BB3:BB7) | BC8: =SUM(BC3:BC7) | BE8: =BC8/BA8 | BF8: =AS8/AR8 | BG8: =AU8/AS8 | BH8: =AU8/AR8 | BI8: =AX8/AU8 | BK8: =AVERAGE(BK3:BK7) | BL8: =AZ8/AX8 | BM8: =AZ8/AR8 | BN8: =BA8/AR8 | BO8: =SUM(BO3:BO7) | BP8: =SUM(BP3:BP7) | BQ8: =SUM(BQ3:BQ7) | BR8: =SUM(BR3:BR7) | BS8: =SUM(BS3:BS7) | BT8: =SUM(BT3:BT7) | BU8: =SUM(BU3:BU7) | BV8: =SUM(BV3:BV7) | ... BX8: =SUM(BX3:BX7) | BZ8: =SUM(BZ3:BZ7) | CA8: =SUM(CA3:CA7) | CB8: =SUM(CB3:CB7) | CC8: =SUM(CC3:CC7) | CD8: =SUM(CD3:CD7) | CE8: =SUM(CE3:CE7) | CF8: =BW8/CE8 | CG8: =SUM(CG3:CG7) | CH8: =SUM(CH3:CH7) | CI8: =BX8/CH8 | CJ8: =SUM(CJ3:CJ7) | CK8: =BX8/CJ8

Sheet 專家鄧明儀
I1: 主投 | AR1: 辅投 | BW1: 汇总
B2: 渠道组 | C2: 供应商 | D2: 渠道名称 | E2: 主投 | F2: 辅投 | G2: 结算方式 | H2: 滚动消耗 | I2: 滚动消耗(不含赠课成本) | J2: 单例子成本 | K2: 例子数 | L2: 分发数 | M2: 剔除毛例子 分发数 | N2: 约课数 | Q2: 到课数 | R2: 滚动到课数 | S2: 当月成交数 | T2: 滚动成交数 | U2: 当月GMV | V2: 滚动GMV | W2: 海外GMV占比 | X2: 滚动ASP | Y2: 例子分发率 | Z2: 分发约课率 | AA2: 例子约课率 | AB2: 约课到课率 | AD2: 滚动应到课率 | AE2: 到课转化率 | AF2: 注册转化率 | AG2: 滚动转化率 | AH2: 滚动ROI2总成本 | AI2: 滚动ROI2 | AJ2: 滚动应到课人数 | AK2: 滚动到课人数 | AL2: 滚动到课人次 | AM2: 运营成本 | AN2: 销售固定成本 | AO2: 销售变动成本 | AP2: TMK费用 | AQ2: DEMO费用 | AR2: 例子数 | AS2: 分发数 | AT2: 剔除毛例子分发数 | AU2: 约课数 | AX2: 到课数 | AY2: 滚动到课数 | AZ2: 当月成交 | BA2: 滚动成交数 | BB2: 当月GMV | BC2: 滚动GMV | BD2: 海外GMV占比 | BE2: 滚动ASP | BF2: 例子分发率 | BG2: 分发约课率 | BH2: 例子约课率 | BI2: 约课到课率 | BK2: 滚动应到课率 | BL2: 到课转化率 | BM2: 注册转化率 | BN2: 滚动转化率 | BO2: 滚动应到课人数 | BP2: 滚动到课人数 | BQ2: 滚动到课人次 | BR2: 运营成本 | BS2: 销售固定成本 | BT2: 销售变动成本 | BU2: TMK费用 | BV2: DEMO费用 | BW2: 当月GMV | BX2: 滚动GMV | BY2: 海外GMV占比 | BZ2: 滚动其他成本 | CA2: 同源其他成本 | CB2: 运营成本 | CC2: 滚动消耗 | CD2: 同源消耗 | CE2: 当月ROI2总成本 | CF2: 当月ROI2 | CG2: 滚动赠课成本 | CH2: 滚动ROI2总成本 | CI2: 滚动ROI2 | CJ2: O-ROI总成本 | CK2: O-ROI
A3: 45931 | H3: 100241.82 | I3: 99169.98 | J3: 481.40767 | K3: 206 | L3: 43 | M3: 43 | N3: 42 | Q3: 33 | R3: 33 | S3: 6 | T3: 6 | U3: 24550 | V3: 24550 | X3: 4091.6667 | Y3: 0.20873786 | Z3: 0.97674419 | AA3: 0.2038835 | AB3: 0.78571429 | AD3: 1 | AE3: 0.18181818 | AF3: 0.029126214 | AG3: 0.029126214 | AH3: 118376.51 | AI3: 0.20738912 | AJ3: 33 | AK3: 33 | AL3: 33 | AM3: 12871.846 | AN3: 6116.6365 | AO3: 2700.5415 | AP3: 2060 | AQ3: 2797.2748 | AR3: 0 | AS3: 0 | AU3: 0 | AX3: 0 | AY3: 0 | AZ3: 0 | BA3: 0 | BB3: 0 | BC3: 0 | BE3: #DIV/0! | BF3: #DIV/0! | BG3: #DIV/0! | BH3: #DIV/0! | BI3: #DIV/0! | BK3: #DIV/0! | BL3: #DIV/0! | BM3: #DIV/0! | BN3: #DIV/0! | BO3: 0 | BP3: 0 | BQ3: 0 | BR3: 0 | BS3: 0 | BT3: 0 | BU3: 0 | BV3: 0 | BW3: 24550 | BX3: 24550 | BZ3: 13674.453 | CA3: 13674.453 | CB3: 12871.846 | CC3: 100241.82 | CD3: 100241.82 | CE3: 118376.51 | CF3: 0.20738912 | CG3: 1071.8348 | CH3: 118376.51 | CI3: 0.20738912 | CJ3: 120954.67 | CK3: 0.20296861
A4: 45962 | H4: 108116.4 | I4: 104363.23 | J4: 719.7464 | K4: 145 | L4: 61 | M4: 63 | N4: 61 | Q4: 40 | R4: 47 | S4: 15 | T4: 21 | U4: 86834 | V4: 116468 | X4: 5546.0952 | Y4: 0.42068966 | Z4: 1 | AA4: 0.42068966 | AB4: 0.6557377 | AD4: 0.98484848 | AE4: 0.375 | AF4: 0.10344828 | AG4: 0.14482759 | AH4: 143580.5 | AI4: 0.81116867 | AJ4: 48 | AK4: 47 | AL4: 51 | AM4: 9438.5592 | AN4: 7440.8018 | AO4: 12811.677 | AP4: 1450 | AQ4: 4323.0611 | AR4: 0 | AS4: 0 | AU4: 0 | AX4: 0 | AY4: 0 | AZ4: 0 | BA4: 0 | BB4: 0 | BC4: 0 | BE4: #DIV/0! | BF4: #DIV/0! | BG4: #DIV/0! | BH4: #DIV/0! | BI4: #DIV/0! | BK4: #DIV/0! | BL4: #DIV/0! | BM4: #DIV/0! | BN4: #DIV/0! | BO4: 0 | BP4: 0 | BQ4: 0 | BR4: 0 | BS4: 0 | BT4: 0 | BU4: 0 | BV4: 0 | BW4: 86834 | BX4: 116468 | BZ4: 26025.54 | CA4: 21851.406 | CB4: 9438.5592 | CC4: 108116.4 | CD4: 107044.06 | CE4: 138334.03 | CF4: 0.62771251 | CG4: 3753.1694 | CH4: 143580.5 | CI4: 0.81116867 | CJ4: 145016.94 | CK4: 0.80313378
A5: 45992 | H5: 87014.392 | I5: 84477.581 | J5: 993.85389 | K5: 85 | L5: 46 | M5: 48 | N5: 47 | O5: 47 | P5: 43 | Q5: 35 | R5: 43 | S5: 12 | T5: 13 | U5: 60348 | V5: 65647 | X5: 5049.7692 | Y5: 0.54117647 | Z5: 1.0217391 | AA5: 0.55294118 | AB5: 0.74468085 | AC5: 0.74468085 | AD5: 1 | AE5: 0.34285714 | AF5: 0.14117647 | AG5: 0.15294118 | AH5: 113433.96 | AI5: 0.57872439 | AJ5: 43 | AK5: 43 | AL5: 48 | AM5: 6342.4071 | AN5: 7066.9378 | AO5: 8120.3611 | AP5: 850 | AQ5: 4039.8641 | AR5: 0 | AS5: 0 | AU5: 0 | AX5: 0 | AY5: 0 | AZ5: 0 | BA5: 0 | BB5: 0 | BC5: 0 | BE5: #DIV/0! | BF5: #DIV/0! | BG5: #DIV/0! | BH5: #DIV/0! | BI5: #DIV/0! | BK5: #DIV/0! | BL5: #DIV/0! | BM5: #DIV/0! | BN5: #DIV/0! | BO5: 0 | BP5: 0 | BQ5: 0 | BR5: 0 | BS5: 0 | BT5: 0 | BU5: 0 | BV5: 0 | BW5: 60348 | BX5: 65647 | BZ5: 20077.163 | CA5: 18453.924 | CB5: 6342.4071 | CC5: 87014.392 | CD5: 86819.252 | CE5: 111615.58 | CF5: 0.54067719 | CG5: 2536.811 | CH5: 113433.96 | CI5: 0.57872439 | CJ5: 113466.55 | CK5: 0.57855815
A6: 46023 | H6: 23325.781 | I6: 23325.781 | J6: 777.52603 | K6: 30 | L6: 15 | M6: 15 | N6: 13 | O6: 13 | P6: 12 | Q6: 9 | R6: 12 | S6: 2 | T6: 2 | U6: 12576 | V6: 12576 | X6: 6288 | Y6: 0.5 | Z6: 0.86666667 | AA6: 0.43333333 | AB6: 0.69230769 | AC6: 0.69230769 | AD6: 1 | AE6: 0.22222222 | AF6: 0.066666667 | AG6: 0.066666667 | AH6: 18916.329 | AI6: 0.66482244 | AJ6: 12 | AK6: 12 | AL6: 12 | AM6: 2809.4544 | AN6: 2344.9882 | AO6: 1555.6181 | AP6: 300 | AQ6: 1009.966 | AR6: 0 | AS6: 0 | AU6: 0 | AX6: 0 | AY6: 0 | AZ6: 0 | BA6: 0 | BB6: 0 | BC6: 0 | BE6: #DIV/0! | BF6: #DIV/0! | BG6: #DIV/0! | BH6: #DIV/0! | BI6: #DIV/0! | BK6: #DIV/0! | BL6: #DIV/0! | BM6: #DIV/0! | BN6: #DIV/0! | BO6: 0 | BP6: 0 | BQ6: 0 | BR6: 0 | BS6: 0 | BT6: 0 | BU6: 0 | BV6: 0 | BW6: 12576 | BX6: 12576 | BZ6: 5210.5723 | CA6: 4958.0808 | CB6: 2809.4544 | CC6: 23325.781 | CD6: 23325.781 | CE6: 18663.838 | CF6: 0.67381641 | CG6: 0 | CH6: 18916.329 | CI6: 0.66482244 | CJ6: 18356.875 | CK6: 0.68508394
A7: 專家鄧明儀-汇总 | H7: =SUM(H3:H6) | I7: =SUM(I3:I6) | J7: =I7/K7 | K7: =SUM(K3:K6) | L7: =SUM(L3:L6) | M7: =SUM(M3:M6) | N7: =SUM(N3:N6) | Q7: =SUM(Q3:Q6) | R7: =SUM(R3:R6) | S7: =SUM(S3:S6) | T7: =SUM(T3:T6) | U7: =SUM(U3:U6) | V7: =SUM(V3:V6) | X7: =V7/T7 | Y7: =L7/K7 | Z7: =N7/L7 | AA7: =N7/K7 | AB7: =Q7/N7 | AD7: =AVERAGE(AD3:AD6) | AE7: =S7/Q7 | AF7: =S7/K7 | AG7: =T7/K7 | AH7: =SUM(AH3:AH6) | AI7: =V7/AH7 | AJ7: =SUM(AJ3:AJ6) | AK7: =SUM(AK3:AK6) | AL7: =SUM(AL3:AL6) | AM7: =SUM(AM3:AM6) | AN7: =SUM(AN3:AN6) | AO7: =SUM(AO3:AO6) | AP7: =SUM(AP3:AP6) | AQ7: =SUM(AQ3:AQ6) | ... AS7: =SUM(AS3:AS6) | AU7: =SUM(AU3:AU6) | AX7: =SUM(AX3:AX6) | AY7: =SUM(AY3:AY6) | AZ7: =SUM(AZ3:AZ6) | BA7: =SUM(BA3:BA6) | BB7: =SUM(BB3:BB6) | BC7: =SUM(BC3:BC6) | BE7: =BC7/BA7 | BF7: =AS7/AR7 | BG7: =AU7/AS7 | BH7: =AU7/AR7 | BI7: =AX7/AU7 | BK7: =AVERAGE(BK3:BK6) | BL7: =AZ7/AX7 | BM7: =AZ7/AR7 | BN7: =BA7/AR7 | BO7: =SUM(BO3:BO6) | BP7: =SUM(BP3:BP6) | BQ7: =SUM(BQ3:BQ6) | BR7: =SUM(BR3:BR6) | BS7: =SUM(BS3:BS6) | BT7: =SUM(BT3:BT6) | BU7: =SUM(BU3:BU6) | BV7: =SUM(BV3:BV6) | ... BX7: =SUM(BX3:BX6) | BZ7: =SUM(BZ3:BZ6) | CA7: =SUM(CA3:CA6) | CB7: =SUM(CB3:CB6) | CC7: =SUM(CC3:CC6) | CD7: =SUM(CD3:CD6) | CE7: =SUM(CE3:CE6) | CF7: =BW7/CE7 | CG7: =SUM(CG3:CG6) | CH7: =SUM(CH3:CH6) | CI7: =BX7/CH7 | CJ7: =SUM(CJ3:CJ6) | CK7: =BX7/CJ7

Sheet 專家鄧明儀-求和
I1: 主投 | AR1: 辅投 | BW1: 汇总
B2: 渠道组 | C2: 供应商 | D2: 渠道名称 | E2: 主投 | F2: 辅投 | G2: 结算方式 | H2: 滚动消耗 | I2: 滚动消耗(不含赠课成本) | J2: 单例子成本 | K2: 例子数 | L2: 分发数 | M2: 剔除毛例子 分发数 | N2: 约课数 | Q2: 到课数 | R2: 滚动到课数 | S2: 当月成交数 | T2: 滚动成交数 | U2: 当月GMV | V2: 滚动GMV | W2: 海外GMV占比 | X2: 滚动ASP | Y2: 例子分发率 | Z2: 分发约课率 | AA2: 例子约课率 | AB2: 约课到课率 | AD2: 滚动应到课率 | AE2: 到课转化率 | AF2: 注册转化率 | AG2: 滚动转化率 | AH2: 滚动ROI2总成本 | AI2: 滚动ROI2 | AJ2: 滚动应到课人数 | AK2: 滚动到课人数 | AL2: 滚动到课人次 | AM2: 运营成本 | AN2: 销售固定成本 | AO2: 销售变动成本 | AP2: TMK费用 | AQ2: DEMO费用 | AR2: 例子数 | AS2: 分发数 | AT2: 剔除毛例子分发数 | AU2: 约课数 | AX2: 到课数 | AY2: 滚动到课数 | AZ2: 当月成交 | BA2: 滚动成交数 | BB2: 当月GMV | BC2: 滚动GMV | BD2: 海外GMV占比 | BE2: 滚动ASP | BF2: 例子分发率 | BG2: 分发约课率 | BH2: 例子约课率 | BI2: 约课到课率 | BK2: 滚动应到课率 | BL2: 到课转化率 | BM2: 注册转化率 | BN2: 滚动转化率 | BO2: 滚动应到课人数 | BP2: 滚动到课人数 | BQ2: 滚动到课人次 | BR2: 运营成本 | BS2: 销售固定成本 | BT2: 销售变动成本 | BU2: TMK费用 | BV2: DEMO费用 | BW2: 当月GMV | BX2: 滚动GMV | BY2: 海外GMV占比 | BZ2: 滚动其他成本 | CA2: 同源其他成本 | CB2: 运营成本 | CC2: 滚动消耗 | CD2: 同源消耗 | CE2: 当月ROI2总成本 | CF2: 当月ROI2 | CG2: 滚动赠课成本 | CH2: 滚动ROI2总成本 | CI2: 滚动ROI2 | CJ2: O-ROI总成本 | CK2: O-ROI
E3: 图片 | H3: 12429.478 | I3: =H3-CG3 | J3: 1035.7899 | K3: 12 | L3: 4 | M3: 4 | N3: 3 | O3: 3 | P3: 4 | Q3: 2 | R3: 4 | S3: 0 | T3: 0 | U3: 0 | V3: 0 | Y3: 0.33333333 | Z3: 0.75 | AA3: 0.25 | AB3: 0.66666667 | AC3: 0.66666667 | AD3: 1 | AE3: 0 | AF3: 0 | AG3: 0 | AH3: 2205.7673 | AI3: 0 | AJ3: 4 | AK3: 4 | AL3: 4 | AM3: 1123.7817 | AN3: 625.33018 | AO3: 0 | AP3: 120 | AQ3: 336.65534 | AR3: 0 | AS3: 0 | AT3: 0 | AU3: 0 | AV3: 0 | AW3: 0 | AX3: 0 | AY3: 0 | AZ3: 0 | BA3: 0 | BB3: 0 | BC3: 0 | BO3: 0 | BP3: 0 | BQ3: 0 | BR3: 0 | BS3: 0 | BT3: 0 | BU3: 0 | BV3: 0 | BW3: 0 | BX3: 0 | BZ3: 1081.9855 | CA3: 913.65785 | CB3: 1123.7817 | CC3: 12429.478 | CD3: 12429.478 | CE3: 2037.4396 | CF3: 0 | CG3: 0 | CH3: 2205.7673 | CI3: 0 | CJ3: 1981.9855 | CK3: 0
A4: 45904 | E4: 视频 | H4: 10896.302 | I4: =H4-CG4 | J4: 605.35014 | K4: 18 | L4: 11 | M4: 11 | N4: 10 | O4: 10 | P4: 8 | Q4: 7 | R4: 8 | S4: 2 | T4: 2 | U4: 12576 | V4: 12576 | W4: 1 | X4: 6288 | Y4: 0.61111111 | Z4: 0.90909091 | AA4: 0.55555556 | AB4: 0.7 | AC4: 0.7 | AD4: 1 | AE4: 0.28571429 | AF4: 0.11111111 | AG4: 0.11111111 | AH4: 16710.562 | AI4: 0.75257793 | AJ4: 8 | AK4: 8 | AL4: 8 | AM4: 1685.6726 | AN4: 1719.658 | AO4: 1555.6181 | AP4: 180 | AQ4: 673.31069 | AR4: 0 | AS4: 0 | AT4: 0 | AU4: 0 | AV4: 0 | AW4: 0 | AX4: 0 | AY4: 0 | AZ4: 0 | BA4: 0 | BB4: 0 | BC4: 0 | BO4: 0 | BP4: 0 | BQ4: 0 | BR4: 0 | BS4: 0 | BT4: 0 | BU4: 0 | BV4: 0 | BW4: 12576 | BX4: 12576 | BY4: 1 | BZ4: 4128.5868 | CA4: 4044.4229 | CB4: 1685.6726 | CC4: 10896.302 | CD4: 10896.302 | CE4: 16626.398 | CF4: 0.75638752 | CG4: 0 | CH4: 16710.562 | CI4: 0.75257793 | CJ4: 16374.889 | CK4: 0.7680052
A5: 專家鄧明儀-汇总 | H5: =SUM(H3:H4) | I5: =SUM(I3:I4) | J5: =I5/K5 | K5: =SUM(K3:K4) | L5: =SUM(L3:L4) | M5: =SUM(M3:M4) | N5: =SUM(N3:N4) | O5: =SUM(O3:O4) | P5: =SUM(P3:P4) | Q5: =SUM(Q3:Q4) | R5: =SUM(R3:R4) | ... V5: =SUM(V3:V4) | X5: =V5/T5 | Y5: =L5/K5 | Z5: =N5/L5 | AA5: =N5/K5 | AB5: =Q5/N5 | AC5: =Q5/O5 | AD5: =AVERAGE(AD3:AD4) | AE5: =S5/Q5 | AF5: =S5/K5 | AG5: =T5/K5 | AH5: =SUM(AH3:AH4) | AI5: =V5/AH5 | AJ5: =SUM(AJ3:AJ4) | AK5: =SUM(AK3:AK4) | AL5: =SUM(AL3:AL4) | AM5: =SUM(AM3:AM4) | AN5: =SUM(AN3:AN4) | AO5: =SUM(AO3:AO4) | AP5: =SUM(AP3:AP4) | AQ5: =SUM(AQ3:AQ4) | ... AS5: =SUM(AS3:AS4) | AU5: =SUM(AU3:AU4) | AX5: =SUM(AX3:AX4) | AY5: =SUM(AY3:AY4) | AZ5: =SUM(AZ3:AZ4) | BA5: =SUM(BA3:BA4) | BB5: =SUM(BB3:BB4) | BC5: =SUM(BC3:BC4) | BE5: =BC5/BA5 | BF5: =AS5/AR5 | BG5: =AU5/AS5 | BH5: =AU5/AR5 | BI5: =AX5/AU5 | BK5: =AVERAGE(BK3:BK4) | BL5: =AZ5/AX5 | BM5: =AZ5/AR5 | BN5: =BA5/AR5 | BO5: =SUM(BO3:BO4) | BP5: =SUM(BP3:BP4) | BQ5: =SUM(BQ3:BQ4) | BR5: =SUM(BR3:BR4) | BS5: =SUM(BS3:BS4) | BT5: =SUM(BT3:BT4) | BU5: =SUM(BU3:BU4) | BV5: =SUM(BV3:BV4) | ... BX5: =SUM(BX3:BX4) | BZ5: =SUM(BZ3:BZ4) | CA5: =SUM(CA3:CA4) | CB5: =SUM(CB3:CB4) | CC5: =SUM(CC3:CC4) | CD5: =SUM(CD3:CD4) | CE5: =SUM(CE3:CE4) | CF5: =BW5/CE5 | CG5: =SUM(CG3:CG4) | CH5: =SUM(CH3:CH4) | CI5: =BX5/CH5 | CJ5: =SUM(CJ3:CJ4) | CK5: =BX5/CJ5

Sheet 陳凱琳
I1: 主投 | AR1: 辅投 | BW1: 汇总
B2: 渠道组 | C2: 供应商 | D2: 渠道名称 | E2: 主投 | F2: 辅投 | G2: 结算方式 | H2: 滚动消耗 | I2: 滚动消耗(不含赠课成本) | J2: 单例子成本 | K2: 例子数 | L2: 分发数 | M2: 剔除毛例子 分发数 | N2: 约课数 | Q2: 到课数 | R2: 滚动到课数 | S2: 当月成交数 | T2: 滚动成交数 | U2: 当月GMV | V2: 滚动GMV | W2: 海外GMV占比 | X2: 滚动ASP | Y2: 例子分发率 | Z2: 分发约课率 | AA2: 例子约课率 | AB2: 约课到课率 | AD2: 滚动应到课率 | AE2: 到课转化率 | AF2: 注册转化率 | AG2: 滚动转化率 | AH2: 滚动ROI2总成本 | AI2: 滚动ROI2 | AJ2: 滚动应到课人数 | AK2: 滚动到课人数 | AL2: 滚动到课人次 | AM2: 运营成本 | AN2: 销售固定成本 | AO2: 销售变动成本 | AP2: TMK费用 | AQ2: DEMO费用 | AR2: 例子数 | AS2: 分发数 | AT2: 剔除毛例子分发数 | AU2: 约课数 | AX2: 到课数 | AY2: 滚动到课数 | AZ2: 当月成交 | BA2: 滚动成交数 | BB2: 当月GMV | BC2: 滚动GMV | BD2: 海外GMV占比 | BE2: 滚动ASP | BF2: 例子分发率 | BG2: 分发约课率 | BH2: 例子约课率 | BI2: 约课到课率 | BK2: 滚动应到课率 | BL2: 到课转化率 | BM2: 注册转化率 | BN2: 滚动转化率 | BO2: 滚动应到课人数 | BP2: 滚动到课人数 | BQ2: 滚动到课人次 | BR2: 运营成本 | BS2: 销售固定成本 | BT2: 销售变动成本 | BU2: TMK费用 | BV2: DEMO费用 | BW2: 当月GMV | BX2: 滚动GMV | BY2: 海外GMV占比 | BZ2: 滚动其他成本 | CA2: 同源其他成本 | CB2: 运营成本 | CC2: 滚动消耗 | CD2: 同源消耗 | CE2: 当月ROI2总成本 | CF2: 当月ROI2 | CG2: 滚动赠课成本 | CH2: 滚动ROI2总成本 | CI2: 滚动ROI2 | CJ2: O-ROI总成本 | CK2: O-ROI
A3: 45931 | H3: 78812.376 | I3: =H3-CG3 | J3: 685.32501 | K3: 115 | L3: 15 | M3: 15 | N3: 14 | Q3: 11 | R3: 11 | S3: 4 | T3: 4 | U3: 21483 | V3: 21483 | W3: 1 | X3: 5370.75 | Y3: 0.13043478 | Z3: 0.93333333 | AA3: 0.12173913 | AB3: 0.78571429 | AD3: 1 | AE3: 0.36363636 | AF3: 0.034782609 | AG3: 0.034782609 | AH3: 92577.417 | AI3: 0.23205443 | AJ3: 11 | AK3: 11 | AL3: 11 | AM3: 7185.7394 | AN3: 2133.7104 | AO3: 2363.1663 | AP3: 1150 | AQ3: 932.42495 | AR3: 0 | AS3: 0 | AT3: 0 | AU3: 0 | AX3: 0 | AY3: 0 | AZ3: 0 | BA3: 0 | BB3: 0 | BC3: 0 | BO3: 0 | BP3: 0 | BQ3: 0 | BR3: 0 | BS3: 0 | BT3: 0 | BU3: 0 | BV3: 0 | BW3: 21483 | BX3: 21483 | BY3: 1 | BZ3: 6579.3017 | CA3: 6579.3017 | CB3: 7185.7394 | CC3: 78812.376 | CD3: 78812.376 | CE3: 92577.417 | CF3: 0.23205443 | CG3: 714.55655 | CH3: 92577.417 | CI3: 0.23205443 | CJ3: 94016.678 | CK3: 0.22850201
A4: 45962 | H4: 136770.3 | I4: =H4-CG4 | J4: 1953.8615 | K4: 70 | L4: 36 | M4: 39 | N4: 37 | Q4: 29 | R4: 33 | S4: 10 | T4: 12 | U4: 42910 | V4: 54228 | W4: 1 | X4: 4519 | Y4: 0.51428571 | Z4: 1.0277778 | AA4: 0.52857143 | AB4: 0.78378378 | AD4: 1 | AE4: 0.34482759 | AF4: 0.14285714 | AG4: 0.17142857 | AH4: 155734.57 | AI4: 0.34820785 | AJ4: 33 | AK4: 33 | AL4: 37 | AM4: 4556.5458 | AN4: 4606.2106 | AO4: 5965.1716 | AP4: 700 | AQ4: 3136.3385 | AR4: 0 | AS4: 0 | AT4: 0 | AU4: 0 | AX4: 0 | AY4: 0 | AZ4: 0 | BA4: 0 | BB4: 0 | BC4: 0 | BO4: 0 | BP4: 0 | BQ4: 0 | BR4: 0 | BS4: 0 | BT4: 0 | BU4: 0 | BV4: 0 | BW4: 42910 | BX4: 54228 | BY4: 1 | BZ4: 14407.721 | CA4: 12469.334 | CB4: 4556.5458 | CC4: 136770.3 | CD4: 136412.86 | CE4: 153438.74 | CF4: 0.27965558 | CG4: 2144.6682 | CH4: 155734.57 | CI4: 0.34820785 | CJ4: 156428.03 | CK4: 0.34666422
A5: 45992 | H5: 95287.029 | I5: =H5-CG5 | J5: 6352.4686 | K5: 15 | L5: 9 | M5: 9 | N5: 8 | O5: 8 | P5: 9 | Q5: 7 | R5: 9 | S5: 2 | T5: 3 | U5: 16548.1 | V5: 20047.1 | W5: 1 | X5: 6682.3667 | Y5: 0.6 | Z5: 0.88888889 | AA5: 0.53333333 | AB5: 0.875 | AC5: 0.875 | AD5: 1 | AE5: 0.28571429 | AF5: 0.13333333 | AG5: 0.2 | AH5: 101202.74 | AI5: 0.19808851 | AJ5: 9 | AK5: 9 | AL5: 10 | AM5: 1119.2483 | AN5: 1325.0508 | AO5: 2479.7735 | AP5: 150 | AQ5: 841.63836 | AR5: 0 | AS5: 0 | AT5: 0 | AU5: 0 | AV5: 0 | AW5: 0 | AX5: 0 | AY5: 0 | AZ5: 0 | BA5: 0 | BB5: 0 | BC5: 0 | BO5: 0 | BP5: 0 | BQ5: 0 | BR5: 0 | BS5: 0 | BT5: 0 | BU5: 0 | BV5: 0 | BW5: 16548.1 | BX5: 20047.1 | BY5: 1 | BZ5: 4796.4627 | CA5: 4195.3179 | CB5: 1119.2483 | CC5: 95287.029 | CD5: 95091.89 | CE5: 100406.46 | CF5: 0.16481111 | CG5: 585.41792 | CH5: 101202.74 | CI5: 0.19808851 | CJ5: 101208.49 | CK5: 0.19807725
A6: 46023 | H6: 61494.924 | I6: =H6-CG6 | J6: 1708.1923 | K6: 36 | L6: 29 | M6: 30 | N6: 29 | O6: 28 | P6: 23 | Q6: 21 | R6: 23 | S6: 6 | T6: 6 | U6: 31928 | V6: 31928 | W6: 1 | X6: 5321.3333 | Y6: 0.80555556 | Z6: 1 | AA6: 0.80555556 | AB6: 0.72413793 | AC6: 0.75 | AD6: 1 | AE6: 0.28571429 | AF6: 0.16666667 | AG6: 0.16666667 | AH6: 77731.325 | AI6: 0.41074818 | AJ6: 23 | AK6: 23 | AL6: 24 | AM6: 3915.6195 | AN6: 5808.2202 | AO6: 4185.5024 | AP6: 360 | AQ6: 1967.0594 | AR6: 0 | AS6: 0 | AT6: 0 | AU6: 0 | AV6: 0 | AW6: 0 | AX6: 0 | AY6: 0 | AZ6: 0 | BA6: 0 | BB6: 0 | BC6: 0 | BO6: 0 | BP6: 0 | BQ6: 0 | BR6: 0 | BS6: 0 | BT6: 0 | BU6: 0 | BV6: 0 | BW6: 31928 | BX6: 31928 | BY6: 1 | BZ6: 12320.782 | CA6: 11963.253 | CB6: 3915.6195 | CC6: 61494.924 | CD6: 61494.924 | CE6: 77373.796 | CF6: 0.41264616 | CG6: 0 | CH6: 77731.325 | CI6: 0.41074818 | CJ6: 76515.706 | CK6: 0.41727381
A7: 46054 | H7: 4957.2301 | I7: =H7-CG7 | J7: 826.20501 | K7: 6 | L7: 2 | M7: 3 | N7: 3 | O7: 3 | P7: 5 | Q7: 1 | R7: 5 | S7: 1 | T7: 1 | U7: 4588 | V7: 4588 | W7: 1 | X7: 4588 | Y7: 0.33333333 | Z7: 1.5 | AA7: 0.5 | AB7: 0.33333333 | AC7: 0.33333333 | AD7: 1 | AE7: 1 | AF7: 0.16666667 | AG7: 0.16666667 | AH7: 7401.0002 | AI7: 0.61991621 | AJ7: 5 | AK7: 5 | AL7: 5 | AM7: 790.80703 | AN7: 581.70946 | AO7: 601.44966 | AP7: 60 | AQ7: 409.80405 | AR7: 0 | AS7: 0 | AT7: 0 | AU7: 0 | AV7: 0 | AW7: 0 | AX7: 0 | AY7: 0 | AZ7: 0 | BA7: 0 | BB7: 0 | BC7: 0 | BO7: 0 | BP7: 0 | BQ7: 0 | BR7: 0 | BS7: 0 | BT7: 0 | BU7: 0 | BV7: 0 | BW7: 4588 | BX7: 4588 | BY7: 1 | BZ7: 1652.9632 | CA7: 1131.2168 | CB7: 790.80703 | CC7: 4957.2301 | CD7: 4957.2301 | CE7: 6879.2539 | CF7: 0.66693279 | CG7: 0 | CH7: 7401.0002 | CI7: 0.61991621 | CJ7: 7060.1932 | CK7: 0.64984057
A8: 陈凯琳-汇总 | H8: =SUM(H3:H7) | I8: =SUM(I3:I7) | J8: =I8/K8 | K8: =SUM(K3:K7) | L8: =SUM(L3:L7) | M8: =SUM(M3:M7) | N8: =SUM(N3:N7) | Q8: =SUM(Q3:Q7) | R8: =SUM(R3:R7) | S8: =SUM(S3:S7) | T8: =SUM(T3:T7) | U8: =SUM(U3:U7) | V8: =SUM(V3:V7) | X8: =V8/T8 | Y8: =L8/K8 | Z8: =N8/L8 | AA8: =N8/K8 | AB8: =Q8/N8 | AD8: =AVERAGE(AD3:AD7) | AE8: =S8/Q8 | AF8: =S8/K8 | AG8: =T8/K8 | AH8: =SUM(AH3:AH7) | AI8: =V8/AH8 | AJ8: =SUM(AJ3:AJ7) | AK8: =SUM(AK3:AK7) | AL8: =SUM(AL3:AL7) | AM8: =SUM(AM3:AM7) | AN8: =SUM(AN3:AN7) | AO8: =SUM(AO3:AO7) | AP8: =SUM(AP3:AP7) | AQ8: =SUM(AQ3:AQ7) | ... AS8: =SUM(AS3:AS7) | AU8: =SUM(AU3:AU7) | AX8: =SUM(AX3:AX7) | AY8: =SUM(AY3:AY7) | AZ8: =SUM(AZ3:AZ7) | BA8: =SUM(BA3:BA7) | BB8: =SUM(BB3:BB7) | BC8: =SUM(BC3:BC7) | BE8: =BC8/BA8 | BF8: =AS8/AR8 | BG8: =AU8/AS8 | BH8: =AU8/AR8 | BI8: =AX8/AU8 | BK8: =AVERAGE(BK3:BK7) | BL8: =AZ8/AX8 | BM8: =AZ8/AR8 | BN8: =BA8/AR8 | BO8: =SUM(BO3:BO7) | BP8: =SUM(BP3:BP7) | BQ8: =SUM(BQ3:BQ7) | BR8: =SUM(BR3:BR7) | BS8: =SUM(BS3:BS7) | BT8: =SUM(BT3:BT7) | BU8: =SUM(BU3:BU7) | BV8: =SUM(BV3:BV7) | ... BX8: =SUM(BX3:BX7) | BZ8: =SUM(BZ3:BZ7) | CA8: =SUM(CA3:CA7) | CB8: =SUM(CB3:CB7) | CC8: =SUM(CC3:CC7) | CD8: =SUM(CD3:CD7) | CE8: =SUM(CE3:CE7) | CF8: =BW8/CE8 | CG8: =SUM(CG3:CG7) | CH8: =SUM(CH3:CH7) | CI8: =BX8/CH8 | CJ8: =SUM(CJ3:CJ7) | CK8: =BX8/CJ8

Sheet 麥雅緻直播
I1: 主投 | AR1: 辅投 | BW1: 汇总
B2: 渠道组 | C2: 供应商 | D2: 渠道名称 | E2: 主投 | F2: 辅投 | G2: 结算方式 | H2: 滚动消耗 | I2: 滚动消耗(不含赠课成本) | J2: 单例子成本 | K2: 例子数 | L2: 分发数 | M2: 剔除毛例子 分发数 | N2: 约课数 | Q2: 到课数 | R2: 滚动到课数 | S2: 当月成交数 | T2: 滚动成交数 | U2: 当月GMV | V2: 滚动GMV | W2: 海外GMV占比 | X2: 滚动ASP | Y2: 例子分发率 | Z2: 分发约课率 | AA2: 例子约课率 | AB2: 约课到课率 | AD2: 滚动应到课率 | AE2: 到课转化率 | AF2: 注册转化率 | AG2: 滚动转化率 | AH2: 滚动ROI2总成本 | AI2: 滚动ROI2 | AJ2: 滚动应到课人数 | AK2: 滚动到课人数 | AL2: 滚动到课人次 | AM2: 运营成本 | AN2: 销售固定成本 | AO2: 销售变动成本 | AP2: TMK费用 | AQ2: DEMO费用 | AR2: 例子数 | AS2: 分发数 | AT2: 剔除毛例子分发数 | AU2: 约课数 | AX2: 到课数 | AY2: 滚动到课数 | AZ2: 当月成交 | BA2: 滚动成交数 | BB2: 当月GMV | BC2: 滚动GMV | BD2: 海外GMV占比 | BE2: 滚动ASP | BF2: 例子分发率 | BG2: 分发约课率 | BH2: 例子约课率 | BI2: 约课到课率 | BK2: 滚动应到课率 | BL2: 到课转化率 | BM2: 注册转化率 | BN2: 滚动转化率 | BO2: 滚动应到课人数 | BP2: 滚动到课人数 | BQ2: 滚动到课人次 | BR2: 运营成本 | BS2: 销售固定成本 | BT2: 销售变动成本 | BU2: TMK费用 | BV2: DEMO费用 | BW2: 当月GMV | BX2: 滚动GMV | BY2: 海外GMV占比 | BZ2: 滚动其他成本 | CA2: 同源其他成本 | CB2: 运营成本 | CC2: 滚动消耗 | CD2: 同源消耗 | CE2: 当月ROI2总成本 | CF2: 当月ROI2 | CG2: 滚动赠课成本 | CH2: 滚动ROI2总成本 | CI2: 滚动ROI2 | CJ2: O-ROI总成本 | CK2: O-ROI
A3: 45962 | H3: 232574.54 | I3: =H3-CG3 | J3: 1284.9422 | K3: 181 | L3: 97 | M3: 97 | N3: 98 | Q3: 76 | R3: 76 | S3: 28 | T3: 28 | U3: 156292 | V3: 156292 | W3: 1 | X3: 5581.8571 | Y3: 0.5359116 | Z3: 1.0103093 | AA3: 0.54143646 | AB3: 0.7755102 | AD3: 0.98701299 | AE3: 0.36842105 | AF3: 0.15469613 | AG3: 0.15469613 | AH3: 281427.06 | AI3: 0.55535526 | AJ3: 77 | AK3: 76 | AL3: 78 | AM3: 11781.926 | AN3: 11456.473 | AO3: 17192.384 | AP3: 1810 | AQ3: 6611.7405 | AR3: 0 | AS3: 0 | AT3: 0 | AU3: 0 | AX3: 0 | AY3: 0 | AZ3: 0 | BA3: 0 | BB3: 0 | BC3: 0 | BO3: 0 | BP3: 0 | BQ3: 0 | BR3: 0 | BS3: 0 | BT3: 0 | BU3: 0 | BV3: 0 | BW3: 156292 | BX3: 156292 | BY3: 1 | BZ3: 37070.597 | CA3: 37070.597 | CB3: 11781.926 | CC3: 232574.54 | CD3: 232574.54 | CE3: 281427.06 | CF3: 0.55535526 | CG3: 5004.2259 | CH3: 281427.06 | CI3: 0.55535526 | CJ3: 283220.14 | CK3: 0.5518393
A4: 45992 | H4: 60942.398 | I4: =H4-CG4 | J4: 2343.9384 | K4: 26 | L4: 13 | M4: 16 | N4: 13 | O4: 13 | P4: 24 | Q4: 12 | R4: 24 | S4: 6 | T4: 10 | U4: 27114 | V4: 51910 | W4: 1 | X4: 5191 | Y4: 0.5 | Z4: 1 | AA4: 0.5 | AB4: 0.92307692 | AC4: 0.92307692 | AD4: 1 | AE4: 0.5 | AF4: 0.23076923 | AG4: 0.38461538 | AH4: 74191.628 | AI4: 0.69967463 | AJ4: 24 | AK4: 24 | AL4: 27 | AM4: 1940.0304 | AN4: 2355.6459 | AO4: 6421.1303 | AP4: 260 | AQ4: 2272.4236 | AR4: 0 | AS4: 0 | AT4: 0 | AU4: 0 | AV4: 0 | AW4: 0 | AX4: 0 | AY4: 0 | AZ4: 0 | BA4: 0 | BB4: 0 | BC4: 0 | BO4: 0 | BP4: 0 | BQ4: 0 | BR4: 0 | BS4: 0 | BT4: 0 | BU4: 0 | BV4: 0 | BW4: 27114 | BX4: 51910 | BY4: 1 | BZ4: 11309.2 | CA4: 6622.0226 | CB4: 1940.0304 | CC4: 60942.398 | CD4: 60161.841 | CE4: 68723.894 | CF4: 0.39453527 | CG4: 1951.3931 | CH4: 74191.628 | CI4: 0.69967463 | CJ4: 74201.598 | CK4: 0.69958062
A5: 麥雅緻直播-汇总 | H5: =SUM(H3:H4) | I5: =SUM(I3:I4) | J5: =I5/K5 | K5: =SUM(K3:K4) | L5: =SUM(L3:L4) | M5: =SUM(M3:M4) | N5: =SUM(N3:N4) | Q5: =SUM(Q3:Q4) | R5: =SUM(R3:R4) | S5: =SUM(S3:S4) | T5: =SUM(T3:T4) | U5: =SUM(U3:U4) | V5: =SUM(V3:V4) | X5: =V5/T5 | Y5: =L5/K5 | Z5: =N5/L5 | AA5: =N5/K5 | AB5: =Q5/N5 | AD5: =AVERAGE(AD3:AD4) | AE5: =S5/Q5 | AF5: =S5/K5 | AG5: =T5/K5 | AH5: =SUM(AH3:AH4) | AI5: =V5/AH5 | AJ5: =SUM(AJ3:AJ4) | AK5: =SUM(AK3:AK4) | AL5: =SUM(AL3:AL4) | AM5: =SUM(AM3:AM4) | AN5: =SUM(AN3:AN4) | AO5: =SUM(AO3:AO4) | AP5: =SUM(AP3:AP4) | AQ5: =SUM(AQ3:AQ4) | ... AS5: =SUM(AS3:AS4) | AU5: =SUM(AU3:AU4) | AX5: =SUM(AX3:AX4) | AY5: =SUM(AY3:AY4) | AZ5: =SUM(AZ3:AZ4) | BA5: =SUM(BA3:BA4) | BB5: =SUM(BB3:BB4) | BC5: =SUM(BC3:BC4) | BE5: =BC5/BA5 | BF5: =AS5/AR5 | BG5: =AU5/AS5 | BH5: =AU5/AR5 | BI5: =AX5/AU5 | BK5: =AVERAGE(BK3:BK4) | BL5: =AZ5/AX5 | BM5: =AZ5/AR5 | BN5: =BA5/AR5 | BO5: =SUM(BO3:BO4) | BP5: =SUM(BP3:BP4) | BQ5: =SUM(BQ3:BQ4) | BR5: =SUM(BR3:BR4) | BS5: =SUM(BS3:BS4) | BT5: =SUM(BT3:BT4) | BU5: =SUM(BU3:BU4) | BV5: =SUM(BV3:BV4) | ... BX5: =SUM(BX3:BX4) | BZ5: =SUM(BZ3:BZ4) | CA5: =SUM(CA3:CA4) | CB5: =SUM(CB3:CB4) | CC5: =SUM(CC3:CC4) | CD5: =SUM(CD3:CD4) | CE5: =SUM(CE3:CE4) | CF5: =BW5/CE5 | CG5: =SUM(CG3:CG4) | CH5: =SUM(CH3:CH4) | CI5: =BX5/CH5 | CJ5: =SUM(CJ3:CJ4) | CK5: =BX5/CJ5

Sheet 呂慧儀直播
I1: 主投 | AR1: 辅投 | BW1: 汇总
B2: 渠道组 | C2: 供应商 | D2: 渠道名称 | E2: 主投 | F2: 辅投 | G2: 结算方式 | H2: 滚动消耗 | I2: 滚动消耗(不含赠课成本) | J2: 单例子成本 | K2: 例子数 | L2: 分发数 | M2: 剔除毛例子 分发数 | N2: 约课数 | Q2: 到课数 | R2: 滚动到课数 | S2: 当月成交数 | T2: 滚动成交数 | U2: 当月GMV | V2: 滚动GMV | W2: 海外GMV占比 | X2: 滚动ASP | Y2: 例子分发率 | Z2: 分发约课率 | AA2: 例子约课率 | AB2: 约课到课率 | AD2: 滚动应到课率 | AE2: 到课转化率 | AF2: 注册转化率 | AG2: 滚动转化率 | AH2: 滚动ROI2总成本 | AI2: 滚动ROI2 | AJ2: 滚动应到课人数 | AK2: 滚动到课人数 | AL2: 滚动到课人次 | AM2: 运营成本 | AN2: 销售固定成本 | AO2: 销售变动成本 | AP2: TMK费用 | AQ2: DEMO费用 | AR2: 例子数 | AS2: 分发数 | AT2: 剔除毛例子分发数 | AU2: 约课数 | AX2: 到课数 | AY2: 滚动到课数 | AZ2: 当月成交 | BA2: 滚动成交数 | BB2: 当月GMV | BC2: 滚动GMV | BD2: 海外GMV占比 | BE2: 滚动ASP | BF2: 例子分发率 | BG2: 分发约课率 | BH2: 例子约课率 | BI2: 约课到课率 | BK2: 滚动应到课率 | BL2: 到课转化率 | BM2: 注册转化率 | BN2: 滚动转化率 | BO2: 滚动应到课人数 | BP2: 滚动到课人数 | BQ2: 滚动到课人次 | BR2: 运营成本 | BS2: 销售固定成本 | BT2: 销售变动成本 | BU2: TMK费用 | BV2: DEMO费用 | BW2: 当月GMV | BX2: 滚动GMV | BY2: 海外GMV占比 | BZ2: 滚动其他成本 | CA2: 同源其他成本 | CB2: 运营成本 | CC2: 滚动消耗 | CD2: 同源消耗 | CE2: 当月ROI2总成本 | CF2: 当月ROI2 | CG2: 滚动赠课成本 | CH2: 滚动ROI2总成本 | CI2: 滚动ROI2 | CJ2: O-ROI总成本 | CK2: O-ROI
A3: 45962 | H3: 103154.49 | I3: =H3-CG3 | J3: 889.26285 | K3: 116 | L3: 56 | M3: 56 | N3: 56 | Q3: 35 | R3: 35 | S3: 11 | T3: 11 | U3: 59729 | V3: 59729 | W3: 1 | X3: 5429.9091 | Y3: 0.48275862 | Z3: 1 | AA3: 0.48275862 | AB3: 0.625 | AD3: 1 | AE3: 0.31428571 | AF3: 0.094827586 | AG3: 0.094827586 | AH3: 128186.01 | AI3: 0.46595567 | AJ3: 35 | AK3: 35 | AL3: 37 | AM3: 7550.8474 | AN3: 6614.046 | AO3: 6570.2909 | AP3: 1160 | AQ3: 3136.3385 | AR3: 0 | AS3: 0 | AT3: 0 | AU3: 0 | AX3: 0 | AY3: 0 | AZ3: 0 | BA3: 0 | BB3: 0 | BC3: 0 | BO3: 0 | BP3: 0 | BQ3: 0 | BR3: 0 | BS3: 0 | BT3: 0 | BU3: 0 | BV3: 0 | BW3: 59729 | BX3: 59729 | BY3: 1 | BZ3: 17480.675 | CA3: 17480.675 | CB3: 7550.8474 | CC3: 103154.49 | CD3: 103154.49 | CE3: 128186.01 | CF3: 0.46595567 | CG3: 1965.9459 | CH3: 128186.01 | CI3: 0.46595567 | CJ3: 129335.17 | CK3: 0.46181562
A4: 45992 | H4: 151817.61 | I4: =H4-CG4 | J4: 1615.081 | K4: 94 | L4: 45 | M4: 51 | N4: 43 | O4: 41 | P4: 43 | Q4: 32 | R4: 42 | S4: 10 | T4: 13 | U4: 44710 | V4: 58096 | W4: 1 | X4: 4468.9231 | Y4: 0.4787234 | Z4: 0.95555556 | AA4: 0.45744681 | AB4: 0.74418605 | AC4: 0.7804878 | AD4: 0.97674419 | AE4: 0.3125 | AF4: 0.10638298 | AG4: 0.13829787 | AH4: 178001.39 | AI4: 0.32637947 | AJ4: 43 | AK4: 42 | AL4: 42 | AM4: 7013.9561 | AN4: 7508.6214 | AO4: 7186.3222 | AP4: 940 | AQ4: 3534.8811 | AR4: 0 | AS4: 0 | AT4: 0 | AU4: 0 | AV4: 0 | AW4: 0 | AX4: 0 | AY4: 0 | AZ4: 0 | BA4: 0 | BB4: 0 | BC4: 0 | BO4: 0 | BP4: 0 | BQ4: 0 | BR4: 0 | BS4: 0 | BT4: 0 | BU4: 0 | BV4: 0 | BW4: 44710 | BX4: 58096 | BY4: 1 | BZ4: 19169.825 | CA4: 15789.006 | CB4: 7013.9561 | CC4: 151817.61 | CD4: 151232.19 | CE4: 174035.16 | CF4: 0.25690212 | CG4: 2536.811 | CH4: 178001.39 | CI4: 0.32637947 | CJ4: 178037.44 | CK4: 0.3263134
A5: 46023 | H5: 74827.384 | I5: =H5-CG5 | J5: 1053.9068 | K5: 71 | L5: 35 | M5: 38 | N5: 35 | O5: 35 | P5: 37 | Q5: 28 | R5: 37 | S5: 9 | T5: 12 | U5: 47892 | V5: 63667.2 | W5: 1 | X5: 5305.6 | Y5: 0.49295775 | Z5: 1 | AA5: 0.49295775 | AB5: 0.8 | AC5: 0.8 | AD5: 1 | AE5: 0.32142857 | AF5: 0.12676056 | AG5: 0.16901408 | AH5: 102159.66 | AI5: 0.62321272 | AJ5: 37 | AK5: 37 | AL5: 39 | AM5: 7722.4719 | AN5: 7357.0789 | AO5: 8346.2546 | AP5: 710 | AQ5: 3196.4716 | AR5: 0 | AS5: 0 | AT5: 0 | AU5: 0 | AV5: 0 | AW5: 0 | AX5: 0 | AY5: 0 | AZ5: 0 | BA5: 0 | BB5: 0 | BC5: 0 | BO5: 0 | BP5: 0 | BQ5: 0 | BR5: 0 | BS5: 0 | BT5: 0 | BU5: 0 | BV5: 0 | BW5: 47892 | BX5: 63667.2 | BY5: 1 | BZ5: 19609.805 | CA5: 16141.374 | CB5: 7722.4719 | CC5: 74827.384 | CD5: 74827.384 | CE5: 98691.23 | CF5: 0.48527108 | CG5: 0 | CH5: 102159.66 | CI5: 0.62321272 | CJ5: 99762.189 | CK5: 0.63818969
A6: 46054 | H6: 28742.762 | I6: =H6-CG6 | J6: 870.99278 | K6: 33 | L6: 10 | M6: 11 | N6: 9 | O6: 7 | P6: 6 | Q6: 6 | R6: 6 | S6: 1 | T6: 1 | U6: 4588 | V6: 4588 | W6: 1 | X6: 4588 | Y6: 0.3030303 | Z6: 0.9 | AA6: 0.27272727 | AB6: 0.66666667 | AC6: 0.85714286 | AD6: 1 | AE6: 0.16666667 | AF6: 0.03030303 | AG6: 0.03030303 | AH6: 36648.349 | AI6: 0.12518981 | AJ6: 6 | AK6: 6 | AL6: 6 | AM6: 4349.4386 | AN6: 2132.9347 | AO6: 601.44966 | AP6: 330 | AQ6: 491.76486 | AR6: 0 | AS6: 0 | AT6: 0 | AU6: 0 | AV6: 0 | AW6: 0 | AX6: 0 | AY6: 0 | AZ6: 0 | BA6: 0 | BB6: 0 | BC6: 0 | BO6: 0 | BP6: 0 | BQ6: 0 | BR6: 0 | BS6: 0 | BT6: 0 | BU6: 0 | BV6: 0 | BW6: 4588 | BX6: 4588 | BY6: 1 | BZ6: 3556.1492 | CA6: 3362.246 | CB6: 4349.4386 | CC6: 28742.762 | CD6: 28742.762 | CE6: 36454.446 | CF6: 0.1258557 | CG6: 0 | CH6: 36648.349 | CI6: 0.12518981 | CJ6: 34773.911 | CK6: 0.13193799
A7: 46082 | H7: 27315.788 | I7: =H7-CG7 | J7: 881.15444 | K7: 31 | L7: 14 | M7: 16 | N7: 14 | O7: 13 | P7: 17 | Q7: 10 | R7: 17 | S7: 4 | T7: 5 | U7: 15852 | V7: 19540 | W7: 1 | X7: 3908 | Y7: 0.4516129 | Z7: 1 | AA7: 0.4516129 | AB7: 0.71428571 | AC7: 0.76923077 | AD7: 1 | AE7: 0.4 | AF7: 0.12903226 | AG7: 0.16129032 | AH7: 36560.997 | AI7: 0.53444932 | AJ7: 17 | AK7: 17 | AL7: 20 | AM7: 2732.1921 | AN7: 2212.3369 | AO7: 2318.8056 | AP7: 310 | AQ7: 1671.875 | AR7: 0 | AS7: 0 | AT7: 0 | AU7: 0 | AV7: 0 | AW7: 0 | AX7: 0 | AY7: 0 | AZ7: 0 | BA7: 0 | BB7: 0 | BC7: 0 | BO7: 0 | BP7: 0 | BQ7: 0 | BR7: 0 | BS7: 0 | BT7: 0 | BU7: 0 | BV7: 0 | BW7: 15852 | BX7: 19540 | BY7: 1 | BZ7: 6513.0175 | CA7: 5213.6653 | CB7: 2732.1921 | CC7: 27315.788 | CD7: 27114.573 | CE7: 35060.431 | CF7: 0.45213364 | CG7: 1006.0719 | CH7: 36560.997 | CI7: 0.53444932 | CJ7: 36153.805 | CK7: 0.5404687
A8: 呂慧儀直播-汇总 | H8: =SUM(H3:H7) | I8: =SUM(I3:I7) | J8: =I8/K8 | K8: =SUM(K3:K7) | L8: =SUM(L3:L7) | M8: =SUM(M3:M7) | N8: =SUM(N3:N7) | Q8: =SUM(Q3:Q7) | R8: =SUM(R3:R7) | S8: =SUM(S3:S7) | T8: =SUM(T3:T7) | U8: =SUM(U3:U7) | V8: =SUM(V3:V7) | X8: =V8/T8 | Y8: =L8/K8 | Z8: =N8/L8 | AA8: =N8/K8 | AB8: =Q8/N8 | AD8: =AVERAGE(AD3:AD7) | AE8: =S8/Q8 | AF8: =S8/K8 | AG8: =T8/K8 | AH8: =SUM(AH3:AH7) | AI8: =V8/AH8 | AJ8: =SUM(AJ3:AJ7) | AK8: =SUM(AK3:AK7) | AL8: =SUM(AL3:AL7) | AM8: =SUM(AM3:AM7) | AN8: =SUM(AN3:AN7) | AO8: =SUM(AO3:AO7) | AP8: =SUM(AP3:AP7) | AQ8: =SUM(AQ3:AQ7) | ... AS8: =SUM(AS3:AS7) | AU8: =SUM(AU3:AU7) | AX8: =SUM(AX3:AX7) | AY8: =SUM(AY3:AY7) | AZ8: =SUM(AZ3:AZ7) | BA8: =SUM(BA3:BA7) | BB8: =SUM(BB3:BB7) | BC8: =SUM(BC3:BC7) | BE8: =BC8/BA8 | BF8: =AS8/AR8 | BG8: =AU8/AS8 | BH8: =AU8/AR8 | BI8: =AX8/AU8 | BK8: =AVERAGE(BK3:BK7) | BL8: =AZ8/AX8 | BM8: =AZ8/AR8 | BN8: =BA8/AR8 | BO8: =SUM(BO3:BO7) | BP8: =SUM(BP3:BP7) | BQ8: =SUM(BQ3:BQ7) | BR8: =SUM(BR3:BR7) | BS8: =SUM(BS3:BS7) | BT8: =SUM(BT3:BT7) | BU8: =SUM(BU3:BU7) | BV8: =SUM(BV3:BV7) | ... BX8: =SUM(BX3:BX7) | BZ8: =SUM(BZ3:BZ7) | CA8: =SUM(CA3:CA7) | CB8: =SUM(CB3:CB7) | CC8: =SUM(CC3:CC7) | CD8: =SUM(CD3:CD7) | CE8: =SUM(CE3:CE7) | CF8: =BW8/CE8 | CG8: =SUM(CG3:CG7) | CH8: =SUM(CH3:CH7) | CI8: =BX8/CH8 | CJ8: =SUM(CJ3:CJ7) | CK8: =BX8/CJ8

Sheet Kayan購物團直播
I1: 主投 | AR1: 辅投 | BW1: 汇总
B2: 渠道组 | C2: 供应商 | D2: 渠道名称 | E2: 主投 | F2: 辅投 | G2: 结算方式 | H2: 滚动消耗 | I2: 滚动消耗(不含赠课成本) | J2: 单例子成本 | K2: 例子数 | L2: 分发数 | M2: 剔除毛例子 分发数 | N2: 约课数 | Q2: 到课数 | R2: 滚动到课数 | S2: 当月成交数 | T2: 滚动成交数 | U2: 当月GMV | V2: 滚动GMV | W2: 海外GMV占比 | X2: 滚动ASP | Y2: 例子分发率 | Z2: 分发约课率 | AA2: 例子约课率 | AB2: 约课到课率 | AD2: 滚动应到课率 | AE2: 到课转化率 | AF2: 注册转化率 | AG2: 滚动转化率 | AH2: 滚动ROI2总成本 | AI2: 滚动ROI2 | AJ2: 滚动应到课人数 | AK2: 滚动到课人数 | AL2: 滚动到课人次 | AM2: 运营成本 | AN2: 销售固定成本 | AO2: 销售变动成本 | AP2: TMK费用 | AQ2: DEMO费用 | AR2: 例子数 | AS2: 分发数 | AT2: 剔除毛例子分发数 | AU2: 约课数 | AX2: 到课数 | AY2: 滚动到课数 | AZ2: 当月成交 | BA2: 滚动成交数 | BB2: 当月GMV | BC2: 滚动GMV | BD2: 海外GMV占比 | BE2: 滚动ASP | BF2: 例子分发率 | BG2: 分发约课率 | BH2: 例子约课率 | BI2: 约课到课率 | BK2: 滚动应到课率 | BL2: 到课转化率 | BM2: 注册转化率 | BN2: 滚动转化率 | BO2: 滚动应到课人数 | BP2: 滚动到课人数 | BQ2: 滚动到课人次 | BR2: 运营成本 | BS2: 销售固定成本 | BT2: 销售变动成本 | BU2: TMK费用 | BV2: DEMO费用 | BW2: 当月GMV | BX2: 滚动GMV | BY2: 海外GMV占比 | BZ2: 滚动其他成本 | CA2: 同源其他成本 | CB2: 运营成本 | CC2: 滚动消耗 | CD2: 同源消耗 | CE2: 当月ROI2总成本 | CF2: 当月ROI2 | CG2: 滚动赠课成本 | CH2: 滚动ROI2总成本 | CI2: 滚动ROI2 | CJ2: O-ROI总成本 | CK2: O-ROI
A3: 45992 | H3: 11978.663 | I3: =H3-CG3 | J3: 998.22192 | K3: 12 | L3: 10 | M3: 10 | N3: 7 | O3: 7 | P3: 7 | Q3: 7 | R3: 7 | S3: 3 | T3: 3 | U3: 10497 | V3: 10497 | W3: 1 | X3: 3499 | Y3: 0.83333333 | Z3: 0.7 | AA3: 0.58333333 | AB3: 1 | AC3: 1 | AD3: 1 | AE3: 0.42857143 | AF3: 0.25 | AG3: 0.25 | AH3: 16353.939 | AI3: 0.64186373 | AJ3: 7 | AK3: 7 | AL3: 7 | AM3: 895.39866 | AN3: 1472.2787 | AO3: 1298.4513 | AP3: 120 | AQ3: 589.14685 | AR3: 0 | AS3: 0 | AT3: 0 | AU3: 0 | AV3: 0 | AW3: 0 | AX3: 0 | AY3: 0 | AZ3: 0 | BA3: 0 | BB3: 0 | BC3: 0 | BO3: 0 | BP3: 0 | BQ3: 0 | BR3: 0 | BS3: 0 | BT3: 0 | BU3: 0 | BV3: 0 | BW3: 10497 | BX3: 10497 | BY3: 1 | BZ3: 3479.8768 | CA3: 3479.8768 | CB3: 895.39866 | CC3: 11978.663 | CD3: 11978.663 | CE3: 16353.939 | CF3: 0.64186373 | CG3: 585.41792 | CH3: 16353.939 | CI3: 0.64186373 | CJ3: 16358.54 | CK3: 0.64168319
A5: Kayan購物團直播-汇总 | H5: =SUM(H3:H4) | I5: =SUM(I3:I4) | J5: =I5/K5 | K5: =SUM(K3:K4) | L5: =SUM(L3:L4) | M5: =SUM(M3:M4) | N5: =SUM(N3:N4) | Q5: =SUM(Q3:Q4) | R5: =SUM(R3:R4) | S5: =SUM(S3:S4) | T5: =SUM(T3:T4) | U5: =SUM(U3:U4) | V5: =SUM(V3:V4) | X5: =V5/T5 | Y5: =L5/K5 | Z5: =N5/L5 | AA5: =N5/K5 | AB5: =Q5/N5 | AD5: =AVERAGE(AD3:AD4) | AE5: =S5/Q5 | AF5: =S5/K5 | AG5: =T5/K5 | AH5: =SUM(AH3:AH4) | AI5: =V5/AH5 | AJ5: =SUM(AJ3:AJ4) | AK5: =SUM(AK3:AK4) | AL5: =SUM(AL3:AL4) | AM5: =SUM(AM3:AM4) | AN5: =SUM(AN3:AN4) | AO5: =SUM(AO3:AO4) | AP5: =SUM(AP3:AP4) | AQ5: =SUM(AQ3:AQ4) | ... AS5: =SUM(AS3:AS4) | AU5: =SUM(AU3:AU4) | AX5: =SUM(AX3:AX4) | AY5: =SUM(AY3:AY4) | AZ5: =SUM(AZ3:AZ4) | BA5: =SUM(BA3:BA4) | BB5: =SUM(BB3:BB4) | BC5: =SUM(BC3:BC4) | BE5: =BC5/BA5 | BF5: =AS5/AR5 | BG5: =AU5/AS5 | BH5: =AU5/AR5 | BI5: =AX5/AU5 | BK5: =AVERAGE(BK3:BK4) | BL5: =AZ5/AX5 | BM5: =AZ5/AR5 | BN5: =BA5/AR5 | BO5: =SUM(BO3:BO4) | BP5: =SUM(BP3:BP4) | BQ5: =SUM(BQ3:BQ4) | BR5: =SUM(BR3:BR4) | BS5: =SUM(BS3:BS4) | BT5: =SUM(BT3:BT4) | BU5: =SUM(BU3:BU4) | BV5: =SUM(BV3:BV4) | ... BX5: =SUM(BX3:BX4) | BZ5: =SUM(BZ3:BZ4) | CA5: =SUM(CA3:CA4) | CB5: =SUM(CB3:CB4) | CC5: =SUM(CC3:CC4) | CD5: =SUM(CD3:CD4) | CE5: =SUM(CE3:CE4) | CF5: =BW5/CE5 | CG5: =SUM(CG3:CG4) | CH5: =SUM(CH3:CH4) | CI5: =BX5/CH5 | CJ5: =SUM(CJ3:CJ4) | CK5: =BX5/CJ5

Sheet 鄧明儀直播
I1: 主投 | AR1: 辅投 | BW1: 汇总
B2: 渠道组 | C2: 供应商 | D2: 渠道名称 | E2: 主投 | F2: 辅投 | G2: 结算方式 | H2: 滚动消耗 | I2: 滚动消耗(不含赠课成本) | J2: 单例子成本 | K2: 例子数 | L2: 分发数 | M2: 剔除毛例子 分发数 | N2: 约课数 | Q2: 到课数 | R2: 滚动到课数 | S2: 当月成交数 | T2: 滚动成交数 | U2: 当月GMV | V2: 滚动GMV | W2: 海外GMV占比 | X2: 滚动ASP | Y2: 例子分发率 | Z2: 分发约课率 | AA2: 例子约课率 | AB2: 约课到课率 | AD2: 滚动应到课率 | AE2: 到课转化率 | AF2: 注册转化率 | AG2: 滚动转化率 | AH2: 滚动ROI2总成本 | AI2: 滚动ROI2 | AJ2: 滚动应到课人数 | AK2: 滚动到课人数 | AL2: 滚动到课人次 | AM2: 运营成本 | AN2: 销售固定成本 | AO2: 销售变动成本 | AP2: TMK费用 | AQ2: DEMO费用 | AR2: 例子数 | AS2: 分发数 | AT2: 剔除毛例子分发数 | AU2: 约课数 | AX2: 到课数 | AY2: 滚动到课数 | AZ2: 当月成交 | BA2: 滚动成交数 | BB2: 当月GMV | BC2: 滚动GMV | BD2: 海外GMV占比 | BE2: 滚动ASP | BF2: 例子分发率 | BG2: 分发约课率 | BH2: 例子约课率 | BI2: 约课到课率 | BK2: 滚动应到课率 | BL2: 到课转化率 | BM2: 注册转化率 | BN2: 滚动转化率 | BO2: 滚动应到课人数 | BP2: 滚动到课人数 | BQ2: 滚动到课人次 | BR2: 运营成本 | BS2: 销售固定成本 | BT2: 销售变动成本 | BU2: TMK费用 | BV2: DEMO费用 | BW2: 当月GMV | BX2: 滚动GMV | BY2: 海外GMV占比 | BZ2: 滚动其他成本 | CA2: 同源其他成本 | CB2: 运营成本 | CC2: 滚动消耗 | CD2: 同源消耗 | CE2: 当月ROI2总成本 | CF2: 当月ROI2 | CG2: 滚动赠课成本 | CH2: 滚动ROI2总成本 | CI2: 滚动ROI2 | CJ2: O-ROI总成本 | CK2: O-ROI
A4: 46023 | H4: 19962.898 | I4: =H4-CG4 | J4: 2495.3622 | K4: 8 | L4: 5 | M4: 5 | N4: 6 | O4: 5 | P4: 3 | Q4: 3 | R4: 3 | S4: 2 | T4: 2 | U4: 10476 | V4: 10476 | W4: 1 | X4: 5238 | Y4: 0.625 | Z4: 1.2 | AA4: 0.75 | AB4: 0.5 | AC4: 0.6 | AD4: 1 | AE4: 0.66666667 | AF4: 0.25 | AG4: 0.25 | AH4: 23500.273 | AI4: 0.44578205 | AJ4: 3 | AK4: 3 | AL4: 3 | AM4: 870.13767 | AN4: 968.0367 | AO4: 1373.3188 | AP4: 80 | AQ4: 245.88243 | AR4: 0 | AS4: 0 | AT4: 0 | AU4: 0 | AV4: 0 | AW4: 0 | AX4: 0 | AY4: 0 | AZ4: 0 | BA4: 0 | BB4: 0 | BC4: 0 | BO4: 0 | BP4: 0 | BQ4: 0 | BR4: 0 | BS4: 0 | BT4: 0 | BU4: 0 | BV4: 0 | BW4: 10476 | BX4: 10476 | BY4: 1 | BZ4: 2667.2379 | CA4: 2667.2379 | CB4: 870.13767 | CC4: 19962.898 | CD4: 19962.898 | CE4: 23500.273 | CF4: 0.44578205 | CG4: 0 | CH4: 23500.273 | CI4: 0.44578205 | CJ4: 23230.135 | CK4: 0.45096594
A5: 46054 | H5: 10737.964 | I5: =H5-CG5 | J5: 5368.982 | K5: 2 | L5: 0 | M5: 0 | N5: 0 | O5: 0 | P5: 2 | Q5: 0 | R5: 2 | S5: 0 | T5: 2 | U5: 0 | V5: 9776 | W5: 1 | X5: 4888 | Y5: 0 | AA5: 0 | AD5: 1 | AF5: 0 | AG5: 1 | AH5: 12467.043 | AI5: 0.78414748 | AJ5: 2 | AK5: 2 | AL5: 2 | AM5: 263.60234 | AN5: 0 | AO5: 1281.5545 | AP5: 20 | AQ5: 163.92162 | AR5: 0 | AS5: 0 | AT5: 0 | AU5: 0 | AV5: 0 | AW5: 0 | AX5: 0 | AY5: 0 | AZ5: 0 | BA5: 0 | BB5: 0 | BC5: 0 | BO5: 0 | BP5: 0 | BQ5: 0 | BR5: 0 | BS5: 0 | BT5: 0 | BU5: 0 | BV5: 0 | BW5: 0 | BX5: 9776 | BY5: 1 | BZ5: 1465.4761 | CA5: 20 | CB5: 263.60234 | CC5: 10737.964 | CD5: 10737.964 | CE5: 11021.566 | CF5: 0 | CG5: 0 | CH5: 12467.043 | CI5: 0.78414748 | CJ5: 12353.44 | CK5: 0.79135851
A6: 專家鄧明儀-汇总 | H6: =SUM(H3:H5) | I6: =SUM(I3:I5) | J6: =I6/K6 | K6: =SUM(K3:K5) | L6: =SUM(L3:L5) | M6: =SUM(M3:M5) | N6: =SUM(N3:N5) | Q6: =SUM(Q3:Q5) | R6: =SUM(R3:R5) | S6: =SUM(S3:S5) | T6: =SUM(T3:T5) | U6: =SUM(U3:U5) | V6: =SUM(V3:V5) | X6: =V6/T6 | Y6: =L6/K6 | Z6: =N6/L6 | AA6: =N6/K6 | AB6: =Q6/N6 | AD6: =AVERAGE(AD3:AD5) | AE6: =S6/Q6 | AF6: =S6/K6 | AG6: =T6/K6 | AH6: =SUM(AH3:AH5) | AI6: =V6/AH6 | AJ6: =SUM(AJ3:AJ5) | AK6: =SUM(AK3:AK5) | AL6: =SUM(AL3:AL5) | AM6: =SUM(AM3:AM5) | AN6: =SUM(AN3:AN5) | AO6: =SUM(AO3:AO5) | AP6: =SUM(AP3:AP5) | AQ6: =SUM(AQ3:AQ5) | ... AS6: =SUM(AS3:AS5) | AU6: =SUM(AU3:AU5) | AX6: =SUM(AX3:AX5) | AY6: =SUM(AY3:AY5) | AZ6: =SUM(AZ3:AZ5) | BA6: =SUM(BA3:BA5) | BB6: =SUM(BB3:BB5) | BC6: =SUM(BC3:BC5) | BE6: =BC6/BA6 | BF6: =AS6/AR6 | BG6: =AU6/AS6 | BH6: =AU6/AR6 | BI6: =AX6/AU6 | BK6: =AVERAGE(BK3:BK5) | BL6: =AZ6/AX6 | BM6: =AZ6/AR6 | BN6: =BA6/AR6 | BO6: =SUM(BO3:BO5) | BP6: =SUM(BP3:BP5) | BQ6: =SUM(BQ3:BQ5) | BR6: =SUM(BR3:BR5) | BS6: =SUM(BS3:BS5) | BT6: =SUM(BT3:BT5) | BU6: =SUM(BU3:BU5) | BV6: =SUM(BV3:BV5) | ... BX6: =SUM(BX3:BX5) | BZ6: =SUM(BZ3:BZ5) | CA6: =SUM(CA3:CA5) | CB6: =SUM(CB3:CB5) | CC6: =SUM(CC3:CC5) | CD6: =SUM(CD3:CD5) | CE6: =SUM(CE3:CE5) | CF6: =BW6/CE6 | CG6: =SUM(CG3:CG5) | CH6: =SUM(CH3:CH5) | CI6: =BX6/CH6 | CJ6: =SUM(CJ3:CJ5) | CK6: =BX6/CJ6

Sheet 周家蔚
I1: 主投 | AR1: 辅投 | BW1: 汇总
B2: 渠道组 | C2: 供应商 | D2: 渠道名称 | E2: 主投 | F2: 辅投 | G2: 结算方式 | H2: 滚动消耗 | I2: 滚动消耗(不含赠课成本) | J2: 单例子成本 | K2: 例子数 | L2: 分发数 | M2: 剔除毛例子 分发数 | N2: 约课数 | Q2: 到课数 | R2: 滚动到课数 | S2: 当月成交数 | T2: 滚动成交数 | U2: 当月GMV | V2: 滚动GMV | W2: 海外GMV占比 | X2: 滚动ASP | Y2: 例子分发率 | Z2: 分发约课率 | AA2: 例子约课率 | AB2: 约课到课率 | AD2: 滚动应到课率 | AE2: 到课转化率 | AF2: 注册转化率 | AG2: 滚动转化率 | AH2: 滚动ROI2总成本 | AI2: 滚动ROI2 | AJ2: 滚动应到课人数 | AK2: 滚动到课人数 | AL2: 滚动到课人次 | AM2: 运营成本 | AN2: 销售固定成本 | AO2: 销售变动成本 | AP2: TMK费用 | AQ2: DEMO费用 | AR2: 例子数 | AS2: 分发数 | AT2: 剔除毛例子分发数 | AU2: 约课数 | AX2: 到课数 | AY2: 滚动到课数 | AZ2: 当月成交 | BA2: 滚动成交数 | BB2: 当月GMV | BC2: 滚动GMV | BD2: 海外GMV占比 | BE2: 滚动ASP | BF2: 例子分发率 | BG2: 分发约课率 | BH2: 例子约课率 | BI2: 约课到课率 | BK2: 滚动应到课率 | BL2: 到课转化率 | BM2: 注册转化率 | BN2: 滚动转化率 | BO2: 滚动应到课人数 | BP2: 滚动到课人数 | BQ2: 滚动到课人次 | BR2: 运营成本 | BS2: 销售固定成本 | BT2: 销售变动成本 | BU2: TMK费用 | BV2: DEMO费用 | BW2: 当月GMV | BX2: 滚动GMV | BY2: 海外GMV占比 | BZ2: 滚动其他成本 | CA2: 同源其他成本 | CB2: 运营成本 | CC2: 滚动消耗 | CD2: 同源消耗 | CE2: 当月ROI2总成本 | CF2: 当月ROI2 | CG2: 滚动赠课成本 | CH2: 滚动ROI2总成本 | CI2: 滚动ROI2 | CJ2: O-ROI总成本 | CK2: O-ROI
A4: 46082 | H4: 64163.976 | I4: =H4-CG4 | J4: 1336.7495 | K4: 48 | L4: 25 | M4: 25 | N4: 24 | O4: 22 | P4: 21 | Q4: 21 | R4: 21 | S4: 4 | T4: 4 | U4: 17944 | V4: 17944 | W4: 1 | X4: 4486 | Y4: 0.52083333 | Z4: 0.96 | AA4: 0.5 | AB4: 0.875 | AC4: 0.95454545 | AD4: 1 | AE4: 0.19047619 | AF4: 0.083333333 | AG4: 0.083333333 | AH4: 76299.715 | AI4: 0.23517781 | AJ4: 21 | AK4: 21 | AL4: 22 | AM4: 4230.491 | AN4: 3456.7764 | AO4: 2129.4088 | AP4: 480 | AQ4: 1839.0625 | AR4: 0 | AS4: 0 | AT4: 0 | AU4: 0 | AV4: 0 | AW4: 0 | AX4: 0 | AY4: 0 | AZ4: 0 | BA4: 0 | BB4: 0 | BC4: 0 | BO4: 0 | BP4: 0 | BQ4: 0 | BR4: 0 | BS4: 0 | BT4: 0 | BU4: 0 | BV4: 0 | BW4: 17944 | BX4: 17944 | BY4: 1 | BZ4: 7905.2476 | CA4: 7905.2476 | CB4: 4230.491 | CC4: 64163.976 | CD4: 64163.976 | CE4: 76299.715 | CF4: 0.23517781 | CG4: 804.85749 | CH4: 76299.715 | CI4: 0.23517781 | CJ4: 75669.224 | CK4: 0.23713736
A5: 46113 | H5: 39769.994 | I5: =H5-CG5 | J5: 4418.8883 | K5: 9 | L5: 6 | M5: 6 | N5: 7 | O5: 7 | P5: 6 | Q5: 5 | R5: 6 | S5: 2 | T5: 3 | U5: 11776 | V5: 16164 | W5: 1 | X5: 5388 | Y5: 0.66666667 | Z5: 1.1666667 | AA5: 0.77777778 | AB5: 0.71428571 | AC5: 0.71428571 | AD5: 1 | AE5: 0.4 | AF5: 0.22222222 | AG5: 0.33333333 | AH5: 43712.423 | AI5: 0.36978046 | AJ5: 6 | AK5: 6 | AL5: 6 | AM5: 933.67165 | AN5: 764.36233 | AO5: 1644.3117 | AP5: 90 | AQ5: 510.08323 | AR5: 0 | AS5: 0 | AT5: 0 | AU5: 0 | AV5: 0 | AW5: 0 | AX5: 0 | AY5: 0 | AZ5: 0 | BA5: 0 | BB5: 0 | BC5: 0 | BO5: 0 | BP5: 0 | BQ5: 0 | BR5: 0 | BS5: 0 | BT5: 0 | BU5: 0 | BV5: 0 | BW5: 11776 | BX5: 16164 | BY5: 1 | BZ5: 3008.7572 | CA5: 2477.3663 | CB5: 933.67165 | CC5: 39769.994 | CD5: 39769.994 | CE5: 43181.032 | CF5: 0.27271233 | CG5: 0 | CH5: 43712.423 | CI5: 0.36978046 | CJ5: 43453.752 | CK5: 0.37198169
A6: 46143 | H6: 8568 | I6: =H6-CG6 | K6: 0 | L6: 0 | M6: 0 | N6: 0 | O6: 0 | P6: 0 | Q6: 0 | R6: 0 | S6: 0 | T6: 0 | U6: 0 | V6: 0 | AH6: 0 | AJ6: 0 | AK6: 0 | AL6: 0 | AM6: 0 | AN6: 0 | AO6: 0 | AP6: 0 | AQ6: 0 | AR6: 0 | AS6: 0 | AT6: 0 | AU6: 0 | AV6: 0 | AW6: 0 | AX6: 0 | AY6: 0 | AZ6: 0 | BA6: 0 | BB6: 0 | BC6: 0 | BO6: 0 | BP6: 0 | BQ6: 0 | BR6: 0 | BS6: 0 | BT6: 0 | BU6: 0 | BV6: 0 | BW6: 0 | BX6: 0 | BZ6: 0 | CA6: 0 | CB6: 0 | CC6: 8568 | CD6: 8568 | CE6: 0 | CG6: 0 | CH6: 0 | CJ6: 0 | CK6: 0.37198169
A7: 周家蔚-汇总 | H7: =SUM(H3:H6) | I7: =SUM(I3:I6) | J7: =I7/K7 | K7: =SUM(K3:K6) | L7: =SUM(L3:L6) | M7: =SUM(M3:M6) | N7: =SUM(N3:N6) | Q7: =SUM(Q3:Q6) | R7: =SUM(R3:R6) | S7: =SUM(S3:S6) | T7: =SUM(T3:T6) | U7: =SUM(U3:U6) | V7: =SUM(V3:V6) | X7: =V7/T7 | Y7: =L7/K7 | Z7: =N7/L7 | AA7: =N7/K7 | AB7: =Q7/N7 | AD7: =AVERAGE(AD3:AD6) | AE7: =S7/Q7 | AF7: =S7/K7 | AG7: =T7/K7 | AH7: =SUM(AH3:AH6) | AI7: =V7/AH7 | AJ7: =SUM(AJ3:AJ6) | AK7: =SUM(AK3:AK6) | AL7: =SUM(AL3:AL6) | AM7: =SUM(AM3:AM6) | AN7: =SUM(AN3:AN6) | AO7: =SUM(AO3:AO6) | AP7: =SUM(AP3:AP6) | AQ7: =SUM(AQ3:AQ6) | ... AS7: =SUM(AS3:AS6) | AU7: =SUM(AU3:AU6) | AX7: =SUM(AX3:AX6) | AY7: =SUM(AY3:AY6) | AZ7: =SUM(AZ3:AZ6) | BA7: =SUM(BA3:BA6) | BB7: =SUM(BB3:BB6) | BC7: =SUM(BC3:BC6) | BE7: =BC7/BA7 | BF7: =AS7/AR7 | BG7: =AU7/AS7 | BH7: =AU7/AR7 | BI7: =AX7/AU7 | BK7: =AVERAGE(BK3:BK6) | BL7: =AZ7/AX7 | BM7: =AZ7/AR7 | BN7: =BA7/AR7 | BO7: =SUM(BO3:BO6) | BP7: =SUM(BP3:BP6) | BQ7: =SUM(BQ3:BQ6) | BR7: =SUM(BR3:BR6) | BS7: =SUM(BS3:BS6) | BT7: =SUM(BT3:BT6) | BU7: =SUM(BU3:BU6) | BV7: =SUM(BV3:BV6) | ... BX7: =SUM(BX3:BX6) | BZ7: =SUM(BZ3:BZ6) | CA7: =SUM(CA3:CA6) | CB7: =SUM(CB3:CB6) | CC7: =SUM(CC3:CC6) | CD7: =SUM(CD3:CD6) | CE7: =SUM(CE3:CE6) | CF7: =BW7/CE7 | CG7: =SUM(CG3:CG6) | CH7: =SUM(CH3:CH6) | CI7: =BX7/CH7 | CJ7: =SUM(CJ3:CJ6) | CK7: =BX7/CJ7

Sheet KOLhk+直播HK
I1: 主投 | AO1: 辅投 | BQ1: 汇总
B2: 渠道组 | C2: 供应商 | D2: 渠道名称 | E2: 主投 | F2: 辅投 | G2: 结算方式 | H2: 滚动消耗 | I2: 滚动消耗(不含赠课成本) | J2: 单例子成本 | K2: 例子数 | L2: 分发数 | M2: 剔除毛例子 分发数 | N2: 约课数 | O2: 到课数 | P2: 滚动到课数 | Q2: 当月成交数 | R2: 滚动成交数 | S2: 当月GMV | T2: 滚动GMV | U2: 海外GMV占比 | V2: 滚动ASP | W2: 例子分发率 | X2: 分发约课率 | Y2: 例子约课率 | Z2: 约课到课率 | AA2: 滚动应到课率 | AB2: 到课转化率 | AC2: 注册转化率 | AD2: 滚动转化率 | AE2: 滚动ROI2总成本 | AF2: 滚动ROI2 | AG2: 滚动应到课人数 | AH2: 滚动到课人数 | AI2: 滚动到课人次 | AJ2: 运营成本 | AK2: 销售固定成本 | AL2: 销售变动成本 | AM2: TMK费用 | AN2: DEMO费用 | AO2: 例子数 | AP2: 分发数 | AQ2: 剔除毛例子分发数 | AR2: 约课数 | AS2: 到课数 | AT2: 滚动到课数 | AU2: 当月成交 | AV2: 滚动成交数 | AW2: 当月GMV | AX2: 滚动GMV | AY2: 海外GMV占比 | AZ2: 滚动ASP | BA2: 例子分发率 | BB2: 分发约课率 | BC2: 例子约课率 | BD2: 约课到课率 | BE2: 滚动应到课率 | BF2: 到课转化率 | BG2: 注册转化率 | BH2: 滚动转化率 | BI2: 滚动应到课人数 | BJ2: 滚动到课人数 | BK2: 滚动到课人次 | BL2: 运营成本 | BM2: 销售固定成本 | BN2: 销售变动成本 | BO2: TMK费用 | BP2: DEMO费用 | BQ2: 当月GMV | BR2: 滚动GMV | BS2: 海外GMV占比 | BT2: 滚动其他成本 | BU2: 同源其他成本 | BV2: 运营成本 | BW2: 滚动消耗 | BX2: 同源消耗 | BY2: 当月ROI2总成本 | BZ2: 当月ROI2 | CA2: 滚动赠课成本 | CB2: 滚动ROI2总成本 | CC2: 滚动ROI2 | CD2: O-ROI总成本 | CE2: O-ROI
A3: KOLHK | H3: 341842.35 | I3: =H3-CA3 | J3: 841.97623 | K3: 406 | L3: 165 | M3: 182 | N3: 164 | O3: 108 | P3: 156 | Q3: 43 | R3: 66 | S3: 255893 | T3: 376559 | U3: 1 | V3: 5705.4394 | W3: 0.40640394 | X3: 0.99393939 | Y3: 0.40394089 | Z3: 0.65853659 | AA3: 0.975 | AB3: 0.39814815 | AC3: 0.10591133 | AD3: 0.16256158 | AE3: 449234.46 | AF3: 0.83822376 | AG3: 160 | AH3: 156 | AI3: 165 | AJ3: 26427.966 | AK3: 21495.65 | AL3: 41422.126 | AM3: 4060 | AN3: 13986.374 | AO3: 1 | AP3: 0 | AQ3: 0 | AR3: 0 | AS3: 0 | AT3: 0 | AU3: 0 | AV3: 0 | AW3: 0 | AX3: 0 | BA3: 0 | BC3: 0 | BG3: 0 | BH3: 0 | BI3: 0 | BJ3: 0 | BK3: 0 | BL3: 0 | BM3: 0 | BN3: 0 | BO3: 10 | BP3: 0 | BQ3: 255893 | BR3: 376559 | BS3: 1 | BT3: 80974.15 | BU3: 61285.024 | BV3: 26427.966 | BW3: 341842.35 | BX3: 337731.73 | BY3: 425444.72 | BZ3: 0.60147179 | CA3: 11795.675 | CB3: 449244.46 | CC3: 0.8382051 | CD3: 453341.5 | CE3: 0.83062989
A4: 直播HK | H4: 35883.213 | I4: =H4-CA4 | J4: 732.31046 | K4: 49 | L4: 27 | M4: 27 | N4: 25 | O4: 19 | P4: 19 | Q4: 7 | R4: 7 | S4: 34213 | T4: 34213 | U4: 1 | V4: 4887.5714 | W4: 0.55102041 | X4: 0.92592593 | Y4: 0.51020408 | Z4: 0.76 | AA4: 1 | AB4: 0.36842105 | AC4: 0.14285714 | AD4: 0.14285714 | AE4: 46383.425 | AF4: 0.73761263 | AG4: 19 | AH4: 19 | AI4: 19 | AJ4: 1447.2574 | AK4: 3188.915 | AL4: 3763.4878 | AM4: 490 | AN4: 1610.5522 | AO4: 0 | AP4: 0 | AQ4: 0 | AR4: 0 | AS4: 0 | AT4: 0 | AU4: 0 | AV4: 0 | AW4: 0 | AX4: 0 | BI4: 0 | BJ4: 0 | BK4: 0 | BL4: 0 | BM4: 0 | BN4: 0 | BO4: 0 | BP4: 0 | BQ4: 34213 | BR4: 34213 | BS4: 1 | BT4: 9052.955 | BU4: 9052.955 | BV4: 1447.2574 | BW4: 35883.213 | BX4: 35883.213 | BY4: 46383.425 | BZ4: 0.73761263 | CA4: 1251.0565 | CB4: 46383.425 | CC4: 0.73761263 | CD4: 48611.168 | CE4: 0.70380947
A5: 麥雅緻直播-汇总 | H5: =SUM(H3:H4) | I5: =SUM(I3:I4) | J5: =I5/K5 | K5: =SUM(K3:K4) | L5: =SUM(L3:L4) | M5: =SUM(M3:M4) | N5: =SUM(N3:N4) | O5: =SUM(O3:O4) | P5: =SUM(P3:P4) | Q5: =SUM(Q3:Q4) | R5: =SUM(R3:R4) | ... T5: =SUM(T3:T4) | V5: =T5/R5 | W5: =L5/K5 | X5: =N5/L5 | Y5: =N5/K5 | Z5: =O5/N5 | AA5: =AVERAGE(AA3:AA4) | AB5: =Q5/O5 | AC5: =Q5/K5 | AD5: =R5/K5 | AE5: =SUM(AE3:AE4) | AF5: =T5/AE5 | AG5: =SUM(AG3:AG4) | AH5: =SUM(AH3:AH4) | AI5: =SUM(AI3:AI4) | AJ5: =SUM(AJ3:AJ4) | AK5: =SUM(AK3:AK4) | AL5: =SUM(AL3:AL4) | AM5: =SUM(AM3:AM4) | AN5: =SUM(AN3:AN4) | ... AP5: =SUM(AP3:AP4) | AR5: =SUM(AR3:AR4) | AS5: =SUM(AS3:AS4) | AT5: =SUM(AT3:AT4) | AU5: =SUM(AU3:AU4) | AV5: =SUM(AV3:AV4) | AW5: =SUM(AW3:AW4) | AX5: =SUM(AX3:AX4) | AZ5: =AX5/AV5 | BA5: =AP5/AO5 | BB5: =AR5/AP5 | BC5: =AR5/AO5 | BD5: =AS5/AR5 | BE5: =AVERAGE(BE3:BE4) | BF5: =AU5/AS5 | BG5: =AU5/AO5 | BH5: =AV5/AO5 | BI5: =SUM(BI3:BI4) | BJ5: =SUM(BJ3:BJ4) | BK5: =SUM(BK3:BK4) | BL5: =SUM(BL3:BL4) | BM5: =SUM(BM3:BM4) | BN5: =SUM(BN3:BN4) | BO5: =SUM(BO3:BO4) | BP5: =SUM(BP3:BP4) | ... BR5: =SUM(BR3:BR4) | BT5: =SUM(BT3:BT4) | BU5: =SUM(BU3:BU4) | BV5: =SUM(BV3:BV4) | BW5: =SUM(BW3:BW4) | BX5: =SUM(BX3:BX4) | BY5: =SUM(BY3:BY4) | BZ5: =BQ5/BY5 | CA5: =SUM(CA3:CA4) | CB5: =SUM(CB3:CB4) | CC5: =BR5/CB5 | CD5: =SUM(CD3:CD4) | CE5: =BR5/CD5

Sheet 海外商务分月数据汇总
I1: 主投 | AO1: 辅投 | BQ1: 汇总
B2: 渠道组 | C2: 供应商 | D2: 渠道名称 | E2: 主投 | F2: 辅投 | G2: 结算方式 | I2: 滚动消耗 | J2: 单例子成本 | K2: 例子数 | L2: 分发数 | M2: 剔除毛例子 分发数 | N2: 约课数 | O2: 到课数 | P2: 滚动到课数 | Q2: 当月成交数 | R2: 滚动成交数 | S2: 当月GMV | T2: 滚动GMV | U2: 海外GMV占比 | V2: 滚动ASP | W2: 例子分发率 | X2: 分发约课率 | Y2: 例子约课率 | Z2: 约课到课率 | AA2: 滚动应到课率 | AB2: 到课转化率 | AC2: 注册转化率 | AD2: 滚动转化率 | AE2: 滚动ROI2总成本 | AF2: 滚动ROI2 | AG2: 滚动应到课人数 | AH2: 滚动到课人数 | AI2: 滚动到课人次 | AJ2: 运营成本 | AK2: 销售固定成本 | AL2: 销售变动成本 | AM2: TMK费用 | AN2: DEMO费用 | AO2: 例子数 | AP2: 分发数 | AQ2: 剔除毛例子分发数 | AR2: 约课数 | AS2: 到课数 | AT2: 滚动到课数 | AU2: 当月成交 | AV2: 滚动成交数 | AW2: 当月GMV | AX2: 滚动GMV | AY2: 海外GMV占比 | AZ2: 滚动ASP | BA2: 例子分发率 | BB2: 分发约课率 | BC2: 例子约课率 | BD2: 约课到课率 | BE2: 滚动应到课率 | BF2: 到课转化率 | BG2: 注册转化率 | BH2: 滚动转化率 | BI2: 滚动应到课人数 | BJ2: 滚动到课人数 | BK2: 滚动到课人次 | BL2: 运营成本 | BM2: 销售固定成本 | BN2: 销售变动成本 | BO2: TMK费用 | BP2: DEMO费用 | BQ2: 当月GMV | BR2: 滚动GMV | BS2: 海外GMV占比 | BT2: 滚动其他成本 | BU2: 同源其他成本 | BV2: 运营成本 | BW2: 滚动消耗 | BX2: 同源消耗 | BY2: 当月ROI2总成本 | BZ2: 当月ROI2 | CB2: 滚动ROI2总成本 | CC2: 滚动ROI2 | CD2: O-ROI总成本 | CE2: O-ROI
A3: 45658 | B3: 总计 | C3: 总计 | D3: 总计 | E3: - | F3: - | G3: - | I3: 47425.323 | J3: 222.6541 | K3: 213 | L3: 92 | M3: 99 | N3: 87 | O3: 67 | P3: 112 | Q3: 21 | R3: 36 | S3: 96795.2 | T3: 164708.4 | U3: 1 | V3: 4575.2333 | W3: 0.43192488 | X3: 0.94565217 | Y3: 0.4084507 | Z3: 0.77011494 | AA3: 0.94117647 | AB3: 0.31343284 | AC3: 0.098591549 | AD3: 0.16901408 | AE3: 111441.11 | AF3: 1.477986 | AG3: 119 | AH3: 112 | AI3: 124 | AJ3: 23881.798 | AK3: 14045.948 | AL3: 13655.955 | AM3: 2366.3324 | AN3: 10065.753 | AO3: 206 | AP3: 52 | AQ3: 81 | AR3: 50 | AS3: 32 | AT3: 41 | AU3: 2 | AV3: 5 | AW3: 6529.2 | AX3: 15657.6 | AY3: 1 | AZ3: 3131.52 | BA3: 0.25242718 | BB3: 0.96153846 | BC3: 0.24271845 | BD3: 0.64 | BE3: 0.63076923 | BF3: 0.0625 | BG3: 0.0097087379 | BH3: 0.024271845 | BI3: 65 | BJ3: 41 | BK3: 42 | BL3: 22369.793 | BM3: 8705.607 | BN3: 1463.1578 | BO3: 2288.5657 | BP3: 3425.1964 | BQ3: 103324.4 | BR3: 180366 | BS3: 1 | BT3: 56016.516 | BU3: 40726.847 | BV3: 46251.591 | BW3: 47425.323 | BX3: 47425.323 | BY3: 134403.76 | BZ3: 0.76876122 | CB3: 149693.43 | CC3: 1.2049026 | CD3: 134866.84 | CE3: 1.3373636
A4: 45690 | B4: 总计 | C4: 总计 | D4: 总计 | E4: - | F4: - | G4: - | I4: 89990.386 | J4: 192.28715 | K4: 468 | L4: 352 | M4: 362 | N4: 270 | O4: 178 | P4: 202 | Q4: 42 | R4: 49 | S4: 198757.6 | T4: 241634.8 | U4: 1 | V4: 4931.3224 | W4: 0.75213675 | X4: 0.76704545 | Y4: 0.57692308 | Z4: 0.65925926 | AA4: 0.94392523 | AB4: 0.23595506 | AC4: 0.08974359 | AD4: 0.10470085 | AE4: 207090.27 | AF4: 1.1668091 | AG4: 214 | AH4: 202 | AI4: 215 | AJ4: 26298.256 | AK4: 46825.782 | AL4: 22427.113 | AM4: 3232.9917 | AN4: 18315.739 | AO4: 446 | AP4: 138 | AQ4: 149 | AR4: 138 | AS4: 76 | AT4: 88 | AU4: 9 | AV4: 11 | AW4: 31959.6 | AX4: 40166.8 | AY4: 0.91174628 | AZ4: 3651.5273 | BA4: 0.30941704 | BB4: 1 | BC4: 0.30941704 | BD4: 0.55072464 | BE4: 0.63309353 | BF4: 0.11842105 | BG4: 0.020179372 | BH4: 0.024663677 | BI4: 139 | BJ4: 88 | BK4: 91 | BL4: 24173.379 | BM4: 13382.967 | BN4: 3869.2452 | BO4: 3259.1286 | BP4: 6721.5926 | BQ4: 230717.2 | BR4: 281801.6 | BS4: 0.98639082 | BT4: 118034.56 | BU4: 107891.53 | BV4: 50471.635 | BW4: 89990.386 | BX4: 89990.386 | BY4: 247128.86 | BZ4: 0.9289869 | CB4: 257271.88 | CC4: 1.0953455 | CD4: 275350.25 | CE4: 1.0234296
A5: 45718 | B5: 总计 | C5: 总计 | D5: 总计 | E5: - | F5: - | G5: - | I5: 340451.94 | J5: 413.16983 | K5: 824 | L5: 426 | M5: 431 | N5: 440 | O5: 343 | P5: 395 | Q5: 128 | R5: 142 | S5: 617660 | T5: 682519.2 | U5: 1 | V5: 4806.4732 | W5: 0.51699029 | X5: 1.0328638 | Y5: 0.53398058 | Z5: 0.77954545 | AA5: 0.94951923 | AB5: 0.37317784 | AC5: 0.15533981 | AD5: 0.1723301 | AE5: 559377.46 | AF5: 1.2201407 | AG5: 416 | AH5: 395 | AI5: 417 | AJ5: 71584.44 | AK5: 42608.353 | AL5: 65338.607 | AM5: 5545.2399 | AN5: 33848.876 | AO5: 64 | AP5: 38 | AQ5: 59 | AR5: 37 | AS5: 28 | AT5: 59 | AU5: 3 | AV5: 11 | AW5: 10964.4 | AX5: 31847.6 | AY5: 1 | AZ5: 2895.2364 | BA5: 0.59375 | BB5: 0.97368421 | BC5: 0.578125 | BD5: 0.75675676 | BE5: 0.74683544 | BF5: 0.10714286 | BG5: 0.046875 | BH5: 0.171875 | BI5: 79 | BJ5: 59 | BK5: 60 | BL5: 4688.9995 | BM5: 4956.4768 | BN5: 3130.1152 | BO5: 430.69825 | BP5: 4893.1377 | BQ5: 628624.4 | BR5: 714366.8 | BS5: 1 | BT5: 160928.07 | BU5: 143415.44 | BV5: 76436.938 | BW5: 340451.94 | BX5: 340451.94 | BY5: 560304.32 | BZ5: 1.1219339 | CB5: 577816.95 | CC5: 1.2363203 | CD5: 568130.01 | CE5: 1.2574002
A7: 海外港澳商务-汇总 | I7: =SUM(I3:I5) | J7: =I7/K7 | K7: =SUM(K3:K5) | L7: =SUM(L3:L5) | M7: =SUM(M3:M5) | N7: =SUM(N3:N5) | O7: =SUM(O3:O5) | P7: =SUM(P3:P5) | Q7: =SUM(Q3:Q5) | R7: =SUM(R3:R5) | ... T7: =SUM(T3:T5) | V7: =T7/R7 | W7: =L7/K7 | X7: =N7/L7 | Y7: =N7/K7 | Z7: =O7/N7 | AA7: =AVERAGE(AA3:AA5) | AB7: =Q7/O7 | AC7: =Q7/K7 | AD7: =R7/K7 | AE7: =SUM(AE3:AE5) | AF7: =T7/AE7 | AG7: =SUM(AG3:AG5) | AH7: =SUM(AH3:AH5) | AI7: =SUM(AI3:AI5) | AJ7: =SUM(AJ3:AJ5) | AK7: =SUM(AK3:AK5) | AL7: =SUM(AL3:AL5) | AM7: =SUM(AM3:AM5) | AO7: =SUM(AO3:AO5) | AP7: =SUM(AP3:AP5) | AR7: =SUM(AR3:AR5) | AS7: =SUM(AS3:AS5) | AT7: =SUM(AT3:AT5) | AU7: =SUM(AU3:AU5) | AV7: =SUM(AV3:AV5) | AW7: =SUM(AW3:AW5) | AX7: =SUM(AX3:AX5) | AZ7: =AX7/AV7 | BA7: =AP7/AO7 | BB7: =AR7/AP7 | BC7: =AR7/AO7 | BD7: =AS7/AR7 | BE7: =AVERAGE(BE3:BE5) | BF7: =AU7/AS7 | BG7: =AU7/AO7 | BH7: =AV7/AO7 | BI7: =SUM(BI3:BI5) | BJ7: =SUM(BJ3:BJ5) | BK7: =SUM(BK3:BK5) | BL7: =SUM(BL3:BL5) | BM7: =SUM(BM3:BM5) | BN7: =SUM(BN3:BN5) | BO7: =SUM(BO3:BO5) | BP7: =SUM(BP3:BP5) | ... BR7: =SUM(BR3:BR5) | BT7: =SUM(BT3:BT5) | BU7: =SUM(BU3:BU5) | BV7: =SUM(BV3:BV5) | BW7: =SUM(BW3:BW5) | BX7: =SUM(BX3:BX5) | BY7: =SUM(BY3:BY5) | BZ7: =BQ7/BY7 | CB7: =SUM(CB3:CB5) | CC7: =BR7/CB7 | CD7: =SUM(CD3:CD5) | CE7: =BR7/CD7
I12: 主投 | AO12: 辅投 | BQ12: 汇总
B13: 渠道组 | C13: 供应商 | D13: 渠道名称 | E13: 主投 | F13: 辅投 | G13: 结算方式 | I13: 滚动消耗 | J13: 单例子成本 | K13: 例子数 | L13: 分发数 | M13: 剔除毛例子 分发数 | N13: 约课数 | O13: 到课数 | P13: 滚动到课数 | Q13: 当月成交数 | R13: 滚动成交数 | S13: 当月GMV | T13: 滚动GMV | U13: 海外GMV占比 | V13: 滚动ASP | W13: 例子分发率 | X13: 分发约课率 | Y13: 例子约课率 | Z13: 约课到课率 | AA13: 滚动应到课率 | AB13: 到课转化率 | AC13: 注册转化率 | AD13: 滚动转化率 | AE13: 滚动ROI2总成本 | AF13: 滚动ROI2 | AG13: 滚动应到课人数 | AH13: 滚动到课人数 | AI13: 滚动到课人次 | AJ13: 运营成本 | AK13: 销售固定成本 | AL13: 销售变动成本 | AM13: TMK费用 | AN13: DEMO费用 | AO13: 例子数 | AP13: 分发数 | AQ13: 剔除毛例子分发数 | AR13: 约课数 | AS13: 到课数 | AT13: 滚动到课数 | AU13: 当月成交 | AV13: 滚动成交数 | AW13: 当月GMV | AX13: 滚动GMV | AY13: 海外GMV占比 | AZ13: 滚动ASP | BA13: 例子分发率 | BB13: 分发约课率 | BC13: 例子约课率 | BD13: 约课到课率 | BE13: 滚动应到课率 | BF13: 到课转化率 | BG13: 注册转化率 | BH13: 滚动转化率 | BI13: 滚动应到课人数 | BJ13: 滚动到课人数 | BK13: 滚动到课人次 | BL13: 运营成本 | BM13: 销售固定成本 | BN13: 销售变动成本 | BO13: TMK费用 | BP13: DEMO费用 | BQ13: 当月GMV | BR13: 滚动GMV | BS13: 海外GMV占比 | BT13: 滚动其他成本 | BU13: 同源其他成本 | BV13: 运营成本 | BW13: 滚动消耗 | BX13: 同源消耗 | BY13: 当月ROI2总成本 | BZ13: 当月ROI2 | CB13: 滚动ROI2总成本 | CC13: 滚动ROI2 | CD13: O-ROI总成本 | CE13: O-ROI
A16: 孙慧雪-4月 | I16: 80325.479 | J16: 892.50532 | K16: 90 | L16: 48 | M16: 50 | N16: 48 | O16: 35 | P16: 45 | Q16: 14 | R16: 20 | S16: 58432 | T16: 80360 | U16: 1 | V16: 4018 | W16: 0.53333333 | X16: 1 | Y16: 0.53333333 | Z16: 0.72916667 | AA16: 0.91836735 | AB16: 0.4 | AC16: 0.15555556 | AD16: 0.22222222 | AE16: 109746.72 | AF16: 0.73223143 | AG16: 49 | AH16: 45 | AI16: 47 | AJ16: 9968.2761 | AK16: 7405.9586 | AL16: 7204.5969 | AM16: 889.52324 | AN16: 3952.8892 | AO16: 0 | AP16: 0 | AQ16: 0 | AR16: 0 | AS16: 0 | AT16: 0 | AU16: 0 | AV16: 0 | AW16: 0 | AX16: 0 | BI16: 0 | BJ16: 0 | BK16: 0 | BL16: 0 | BM16: 0 | BN16: 0 | BO16: 0 | BP16: 0 | BQ16: 58432 | BR16: 80360 | BS16: 1 | BT16: 19555.481 | BU16: 16349.756 | BV16: 9968.2761 | BW16: 80325.479 | BX16: 80325.479 | BY16: 106643.51 | BZ16: 0.54791894 | CB16: 109849.24 | CC16: 0.7315481 | CD16: 106630.96 | CE16: 0.75362728
A17: 陈倩扬-4月 | I17: 48781.331 | J17: 1084.0296 | K17: 45 | L17: 28 | M17: 31 | N17: 29 | O17: 21 | P17: 28 | Q17: 5 | R17: 11 | S17: 23940 | T17: 45568 | U17: 1 | V17: 4142.5455 | W17: 0.62222222 | X17: 1.0357143 | Y17: 0.64444444 | Z17: 0.72413793 | AA17: 0.93333333 | AB17: 0.23809524 | AC17: 0.11111111 | AD17: 0.24444444 | AE17: 65326.296 | AF17: 0.69754453 | AG17: 30 | AH17: 28 | AI17: 29 | AJ17: 4984.1381 | AK17: 4591.6944 | AL17: 4085.3543 | AM17: 444.76162 | AN17: 2439.0168 | AO17: 0 | AP17: 0 | AQ17: 0 | AR17: 0 | AS17: 0 | AT17: 0 | AU17: 0 | AV17: 0 | AW17: 0 | AX17: 0 | BI17: 0 | BJ17: 0 | BK17: 0 | BL17: 0 | BM17: 0 | BN17: 0 | BO17: 0 | BP17: 0 | BQ17: 23940 | BR17: 45568 | BS17: 1 | BT17: 12047.293 | BU17: 8888.5526 | BV17: 5193.4319 | BW17: 48781.331 | BX17: 48781.331 | BY17: 62863.315 | BZ17: 0.38082624 | CB17: 66022.055 | CC17: 0.6901936 | CD17: 64353.623 | CE17: 0.70808756
A18: bob-4月 | I18: 46341.657 | J18: 311.01783 | K18: 149 | L18: 82 | M18: 82 | N18: 79 | O18: 57 | P18: 57 | Q18: 22 | R18: 22 | S18: 96736 | T18: 96736 | U18: 1 | V18: 4397.0909 | W18: 0.55033557 | X18: 0.96341463 | Y18: 0.53020134 | Z18: 0.72151899 | AA18: 0.96610169 | AB18: 0.38596491 | AC18: 0.14765101 | AD18: 0.14765101 | AE18: 90013.923 | AF18: 1.0746782 | AG18: 59 | AH18: 57 | AI18: 58 | AJ18: 16503.035 | AK18: 12145.772 | AL18: 8672.7711 | AM18: 1472.6551 | AN18: 4878.0335 | AO18: 0 | AP18: 0 | AQ18: 0 | AR18: 0 | AS18: 0 | AT18: 0 | AU18: 0 | AV18: 0 | AW18: 0 | AX18: 0 | BI18: 0 | BJ18: 0 | BK18: 0 | BL18: 0 | BM18: 0 | BN18: 0 | BO18: 0 | BP18: 0 | BQ18: 96736 | BR18: 96736 | BS18: 1 | BT18: 27169.232 | BU18: 27169.232 | BV18: 16503.035 | BW18: 46341.657 | BX18: 46341.657 | BY18: 90013.923 | BZ18: 1.0746782 | CB18: 90013.923 | CC18: 1.0746782 | CD18: 84685.889 | CE18: 1.1422918
A19: 叶翠翠-4月 | I19: 15480.518 | J19: 418.39239 | K19: 37 | L19: 15 | M19: 15 | N19: 15 | O19: 9 | P19: 9 | Q19: 4 | R19: 4 | S19: 16752 | T19: 16752 | U19: 1 | V19: 4188 | W19: 0.40540541 | X19: 1 | Y19: 0.40540541 | Z19: 0.6 | AA19: 1 | AB19: 0.44444444 | AC19: 0.10810811 | AD19: 0.10810811 | AE19: 24424.888 | AF19: 0.6858578 | AG19: 9 | AH19: 9 | AI19: 9 | AJ19: 4098.0691 | AK19: 2221.7876 | AL19: 1501.8841 | AM19: 365.69289 | AN19: 756.93623 | AO19: 0 | AP19: 0 | AQ19: 0 | AR19: 0 | AS19: 0 | AT19: 0 | AU19: 0 | AV19: 0 | AW19: 0 | AX19: 0 | BI19: 0 | BJ19: 0 | BK19: 0 | BL19: 0 | BM19: 0 | BN19: 0 | BO19: 0 | BP19: 0 | BQ19: 16752 | BR19: 16752 | BS19: 1 | BT19: 4846.3008 | BU19: 4846.3008 | BV19: 4098.0691 | BW19: 15480.518 | BX19: 15480.518 | BY19: 24424.888 | BZ19: 0.6858578 | CB19: 24424.888 | CC19: 0.6858578 | CD19: 23101.819 | CE19: 0.7251377
A20: 陈琪-4月 | I20: 131731.98 | J20: 539.88517 | K20: 244 | L20: 122 | M20: 128 | N20: 127 | O20: 100 | P20: 124 | Q20: 41 | R20: 48 | S20: 180708 | T20: 211424 | U20: 1 | V20: 4404.6667 | W20: 0.5 | X20: 1.0409836 | Y20: 0.5204918 | Z20: 0.78740157 | AA20: 0.98412698 | AB20: 0.41 | AC20: 0.16803279 | AD20: 0.19672131 | AE20: 210352.89 | AF20: 1.005092 | AG20: 126 | AH20: 124 | AI20: 134 | AJ20: 27025.104 | AK20: 18959.254 | AL20: 18955.011 | AM20: 2411.5963 | AN20: 11269.939 | AO20: 20 | AP20: 18 | AQ20: 20 | AR20: 18 | AS20: 11 | AT20: 13 | AU20: 0 | AV20: 0 | AW20: 0 | AX20: 0 | BA20: 0.9 | BB20: 1 | BC20: 0.9 | BD20: 0.61111111 | BE20: 0.65 | BF20: 0 | BG20: 0 | BH20: 0 | BI20: 20 | BJ20: 13 | BK20: 14 | BL20: 2092.9385 | BM20: 2050.2685 | BN20: 0 | BO20: 197.67183 | BP20: 1114.1083 | BQ20: 180708 | BR20: 211424 | BS20: 1 | BT20: 54957.85 | BU20: 48848.536 | BV20: 29118.043 | BW20: 131731.98 | BX20: 131731.98 | BY20: 209698.56 | BZ20: 0.86175127 | CB20: 215807.87 | CC20: 0.97968622 | CD20: 206489.83 | CE20: 1.0238955
A22: 4月-汇总 | I22: =SUM(I14:I20) | J22: =I22/K22 | K22: =SUM(K14:K20) | L22: =SUM(L14:L20) | M22: =SUM(M14:M20) | N22: =SUM(N14:N20) | O22: =SUM(O14:O20) | P22: =SUM(P14:P20) | Q22: =SUM(Q14:Q20) | R22: =SUM(R14:R20) | ... T22: =SUM(T14:T20) | V22: =T22/R22 | W22: =L22/K22 | X22: =N22/L22 | Y22: =N22/K22 | Z22: =O22/N22 | AA22: =AVERAGE(AA14:AA20) | AB22: =Q22/O22 | AC22: =Q22/K22 | AD22: =R22/K22 | AE22: =SUM(AE14:AE20) | AF22: =T22/AE22 | AG22: =SUM(AG14:AG20) | AH22: =SUM(AH14:AH20) | AI22: =SUM(AI14:AI20) | AJ22: =SUM(AJ14:AJ20) | AK22: =SUM(AK14:AK20) | AL22: =SUM(AL14:AL20) | AM22: =SUM(AM14:AM20) | AN22: =SUM(AN14:AN20) | ... AP22: =SUM(AP14:AP20) | AR22: =SUM(AR14:AR20) | AS22: =SUM(AS14:AS20) | AT22: =SUM(AT14:AT20) | AU22: =SUM(AU14:AU20) | AV22: =SUM(AV14:AV20) | AW22: =SUM(AW14:AW20) | AX22: =SUM(AX14:AX20) | AZ22: =AX22/AV22 | BA22: =AP22/AO22 | BB22: =AR22/AP22 | BC22: =AR22/AO22 | BD22: =AS22/AR22 | BE22: =AVERAGE(BE14:BE20) | BF22: =AU22/AS22 | BG22: =AU22/AO22 | BH22: =AV22/AO22 | BI22: =SUM(BI14:BI20) | BJ22: =SUM(BJ14:BJ20) | BK22: =SUM(BK14:BK20) | BL22: =SUM(BL14:BL20) | BM22: =SUM(BM14:BM20) | BN22: =SUM(BN14:BN20) | BO22: =SUM(BO14:BO20) | BP22: =SUM(BP14:BP20) | ... BR22: =SUM(BR14:BR20) | BT22: =SUM(BT14:BT20) | BU22: =SUM(BU14:BU20) | BV22: =SUM(BV14:BV20) | BW22: =SUM(BW14:BW20) | BX22: =SUM(BX14:BX20) | BY22: =SUM(BY14:BY20) | BZ22: =BQ22/BY22 | CB22: =SUM(CB14:CB20) | CC22: =BR22/CB22 | CD22: =SUM(CD14:CD20) | CE22: =BR22/CD22
I25: 主投 | AO25: 辅投 | BQ25: 汇总
B26: 渠道组 | C26: 供应商 | D26: 渠道名称 | E26: 主投 | F26: 辅投 | G26: 结算方式 | I26: 滚动消耗 | J26: 单例子成本 | K26: 例子数 | L26: 分发数 | M26: 剔除毛例子 分发数 | N26: 约课数 | O26: 到课数 | P26: 滚动到课数 | Q26: 当月成交数 | R26: 滚动成交数 | S26: 当月GMV | T26: 滚动GMV | U26: 海外GMV占比 | V26: 滚动ASP | W26: 例子分发率 | X26: 分发约课率 | Y26: 例子约课率 | Z26: 约课到课率 | AA26: 滚动应到课率 | AB26: 到课转化率 | AC26: 注册转化率 | AD26: 滚动转化率 | AE26: 滚动ROI2总成本 | AF26: 滚动ROI2 | AG26: 滚动应到课人数 | AH26: 滚动到课人数 | AI26: 滚动到课人次 | AJ26: 运营成本 | AK26: 销售固定成本 | AL26: 销售变动成本 | AM26: TMK费用 | AN26: DEMO费用 | AO26: 例子数 | AP26: 分发数 | AQ26: 剔除毛例子分发数 | AR26: 约课数 | AS26: 到课数 | AT26: 滚动到课数 | AU26: 当月成交 | AV26: 滚动成交数 | AW26: 当月GMV | AX26: 滚动GMV | AY26: 海外GMV占比 | AZ26: 滚动ASP | BA26: 例子分发率 | BB26: 分发约课率 | BC26: 例子约课率 | BD26: 约课到课率 | BE26: 滚动应到课率 | BF26: 到课转化率 | BG26: 注册转化率 | BH26: 滚动转化率 | BI26: 滚动应到课人数 | BJ26: 滚动到课人数 | BK26: 滚动到课人次 | BL26: 运营成本 | BM26: 销售固定成本 | BN26: 销售变动成本 | BO26: TMK费用 | BP26: DEMO费用 | BQ26: 当月GMV | BR26: 滚动GMV | BS26: 海外GMV占比 | BT26: 滚动其他成本 | BU26: 同源其他成本 | BV26: 运营成本 | BW26: 滚动消耗 | BX26: 同源消耗 | BY26: 当月ROI2总成本 | BZ26: 当月ROI2 | CB26: 滚动ROI2总成本 | CC26: 滚动ROI2 | CD26: O-ROI总成本 | CE26: O-ROI
I28: 110488 | J28: 584.59259 | K28: 189 | L28: 84 | M28: 88 | N28: 80 | O28: 52 | P28: 67 | Q28: 20 | R28: 29 | S28: 87960 | T28: 131352 | U28: 1 | V28: 4529.3793 | W28: 0.44444444 | X28: 0.95238095 | Y28: 0.42328042 | Z28: 0.65 | AA28: 0.95714286 | AB28: 0.38461538 | AC28: 0.10582011 | AD28: 0.15343915 | AE28: 152693.58 | AF28: 0.86023264 | AG28: 70 | AH28: 67 | AI28: 74 | AJ28: 11718.306 | AK28: 10340.142 | AL28: 11776.235 | AM28: 2147.1976 | AN28: 6223.6979 | AO28: 3 | AP28: 3 | AQ28: 4 | AR28: 3 | AS28: 1 | AT28: 3 | AU28: 0 | AV28: 0 | AW28: 0 | AX28: 0 | BA28: 1 | BB28: 1 | BC28: 1 | BD28: 0.33333333 | BE28: 0.6 | BF28: 0 | BG28: 0 | BH28: 0 | BI28: 5 | BJ28: 3 | BK28: 3 | BL28: 167.12506 | BM28: 500.82178 | BN28: 0 | BO28: 34.082502 | BP28: 238.7375 | BQ28: 87960 | BR28: 131352 | BS28: 1 | BT28: 31260.914 | BU28: 25354.717 | BV28: 11885.431 | BW28: 110488 | BX28: 110488 | BY28: 147728.15 | BZ28: 0.59541801 | CB28: 153634.35 | CC28: 0.85496508 | CD28: 156148.91 | CE28: 0.84119701
I29: 83971.502 | J29: 368.29606 | K29: 228 | L29: 97 | M29: 97 | N29: 98 | O29: 61 | P29: 61 | Q29: 21 | R29: 21 | S29: 116448 | T29: 116448 | U29: 1 | V29: 5545.1429 | W29: 0.4254386 | X29: 1.0103093 | Y29: 0.42982456 | Z29: 0.62244898 | AA29: 0.92424242 | AB29: 0.3442623 | AC29: 0.092105263 | AD29: 0.092105263 | AE29: 128170.8 | AF29: 0.90853767 | AG29: 66 | AH29: 61 | AI29: 67 | AJ29: 14136.369 | AK29: 11397.657 | AL29: 10440.031 | AM29: 2590.2701 | AN29: 5634.9697 | AO29: 0 | AP29: 0 | AQ29: 0 | AR29: 0 | AS29: 0 | AT29: 0 | AU29: 0 | AV29: 0 | AW29: 0 | AX29: 0 | BI29: 0 | BJ29: 0 | BK29: 0 | BL29: 0 | BM29: 0 | BN29: 0 | BO29: 0 | BP29: 0 | BQ29: 116448 | BR29: 116448 | BS29: 1 | BT29: 30062.928 | BU29: 30062.928 | BV29: 14136.369 | BW29: 83971.502 | BX29: 83971.502 | BY29: 128170.8 | BZ29: 0.90853767 | CB29: 128170.8 | CC29: 0.90853767 | CD29: 131134.43 | CE29: 0.88800477
I30: 54585.868 | J30: 791.09953 | K30: 69 | L30: 36 | M30: 37 | N30: 35 | O30: 23 | P30: 30 | Q30: 6 | R30: 10 | S30: 27428 | T30: 48671.2 | U30: 1 | V30: 4867.12 | W30: 0.52173913 | X30: 0.97222222 | Y30: 0.50724638 | Z30: 0.65714286 | AA30: 0.90909091 | AB30: 0.26086957 | AC30: 0.086956522 | AD30: 0.14492754 | AE30: 71470.854 | AF30: 0.68099368 | AG30: 33 | AH30: 30 | AI30: 37 | AJ30: 4278.1117 | AK30: 4347.5599 | AL30: 4363.5687 | AM30: 783.89754 | AN30: 3111.849 | AO30: 0 | AP30: 0 | AQ30: 0 | AR30: 0 | AS30: 0 | AT30: 0 | AU30: 0 | AV30: 0 | AW30: 0 | AX30: 0 | BI30: 0 | BJ30: 0 | BK30: 0 | BL30: 0 | BM30: 0 | BN30: 0 | BO30: 0 | BP30: 0 | BQ30: 27428 | BR30: 48671.2 | BS30: 1 | BT30: 12606.875 | BU30: 9743.7949 | BV30: 4278.1117 | BW30: 54585.868 | BX30: 54585.868 | BY30: 68607.774 | BZ30: 0.39977977 | CB30: 71470.854 | CC30: 0.68099368 | CD30: 72367.743 | CE30: 0.67255379
I31: 101407.79 | J31: 751.16885 | K31: 135 | L31: 57 | M31: 62 | N31: 59 | O31: 47 | P31: 54 | Q31: 25 | R31: 26 | S31: 120500 | T31: 124088 | U31: 1 | V31: 4772.6154 | W31: 0.42222222 | X31: 1.0350877 | Y31: 0.43703704 | Z31: 0.79661017 | AA31: 0.96428571 | AB31: 0.53191489 | AC31: 0.18518519 | AD31: 0.19259259 | AE31: 134515.74 | AF31: 0.92247939 | AG31: 56 | AH31: 54 | AI31: 57 | AJ31: 8370.2186 | AK31: 7285.1004 | AL31: 11124.988 | AM31: 1533.7126 | AN31: 4793.9295 | AO31: 0 | AP31: 0 | AQ31: 0 | AR31: 0 | AS31: 0 | AT31: 0 | AU31: 0 | AV31: 0 | AW31: 0 | AX31: 0 | BI31: 0 | BJ31: 0 | BK31: 0 | BL31: 0 | BM31: 0 | BN31: 0 | BO31: 0 | BP31: 0 | BQ31: 120500 | BR31: 124088 | BS31: 1 | BT31: 24737.73 | BU31: 23239.815 | BV31: 8370.2186 | BW31: 101407.79 | BX31: 101407.79 | BY31: 133017.83 | BZ31: 0.90589361 | CB31: 134515.74 | CC31: 0.92247939 | CD31: 136270.52 | CE31: 0.91060044
I32: 67417.501 | J32: 1105.2049 | K32: 61 | L32: 28 | M32: 31 | N32: 26 | O32: 16 | P32: 22 | Q32: 5 | R32: 5 | S32: 18140 | T32: 18140 | U32: 1 | V32: 3628 | W32: 0.45901639 | X32: 0.92857143 | Y32: 0.42622951 | Z32: 0.61538462 | AA32: 0.91666667 | AB32: 0.3125 | AC32: 0.081967213 | AD32: 0.081967213 | AE32: 79011.774 | AF32: 0.22958604 | AG32: 24 | AH32: 22 | AI32: 22 | AJ32: 3782.0988 | AK32: 3642.5502 | AL32: 1626.3239 | AM32: 693.01087 | AN32: 1850.2886 | AO32: 0 | AP32: 0 | AQ32: 0 | AR32: 0 | AS32: 0 | AT32: 0 | AU32: 0 | AV32: 0 | AW32: 0 | AX32: 0 | BI32: 0 | BJ32: 0 | BK32: 0 | BL32: 0 | BM32: 0 | BN32: 0 | BO32: 0 | BP32: 0 | BQ32: 18140 | BR32: 18140 | BS32: 1 | BT32: 7812.1735 | BU32: 6955.0445 | BV32: 3782.0988 | BW32: 67417.501 | BX32: 67417.501 | BY32: 78154.645 | BZ32: 0.23210393 | CB32: 79011.774 | CC32: 0.22958604 | CD32: 79804.675 | CE32: 0.22730498
I33: 124442.65 | J33: 719.32169 | K33: 173 | L33: 72 | M33: 78 | N33: 75 | O33: 53 | P33: 71 | Q33: 13 | R33: 17 | S33: 76044 | T33: 90496 | U33: 1 | V33: 5323.2941 | W33: 0.41618497 | X33: 1.0416667 | Y33: 0.43352601 | Z33: 0.70666667 | AA33: 0.98611111 | AB33: 0.24528302 | AC33: 0.075144509 | AD33: 0.098265896 | AE33: 160636.51 | AF33: 0.56335885 | AG33: 72 | AH33: 71 | AI33: 74 | AJ33: 10726.28 | AK33: 9165.1263 | AL33: 8113.33 | AM33: 1965.4243 | AN33: 6223.6979 | AO33: 0 | AP33: 0 | AQ33: 0 | AR33: 0 | AS33: 0 | AT33: 0 | AU33: 0 | AV33: 0 | AW33: 0 | AX33: 0 | BI33: 0 | BJ33: 0 | BK33: 0 | BL33: 0 | BM33: 0 | BN33: 0 | BO33: 0 | BP33: 0 | BQ33: 76044 | BR33: 90496 | BS33: 1 | BT33: 25467.578 | BU33: 21868.912 | BV33: 10726.28 | BW33: 124442.65 | BX33: 124442.65 | BY33: 157037.85 | BZ33: 0.48423996 | CB33: 160636.51 | CC33: 0.56335885 | CD33: 162885.23 | CE33: 0.55558137
